{
  "job_description": "### Gerente de contas -chave na Luxotech Solutions\n\n** Localização: ** Karachi, Paquistão\n\n** Departamento: ** Vendas e marketing\n\n** Relatórios para: ** Diretor de vendas\n\n** Visão geral da função: **\nJunte -se à Luxotech Solutions como gerente de contas importantes, onde você será responsável pelo gerenciamento das principais contas nos segmentos de varejo e hospitalidade em todo o Paquistão. Você impulsionará o crescimento das vendas, gerenciando contas existentes e desenvolvendo estratégias para novas contas. Sua função envolverá coordenar com equipes multifuncionais, analisar tendências do mercado e liderar iniciativas para cumprir as metas de receita.\n\nResponsabilidades ####:\n- Gerencie um portfólio de mais de 15 contas principais, compreendendo usuários finais e parceiros de canal.\n- Dirija a expansão para novos segmentos de mercado, identificando e se envolvendo com possíveis leads.\n- Desenvolva e execute estratégias de gerenciamento de contas para alcançar 110% de obtenção alvo de receita.\n- Utilize ferramentas de análise de dados, como o Power BI, para avaliar as tendências do mercado e gerar insights.\n- Coordenar com equipes internas, incluindo marketing e operações, para garantir o alinhamento estratégico.\n- Liderar negociações contratadas e gerenciar estratégias de preços para otimizar a lucratividade.\n- Relatório sobre o desempenho da conta e as oportunidades de mercado para a gerência sênior regularmente.\n\n#### habilidades essenciais:\n- Fortes habilidades de liderança e gerenciamento de partes interessadas.\n- Proficiência na análise de dados e previsão para informar a tomada de decisão.\n- Experiência em ferramentas como Salesforce, Vistex e SAP ERP para gerenciar funções de vendas.\n- Excelentes habilidades de comunicação para interações com clientes e colaborações internas.\n\n#### qualificações:\n- Mestre de preferência; É necessário um diploma de bacharel em administração de empresas ou campo relacionado.\n- Mais de 5 anos de experiência em gerenciamento de vendas ou desenvolvimento de negócios, com foco no gerenciamento de contas principais.\n- O sucesso demonstrado em contas crescentes e atingindo metas de receita.\n\n#### Benefícios:\n- Salário competitivo com bônus de desempenho.\n- Oportunidades de desenvolvimento profissional e acesso a seminários da indústria.\n- Horário de trabalho flexível.",
  "additional_info": "A Luxotech Solutions valoriza a diversidade e busca candidatos de uma variedade de origens e experiências. As instituições preferidas incluem o Instituto de Administração de Empresas, Karachi e Nuces Fast. A empresa suporta acordos de trabalho híbridos e oferece assistência de realocação para candidatos excepcionais. As habilidades são avaliadas através de uma combinação de testes técnicos, estudos de caso e entrevistas estruturadas com membros do painel de vários departamentos.",
  "resume": "Afnan Faiz \n  \n  \n  \nResumo profissional  \nUm comunicador qualificado e direcionado para a meta, equipespitited, persuasiva, \nIndivíduo adaptável, auto -motivado e orientado para a carreira, buscando \nutilizar habilidades e experiência analíticas para contribuir com o seu \ncrescimento e objetivos da organização.  \n  \n  \n  \nHistória do trabalho  \n \nExecutivo de Desenvolvimento de Negócios (março de 202 2 a julho de 2022)   \nTechnerds Inc. - Lahore, Punjab   \n   \n· Gerenciamento de lances de upwork.  \n· LinkedIn com o Sales Navigator às perspectivas de destino.   \n· Análise de projetos e desenvolvimento de propostas.    \n· Relatórios de sucesso da equipe de desenvolvimento mensal e semanal.   \n· Marketing por e -mail.  \n \n \nOficial sênior de desenvolvimento de negócios (outubro de 2021 - fevereiro de 2022) \nCybexo Inc. - Lahore, Punjab  \n \n· Gerenciamento de lances de upwork.  \n· LinkedIn com o Sales Navigator às perspectivas de destino.  \n· Desenvolvimento de sites e Desenvolvimento de aplicativos Manuseio de clientes.   \n· Gerenciamento de desenvolvimento de projetos e reuniões de clientes \ngerenciamento.  \n· Análise de projetos e desenvolvimento de propostas.  \n· Relatórios de sucesso da equipe de desenvolvimento mensal e semanal.  \n· Colaborar com a equipe de desenvolvimento e fornecer a todos \nas informações para o desenvolvimento do projeto. \n· Marketing por e -mail via Sendy.  \n \n \nOficial de Desenvolvimento de Negócios (outubro de 2019 - outubro de 2021) \nWebsouls - Lahore, Punjab  \n \n· Desenvolvimento de sites, SEO e manuseio de clientes SMM.   \n· Gerenciamento de desenvolvimento de projetos e reuniões de clientes \ngerenciamento.  \n· Análise de projetos e desenvolvimento de propostas.  \n· Relatórios mensais da equipe de desenvolvimento semanal.  \n· Colaborar com a equipe de desenvolvimento e fornecer a todos \nas informações para o desenvolvimento do projeto. \n· Marketing por e -mail. \n· Coupa de cinco, upwork e freelancer CAs e gerenciamento de lances.  \n \nEmail Support Executive - Systems Limited (janeiro de 2019 - março de 2019):   \n· Manipulação de bate -papos e e -mails de clientes internacionais.     \nCONTATO  \nEndereço: Lahore, PB 54000   \nTelefone: +92 (304) (1418484)  \nE -mail: afnanfaiz273@gmail.com  \nLinkedIn: https://www.linkedin.com/in\n/Afnanfaiz/  \n  \n  \n  \nHABILIDADES  \n● Microsoft Office.  \n● Trabalho de pesquisa.  \n● Aprendiz rápido.  \n● Apresentações projetando e \ndesenvolvimento . \n● Desenvolvimento de negócios.  \n● Construindo relações com os clientes.  \n● Engajamento do cliente.  \n● Relatórios de análise.  \n● Gerenciamento de projetos. \n● Desenvolvimento da proposta.  \n● Marketing por e -mail.  \n  · Assistência inclui rastrear os pedidos dos clientes de diferentes correios \nportais e fornecendo as informações e soluções corretas para o \nclientes de acordo com as políticas da organização.  \n \nEmail Support Executive - Mindbridge (maio de 2017 - dezembro de 2018):  \n                 \n· Lidar com e -mails dos clientes internacionais da Uber.  \n· Assistência inclui rastrear os registros dos clientes e fornecer o direito \ninformações e soluções para os clientes, de acordo com os da organização \npolíticas.  \n \n \n  \n  \n  \nEDUCAÇÃO  \n(2020 -2022) Mestrado em Administração de Empresas (MBA) de  \nRápido -NUCE LAHORE.          \n(2015 -2019) Bacharelado em Administração de Empresas (BBA Hons) \nde NCBA & e. \n(2012-2014) Intermediário em ciências do computador (ICS) de \nGrupo de Faculdades Punjab. \n(2010-2012) Matrícula  \nGovt. Escola piloto de garotas secundárias piloto.",
  "details": {
    "name": "Afnan Faiz",
    "number": "923041418484",
    "skills": [
      "Microsoft Office",
      "Desenvolvimento de negócios",
      "Gerenciamento de projetos",
      "Desenvolvimento da proposta",
      "Marketing por e -mail"
    ],
    "email_id": "afnanfaiz273@gmail.com",
    "location": "Lahore, PB 54000",
    "projects": [],
    "education": [
      {
        "end_date": "06-2022",
        "university": "Rápido -NUCE LAHORE",
        "degree_title": "Mestrado em Administração de Empresas (MBA)"
      },
      {
        "end_date": "06-2019",
        "university": "NCBA & E.",
        "degree_title": "Bacharelado em Administração de Empresas (BBA Hons)"
      },
      {
        "end_date": "06-2014",
        "university": "Grupo de Faculdades Punjab",
        "degree_title": "Intermediário em ciências do computador (ICS)"
      },
      {
        "end_date": "06-2012",
        "university": "Govt. Escola piloto de garotas secundárias piloto",
        "degree_title": "Matrícula"
      }
    ],
    "achievements": [],
    "publications": [],
    "certifications": [],
    "additional_urls": [
      {
        "url": "linkedin.com/in/afnanfaiz/",
        "website_name": "LinkedIn"
      }
    ],
    "executive_summary": "A Afnan Faiz é um profissional dedicado de desenvolvimento de negócios, com uma forte formação no gerenciamento de projetos e propostas, qualificada em marketing por email e proficiente no Microsoft Office. Com experiência em várias funções, Afnan demonstrou a capacidade de envolver os clientes de maneira eficaz e contribuir para o crescimento organizacional.",
    "employment_history": [
      {
        "details": "O Upwork Bids Management, LinkedIn com o Navigator de vendas a perspectivas de destino, análise de projetos e desenvolvimento de propostas, relatórios de sucesso da equipe de desenvolvimento mensal e semanal, marketing por email.",
        "end_date": "07-2022",
        "location": "Lahore, Punjab",
        "job_title": "Executivo de Desenvolvimento de Negócios",
        "start_date": "03-2022",
        "company_name": "Technerds Inc."
      },
      {
        "details": "A UPWORK BIDS Management, LinkedIn com o navegador de vendas a perspectivas de destino, desenvolvimento de sites e desenvolvimento de clientes de aplicativos, gerenciamento de gerenciamento de desenvolvimento de projetos e gerenciamento de reuniões de clientes, análise de projetos e desenvolvimento de propostas, reportagem de sucesso da equipe de desenvolvimento mensal e semanal, colabore com a equipe de desenvolvimento e forneça todas as informações para o desenvolvimento do projeto, marketing por email por meio de envio.",
        "end_date": "02-2022",
        "location": "Lahore, Punjab",
        "job_title": "Diretor de Desenvolvimento de Negócios Sênior",
        "start_date": "10-2021",
        "company_name": "Cybexo Inc."
      },
      {
        "details": "Desenvolvimento de sites, Manuseio de clientes SMM e SMM, Gerenciamento de desenvolvimento de projetos e Gerenciamento de reuniões de clientes, análise de projetos e desenvolvimento de propostas, Relatórios mensais da equipe de desenvolvimento semanal, colaboram com a equipe de desenvolvimento e fornecem todas as informações para o desenvolvimento do projeto, marketing por email, cinco, trabalhos e contas freelancers e gerenciamento de lances.",
        "end_date": "10-2021",
        "location": "Lahore, Punjab",
        "job_title": "Oficial de Desenvolvimento de Negócios",
        "start_date": "10-2019",
        "company_name": "Websouls"
      },
      {
        "details": "Manipulação de bate -papos e e -mails de clientes internacionais.",
        "end_date": "03-2019",
        "location": "",
        "job_title": "Email Support Executive",
        "start_date": "01-2019",
        "company_name": "Systems Limited"
      },
      {
        "details": "O manuseio de e -mails dos clientes internacionais da Uber, a assistência inclui rastrear os registros dos clientes e fornecer as informações e soluções corretas para os clientes, de acordo com as políticas da organização.",
        "end_date": "12-2018",
        "location": "",
        "job_title": "Email Support Executive",
        "start_date": "05-2017",
        "company_name": "Mindbridge"
      }
    ]
  }
}