{
  "job_description": "## Generação de leads e especialista em inteligência de negócios\n\nJunte -se a ** Innovate Connections Inc. ** Como uma geração de leads e especialista em inteligência de negócios. Você desempenhará um papel fundamental na condução do crescimento dos negócios, liderando iniciativas de geração de leads e fornecendo informações estratégicas por meio da análise de dados. Estamos à procura de um profissional altamente qualificado, com uma forte experiência em geração de leads, gerenciamento de dados e inteligência de negócios.\n\n### Responsabilidades -chave:\n- Desenvolva e execute estratégias de geração de leads usando técnicas de marketing digital, chamadas a frio e ferramentas de raspagem de dados.\n- Colabore com equipes multifuncionais para otimizar estratégias de aquisição de clientes.\n- Utilize sistemas de CRM para gerenciar e analisar os dados do cliente para obter a qualificação do lead.\n- Crie e gerencie cronogramas e planos de trabalho detalhados, utilizando as melhores práticas e padrões para a execução do projeto.\n- Desenvolva modelos financeiros e estratégias de crescimento de negócios com base em insights de dados.\n- Utilize ferramentas como Power BI, SQL e Tableau para desenvolver relatórios e painéis abrangentes de dados.\n\n### Habilidades e experiência desejadas:\n- Fortes habilidades de programação em C ++, HTML e CSS.\n- Proficiência em plataformas de marketing digital, marketing por e -mail e mídia social.\n- Experiência no gerenciamento de grandes conjuntos de dados e no uso de ferramentas de BI (Power BI, Excel, Tableau).\n- Excelentes habilidades de comunicação e capacidade de desenvolver relacionamentos fortes do cliente.\n- Capacidade de trabalhar de forma independente e gerenciar vários projetos simultaneamente.\n\n### Por que a Inovate Connections Inc.?\n- Innovamos na vanguarda da tecnologia e permitimos que os membros da nossa equipe cresçam ao lado da empresa.\n-Valorizamos a tomada de decisão orientada a dados e capacitamos nossas equipes com as ferramentas certas para ter sucesso.\n- Oferecendo um ambiente de trabalho de apoio e oportunidades de avanço na carreira.\n\n### Como se inscrever:\nEnvie seu currículo e carta de apresentação detalhando sua experiência relevante e por que você está interessado em ingressar na Innovate Connections Inc.",
  "additional_info": "A Innovate Connections Inc. prefere candidatos de universidades reconhecidas, como a Universidade de Gerenciamento e Tecnologia e a Lahore School of Economics. Incentivamos um ambiente de trabalho remoto, mas exige presença física para sessões de construção de equipes e estratégicas duas vezes por trimestre. A assistência à realocação está disponível para candidatos excepcionais. Nossa avaliação abrangente inclui um teste técnico seguido de entrevistas estruturadas para avaliar as habilidades técnicas e sociais de forma abrangente.",
  "resume": "Idiomas SpokenProspecting, Qualificação, Desenvolvimento de Pipeline de Vendas.\nDemonstrações de produtos.\nProprietário do produto.\nGeração de chumbo e promovendo -os: gerar o novo líder e\npromove -os.\nExaminar o requisito do cliente e, mantendo o\ndocumentos de requisito.\nPerspectivas de vendas, mantendo perspectivas saudáveis ​​de vendas. Agindo como um\nligação entre a equipe de desenvolvimento e a equipe de negócios,\npermanecendo conectado com o cliente.\nDemonstração mensal de MVPs aos clientes.\nChamada a frio - e -mail frio: alcançando novos clientes e tomando acompanhamento\nUPS para perspectivas futuras.\nIniciar o relacionamento com as perspectivas saudáveis ​​através\nLinkedIn.\nDemonstrações de produtos para os clientes depois de definir bem -sucedido\nreuniões.\nEspecialista sênior de suporte ao cliente Suporte contratado | Julho de 2020 - Jan\n2021\nEntrei para o apoio contratado como especialista sênior de suporte ao cliente\nPara promover minhas habilidades escritas.\nReceba e responda prontamente às consultas do cliente.\nDocumentar problemas e resoluções.\nAprenda sobre novos produtos e serviços. Keep Truckin\nExecutivo de contas | Novembro de 2021 - presente\nQuadrado viral\nOficial de Desenvolvimento de Negócios | Fevereiro de 2021- novembro de 2021\nSuporte contratado\nUniversidade de Punjab Central\nMestrado em Administração de Empresas 2021 - Presente\nComecei meu mestrado em administração de empresas da universidade\ndo Punjab central para promover minha experiência ainda mais conforme a necessidade do\nmercado, para entender melhor as perspectivas de vendas.\nUniversidade Hazara\nBacharelado em Administração de Empresas 2014 - 2018\nEu fiz meus solteiros da Universidade de Hazara, garantindo coloridos\nnotas, escolheu as finanças como minha principal área de pesquisa. Experiência de trabalho\nDestaques da educação: +923475130731\nUmersaleemzaman1308@gmail.com\nLinkedIn.com/in/umersaleemzaman/ \nJohar Town, Lahore, Paquistanumer Saleem\nOficial de Desenvolvimento de Negócios\nNegócios experientes\nDesenvolvimento e cliente\nExecutivo com um\nHistória demonstrada de\nTrabalhando como contato de vendas\nentre o cliente e o\nEmpresa. Eu tenho acuminado\nhabilidades em gerenciamento de clientes,\nRequisitos de coleta e\nPotencial convincente\nClientes, um pensamento que\nimpulsiona a execução, muito\nconhecedor em uma ampla\nVariedade de profissional\ndisciplinas que maximizam\ncrescimento da marca, incluindo\nfinanças, marketing e tudo\nFacetas de operações comerciais\ndo desenvolvimento de produtos para\nengajamento do cliente. Resumo executivo\nGeração de chumbo\nSalesFroce\nSalloft\nMicrosoft Office\nZendesk\nTawlk.to\nPipeline de vendas\nDesenvolvimento de vendas\nDemonstrações de produtos\nINGLÊS\nURDU \nHINDI",
  "details": {
    "name": "Umer Saleem",
    "number": "923475130731",
    "skills": [
      "Geração de chumbo",
      "SalesFroce",
      "Salloft",
      "Microsoft Office",
      "Zendesk",
      "Tawlk.to",
      "Pipeline de vendas",
      "Desenvolvimento de vendas",
      "Demonstrações de produtos"
    ],
    "email_id": "Umersaleemzaman1308@gmail.com",
    "location": "Johar Town, Lahore, Paquistão",
    "projects": [],
    "education": [
      {
        "end_date": "12-2021",
        "university": "Universidade de Punjab Central",
        "degree_title": "Mestrado em Administração de Empresas"
      },
      {
        "end_date": "05-2018",
        "university": "Universidade Hazara",
        "degree_title": "Bacharelado em Administração de Empresas"
      }
    ],
    "achievements": [],
    "publications": [],
    "certifications": [],
    "additional_urls": [
      {
        "url": "LinkedIn.com/in/umersaleemzaman/",
        "website_name": "LinkedIn"
      }
    ],
    "executive_summary": "A UMER Saleem é um oficial de desenvolvimento de negócios experiente, com uma forte experiência em gerenciamento e vendas de clientes. Ele demonstrou experiência em geração de leads, demonstrações de produtos e manutenção de perspectivas de vendas saudáveis, atuando efetivamente como uma ligação entre os clientes e a empresa.",
    "employment_history": [
      {
        "details": "Atuando como uma ligação entre a equipe de desenvolvimento e a equipe de negócios, mantendo -se conectado ao cliente. Demonstração mensal de MVPs aos clientes. Chamada a frio - e -mail frio: alcançando novos clientes e aceitando acompanhamentos para futuras perspectivas.",
        "end_date": "Presente",
        "location": "",
        "job_title": "Executivo de contas",
        "start_date": "11-2021",
        "company_name": "Mantenha o caminhão"
      },
      {
        "details": "Promover habilidades escritas e responder prontamente às consultas do cliente. Documentando problemas e resoluções.",
        "end_date": "01-2021",
        "location": "",
        "job_title": "Especialista sênior de suporte ao cliente",
        "start_date": "07-2020",
        "company_name": "Suporte contratado"
      },
      {
        "details": "Responsável pelo desenvolvimento de negócios e gerenciamento de clientes, concentrando -se em gerar novos leads e manter relacionamentos com clientes em potencial.",
        "end_date": "11-2021",
        "location": "",
        "job_title": "Oficial de Desenvolvimento de Negócios",
        "start_date": "02-2021",
        "company_name": "Quadrado viral"
      }
    ]
  }
}