{
  "job_description": "### Gerente de contas -chave na Luxotech Solutions\n\n** Localização: ** Karachi, Paquistão\n\n** Departamento: ** Vendas e marketing\n\n** Relatórios para: ** Diretor de vendas\n\n** Visão geral da função: **\nJunte -se à Luxotech Solutions como gerente de contas importantes, onde você será responsável pelo gerenciamento das principais contas nos segmentos de varejo e hospitalidade em todo o Paquistão. Você impulsionará o crescimento das vendas, gerenciando contas existentes e desenvolvendo estratégias para novas contas. Sua função envolverá coordenar com equipes multifuncionais, analisar tendências do mercado e liderar iniciativas para cumprir as metas de receita.\n\nResponsabilidades ####:\n- Gerencie um portfólio de mais de 15 contas principais, compreendendo usuários finais e parceiros de canal.\n- Dirija a expansão para novos segmentos de mercado, identificando e se envolvendo com possíveis leads.\n- Desenvolva e execute estratégias de gerenciamento de contas para alcançar 110% de obtenção alvo de receita.\n- Utilize ferramentas de análise de dados, como o Power BI, para avaliar as tendências do mercado e gerar insights.\n- Coordenar com equipes internas, incluindo marketing e operações, para garantir o alinhamento estratégico.\n- Liderar negociações contratadas e gerenciar estratégias de preços para otimizar a lucratividade.\n- Relatório sobre o desempenho da conta e as oportunidades de mercado para a gerência sênior regularmente.\n\n#### habilidades essenciais:\n- Fortes habilidades de liderança e gerenciamento de partes interessadas.\n- Proficiência na análise de dados e previsão para informar a tomada de decisão.\n- Experiência em ferramentas como Salesforce, Vistex e SAP ERP para gerenciar funções de vendas.\n- Excelentes habilidades de comunicação para interações com clientes e colaborações internas.\n\n#### qualificações:\n- Mestre de preferência; É necessário um diploma de bacharel em administração de empresas ou campo relacionado.\n- Mais de 5 anos de experiência em gerenciamento de vendas ou desenvolvimento de negócios, com foco no gerenciamento de contas principais.\n- O sucesso demonstrado em contas crescentes e atingindo metas de receita.\n\n#### Benefícios:\n- Salário competitivo com bônus de desempenho.\n- Oportunidades de desenvolvimento profissional e acesso a seminários da indústria.\n- Horário de trabalho flexível.",
  "additional_info": "A Luxotech Solutions valoriza a diversidade e busca candidatos de uma variedade de origens e experiências. As instituições preferidas incluem o Instituto de Administração de Empresas, Karachi e Nuces Fast. A empresa suporta acordos de trabalho híbridos e oferece assistência de realocação para candidatos excepcionais. As habilidades são avaliadas através de uma combinação de testes técnicos, estudos de caso e entrevistas estruturadas com membros do painel de vários departamentos.",
  "resume": "Idiomas SpokenProspecting, Qualificação, Desenvolvimento de Pipeline de Vendas.\nDemonstrações de produtos.\nProprietário do produto.\nGeração de chumbo e promovendo -os: gerar o novo líder e\npromove -os.\nExaminar o requisito do cliente e, mantendo o\ndocumentos de requisito.\nPerspectivas de vendas, mantendo perspectivas saudáveis ​​de vendas. Agindo como um\nligação entre a equipe de desenvolvimento e a equipe de negócios,\npermanecendo conectado com o cliente.\nDemonstração mensal de MVPs aos clientes.\nChamada a frio - e -mail frio: alcançando novos clientes e tomando acompanhamento\nUPS para perspectivas futuras.\nIniciar o relacionamento com as perspectivas saudáveis ​​através\nLinkedIn.\nDemonstrações de produtos para os clientes depois de definir bem -sucedido\nreuniões.\nEspecialista sênior de suporte ao cliente Suporte contratado | Julho de 2020 - Jan\n2021\nEntrei para o apoio contratado como especialista sênior de suporte ao cliente\nPara promover minhas habilidades escritas.\nReceba e responda prontamente às consultas do cliente.\nDocumentar problemas e resoluções.\nAprenda sobre novos produtos e serviços. Keep Truckin\nExecutivo de contas | Novembro de 2021 - presente\nQuadrado viral\nOficial de Desenvolvimento de Negócios | Fevereiro de 2021- novembro de 2021\nSuporte contratado\nUniversidade de Punjab Central\nMestrado em Administração de Empresas 2021 - Presente\nComecei meu mestrado em administração de empresas da universidade\ndo Punjab central para promover minha experiência ainda mais conforme a necessidade do\nmercado, para entender melhor as perspectivas de vendas.\nUniversidade Hazara\nBacharelado em Administração de Empresas 2014 - 2018\nEu fiz meus solteiros da Universidade de Hazara, garantindo coloridos\nnotas, escolheu as finanças como minha principal área de pesquisa. Experiência de trabalho\nDestaques da educação: +923475130731\nUmersaleemzaman1308@gmail.com\nLinkedIn.com/in/umersaleemzaman/ \nJohar Town, Lahore, Paquistanumer Saleem\nOficial de Desenvolvimento de Negócios\nNegócios experientes\nDesenvolvimento e cliente\nExecutivo com um\nHistória demonstrada de\nTrabalhando como contato de vendas\nentre o cliente e o\nEmpresa. Eu tenho acuminado\nhabilidades em gerenciamento de clientes,\nRequisitos de coleta e\nPotencial convincente\nClientes, um pensamento que\nimpulsiona a execução, muito\nconhecedor em uma ampla\nVariedade de profissional\ndisciplinas que maximizam\ncrescimento da marca, incluindo\nfinanças, marketing e tudo\nFacetas de operações comerciais\ndo desenvolvimento de produtos para\nengajamento do cliente. Resumo executivo\nGeração de chumbo\nSalesFroce\nSalloft\nMicrosoft Office\nZendesk\nTawlk.to\nPipeline de vendas\nDesenvolvimento de vendas\nDemonstrações de produtos\nINGLÊS\nURDU \nHINDI",
  "details": {
    "name": "Umer Saleem",
    "number": "923475130731",
    "skills": [
      "Geração de chumbo",
      "SalesFroce",
      "Salloft",
      "Microsoft Office",
      "Zendesk",
      "Tawlk.to",
      "Pipeline de vendas",
      "Desenvolvimento de vendas",
      "Demonstrações de produtos"
    ],
    "email_id": "Umersaleemzaman1308@gmail.com",
    "location": "Johar Town, Lahore, Paquistão",
    "projects": [],
    "education": [
      {
        "end_date": "12-2021",
        "university": "Universidade de Punjab Central",
        "degree_title": "Mestrado em Administração de Empresas"
      },
      {
        "end_date": "05-2018",
        "university": "Universidade Hazara",
        "degree_title": "Bacharelado em Administração de Empresas"
      }
    ],
    "achievements": [],
    "publications": [],
    "certifications": [],
    "additional_urls": [
      {
        "url": "LinkedIn.com/in/umersaleemzaman/",
        "website_name": "LinkedIn"
      }
    ],
    "executive_summary": "A UMER Saleem é um oficial de desenvolvimento de negócios experiente, com uma forte experiência em gerenciamento e vendas de clientes. Ele demonstrou experiência em geração de leads, demonstrações de produtos e manutenção de perspectivas de vendas saudáveis, atuando efetivamente como uma ligação entre os clientes e a empresa.",
    "employment_history": [
      {
        "details": "Atuando como uma ligação entre a equipe de desenvolvimento e a equipe de negócios, mantendo -se conectado ao cliente. Demonstração mensal de MVPs aos clientes. Chamada a frio - e -mail frio: alcançando novos clientes e aceitando acompanhamentos para futuras perspectivas.",
        "end_date": "Presente",
        "location": "",
        "job_title": "Executivo de contas",
        "start_date": "11-2021",
        "company_name": "Mantenha o caminhão"
      },
      {
        "details": "Promover habilidades escritas e responder prontamente às consultas do cliente. Documentando problemas e resoluções.",
        "end_date": "01-2021",
        "location": "",
        "job_title": "Especialista sênior de suporte ao cliente",
        "start_date": "07-2020",
        "company_name": "Suporte contratado"
      },
      {
        "details": "Responsável pelo desenvolvimento de negócios e gerenciamento de clientes, concentrando -se em gerar novos leads e manter relacionamentos com clientes em potencial.",
        "end_date": "11-2021",
        "location": "",
        "job_title": "Oficial de Desenvolvimento de Negócios",
        "start_date": "02-2021",
        "company_name": "Quadrado viral"
      }
    ]
  }
}