{
  "job_description": "### Gerente de contas -chave na Luxotech Solutions\n\n** Localização: ** Karachi, Paquistão\n\n** Departamento: ** Vendas e marketing\n\n** Relatórios para: ** Diretor de vendas\n\n** Visão geral da função: **\nJunte -se à Luxotech Solutions como gerente de contas importantes, onde você será responsável pelo gerenciamento das principais contas nos segmentos de varejo e hospitalidade em todo o Paquistão. Você impulsionará o crescimento das vendas, gerenciando contas existentes e desenvolvendo estratégias para novas contas. Sua função envolverá coordenar com equipes multifuncionais, analisar tendências do mercado e liderar iniciativas para cumprir as metas de receita.\n\nResponsabilidades ####:\n- Gerencie um portfólio de mais de 15 contas principais, compreendendo usuários finais e parceiros de canal.\n- Dirija a expansão para novos segmentos de mercado, identificando e se envolvendo com possíveis leads.\n- Desenvolva e execute estratégias de gerenciamento de contas para alcançar 110% de obtenção alvo de receita.\n- Utilize ferramentas de análise de dados, como o Power BI, para avaliar as tendências do mercado e gerar insights.\n- Coordenar com equipes internas, incluindo marketing e operações, para garantir o alinhamento estratégico.\n- Liderar negociações contratadas e gerenciar estratégias de preços para otimizar a lucratividade.\n- Relatório sobre o desempenho da conta e as oportunidades de mercado para a gerência sênior regularmente.\n\n#### habilidades essenciais:\n- Fortes habilidades de liderança e gerenciamento de partes interessadas.\n- Proficiência na análise de dados e previsão para informar a tomada de decisão.\n- Experiência em ferramentas como Salesforce, Vistex e SAP ERP para gerenciar funções de vendas.\n- Excelentes habilidades de comunicação para interações com clientes e colaborações internas.\n\n#### qualificações:\n- Mestre de preferência; É necessário um diploma de bacharel em administração de empresas ou campo relacionado.\n- Mais de 5 anos de experiência em gerenciamento de vendas ou desenvolvimento de negócios, com foco no gerenciamento de contas principais.\n- O sucesso demonstrado em contas crescentes e atingindo metas de receita.\n\n#### Benefícios:\n- Salário competitivo com bônus de desempenho.\n- Oportunidades de desenvolvimento profissional e acesso a seminários da indústria.\n- Horário de trabalho flexível.",
  "additional_info": "A Luxotech Solutions valoriza a diversidade e busca candidatos de uma variedade de origens e experiências. As instituições preferidas incluem o Instituto de Administração de Empresas, Karachi e Nuces Fast. A empresa suporta acordos de trabalho híbridos e oferece assistência de realocação para candidatos excepcionais. As habilidades são avaliadas através de uma combinação de testes técnicos, estudos de caso e entrevistas estruturadas com membros do painel de vários departamentos.",
  "resume": "Zubair Ahmed \nExecutivo de Desenvolvimento de Negócios \nUm prospectivo analista de marketing e negócios, um destinatário de ciências da gestão da Universidade de Engenharia e Tecnologia de Ned,\nquem se esforça para posar e responder com uma atitude comercial orientada a resultados no desenvolvimento de garantias de marketing criativo para diversos\nprojetos. Estabelece padrões claros e aplica protocolos para resultados consistentes e de alta qualidade, utilizando habilidades interpessoais, dados\nHabilidades analíticas, excelente gerenciamento de tempo e habilidades de solução de problemas. \nza05760@gmail.com \n03310211624 \nR-280, folha 51, Bloco B, Villas Saima Arabian, Karachi. \nExperiência de trabalho \nExecutivo de Desenvolvimento de Negócios \nPayMob \n2021 - presente\n, Assim, \n \nCarachi \nDefinidas e integradas funções, responsabilidades e processos para\nEquipe de negócios e organização de gerenciamento de dados. \nCriou planilhas usando o Microsoft Excel para diariamente, semanalmente e\nRelatórios mensais. \nDesenvolveu e executou iniciativas estratégicas para implementar a chave\nmudanças e melhorias no desenvolvimento de negócios e vendas\nprogramas. \nUsou o pensamento crítico para dividir problemas, avaliar soluções\ne tomar decisões. \nAnalista de pesquisa de mercado \nEquipamento de engenharia de precisão FZE \n2019 - 2021\n, Assim, \n \nCarachi \nTrabalhou em estreita colaboração com as equipes de desenvolvimento de produtos para criar e\nManter materiais de marketing para apresentações de vendas e cliente\nreuniões na indústria. \nAnalisou os planos de marketing de pré-temporada para gerar melhores vendas e\nComunique -se com os clientes através da chamada/e -mail. \nDesenvolveu estratégias de marketing e problemas resolvidos para dirigir\nVendas, por meio de CRM e informações de banco de dados gerenciadas do mercado. \nUtilizou diferentes ferramentas para analisar tendências de marketing e financeiras como\nAS, SQL, Excel e Power BI e medidas sugeridas para reduzir custos\ne melhorar os processos de negócios. \nEstágio \nUnilever Paquistão \n2019\n, Assim, \n \nCarachi \nAnalisar e examinar os requisitos da empresa para contínua\nprojetos e contratos. \nAtualize e gerencie o banco de dados interno para a seleção do futuro fornecedor\nE seus termos, essas informações são úteis para os próximos projetos. \nRelacionamentos de fornecedores desenvolvidos e reforçados. \nEDUCAÇÃO \nBS - Ciência da Gestão \nUniversidade de Engenharia e Tecnologia de Ned \n2022\n, Assim, \n \nCarachi \nHABILIDADES \nResolução de problemas e análise de negócios \nDesenvolvimento de produtos e estrategista \nCRM \nComunicação comercial e relatórios \nSQL \nMarketing digital \nAnalista de pesquisa de mercado \nEntusiasta da ciência de dados \nHabilidade de liderança \nProjeto e gerenciamento de marca \nHubSpot \nSalesforce \nBoa redociação \nPython \nVisualização de dados \nQuadro \nPower bi \nProjetos pessoais \nCPEC \n- \nProjeto do ano final \nAnalisando o desenvolvimento da infraestrutura logística do Paquistão\ndepois do CPEC e como ele renovará ou reabilitará o\nInfraestrutura do Paquistão, desenvolvendo o especial\nZonas econômicas. Analisamos os diferentes dados industriais em\ncada província do Paquistão e o impacto de SEZs que vão\nremodelar a economia da indústria no Paquistão \nSegurança Midas Paquistão \n- \nProjeto do curso \nProjeto em Midas Safety Pakistan (unidade Karachi) onde eu\nidentificar o processo envolvido na fabricação de seus\nProdutos, isto é, luvas e mangas de segurança. Eu basicamente analisei\nDrivers da cadeia de suprimentos de Midas e examinaram o uso \nde\ntecnologia da Informação. \nIdiomas \nInglês \nProfiência profissional completa \nRealizações/tarefas \nRealizações/tarefas \nRealizações/tarefas",
  "details": {
    "name": "Zubair Ahmed",
    "number": "03310211624",
    "skills": [
      "SQL",
      "Excel",
      "Python",
      "Power bi",
      "Quadro",
      "HubSpot",
      "Salesforce"
    ],
    "email_id": "za05760@gmail.com",
    "location": "Carachi",
    "projects": [
      {
        "title": "CPEC - Projeto do ano final",
        "description": "Analisando o desenvolvimento da infraestrutura logística do Paquistão após o CPEC."
      },
      {
        "title": "Midas Safety Pakistan - Projeto de curso",
        "description": "Analisou os motoristas da cadeia de suprimentos de Midas e examinaram o uso da tecnologia da informação."
      }
    ],
    "education": [
      {
        "end_date": "06-2022",
        "university": "Universidade de Engenharia e Tecnologia de Ned",
        "degree_title": "BS - Ciência da Gestão"
      }
    ],
    "achievements": [],
    "publications": [],
    "certifications": [],
    "additional_urls": [
      {
        "url": "LinkedIn.com/in/zubairahmed",
        "website_name": "LinkedIn"
      }
    ],
    "executive_summary": "Zubair Ahmed é um executivo dedicado de desenvolvimento de negócios, com uma forte experiência em marketing e análise de negócios. Ele demonstrou experiência em SQL, Excel e Python e contribuiu com sucesso para iniciativas estratégicas em programas de desenvolvimento e vendas de negócios.",
    "employment_history": [
      {
        "details": "Funções, responsabilidades e processos definidos e integrados para a equipe de equipes e gerenciamento de dados. Criou planilhas usando o Microsoft Excel para relatórios diários, semanais e mensais. Desenvolveu e executou iniciativas estratégicas para implementar as principais mudanças e melhorias nos programas de desenvolvimento e vendas de negócios.",
        "end_date": "Presente",
        "location": "Carachi",
        "job_title": "Executivo de Desenvolvimento de Negócios",
        "start_date": "01-2021",
        "company_name": "PayMob"
      },
      {
        "details": "Trabalhou em estreita colaboração com as equipes de desenvolvimento de produtos para criar e manter materiais de marketing para apresentações de vendas e reuniões de clientes. Analisou os planos de marketing de pré-temporada para gerar melhores vendas e se comunicar com os clientes através da chamada/e-mail. Desenvolveu estratégias de marketing e problemas resolvidos para impulsionar as vendas, por meio do CRM e das informações gerenciadas do banco de dados do mercado.",
        "end_date": "12-2021",
        "location": "Carachi",
        "job_title": "Analista de pesquisa de mercado",
        "start_date": "01-2019",
        "company_name": "Equipamento de engenharia de precisão FZE"
      },
      {
        "details": "Analisando e examinando os requisitos da empresa para projetos e contratos em andamento. Atualize e gerencie o banco de dados interno para a seleção do fornecedor futuro e seus termos, essas informações são úteis para os próximos projetos. Relacionamentos de fornecedores desenvolvidos e reforçados.",
        "end_date": "12-2019",
        "location": "Carachi",
        "job_title": "Estágio",
        "start_date": "01-2019",
        "company_name": "Unilever Paquistão"
      }
    ]
  }
}