{
  "job_description": "## Generação de leads e especialista em inteligência de negócios\n\nJunte -se a ** Innovate Connections Inc. ** Como uma geração de leads e especialista em inteligência de negócios. Você desempenhará um papel fundamental na condução do crescimento dos negócios, liderando iniciativas de geração de leads e fornecendo informações estratégicas por meio da análise de dados. Estamos à procura de um profissional altamente qualificado, com uma forte experiência em geração de leads, gerenciamento de dados e inteligência de negócios.\n\n### Responsabilidades -chave:\n- Desenvolva e execute estratégias de geração de leads usando técnicas de marketing digital, chamadas a frio e ferramentas de raspagem de dados.\n- Colabore com equipes multifuncionais para otimizar estratégias de aquisição de clientes.\n- Utilize sistemas de CRM para gerenciar e analisar os dados do cliente para obter a qualificação do lead.\n- Crie e gerencie cronogramas e planos de trabalho detalhados, utilizando as melhores práticas e padrões para a execução do projeto.\n- Desenvolva modelos financeiros e estratégias de crescimento de negócios com base em insights de dados.\n- Utilize ferramentas como Power BI, SQL e Tableau para desenvolver relatórios e painéis abrangentes de dados.\n\n### Habilidades e experiência desejadas:\n- Fortes habilidades de programação em C ++, HTML e CSS.\n- Proficiência em plataformas de marketing digital, marketing por e -mail e mídia social.\n- Experiência no gerenciamento de grandes conjuntos de dados e no uso de ferramentas de BI (Power BI, Excel, Tableau).\n- Excelentes habilidades de comunicação e capacidade de desenvolver relacionamentos fortes do cliente.\n- Capacidade de trabalhar de forma independente e gerenciar vários projetos simultaneamente.\n\n### Por que a Inovate Connections Inc.?\n- Innovamos na vanguarda da tecnologia e permitimos que os membros da nossa equipe cresçam ao lado da empresa.\n-Valorizamos a tomada de decisão orientada a dados e capacitamos nossas equipes com as ferramentas certas para ter sucesso.\n- Oferecendo um ambiente de trabalho de apoio e oportunidades de avanço na carreira.\n\n### Como se inscrever:\nEnvie seu currículo e carta de apresentação detalhando sua experiência relevante e por que você está interessado em ingressar na Innovate Connections Inc.",
  "additional_info": "A Innovate Connections Inc. prefere candidatos de universidades reconhecidas, como a Universidade de Gerenciamento e Tecnologia e a Lahore School of Economics. Incentivamos um ambiente de trabalho remoto, mas exige presença física para sessões de construção de equipes e estratégicas duas vezes por trimestre. A assistência à realocação está disponível para candidatos excepcionais. Nossa avaliação abrangente inclui um teste técnico seguido de entrevistas estruturadas para avaliar as habilidades técnicas e sociais de forma abrangente.",
  "resume": "EDUCAÇÃO\nBacharel em Engenharia de Software\nUniversidade de Gerenciamento e Tecnologia | 2016 - 2020about\nSou engenheiro de software com experiência em desenvolvimento de negócios, tenho proficiência em\nGerando leads, expansão de negócios, vendas, lucratividade e criação de estratégia. \nSou adepto com várias metodologias de desenvolvimento de negócios, coleta e analisando dados sobre\nVendas e marketing, minha experiência se estende a chamadas frias, marketing por email, orçamento\nGerenciamento, comunicação do cliente, documentação e gerenciamento de partes interessadas.\nExperiência de trabalho\nExecutivo de marketing digital\nTECNOLOGIA OZI | Jan 2020 - outubro de 2020\nIdentifique tendências e insights com o site do gerenciamento da organização, mídia social\nPlataformas e mantenha -as, mantendo as melhores práticas em mente. \nOtimize o conteúdo para o site e as plataformas de mídia social. \nTrabalhe com vários formatos de conteúdo, como blogs, vídeos, design gráfico, etc.\nForneça relatórios internos e colaborações criativas entre tecnologias e plataformas. Gerente de desenvolvimento de negócios\nSoluções Shayan | Outubro de 2020 - presente \nGerenciou com sucesso milhões de projetos orçamentários e alcançou as metas agendadas do projeto. \nImplementação e gerenciamento do CRM que se concentrou em alavancar a empresa\nativo de dados.\nLeads de geração e gerenciamento práticos usando Salesforce, LinkedIn Sales Navigator,\nAeroleads, etc. \nAlcançaram as metas de vendas, apresentando serviços da empresa a clientes atuais e potenciais em\nRegiões dos EUA, Austrália e Europa.\nDesenvolveu e implementou novos planos de marketing e vendas, como serviços remotos,\nCampanhas de marketing, etc. \nEscrever e projetar e -mails e garantir a entrega de email adequada aos leads.\nTrabalhar em estreita colaboração com desenvolvedores e engenheiros de controle de qualidade para garantir a qualidade e os padrões de\no projeto. \nImensa experiência em vendas, parcerias e desenvolvimento de negócios no Top B2B\nEmpresas de tecnologia.\nRevisou constantemente o feedback do cliente e depois sugeriu maneiras de melhorar o\nníveis de processo e atendimento ao cliente.\nGarantiu que novos clientes se transformassem em uma base de clientes fiel em um nicho especializado\nmercado.\nGerencie os projetos para que o cliente obtenha os melhores e os resultados da qualidade dentro do tempo. CONTATO\nTelefone: +92 3354059293\nE -mail: mzunair60@gmail.com\nBlog: zunair.medium.com\nEndereço: Sociedade de Valencia,\nLahore.\nJava, C#, programação C ++\nWeb e desenvolvimento móvel\nDesenvolvimento funcional cruzado\nDesenvolvimento de Conteúdo da Web\nSdlc\nDocumentationProfessional\nHABILIDADES\nNavigador de vendas\nAeroleads\nSalesforce\nKrayin CRM\nUpwork\nTrello\nJira\nAsana\nNetbeans\nVisual Studio\nUnidade\nAndroid Studioplatforms &\nFerramentas u h a m m a d m u h a m m a d\nZ u n a i r z u n a i rprojects\nEtradn é um aplicativo disponível na App Store e no Google Play. É um mercado online\nApp.\nO aplicativo pertence a um cliente baseado nos EUA e recebeu este projeto da Upwork.\nAs tecnologias usadas são vibração, figma, php, laravel, trello e github.\nTabadol é um aplicativo de mercado on -line com suporte de múltiplos idiomas para compra e\nServiços e bens de venda.\nTrabalhou com equipe, incluindo um líder de equipe, 4 desenvolvedores e 2 engenheiros de controle de qualidade.\nMonitorando os sistemas existentes. Garantir que o sistema forneça um funil eficaz. Desenvolvido\ne implementou técnicas de marketing.\nAs tecnologias usadas são reagir nativas, redux, node.js, react.js, react-i18next, momento.js,\nAxios.\nÉ um aplicativo, assim como o Club House desenvolvido para dispositivos iOS. O aplicativo inclui simples\nNo entanto, a interface do usuário atraente com funcionalidades minimalistas.\nAs tecnologias usadas são rápidas, iOS SDK.\nÉ o jogo de cassino online da loteria.\nServiço amigável em compatibilidade com navegadores da Web, tablets e telefones celulares.\nLaravel, JavaScript, JQuery, JQuery Ui, Moment.js, React.js, Git, etc.\nAplicação funcional cruzada para iOS e Android. Um aplicativo de compras on -line.\nTecnologias usadas são vibração, flagelo sdk, fixação de vibração, arquivo pubspec, recarga a quente, devtools,\nHtml, figma e git.etradn\nTabadol\nFale fácil\nOCG\nNovo TempusProposal & E -mail escrevendo\nForte analítico e \nComunicação\nSolucionador de problemas\nBoas habilidades de análise de negócios\nGerenciamento de tempo\nJogador de equipe\nAprendiz rápido \nHABILIDADES\nProjetos e trabalho de pesquisa\nUi/ ux\nAnimação\nScript\nAndroid Studio\nAndroid SDK\nSQL\nPesquisa sobre novas tendências usando o reconhecimento de texto\nTécnicas e ferramentas usadas\nComunicação com a pessoa de recursos e membros da equipe em primeira pessoa atirando em jogo 3D\nAplicativo de atendimento on -line\nArtigo de pesquisa sobre reconhecimento de texto",
  "details": {
    "name": "Muhammad Zunair",
    "number": "923354059293",
    "skills": [
      "Java",
      "C#",
      "C ++",
      "Web e desenvolvimento móvel",
      "Desenvolvimento funcional cruzado",
      "Desenvolvimento de Conteúdo da Web",
      "Sdlc",
      "Documentação",
      "Navigador de vendas",
      "Aeroleads",
      "Salesforce",
      "Krayin CRM",
      "Upwork",
      "Trello",
      "Jira",
      "Asana",
      "Netbeans",
      "Visual Studio",
      "Unidade",
      "Android Studio",
      "SQL"
    ],
    "email_id": "mzunair60@gmail.com",
    "location": "Sociedade de Valencia, Lahore",
    "projects": [
      {
        "title": "Etradn",
        "description": "Um aplicativo de mercado on -line disponível na App Store e no Google Play."
      },
      {
        "title": "Tabadol",
        "description": "Um aplicativo de mercado on -line com suporte de múltiplos idiomas para compra e venda de serviços e bens."
      },
      {
        "title": "Fale fácil",
        "description": "Um aplicativo desenvolvido para dispositivos iOS com interface do usuário simples e atraente."
      },
      {
        "title": "OCG",
        "description": "Um jogo de cassino online da loteria."
      },
      {
        "title": "Novo Tempus",
        "description": "Um aplicativo multifuncional para iOS e Android, um aplicativo de compras on-line."
      }
    ],
    "education": [
      {
        "end_date": "06-2020",
        "university": "Universidade de Gerenciamento e Tecnologia",
        "degree_title": "Bacharel em Engenharia de Software"
      }
    ],
    "achievements": [],
    "publications": [],
    "certifications": [],
    "additional_urls": [
      {
        "url": "zunair.medium.com",
        "website_name": "Blog"
      }
    ],
    "executive_summary": "Muhammad Zunair é um engenheiro de software qualificado, com uma forte experiência em desenvolvimento da Web e móveis, proficiente em várias linguagens e ferramentas de programação. Ele demonstrou experiência em desenvolvimento de negócios e gerenciamento de projetos, liderando com sucesso as equipes e gerenciando orçamentos significativos para atingir as metas do projeto.",
    "employment_history": [
      {
        "details": "Identifique tendências e insights com o gerenciamento do site da organização, as plataformas de mídia social e mantenha -as, mantendo as melhores práticas em mente. Otimize o conteúdo para o site e as plataformas de mídia social. Trabalhe com vários formatos de conteúdo, como blogs, vídeos, design gráfico etc. Forneça relatórios internos e colaborações criativas entre tecnologias e plataformas.",
        "end_date": "10-2020",
        "location": "Tecnologia Ozi",
        "job_title": "Executivo de marketing digital",
        "start_date": "01-2020",
        "company_name": "Tecnologia Ozi"
      },
      {
        "details": "Gerenciou com sucesso milhões de projetos orçamentários e alcançou as metas agendadas do projeto. Implementação e gerenciamento do CRM focado em alavancar o ativo de dados da empresa. Os leads práticos de geração e gerenciamento usando o Salesforce, o LinkedIn Sales Navigator, a Aeroleads etc. alcançaram as metas de vendas, apresentando serviços da empresa a clientes atuais e potenciais nos EUA, Austrália e Europa. Desenvolvi e implementou novos planos de marketing e vendas, como serviços remotos, campanhas de marketing etc. Escrever e projetar e -mails e garantir a entrega de email adequada aos leads. Trabalhe em estreita colaboração com desenvolvedores e engenheiros de controle de qualidade para garantir a qualidade e os padrões do projeto. Intensidade especializada em vendas, parcerias e desenvolvimento de negócios nas principais empresas de tecnologia B2B. Revisou constantemente o feedback do cliente e depois sugeriu maneiras de melhorar o processo e os níveis de atendimento ao cliente. Garantiu que novos clientes se transformassem em uma base de clientes fiel em um mercado de nicho especializado. Gerencie os projetos para que o cliente obtenha os melhores e os resultados da qualidade dentro do tempo.",
        "end_date": "Presente",
        "location": "Soluções Shayan",
        "job_title": "Gerente de Desenvolvimento de Negócios",
        "start_date": "10-2020",
        "company_name": "Soluções Shayan"
      }
    ]
  }
}