{
  "job_description": "### Executivo de Desenvolvimento de Negócios\n\n** Empresa: ** Innovate Dynamics Ltd.\n\n** Localização: ** Hyderabad, Índia\n\n** Visão geral da função: **\nParticipe da Innovate Dynamics Ltd. como executivo de desenvolvimento de negócios, onde você desempenhará um papel fundamental na condução do crescimento dos negócios, gerando leads e gerenciando as principais contas do cliente. Aproveite sua experiência em análise econômica e estratégias de marketing para aprimorar nossa presença no mercado e criar relacionamentos fortes dos clientes.\n\n** Responsabilidades: **\n- Desenvolver e executar planos abrangentes de desenvolvimento de negócios para alcançar os objetivos da empresa.\n- Identifique e envolva clientes em potencial em diversos nichos, incluindo desenvolvimento e terceirização de software.\n- Gerenciar e aumentar as relações com as principais contas para impulsionar o sucesso a longo prazo.\n- Utilize estratégias de marketing digital para aumentar o envolvimento e a retenção do cliente.\n- Colabore com equipes multifuncionais para desenvolver soluções de clientes personalizados.\n- Utilize o LinkedIn Sales Navigator para identificar e abordar novos leads de negócios.\n\n** Qualificações: **\n- Bacharel em Administração de Empresas, Economia ou Campo Relacionado.\n- 3-5 anos de experiência em desenvolvimento de negócios ou campos relacionados.\n- Forte proficiência com as ferramentas de MS Office Suite e Análise de Dados como o STATA.\n- Excelentes habilidades de comunicação verbal e escrita.\n- Capacidade de multitarefa e gerenciar vários projetos simultaneamente.",
  "additional_info": "A Innovate Dynamics Ltd. prioriza os candidatos de universidades de primeira linha, como [University X] e [University Y]. A assistência à realocação está disponível para candidatos dispostos a se mudar para Hyderabad. As habilidades técnicas são avaliadas através de testes padronizados e uma série de entrevistas. Nossa empresa incentiva a diversidade e a inclusão no processo de contratação.",
  "resume": "Izma bint-e-atif\nAnalista de negócios\nPensamento crítico\nManter confidencialidade\nControle de qualidade\nDistribuição\nHabilidades organizacionais\nSolução de problemas\nAnálise Estatística\nComunicação verbal/virtual\nFortes habilidades analíticas\nAuxiliar de gerenciamento de produtos técnicos\nDesigningskills de circuito+92 331 0483113\nCasa nº 530, Bloco J3, Johar\nTown, Lahore izma.b.atif@gmail.com Antecedentes Trabalhando com clientes internos e externos para reunir\ne providenciar requisitos, fornecer análise, auxiliar na criação de usuário\ninterfaces e desenvolva prazos de implementação em ambiente ágil.\nBuscando uma oportunidade desafiadora, onde poderei utilizar meu\nfortes habilidades organizacionais, formação educacional e capacidade de trabalhar\nbem com as pessoas, o que me permitirá crescer pessoalmente e\nPerfil profissionalmente de carros\nEXPERIÊNCIAS\nNextbridge Unip. Ltd. \nRed Communication Arts Pvt. LTD2021 - Presente\n2020 - 2021 Business Development Executive\nConduzir análises de mercado para as linhas de produtos e para o geral\nlucratividade do negócio\nAuxiliar no planejamento e execução dos planos de teste para integração\ne teste de processo, incluindo o aumento de logs de falhas.\nDesenvolva conceitos de projeto e mantenha o fluxo de trabalho ideal.\nComunicação forte e habilidades interpessoais para construir significativas\nrelacionamentos com clientes. \nAtenção aos detalhes para aprimorar cada tarefa necessária. \nTomada de decisão avançada e habilidades de solução de problemas.\nAnalista de negócios júnior\nAnalisar e priorizar os requisitos do cliente. \nTraduzir os requisitos do cliente em resumos de projeto especificados por\nEntendendo o ciclo de vida do desenvolvimento de software.\nTrabalhando diretamente com usuários/clientes e entendendo problemas de negócios,\nEstabelecendo solução e apresentando de volta às principais partes interessadas\nCriando uma análise de negócios detalhada, descrevendo problemas, oportunidades\ne soluções para um negócio\nAnálise de processo e produção de artefato acordado adequado para internos\nuse e/ou revisão do cliente e assinatura.educação\nFastNuces2020 - Bacharel em\nEngenharia Elétrica\nQueen Mary College for Women2015 - FSC pré -engenharia\nEscola do Convento do Coração Sagrado2013 - MatriculationBalsamiq \nMatlab \nCAD automático\nSketchup \nSoftware do Visual Studio \nProjetos\nImpressora 3D com mecanismo cartesiano (FYP) \nProjetou uma impressora 3D com mecanismo cartesiano usando deposição fundida\nTecnologia de modelagem (FDM) seguindo o método de fabricação aditiva. \nInglês\nUrdulanguagesmicrosoft Office \nLinguagens de programação (c ++, c, linguagem de montagem,\nOOP) \nSQL \nProjeto de circuito, plc\nPrograma de gerenciamento hospitalar\nProjetou um código OPD (departamento de paciente ao ar livre) em C ++.\nReferências\nPode ser fornecido mediante necessidade. Desenvolvimento de negócios\nAnálise de negócios \nLiderança \nSolução de problemas \nNegociação \nPensador crítico \nCompetências de Habilidades de Apresentação e Negociação de Apresentação e Negociação\nViajando\nEsportes \nEscrita \nAssistindo a filmes interincores e\nHobbies",
  "details": {
    "name": "Izma bint-e-atif",
    "number": "923310483113",
    "skills": [
      "Projeto de circuito",
      "Balsamiq",
      "Matlab",
      "CAD automático",
      "Sketchup",
      "Visual Studio",
      "C ++",
      "C",
      "Linguagem de montagem",
      "OOP",
      "SQL",
      "Plc"
    ],
    "email_id": "izma.b.atif@gmail.com",
    "location": "Casa nº 530, Bloco J3, Johar Town, Lahore",
    "projects": [
      {
        "title": "Impressora 3D com mecanismo cartesiano",
        "description": "Projetou uma impressora 3D com mecanismo cartesiano usando a tecnologia de modelagem de deposição fundida (FDM) seguindo o método de fabricação aditiva."
      },
      {
        "title": "Programa de gerenciamento hospitalar",
        "description": "Projetou um código OPD (departamento de paciente ao ar livre) em C ++."
      }
    ],
    "education": [
      {
        "end_date": "06-2020",
        "university": "FastNuces",
        "degree_title": "Bacharel em Engenharia Elétrica"
      },
      {
        "end_date": "06-2015",
        "university": "Queen Mary College for Women",
        "degree_title": "FSC pré -engenharia"
      },
      {
        "end_date": "06-2013",
        "university": "Escola de Convento do Coração Sagrado",
        "degree_title": "Matrícula"
      }
    ],
    "achievements": [],
    "publications": [],
    "certifications": [],
    "additional_urls": [
      {
        "url": "LinkedIn.com/in/izma-bint-e-atif",
        "website_name": "LinkedIn"
      }
    ],
    "executive_summary": "A IZMA Bint-E-ATIF é um analista de negócios qualificado com uma forte experiência em engenharia elétrica e vasta experiência em análise de mercado, gerenciamento de projetos e desenvolvimento de software. Ela demonstrou proficiência em várias linguagens de programação e ferramentas de software, contribuindo para resultados bem -sucedidos de projetos em ambientes ágeis. Sua experiência técnica é complementada por sua capacidade de comunicar e colaborar efetivamente com clientes e partes interessadas.",
    "employment_history": [
      {
        "details": "Realize análises de mercado para as linhas de produtos e a lucratividade geral dos negócios. Auxiliar no planejamento e execução dos planos de teste para integração e teste de processo, incluindo o aumento de logs de falhas. Desenvolva conceitos de projeto e mantenha o fluxo de trabalho ideal.",
        "end_date": "Presente",
        "location": "Nextbridge Unip. Ltd.",
        "job_title": "Executivo de Desenvolvimento de Negócios",
        "start_date": "01-2021",
        "company_name": "Nextbridge Unip. Ltd."
      },
      {
        "details": "Analisar e priorizar os requisitos do cliente. Traduzir os requisitos do cliente em resumos especificados do projeto, compreendendo o ciclo de vida do desenvolvimento de software. Trabalhando diretamente com usuários/clientes e compreendendo problemas de negócios, estabelecendo solução e apresentando de volta às principais partes interessadas. Criando uma análise de negócios detalhada, descrevendo problemas, oportunidades e soluções para um negócio. Análise de processo e produção de artefato acordado adequado para uso interno e/ou revisão e assinatura do cliente.",
        "end_date": "12-2021",
        "location": "Red Communication Arts Pvt. Ltd.",
        "job_title": "Analista de negócios júnior",
        "start_date": "01-2020",
        "company_name": "Red Communication Arts Pvt. Ltd."
      }
    ]
  }
}