{
  "job_description": "## Generação de leads e especialista em inteligência de negócios\n\nJunte -se a ** Innovate Connections Inc. ** Como uma geração de leads e especialista em inteligência de negócios. Você desempenhará um papel fundamental na condução do crescimento dos negócios, liderando iniciativas de geração de leads e fornecendo informações estratégicas por meio da análise de dados. Estamos à procura de um profissional altamente qualificado, com uma forte experiência em geração de leads, gerenciamento de dados e inteligência de negócios.\n\n### Responsabilidades -chave:\n- Desenvolva e execute estratégias de geração de leads usando técnicas de marketing digital, chamadas a frio e ferramentas de raspagem de dados.\n- Colabore com equipes multifuncionais para otimizar estratégias de aquisição de clientes.\n- Utilize sistemas de CRM para gerenciar e analisar os dados do cliente para obter a qualificação do lead.\n- Crie e gerencie cronogramas e planos de trabalho detalhados, utilizando as melhores práticas e padrões para a execução do projeto.\n- Desenvolva modelos financeiros e estratégias de crescimento de negócios com base em insights de dados.\n- Utilize ferramentas como Power BI, SQL e Tableau para desenvolver relatórios e painéis abrangentes de dados.\n\n### Habilidades e experiência desejadas:\n- Fortes habilidades de programação em C ++, HTML e CSS.\n- Proficiência em plataformas de marketing digital, marketing por e -mail e mídia social.\n- Experiência no gerenciamento de grandes conjuntos de dados e no uso de ferramentas de BI (Power BI, Excel, Tableau).\n- Excelentes habilidades de comunicação e capacidade de desenvolver relacionamentos fortes do cliente.\n- Capacidade de trabalhar de forma independente e gerenciar vários projetos simultaneamente.\n\n### Por que a Inovate Connections Inc.?\n- Innovamos na vanguarda da tecnologia e permitimos que os membros da nossa equipe cresçam ao lado da empresa.\n-Valorizamos a tomada de decisão orientada a dados e capacitamos nossas equipes com as ferramentas certas para ter sucesso.\n- Oferecendo um ambiente de trabalho de apoio e oportunidades de avanço na carreira.\n\n### Como se inscrever:\nEnvie seu currículo e carta de apresentação detalhando sua experiência relevante e por que você está interessado em ingressar na Innovate Connections Inc.",
  "additional_info": "A Innovate Connections Inc. prefere candidatos de universidades reconhecidas, como a Universidade de Gerenciamento e Tecnologia e a Lahore School of Economics. Incentivamos um ambiente de trabalho remoto, mas exige presença física para sessões de construção de equipes e estratégicas duas vezes por trimestre. A assistência à realocação está disponível para candidatos excepcionais. Nossa avaliação abrangente inclui um teste técnico seguido de entrevistas estruturadas para avaliar as habilidades técnicas e sociais de forma abrangente.",
  "resume": "Shahrukh Ali\nshahrukh.ali@descon.com 4618452\nLinkedIn.com/in/shahrukh-ali-3021ab24a\nResumo\nUm executivo de desenvolvimento de negócios altamente motivado e orientado a resultados, que também serviu como finanças &\nContas profissionais com 12 anos de experiência inestimável, incluindo ser qualificado em vários negócios\nCampos de desenvolvimento, financeiro e contábil. Eu tenho a capacidade de lidar com atribuições complexas de maneira eficaz e\nPossuindo a confiança para trabalhar como parte de uma equipe ou de forma independente. Uma reputação estabelecida de auto-\nMotivação, atenção aos detalhes excelentes habilidades organizacionais e alta conduta ética. Atualmente procurando o\nMelhor oportunidade com uma empresa orientada a objetivos, onde posso me destacar, entregar e alcançar de acordo com o meu potencial. EU\nEstou entusiasmado em aprender profundamente sobre desenvolvimentos emergentes em meu setor de trabalho.\nExperiência\nAssociado sênior\nKPMG no Paquistão\nAgosto de 2021 - fevereiro de 2022 (7 meses)\nSupervisão da equipe e treinamento\nAnalista de entrada de dados: Atualize o sistema conforme as faturas são recebidas.\nAnalista de pagamento bancário: Contas de processamento e pagamentos recebidos em conformidade.\nSAP ERP\nOráculo\nPolíticas e procedimentos financeiros.\nAnalista de exceções: abordar disputas e problemas de falha de pagamento.\nAnalista de manutenção de fornecedores: mantenha um banco de dados de fornecedor preciso.\nAnalista de finanças: realizando transações financeiras diárias, incluindo verificação, classificação,\nDados de computação, postagem e registro de contas a receber\nExecutivo de Desenvolvimento de Negócios\nInspecion (Private) Limited\nFevereiro de 2022 - presente (7 meses +)\nContabilidade, finanças e receita de desenvolvimento de negócios\nRelações com o cliente\nNegociação de clientes\nExecutivo de contas\nDescon Engineering Limited\nAgosto de 2009 - 2021 de julho (12 anos)\nAnalista de entrada de dados: Atualize o sistema conforme as faturas são recebidas.\nAnalista de pagamento bancário\nSAP ERP\nOráculo\nPolíticas e procedimentos financeiros.\nAnalista de exceções: abordar disputas e problemas de falha de pagamento.\nShahrukh Ali - Analista de manutenção do fornecedor: Mantenha um banco de dados de fornecedor preciso.\nAnalista de finanças: realizando transações financeiras diárias, incluindo verificação, classificação,\nDados de computação, postagem e registro de contas a receber\nEducação\nUniversidade de Punjab Central\nMBA\nUniversidade de Hajvery\nBacharel em Comércio\nHabilidades\nAbacus • Contabilidade • Contas a receber • ACCPAC • Análise • Lei de Negócios • CEO •  \nConsultoria • Entrada de dados • Administração de banco de dados\nShahrukh Ali - Página 2",
  "details": {
    "name": "Shahrukh Ali",
    "number": "4618452",
    "skills": [
      "SAP ERP",
      "Oráculo",
      "ábaco",
      "contabilidade",
      "contas a receber",
      "Accpac",
      "entrada de dados",
      "Administração de banco de dados"
    ],
    "email_id": "shahrukh.ali@descon.com",
    "location": "",
    "projects": [],
    "education": [
      {
        "end_date": "06-2010",
        "university": "Universidade de Hajvery",
        "degree_title": "Bacharel em Comércio"
      },
      {
        "end_date": "06-2012",
        "university": "Universidade de Punjab Central",
        "degree_title": "MBA"
      }
    ],
    "achievements": [],
    "publications": [],
    "certifications": [],
    "additional_urls": [
      {
        "url": "LinkedIn.com/in/shahrukh-ali-3021ab24a",
        "website_name": "LinkedIn"
      }
    ],
    "executive_summary": "Shahrukh Ali é um executivo de desenvolvimento de negócios altamente motivado e orientado a resultados, com 12 anos de experiência inestimável em desenvolvimento de negócios, finanças e contabilidade. Ele possui fortes habilidades técnicas no SAP ERP e Oracle e possui um histórico comprovado em lidar com atribuições complexas de maneira eficaz.",
    "employment_history": [
      {
        "details": "Supervisão e treinamento da equipe, analista de entrada de dados: Atualize o sistema conforme as faturas são recebidas, analista de pagamento bancário: processamento de contas e pagamentos recebidos em conformidade, analista de exceções: abordagem de disputas e problemas de falha de pagamento, analistas de manutenção de fornecedores: Manter um banco de dados de dados, com realização de transações financeiras, incluindo a classificação, a classificação, a classificação precisa, a classificação precisa.",
        "end_date": "02-2022",
        "location": "Paquistão",
        "job_title": "Associado sênior",
        "start_date": "08-2021",
        "company_name": "KPMG no Paquistão"
      },
      {
        "details": "Contabilidade, finanças e receita de desenvolvimento de negócios, relações com clientes, negociação de clientes.",
        "end_date": "",
        "location": "",
        "job_title": "Executivo de Desenvolvimento de Negócios",
        "start_date": "02-2022",
        "company_name": "Inspecion (Private) Limited"
      },
      {
        "details": "Analista de entrada de dados: Atualize o sistema conforme as faturas são recebidas, analista de pagamento bancário, analista de exceções: abordagem de disputas e problemas de falha de pagamento, analista de manutenção de fornecedores: mantenha um banco de dados preciso do fornecedor, analista de finanças: executando transações financeiras diárias, incluindo a verificação, classificação, computação e registro de contas de contas de contas.",
        "end_date": "07-2021",
        "location": "",
        "job_title": "Executivo de contas",
        "start_date": "08-2009",
        "company_name": "Descon Engineering Limited"
      }
    ]
  }
}