{
  "job_description": "## Generação de leads e especialista em inteligência de negócios\n\nJunte -se a ** Innovate Connections Inc. ** Como uma geração de leads e especialista em inteligência de negócios. Você desempenhará um papel fundamental na condução do crescimento dos negócios, liderando iniciativas de geração de leads e fornecendo informações estratégicas por meio da análise de dados. Estamos à procura de um profissional altamente qualificado, com uma forte experiência em geração de leads, gerenciamento de dados e inteligência de negócios.\n\n### Responsabilidades -chave:\n- Desenvolva e execute estratégias de geração de leads usando técnicas de marketing digital, chamadas a frio e ferramentas de raspagem de dados.\n- Colabore com equipes multifuncionais para otimizar estratégias de aquisição de clientes.\n- Utilize sistemas de CRM para gerenciar e analisar os dados do cliente para obter a qualificação do lead.\n- Crie e gerencie cronogramas e planos de trabalho detalhados, utilizando as melhores práticas e padrões para a execução do projeto.\n- Desenvolva modelos financeiros e estratégias de crescimento de negócios com base em insights de dados.\n- Utilize ferramentas como Power BI, SQL e Tableau para desenvolver relatórios e painéis abrangentes de dados.\n\n### Habilidades e experiência desejadas:\n- Fortes habilidades de programação em C ++, HTML e CSS.\n- Proficiência em plataformas de marketing digital, marketing por e -mail e mídia social.\n- Experiência no gerenciamento de grandes conjuntos de dados e no uso de ferramentas de BI (Power BI, Excel, Tableau).\n- Excelentes habilidades de comunicação e capacidade de desenvolver relacionamentos fortes do cliente.\n- Capacidade de trabalhar de forma independente e gerenciar vários projetos simultaneamente.\n\n### Por que a Inovate Connections Inc.?\n- Innovamos na vanguarda da tecnologia e permitimos que os membros da nossa equipe cresçam ao lado da empresa.\n-Valorizamos a tomada de decisão orientada a dados e capacitamos nossas equipes com as ferramentas certas para ter sucesso.\n- Oferecendo um ambiente de trabalho de apoio e oportunidades de avanço na carreira.\n\n### Como se inscrever:\nEnvie seu currículo e carta de apresentação detalhando sua experiência relevante e por que você está interessado em ingressar na Innovate Connections Inc.",
  "additional_info": "A Innovate Connections Inc. prefere candidatos de universidades reconhecidas, como a Universidade de Gerenciamento e Tecnologia e a Lahore School of Economics. Incentivamos um ambiente de trabalho remoto, mas exige presença física para sessões de construção de equipes e estratégicas duas vezes por trimestre. A assistência à realocação está disponível para candidatos excepcionais. Nossa avaliação abrangente inclui um teste técnico seguido de entrevistas estruturadas para avaliar as habilidades técnicas e sociais de forma abrangente.",
  "resume": "Syed Ali Sher Rizvi \nGerente de Desenvolvimento de Negócios \nUm profissional organizado e criativo com habilidades de marketing comprovadas e um desejo de aprender mais. Possuir\nMais de 4 anos de experiência trabalhando para um grupo diversificado de organizações e clientes. Ganhou experiência em dados\nAnálise, marketing de publicação e publicidade baseada na Web. Procurando utilizar meu conjunto de habilidades existentes para\nAumentar a lucratividade da empresa na SPLEEN MANUFACTURAÇÃO (PVT) LTD. \nsahibzadaali66@gmail.com \n03015062755 \nLahore, Paquistão \nLinkedIn.com/in/syed-ali-hair-rizvi-7bb859171 \nExperiência de trabalho \nGerente de Desenvolvimento de Negócios \nFeliztanent \n01/2022 - presente\n, Assim, \n \nLahore/Dubai, Emirados Árabes Unidos \nHappytenant é uma empresa base dos Emirados Árabes Unidos, estou trabalhando aqui (remotamente) para desenvolver seus\nNegócios no Paquistão, EUA e Emirados Árabes Unidos também. \nDefinindo metas e desenvolvendo planos para negócios e receita\ncrescimento. \nPlanejando e supervisionando novas iniciativas de marketing. \nAumentando o valor dos clientes atuais enquanto atrai novos\nuns. \nParticipando de conferências, reuniões e eventos do setor. \nCoordenador de mídia social \nCarrinho de minoras \n01/2022 - presente\n, Assim, \n \nLahore/Dubai, Emirados Árabes Unidos \nhttps://www.minoracart.com/ \nAnalisou e relatou presença de mídia social, engajamento e\neficiência em todas as plataformas \nEnvolvido em interações consistentes com clientes, doadores e fãs \nDoubled Website Trafil de 15.000 visitantes médios para 31.000 \nAsst. Gerente Marketing \nSPLEEN MANUFACTURAÇÃO (PVT) LTD 08/2018 - Presente, \n10/2018 - 02/2022\n, Assim, \n \nLahore, Paquistão \nFornecendo soluções de engenharia para todos os tipos de fabricações leves e pesadas \nCampanhas de ponta de lança com sucesso em plataformas de mídia social\nincluindo Facebook, Twitter e Instagram \nContato \n:\n-\nRana Shahbaz Ahmed (cabeça BD & Marketing) \n0300 8463927 \nEDUCAÇÃO \nMSC Marketing \nColagem Nacional de Administração de Empresas e\nEconomia \n2020 - presente\n, Assim, \n \nLahore. Paquistão \nTerceirização global \nGerenciamento de contratos \nEmpreendedorismo \nGerenciamento Final \nBacharel em Comércio \nUniversidade de Punjab \n12/2016 - 05/05/2018\n, Assim, \n \nLahore Paquistão \nHABILIDADES \nMS OFICE \nZoho CRM \nMailChimp \nNegociação \nCapacidade de se envolver \nExcelente comunicação verbal e escrita \nCapacidade de persuadir \nMarketing por e -mail \nGeração de chumbo \nNavigador de vendas \nSignalhire \nApollo.io \nBUFE \nPublicidade digital \nRealizações \nCurso de marketing digital do PNY Institute\n (09/2021)\n \nMarketing de mídia social, palavras de anúncio do Google, SMM, celular\nMarketing \nGerenciamento da Huawei\n (2018 - presente)\n \nPortal Huawei de manuseio completo \ntotalmente coordenado com sua equipe para\ncontratos recentes e negociação futura em cotractos \nERP (SARP) \nSoftware ERP de manipulação completa e tem consciência suficiente que pode\nlidar com cada departamento através dele. \nAchiever do ano (fabricação de baço)\n (2019 - 2020)\n \nProjetos da empresa \nCarrinho de minoras\n (06/2022 - presente)\n \nAnúncio de mídia social \nNome do projeto \nDelux - Serviços de Controle de Pragas\n (12/2022 - presente)\n \nMarketing de mídia social (baixo CPC - Altas conversões) \n220 KV DHABJI LINHA DE PROJETOS DE LINHA\n (09/2021 - 11/2021)\n \nProjetos da Huawei (CMPAK, Jazz, Ufone Telenor)\n (02/2021 - presente)\n \nCertificados \nMarketing digital\n (2021 - presente)\n \nMarketing do YouTube\n (2021 - presente)\n \nRealizações/tarefas \nRealizações/tarefas \nRealizações/tarefas \nCursos",
  "details": {
    "name": "Syed Ali Sher Rizvi",
    "number": "03015062755",
    "skills": [
      "MS Office",
      "Zoho CRM",
      "MailChimp",
      "Marketing por e -mail",
      "Geração de chumbo",
      "Navigador de vendas",
      "Signalhire",
      "Apollo.io",
      "Buffer",
      "Publicidade digital"
    ],
    "email_id": "sahibzadaali66@gmail.com",
    "location": "Lahore, Paquistão",
    "projects": [
      {
        "title": "Carrinho de minoras",
        "description": "Anúncio de mídia social"
      },
      {
        "title": "Delux - Serviços de Controle de Pragas",
        "description": "Marketing de mídia social (baixo CPC - Altas conversões)"
      },
      {
        "title": "220 KV DHABJI LINHA DE PROJETOS DE LINHA",
        "description": ""
      },
      {
        "title": "Projetos da Huawei (CMPAK, Jazz, Ufone Telenor)",
        "description": ""
      }
    ],
    "education": [
      {
        "end_date": "05-2018",
        "university": "Universidade de Punjab",
        "degree_title": "Bacharel em Comércio"
      },
      {
        "end_date": "Presente",
        "university": "Colagem Nacional de Administração de Empresas e Economia",
        "degree_title": "MSC Marketing"
      }
    ],
    "achievements": [
      "Curso de marketing digital do PNY Institute (09-2021)",
      "Achiever of the Year (Manufacturing) (2019 - 2020)"
    ],
    "publications": [],
    "certifications": [
      {
        "certification_name": "Marketing digital",
        "issuing_organization": "Não especificado",
        "date_of_issuance": "2021"
      },
      {
        "certification_name": "Marketing do YouTube",
        "issuing_organization": "Não especificado",
        "date_of_issuance": "2021"
      }
    ],
    "additional_urls": [
      {
        "url": "LinkedIn.com/in/syed-ali-hair-rizvi-7bb859171",
        "website_name": "LinkedIn"
      }
    ],
    "executive_summary": "Syed Ali Sher Rizvi é gerente de desenvolvimento de negócios com mais de 4 anos de experiência em estratégias de marketing e crescimento de negócios. Ele tem uma forte formação em análise de dados, marketing de publicação e publicidade baseada na Web e atualmente está focada em melhorar a lucratividade para a Sleen Manufacturing (PVT) Ltd.",
    "employment_history": [
      {
        "details": "Desenvolvimento de negócios no Paquistão, EUA e Emirados Árabes Unidos, estabelecendo metas e desenvolvendo planos para crescimento de negócios e receita.",
        "end_date": "Presente",
        "location": "Lahore/Dubai, Emirados Árabes Unidos",
        "job_title": "Gerente de Desenvolvimento de Negócios",
        "start_date": "01-2022",
        "company_name": "Feliztanent"
      },
      {
        "details": "Analisou e relatou presença, engajamento e eficácia da mídia social em todas as plataformas, dobrou o tráfego do site.",
        "end_date": "Presente",
        "location": "Lahore/Dubai, Emirados Árabes Unidos",
        "job_title": "Coordenador de mídia social",
        "start_date": "01-2022",
        "company_name": "Carrinho de minoras"
      },
      {
        "details": "Com êxito, liderou campanhas em plataformas de mídia social, incluindo Facebook, Twitter e Instagram.",
        "end_date": "02-2022",
        "location": "Lahore, Paquistão",
        "job_title": "Asst. Gerente Marketing",
        "start_date": "10-2018",
        "company_name": "SPLEEN MANUFACTURAÇÃO (PVT) LTD"
      }
    ]
  }
}