{
  "job_description": "## Título do trabalho: Especialista em gerenciamento de vendas e SEO  \n\n### Localização: Lahore, Paquistão  \n\n### Empresa: Innovate Digital Solutions Inc.  \n\nResumo do trabalho:  \nParticipe da Innovate Digital Solutions Inc. como especialista em gerenciamento de vendas e SEO. Você fará parte de uma equipe dinâmica responsável por impulsionar o envolvimento do cliente e garantir o desempenho ideal em estratégias de marketing digital. Sua função incluirá o gerenciamento do relacionamento com os clientes, a melhoria das estratégias de SEO e a liderança de sua equipe a atingir metas de vendas.  \n\n### Responsabilidades -chave:  \n- Envolva -se proativamente com clientes em potencial para entender suas necessidades de negócios e fornecer soluções inovadoras.  \n- Projete e execute estratégias de SEO em alinhamento com os objetivos de marketing do cliente.  \n- Gerenciar e otimizar as campanhas do PPC para maximizar o ROI e a visibilidade da marca.  \n- Desenvolva e mantenha um forte relacionamento com os clientes por meio de soluções de marketing personalizadas.  \n- Lidere uma equipe a alcançar e superar as metas de vendas, fornecendo um atendimento excepcional ao cliente.  \n- Analise as tendências e algoritmos do mercado para adaptar as estratégias de SEO de acordo.  \n- Produza relatórios que acompanham o progresso e medem o sucesso contra os KPIs.  \n\n### Perfil de candidato ideal:  \nVocê é um profissional qualificado de vendas e marketing, com fortes habilidades analíticas adequadas para identificar e executar oportunidades de SEO. Você se destaca nas interações do cliente, possuindo a capacidade de transformar possíveis leads em clientes satisfeitos por meio de iniciativas de marketing estratégicas e bem executadas. As habilidades de liderança e gerenciamento de equipes serão fundamentais para impulsionar as vendas e motivar sua equipe.  \n\n### benefícios:  \n- Pacote de salário competitivo  \n- Benefícios de saúde e bem -estar  \n- Bônus de desempenho  \n- Oportunidades de avanço na carreira  \n\nJunte -se a nós para redefinir o engajamento digital e liderar estratégias de mercado com agilidade e inovação.",
  "additional_info": "A Innovate Digital Solutions Inc. prefere candidatos de instituições respeitáveis ​​como [Universidade de Lahore], [Universidade de Punjab]. As opções de trabalho remotas estão disponíveis sujeitas a funções e responsabilidades. Avaliamos as habilidades por meio de uma combinação de testes técnicos, entrevistas e cenários de solução de problemas do mundo real para avaliar a competência prática em contextos estratégicos de marketing.",
  "resume": "Shahrukh Ali\nshahrukh.ali@descon.com 4618452\nLinkedIn.com/in/shahrukh-ali-3021ab24a\nResumo\nUm executivo de desenvolvimento de negócios altamente motivado e orientado a resultados, que também serviu como finanças &\nContas profissionais com 12 anos de experiência inestimável, incluindo ser qualificado em vários negócios\nCampos de desenvolvimento, financeiro e contábil. Eu tenho a capacidade de lidar com atribuições complexas de maneira eficaz e\nPossuindo a confiança para trabalhar como parte de uma equipe ou de forma independente. Uma reputação estabelecida de auto-\nMotivação, atenção aos detalhes excelentes habilidades organizacionais e alta conduta ética. Atualmente procurando o\nMelhor oportunidade com uma empresa orientada a objetivos, onde posso me destacar, entregar e alcançar de acordo com o meu potencial. EU\nEstou entusiasmado em aprender profundamente sobre desenvolvimentos emergentes em meu setor de trabalho.\nExperiência\nAssociado sênior\nKPMG no Paquistão\nAgosto de 2021 - fevereiro de 2022 (7 meses)\nSupervisão da equipe e treinamento\nAnalista de entrada de dados: Atualize o sistema conforme as faturas são recebidas.\nAnalista de pagamento bancário: Contas de processamento e pagamentos recebidos em conformidade.\nSAP ERP\nOráculo\nPolíticas e procedimentos financeiros.\nAnalista de exceções: abordar disputas e problemas de falha de pagamento.\nAnalista de manutenção de fornecedores: mantenha um banco de dados de fornecedor preciso.\nAnalista de finanças: realizando transações financeiras diárias, incluindo verificação, classificação,\nDados de computação, postagem e registro de contas a receber\nExecutivo de Desenvolvimento de Negócios\nInspecion (Private) Limited\nFevereiro de 2022 - presente (7 meses +)\nContabilidade, finanças e receita de desenvolvimento de negócios\nRelações com o cliente\nNegociação de clientes\nExecutivo de contas\nDescon Engineering Limited\nAgosto de 2009 - 2021 de julho (12 anos)\nAnalista de entrada de dados: Atualize o sistema conforme as faturas são recebidas.\nAnalista de pagamento bancário\nSAP ERP\nOráculo\nPolíticas e procedimentos financeiros.\nAnalista de exceções: abordar disputas e problemas de falha de pagamento.\nShahrukh Ali - Analista de manutenção do fornecedor: Mantenha um banco de dados de fornecedor preciso.\nAnalista de finanças: realizando transações financeiras diárias, incluindo verificação, classificação,\nDados de computação, postagem e registro de contas a receber\nEducação\nUniversidade de Punjab Central\nMBA\nUniversidade de Hajvery\nBacharel em Comércio\nHabilidades\nAbacus • Contabilidade • Contas a receber • ACCPAC • Análise • Lei de Negócios • CEO •  \nConsultoria • Entrada de dados • Administração de banco de dados\nShahrukh Ali - Página 2",
  "details": {
    "name": "Shahrukh Ali",
    "number": "4618452",
    "skills": [
      "SAP ERP",
      "Oráculo",
      "ábaco",
      "contabilidade",
      "contas a receber",
      "Accpac",
      "entrada de dados",
      "Administração de banco de dados"
    ],
    "email_id": "shahrukh.ali@descon.com",
    "location": "",
    "projects": [],
    "education": [
      {
        "end_date": "06-2010",
        "university": "Universidade de Hajvery",
        "degree_title": "Bacharel em Comércio"
      },
      {
        "end_date": "06-2012",
        "university": "Universidade de Punjab Central",
        "degree_title": "MBA"
      }
    ],
    "achievements": [],
    "publications": [],
    "certifications": [],
    "additional_urls": [
      {
        "url": "LinkedIn.com/in/shahrukh-ali-3021ab24a",
        "website_name": "LinkedIn"
      }
    ],
    "executive_summary": "Shahrukh Ali é um executivo de desenvolvimento de negócios altamente motivado e orientado a resultados, com 12 anos de experiência inestimável em desenvolvimento de negócios, finanças e contabilidade. Ele possui fortes habilidades técnicas no SAP ERP e Oracle e possui um histórico comprovado em lidar com atribuições complexas de maneira eficaz.",
    "employment_history": [
      {
        "details": "Supervisão e treinamento da equipe, analista de entrada de dados: Atualize o sistema conforme as faturas são recebidas, analista de pagamento bancário: processamento de contas e pagamentos recebidos em conformidade, analista de exceções: abordagem de disputas e problemas de falha de pagamento, analistas de manutenção de fornecedores: Manter um banco de dados de dados, com realização de transações financeiras, incluindo a classificação, a classificação, a classificação precisa, a classificação precisa.",
        "end_date": "02-2022",
        "location": "Paquistão",
        "job_title": "Associado sênior",
        "start_date": "08-2021",
        "company_name": "KPMG no Paquistão"
      },
      {
        "details": "Contabilidade, finanças e receita de desenvolvimento de negócios, relações com clientes, negociação de clientes.",
        "end_date": "",
        "location": "",
        "job_title": "Executivo de Desenvolvimento de Negócios",
        "start_date": "02-2022",
        "company_name": "Inspecion (Private) Limited"
      },
      {
        "details": "Analista de entrada de dados: Atualize o sistema conforme as faturas são recebidas, analista de pagamento bancário, analista de exceções: abordagem de disputas e problemas de falha de pagamento, analista de manutenção de fornecedores: mantenha um banco de dados preciso do fornecedor, analista de finanças: executando transações financeiras diárias, incluindo a verificação, classificação, computação e registro de contas de contas de contas.",
        "end_date": "07-2021",
        "location": "",
        "job_title": "Executivo de contas",
        "start_date": "08-2009",
        "company_name": "Descon Engineering Limited"
      }
    ]
  }
}