{
  "job_description": "### Executivo de Desenvolvimento de Negócios\n\n** Empresa: ** Innovate Dynamics Ltd.\n\n** Localização: ** Hyderabad, Índia\n\n** Visão geral da função: **\nParticipe da Innovate Dynamics Ltd. como executivo de desenvolvimento de negócios, onde você desempenhará um papel fundamental na condução do crescimento dos negócios, gerando leads e gerenciando as principais contas do cliente. Aproveite sua experiência em análise econômica e estratégias de marketing para aprimorar nossa presença no mercado e criar relacionamentos fortes dos clientes.\n\n** Responsabilidades: **\n- Desenvolver e executar planos abrangentes de desenvolvimento de negócios para alcançar os objetivos da empresa.\n- Identifique e envolva clientes em potencial em diversos nichos, incluindo desenvolvimento e terceirização de software.\n- Gerenciar e aumentar as relações com as principais contas para impulsionar o sucesso a longo prazo.\n- Utilize estratégias de marketing digital para aumentar o envolvimento e a retenção do cliente.\n- Colabore com equipes multifuncionais para desenvolver soluções de clientes personalizados.\n- Utilize o LinkedIn Sales Navigator para identificar e abordar novos leads de negócios.\n\n** Qualificações: **\n- Bacharel em Administração de Empresas, Economia ou Campo Relacionado.\n- 3-5 anos de experiência em desenvolvimento de negócios ou campos relacionados.\n- Forte proficiência com as ferramentas de MS Office Suite e Análise de Dados como o STATA.\n- Excelentes habilidades de comunicação verbal e escrita.\n- Capacidade de multitarefa e gerenciar vários projetos simultaneamente.",
  "additional_info": "A Innovate Dynamics Ltd. prioriza os candidatos de universidades de primeira linha, como [University X] e [University Y]. A assistência à realocação está disponível para candidatos dispostos a se mudar para Hyderabad. As habilidades técnicas são avaliadas através de testes padronizados e uma série de entrevistas. Nossa empresa incentiva a diversidade e a inclusão no processo de contratação.",
  "resume": "MBA 2023 Muhammad Kalim  \n+92-321-9474340 | mkalim70@gmail.com | www.linkedin.com/in/mkalim70  \n \nEducação   \nSciences da Universidade de Gerenciamento de Lahore Lahore, Paquistão  \nMestre em Administração de Empresas 2021 -2023  \nUniversidade do Punjab Lahore, Paquistão  \nBacharel em Ciências em Engenharia Química 2014-2018  \nHabilidades   \n \nVisualização de dados e relatórios Microsoft Office, Tableau  \nSoft Skills Comunicação eficaz, resolução de problemas e liderança  \nOutros SQL e R  \n \nExperiência de trabalho   \nAkzonobel Paquistão Lahore, Paquistão  \nConculadora de pesquisa de mercado: janeiro de 2023 - maio de 2023 \n- pesquisado, entrevistado e analisou os dados coletados sobre a demanda potencial para a marca Interpon de \nAkzonobel e os requisitos de revestimento em pó dos fabricantes de eletrônicos de consumo.  \n- Forneceu informações acionáveis ​​para Akzonobel sobre a exploração da vertical do revestimento em pó.  \nGrupo Fatima Lahore, Paquistão  \nEstagiário de vendas: julho de 2022 - agosto de 2022  \n- Desenvolveu planos de evacuação de emergência para dez grupos de Fátima armazéns localizados na zona norte do Paquistão para reduzir o \nIncidentes de segurança que podem afetar mais de 20 funcionários. Esta foi uma iniciativa combinada do departamento de vendas e corporativo  \nHSE.  \n- Realizou o treinamento dos 10 oficiais de armazém em colaboração com o Departamento de HSE para garantir a implementação do \nPlano de evacuação.  \n- Auditorias observadas e conduzidas das operações do armazém.  \nPak Elektron Limited Lahore, Paquistão  \nEstagiário de marketing: junho de 2022 - julho de 2022  \n- Liderou uma equipe de cinco pessoas a conduzir pesquisas sobre a redução das vendas de aparelhos PEL no principal aparelho \nmercado de Lahore e proposto soluções de possibilidades para melhorar as vendas.  \n- Realizou visitas de rotina aos varejistas para entender os desafios enfrentados pelos varejistas.  \n     Fauji Fertilizer bin Qasim Limited Karachi, Paquistão  \nAssociado de Gerenciamento (Operações: Utilitários): abril de 2019 - maio de 2020  \n- realizado em análise em profundidade da torre de resfriamento que resultou em uma economia de 14% em termos de dosagem química no resfriamento \ntorre.  A dose de produtos químicos na torre de resfriamento estava aumentando, o que era um ônus financeiro.  Para combater o problema \ndo aumento da dosagem, avaliou a condição da torre de resfriamento preenche e criou uma estratégia de substituição após alternativa \nano.  \n- Trabalhou como líder de turno, gerenciando uma equipe de 12 pessoas em campo, realizou tarefas de rotina, como a preparação de permissões de trabalho  \ne relatórios de atividades diárias de status e manutenção no SAP.  \n- Realizou negociações semanais de segurança com os operadores de turno sobre como executar tarefas de acordo com os princípios de HSE.  \n-Realizou sessões de treinamento para os 12 associados não administrados e 4 estagiários de verão.  \n \nTrabalho do projeto   \nLivro branco sobre o estabelecimento da marca de equipamentos esportivos locais  \n- Realizou pesquisas sobre o mercado de equipamentos esportivos locais e deu recomendações aos fabricantes de esportes locais \nDurante o aprendizado experimental de MBA -i. \n. \nCertificações e treinamento W O R K S H O P S  \n- Google Data Analytics Certificado por Coursera  \n- MBA Business Games 2023 (simulação de marketing estratégico por Markstrat) na LUMS  \n- Participou do treinamento da SAP Realizado pelos Serviços de TI pela FFCL (outubro de 2020)",
  "details": {
    "name": "Muhammad Kalim",
    "number": "923219474340",
    "skills": [
      "Visualização de dados e relatórios",
      "Microsoft Office",
      "Quadro",
      "SQL",
      "R"
    ],
    "email_id": "mkalim70@gmail.com",
    "location": "Lahore, Paquistão",
    "projects": [
      {
        "title": "Livro branco sobre o estabelecimento da marca de equipamentos esportivos locais",
        "description": "Realizou pesquisas sobre o mercado de equipamentos esportivos locais e deu recomendações aos fabricantes de esportes locais durante o aprendizado experimental de MBA -i."
      }
    ],
    "education": [
      {
        "end_date": "05-2023",
        "university": "Lahore University of Management Sciences",
        "degree_title": "Mestre em Administração de Empresas"
      },
      {
        "end_date": "05-2018",
        "university": "Universidade do Punjab",
        "degree_title": "Bacharel em Ciências em Engenharia Química"
      }
    ],
    "achievements": [],
    "publications": [],
    "certifications": [
      {
        "certification_name": "Google Data Analytics Certificado",
        "issuing_organization": "Coursera",
        "date_of_issuance": "01-2023"
      },
      {
        "certification_name": "MBA Business Games 2023 (simulação de marketing estratégico por Markstrat)",
        "issuing_organization": "Lums",
        "date_of_issuance": "01-2023"
      },
      {
        "certification_name": "Treinamento da SAP",
        "issuing_organization": "Serviços de TI por FFCL",
        "date_of_issuance": "10-2020"
      }
    ],
    "additional_urls": [
      {
        "url": "LinkedIn.com/in/mkalim70",
        "website_name": "LinkedIn"
      }
    ],
    "executive_summary": "Muhammad Kalim é um profissional qualificado, com uma forte experiência em visualização e relatórios de dados, proficiente em ferramentas como o Microsoft Office e o Tableau, além de programar linguagens SQL e R. Ele tem experiência em pesquisa de mercado e gerenciamento de operações, demonstrando um compromisso de fornecer insights acionáveis ​​e melhorar a eficiência operacional.",
    "employment_history": [
      {
        "details": "Pesquisou, entrevistou e analisou os dados coletados sobre a demanda potencial da marca Interpon de Akzonobel e os requisitos de revestimento em pó dos fabricantes de eletrônicos de consumo. Forneceu informações acionáveis ​​para Akzonobel sobre a exploração da vertical do revestimento em pó.",
        "end_date": "05-2023",
        "location": "Lahore, Paquistão",
        "job_title": "Consultor de pesquisa de mercado",
        "start_date": "01-2023",
        "company_name": "Akzonobel Paquistão"
      },
      {
        "details": "Desenvolveu planos de evacuação de emergência para dez grupos de Fátima armazéns localizados na zona norte do Paquistão para reduzir os incidentes de segurança que podem afetar mais de 20 funcionários. Conduziu o treinamento dos 10 oficiais de armazém em colaboração com o Departamento de HSE para garantir a implementação do plano de evacuação. Observou e conduziu auditorias das operações do armazém.",
        "end_date": "08-2022",
        "location": "Lahore, Paquistão",
        "job_title": "Estagiário de vendas",
        "start_date": "07-2022",
        "company_name": "Grupo Fátima"
      },
      {
        "details": "Liderou uma equipe de cinco pessoas a conduzir pesquisas sobre a redução das vendas de aparelhos PEL no mercado principal de eletrodomésticos de Lahore e propuseram possíveis soluções para melhorar as vendas. Conduziu visitas de rotina aos varejistas para entender os desafios enfrentados pelos varejistas.",
        "end_date": "07-2022",
        "location": "Lahore, Paquistão",
        "job_title": "Estagiário de marketing",
        "start_date": "06-2022",
        "company_name": "Pak Elektron Limited"
      },
      {
        "details": "Realizada em análise em profundidade da torre de resfriamento que resultou em uma economia de 14% em termos de dosagem química na torre de resfriamento. Trabalhou como líder de turno, gerenciando uma equipe de 12 pessoas em campo, realizou tarefas de rotina, como a preparação de permissões de trabalho e o relatório de atividades diárias de status e manutenção no SAP. Realizou negociações semanais de segurança com os operadores de turno sobre como executar tarefas de acordo com os princípios de HSE. Realizou sessões de treinamento para os 12 associados não-gerentes e 4 estagiários de verão.",
        "end_date": "05-2020",
        "location": "Karachi, Paquistão",
        "job_title": "Associado de Gerenciamento (Operações: Utilitários)",
        "start_date": "04-2019",
        "company_name": "Fauji Fertilizer bin Qasim Limited"
      }
    ]
  }
}