{
  "job_description": "### Gerente de contas -chave na Luxotech Solutions\n\n** Localização: ** Karachi, Paquistão\n\n** Departamento: ** Vendas e marketing\n\n** Relatórios para: ** Diretor de vendas\n\n** Visão geral da função: **\nJunte -se à Luxotech Solutions como gerente de contas importantes, onde você será responsável pelo gerenciamento das principais contas nos segmentos de varejo e hospitalidade em todo o Paquistão. Você impulsionará o crescimento das vendas, gerenciando contas existentes e desenvolvendo estratégias para novas contas. Sua função envolverá coordenar com equipes multifuncionais, analisar tendências do mercado e liderar iniciativas para cumprir as metas de receita.\n\nResponsabilidades ####:\n- Gerencie um portfólio de mais de 15 contas principais, compreendendo usuários finais e parceiros de canal.\n- Dirija a expansão para novos segmentos de mercado, identificando e se envolvendo com possíveis leads.\n- Desenvolva e execute estratégias de gerenciamento de contas para alcançar 110% de obtenção alvo de receita.\n- Utilize ferramentas de análise de dados, como o Power BI, para avaliar as tendências do mercado e gerar insights.\n- Coordenar com equipes internas, incluindo marketing e operações, para garantir o alinhamento estratégico.\n- Liderar negociações contratadas e gerenciar estratégias de preços para otimizar a lucratividade.\n- Relatório sobre o desempenho da conta e as oportunidades de mercado para a gerência sênior regularmente.\n\n#### habilidades essenciais:\n- Fortes habilidades de liderança e gerenciamento de partes interessadas.\n- Proficiência na análise de dados e previsão para informar a tomada de decisão.\n- Experiência em ferramentas como Salesforce, Vistex e SAP ERP para gerenciar funções de vendas.\n- Excelentes habilidades de comunicação para interações com clientes e colaborações internas.\n\n#### qualificações:\n- Mestre de preferência; É necessário um diploma de bacharel em administração de empresas ou campo relacionado.\n- Mais de 5 anos de experiência em gerenciamento de vendas ou desenvolvimento de negócios, com foco no gerenciamento de contas principais.\n- O sucesso demonstrado em contas crescentes e atingindo metas de receita.\n\n#### Benefícios:\n- Salário competitivo com bônus de desempenho.\n- Oportunidades de desenvolvimento profissional e acesso a seminários da indústria.\n- Horário de trabalho flexível.",
  "additional_info": "A Luxotech Solutions valoriza a diversidade e busca candidatos de uma variedade de origens e experiências. As instituições preferidas incluem o Instituto de Administração de Empresas, Karachi e Nuces Fast. A empresa suporta acordos de trabalho híbridos e oferece assistência de realocação para candidatos excepcionais. As habilidades são avaliadas através de uma combinação de testes técnicos, estudos de caso e entrevistas estruturadas com membros do painel de vários departamentos.",
  "resume": "Reham Shah  \n \n \n             +923328079859 reham.altaf2@gmail.com @gmail.com  \nValencia Town Lahore, Paquistão Linkedin.com/in/reham -shah -a72b46172  \n \nB2B Sales Development Client Liaison Online Living  \n \nExecutivo de Desenvolvimento de Negócios de julho de 2020 - atual  \n \n❖ Construir e manter relacionamentos bem -sucedidos com clientes em potencial e clientes existentes. \n❖ Colaborar com executivos sobre estratégia de negócios para determinar os objetivos. \n❖ Os leads de clientes com melhor classificação gerados por meio de plataformas freelancers como Upwork, \nFreelancers, Fiverr, LinkedIn.  \n❖ Produtividade maximizada analisando protocolos e identificando áreas para melhoria.  \n❖ Envolvido com os clientes para criar efetivamente relacionamento e relacionamentos duradouros. Resolvido \nDesafios do cliente, oferecendo produtos e serviços relevantes.  \n❖ Forneceu primeiras impressões positivas para receber clientes existentes, novos e em potencial.  \n❖ Ajudou a desenvolver processos de automação de vendas e automação de geração de leads  \n❖ Manutenção de projetos de clientes relacionados ao desenvolvimento de software.  \n❖ Trabalhou com CRMs como Salesforce e Odoo. \n \nExperiências: \n \n Oficial de Desenvolvimento de Negócios da Kodex Technologies (julho de 2020 a setembro de 2020)  \n \n❖ Trabalhou como licitante em várias plataformas de freelancer. \n❖ Trabalhou na geração de leads do LinkedIn. \n❖ Lidou com projetos de clientes relacionados ao desenvolvimento de software. \n \nExecutivo de Desenvolvimento de Negócios na S.T.A.R.S Pvt. (Ltd) (outubro de 2020 a abril de 2021)  \n \n❖ Trabalhou como licitante em várias plataformas de freelancer. \n❖ Trabalhou na geração de leads do LinkedIn. \n❖ Lidou com projetos de clientes relacionados ao desenvolvimento de software.  \n❖ Reunião técnica necessária.  \n❖ Criou escopo de documentos, dtls. \n \nRepresentante de Desenvolvimento de Vendas no TKXEL (maio de 2021 a outubro de 2021)  \n ❖ Enviando e -mail para os leads qualifas do mercado.  \n❖ Convertendo MQLs em chamada de descoberta.  \n❖ Agenda a reunião do Zoom com clientes.  \n❖ Mantenha os dados do cliente no Salesforce CRM.  \n❖ Acompanhamentos de acompanhamentos para leads existentes.  \n \nExecutivo de Desenvolvimento de Negócios no THD Infinity (novembro de 2021 até o presente)  \n \n❖ A licitação em projetos de desenvolvimento de software sobre o upwork platfrom. \n❖ Agenda a chamada de descoberta.  \n❖ Cetação de requisitos técnicos, análise de produtos.  \n❖ Criando documento SOW. \n❖ Criar DTLs e ajudar o desenvolvedor a entender as necessidades do cliente.  \n❖ Acompanhamentos de acompanhamento com clientes existentes e gerando novos leads.    \n \nQualificação acadêmica:  \n \nCiências da Computação - Universidade de Bahria, Lahore - 2016 -2020  \n \nHabilidades suaves e tecnológicas:  \n❖ Boas habilidades de comunicação, verbal e escrita. \n❖ Experiente em lidar com clientes baseados nos EUA. \n❖ Líder de equipe na S.T.A.R.S Corporation.  \n❖ Familiar em variedade de tecnologias e conceitos de desenvolvimento, incluindo C ++, Java, \nHTML/CSS, ágil/scrum, inteligência de negócios. \n❖ Curso da Web e Graphics (NexxusBerry). \n❖ Líder da equipe para o projeto do último ano. \n \nRealizações: \n \n❖ Bahria Got Talent Bulc (cantando). \n❖ 2ª posição garantida no concurso de debates na Universidade de Bahria. \n❖ Funcionário do mês na S.T.A.R.S. \n \nReferências:  \n \nUsman Farooqi, gerente de negócios da Kodex Technologies  \nUsmanfarooqi22@email, +92 3214445372",
  "details": {
    "name": "Reham Shah",
    "number": "923328079859",
    "skills": [
      "C ++",
      "Java",
      "HTML/CSS",
      "Ágil/scrum",
      "Inteligência de negócios",
      "Salesforce",
      "ODOO"
    ],
    "email_id": "reham.altaf2@gmail.com",
    "location": "Valencia Town Lahore, Paquistão",
    "projects": [],
    "education": [
      {
        "end_date": "2020-12",
        "university": "Universidade da Bahria",
        "degree_title": "Ciências do computador"
      }
    ],
    "achievements": [
      "2ª posição garantida no concurso de debates na Universidade de Bahria",
      "Funcionário do mês na S.T.A.R.S"
    ],
    "publications": [],
    "certifications": [],
    "additional_urls": [
      {
        "url": "LinkedIn.com/in/reham-shah-a72b46172",
        "website_name": "LinkedIn"
      }
    ],
    "executive_summary": "Reham Shah é um executivo de desenvolvimento de negócios qualificado, com forte experiência em desenvolvimento de software e relações com clientes. Ela demonstrou experiência em várias linguagens e ferramentas de programação, contribuindo para o gerenciamento bem -sucedido de projetos e os esforços de geração de leads em várias plataformas freelancers.",
    "employment_history": [
      {
        "details": "Construir e manter relacionamentos bem -sucedidos com clientes em potencial e clientes existentes. Colaborar com executivos sobre estratégia de negócios para determinar os objetivos. Os leads de clientes com melhor classificação gerados por meio de plataformas freelancers como Upwork, Freelancers, Fiverr, LinkedIn. Produtividade maximizada analisando protocolos e identificando áreas para melhoria. Envolvido com os clientes para criar efetivamente relacionamento e relacionamentos duradouros. Resolveu os desafios do cliente, oferecendo produtos e serviços relevantes. Forneceu as primeiras impressões positivas para receber clientes existentes, novos e em potencial. Ajudou a desenvolver processos de automação de vendas e automação de geração de leads. Lidou com projetos de clientes relacionados ao desenvolvimento de software. Trabalhou com CRMs como Salesforce e Odoo.",
        "end_date": "Atual",
        "location": "Lahore, Paquistão",
        "job_title": "Executivo de Desenvolvimento de Negócios",
        "start_date": "07-2020",
        "company_name": "Thd infinito"
      },
      {
        "details": "Trabalhou como licitante em várias plataformas freelancers. Trabalhou na geração de leads do LinkedIn. Lidou com projetos de clientes relacionados ao desenvolvimento de software.",
        "end_date": "09-2020",
        "location": "Lahore, Paquistão",
        "job_title": "Oficial de Desenvolvimento de Negócios",
        "start_date": "07-2020",
        "company_name": "Kodex Technologies"
      },
      {
        "details": "Trabalhou como licitante em várias plataformas freelancers. Trabalhou na geração de leads do LinkedIn. Lidou com projetos de clientes relacionados ao desenvolvimento de software. Coleta de requisitos técnicos. Criou escopo de documentos, DTLS.",
        "end_date": "04-2021",
        "location": "Lahore, Paquistão",
        "job_title": "Executivo de Desenvolvimento de Negócios",
        "start_date": "10-2020",
        "company_name": "S.T.A.R.S Pvt. (Ltd)"
      },
      {
        "details": "Enviando email para leads qualificados do mercado. Convertendo MQLs em chamadas de descoberta. Agendar reuniões de zoom com clientes. Mantenha os dados do cliente sobre o Salesforce CRM. Acompanhamentos de leads existentes.",
        "end_date": "10-2021",
        "location": "Lahore, Paquistão",
        "job_title": "Representante de desenvolvimento de vendas",
        "start_date": "05-2021",
        "company_name": "Tkxel"
      }
    ]
  }
}