{
  "job_description": "Participe ** Techventures Inc. ** Como um gerente de projeto sênior **, onde você supervisionará a entrega de projetos de gerenciamento de dados e análise de dados. Estamos à procura de um líder inovador que possa estabelecer e defender os padrões de entrega, gerenciando equipes multifuncionais para alcançar os mais altos níveis de excelência em serviços. Sua experiência em pré-vendas, arquitetura de soluções e gerenciamento de relacionamento com clientes impulsionará nossa expansão para novos mercados e otimizará os processos existentes.\n\n### Responsabilidades -chave:\n- Liderar e gerenciar projetos complexos de análise de dados e gerenciamento desde o início até a conclusão.\n- Desenvolver e implementar sistemas de qualidade e gerenciamento de projetos para se alinhar com as metas organizacionais.\n- Coordenar as atividades de arquitetura de soluções e pré-vendas, incluindo a preparação de RFPs e EOIs.\n- Mentor e orientar os membros da equipe júnior em desenvolvimento profissional e execução do projeto.\n- Envolva -se com os clientes para fornecer soluções de negócios personalizadas e melhorar a satisfação do cliente.\n- Colabore com outros departamentos para identificar oportunidades de melhoria e otimizar processos.\n\n### Habilidades preferidas:\n- Proficiência em ferramentas de dados como Powerbi, Oracle DV e Tableau.\n- Forte entendimento das metodologias de desenvolvimento de software, incluindo Agile e Scrum.\n- Capacidade demonstrada de liderar grandes equipes técnicas e lidar com as comunicações das partes interessadas de maneira eficaz.\n- Especialização em implementação de inteligência de negócios e data warehousing corporativo.\n\n### Por que se juntar a nós?\n- Oportunidade de trabalhar em projetos impactantes com alcance global.\n- ambiente de trabalho colaborativo e inclusivo.\n- Aprendizagem contínua e oportunidades de desenvolvimento profissional.\n\nTorne -se parte de uma equipe que valorize a integridade, a excelência e a inovação e ajude -nos a redefinir o que é possível no setor de tecnologia.",
  "additional_info": "As universidades preferenciais incluem a Universidade Nacional de Computação e Ciências Emergentes no Paquistão e instituições equivalentes. Oferecemos apoio de realocação a candidatos baseados fora da cidade de contratação, sujeitos à aprovação da gerência. As habilidades são avaliadas através de uma combinação de testes técnicos, estudos de caso de gerenciamento de projetos e entrevistas com painéis que consistem em chefes departamentais e representantes de RH.",
  "resume": "Reham Shah  \n \n \n             +923328079859 reham.altaf2@gmail.com @gmail.com  \nValencia Town Lahore, Paquistão Linkedin.com/in/reham -shah -a72b46172  \n \nB2B Sales Development Client Liaison Online Living  \n \nExecutivo de Desenvolvimento de Negócios de julho de 2020 - atual  \n \n❖ Construir e manter relacionamentos bem -sucedidos com clientes em potencial e clientes existentes. \n❖ Colaborar com executivos sobre estratégia de negócios para determinar os objetivos. \n❖ Os leads de clientes com melhor classificação gerados por meio de plataformas freelancers como Upwork, \nFreelancers, Fiverr, LinkedIn.  \n❖ Produtividade maximizada analisando protocolos e identificando áreas para melhoria.  \n❖ Envolvido com os clientes para criar efetivamente relacionamento e relacionamentos duradouros. Resolvido \nDesafios do cliente, oferecendo produtos e serviços relevantes.  \n❖ Forneceu primeiras impressões positivas para receber clientes existentes, novos e em potencial.  \n❖ Ajudou a desenvolver processos de automação de vendas e automação de geração de leads  \n❖ Manutenção de projetos de clientes relacionados ao desenvolvimento de software.  \n❖ Trabalhou com CRMs como Salesforce e Odoo. \n \nExperiências: \n \n Oficial de Desenvolvimento de Negócios da Kodex Technologies (julho de 2020 a setembro de 2020)  \n \n❖ Trabalhou como licitante em várias plataformas de freelancer. \n❖ Trabalhou na geração de leads do LinkedIn. \n❖ Lidou com projetos de clientes relacionados ao desenvolvimento de software. \n \nExecutivo de Desenvolvimento de Negócios na S.T.A.R.S Pvt. (Ltd) (outubro de 2020 a abril de 2021)  \n \n❖ Trabalhou como licitante em várias plataformas de freelancer. \n❖ Trabalhou na geração de leads do LinkedIn. \n❖ Lidou com projetos de clientes relacionados ao desenvolvimento de software.  \n❖ Reunião técnica necessária.  \n❖ Criou escopo de documentos, dtls. \n \nRepresentante de Desenvolvimento de Vendas no TKXEL (maio de 2021 a outubro de 2021)  \n ❖ Enviando e -mail para os leads qualifas do mercado.  \n❖ Convertendo MQLs em chamada de descoberta.  \n❖ Agenda a reunião do Zoom com clientes.  \n❖ Mantenha os dados do cliente no Salesforce CRM.  \n❖ Acompanhamentos de acompanhamentos para leads existentes.  \n \nExecutivo de Desenvolvimento de Negócios no THD Infinity (novembro de 2021 até o presente)  \n \n❖ A licitação em projetos de desenvolvimento de software sobre o upwork platfrom. \n❖ Agenda a chamada de descoberta.  \n❖ Cetação de requisitos técnicos, análise de produtos.  \n❖ Criando documento SOW. \n❖ Criar DTLs e ajudar o desenvolvedor a entender as necessidades do cliente.  \n❖ Acompanhamentos de acompanhamento com clientes existentes e gerando novos leads.    \n \nQualificação acadêmica:  \n \nCiências da Computação - Universidade de Bahria, Lahore - 2016 -2020  \n \nHabilidades suaves e tecnológicas:  \n❖ Boas habilidades de comunicação, verbal e escrita. \n❖ Experiente em lidar com clientes baseados nos EUA. \n❖ Líder de equipe na S.T.A.R.S Corporation.  \n❖ Familiar em variedade de tecnologias e conceitos de desenvolvimento, incluindo C ++, Java, \nHTML/CSS, ágil/scrum, inteligência de negócios. \n❖ Curso da Web e Graphics (NexxusBerry). \n❖ Líder da equipe para o projeto do último ano. \n \nRealizações: \n \n❖ Bahria Got Talent Bulc (cantando). \n❖ 2ª posição garantida no concurso de debates na Universidade de Bahria. \n❖ Funcionário do mês na S.T.A.R.S. \n \nReferências:  \n \nUsman Farooqi, gerente de negócios da Kodex Technologies  \nUsmanfarooqi22@email, +92 3214445372",
  "details": {
    "name": "Reham Shah",
    "number": "923328079859",
    "skills": [
      "C ++",
      "Java",
      "HTML/CSS",
      "Ágil/scrum",
      "Inteligência de negócios",
      "Salesforce",
      "ODOO"
    ],
    "email_id": "reham.altaf2@gmail.com",
    "location": "Valencia Town Lahore, Paquistão",
    "projects": [],
    "education": [
      {
        "end_date": "2020-12",
        "university": "Universidade da Bahria",
        "degree_title": "Ciências do computador"
      }
    ],
    "achievements": [
      "2ª posição garantida no concurso de debates na Universidade de Bahria",
      "Funcionário do mês na S.T.A.R.S"
    ],
    "publications": [],
    "certifications": [],
    "additional_urls": [
      {
        "url": "LinkedIn.com/in/reham-shah-a72b46172",
        "website_name": "LinkedIn"
      }
    ],
    "executive_summary": "Reham Shah é um executivo de desenvolvimento de negócios qualificado, com forte experiência em desenvolvimento de software e relações com clientes. Ela demonstrou experiência em várias linguagens e ferramentas de programação, contribuindo para o gerenciamento bem -sucedido de projetos e os esforços de geração de leads em várias plataformas freelancers.",
    "employment_history": [
      {
        "details": "Construir e manter relacionamentos bem -sucedidos com clientes em potencial e clientes existentes. Colaborar com executivos sobre estratégia de negócios para determinar os objetivos. Os leads de clientes com melhor classificação gerados por meio de plataformas freelancers como Upwork, Freelancers, Fiverr, LinkedIn. Produtividade maximizada analisando protocolos e identificando áreas para melhoria. Envolvido com os clientes para criar efetivamente relacionamento e relacionamentos duradouros. Resolveu os desafios do cliente, oferecendo produtos e serviços relevantes. Forneceu as primeiras impressões positivas para receber clientes existentes, novos e em potencial. Ajudou a desenvolver processos de automação de vendas e automação de geração de leads. Lidou com projetos de clientes relacionados ao desenvolvimento de software. Trabalhou com CRMs como Salesforce e Odoo.",
        "end_date": "Atual",
        "location": "Lahore, Paquistão",
        "job_title": "Executivo de Desenvolvimento de Negócios",
        "start_date": "07-2020",
        "company_name": "Thd infinito"
      },
      {
        "details": "Trabalhou como licitante em várias plataformas freelancers. Trabalhou na geração de leads do LinkedIn. Lidou com projetos de clientes relacionados ao desenvolvimento de software.",
        "end_date": "09-2020",
        "location": "Lahore, Paquistão",
        "job_title": "Oficial de Desenvolvimento de Negócios",
        "start_date": "07-2020",
        "company_name": "Kodex Technologies"
      },
      {
        "details": "Trabalhou como licitante em várias plataformas freelancers. Trabalhou na geração de leads do LinkedIn. Lidou com projetos de clientes relacionados ao desenvolvimento de software. Coleta de requisitos técnicos. Criou escopo de documentos, DTLS.",
        "end_date": "04-2021",
        "location": "Lahore, Paquistão",
        "job_title": "Executivo de Desenvolvimento de Negócios",
        "start_date": "10-2020",
        "company_name": "S.T.A.R.S Pvt. (Ltd)"
      },
      {
        "details": "Enviando email para leads qualificados do mercado. Convertendo MQLs em chamadas de descoberta. Agendar reuniões de zoom com clientes. Mantenha os dados do cliente sobre o Salesforce CRM. Acompanhamentos de leads existentes.",
        "end_date": "10-2021",
        "location": "Lahore, Paquistão",
        "job_title": "Representante de desenvolvimento de vendas",
        "start_date": "05-2021",
        "company_name": "Tkxel"
      }
    ]
  }
}