{
  "job_description": "### Executivo de Desenvolvimento de Negócios\n\n** Empresa: ** Innovate Dynamics Ltd.\n\n** Localização: ** Hyderabad, Índia\n\n** Visão geral da função: **\nParticipe da Innovate Dynamics Ltd. como executivo de desenvolvimento de negócios, onde você desempenhará um papel fundamental na condução do crescimento dos negócios, gerando leads e gerenciando as principais contas do cliente. Aproveite sua experiência em análise econômica e estratégias de marketing para aprimorar nossa presença no mercado e criar relacionamentos fortes dos clientes.\n\n** Responsabilidades: **\n- Desenvolver e executar planos abrangentes de desenvolvimento de negócios para alcançar os objetivos da empresa.\n- Identifique e envolva clientes em potencial em diversos nichos, incluindo desenvolvimento e terceirização de software.\n- Gerenciar e aumentar as relações com as principais contas para impulsionar o sucesso a longo prazo.\n- Utilize estratégias de marketing digital para aumentar o envolvimento e a retenção do cliente.\n- Colabore com equipes multifuncionais para desenvolver soluções de clientes personalizados.\n- Utilize o LinkedIn Sales Navigator para identificar e abordar novos leads de negócios.\n\n** Qualificações: **\n- Bacharel em Administração de Empresas, Economia ou Campo Relacionado.\n- 3-5 anos de experiência em desenvolvimento de negócios ou campos relacionados.\n- Forte proficiência com as ferramentas de MS Office Suite e Análise de Dados como o STATA.\n- Excelentes habilidades de comunicação verbal e escrita.\n- Capacidade de multitarefa e gerenciar vários projetos simultaneamente.",
  "additional_info": "A Innovate Dynamics Ltd. prioriza os candidatos de universidades de primeira linha, como [University X] e [University Y]. A assistência à realocação está disponível para candidatos dispostos a se mudar para Hyderabad. As habilidades técnicas são avaliadas através de testes padronizados e uma série de entrevistas. Nossa empresa incentiva a diversidade e a inclusão no processo de contratação.",
  "resume": "Arslan Iqbal\nExecutivo de Desenvolvimento de Negócios \nPerfil pessoal\nLahore, \nPaquistão\n+9233336662181\narsllan.181@hotmail.com\nLinks\nhttps://www.linkedin.com/in/ar-\nslan-iqbal1/\nHabilidades\nVendas e desenvolvimento organizacional \nAtendimento ao Cliente\nPesquisa e análise de mercado \nEmail marketing e aquisição de clientes\nPensamento crítico e resolução de problemas\nPrêmios e certificação\n• Prêmio de melhor geração de leads  \n Gala de Marketing 2022, UCP \nEscola de Negócios.\n• Os fundamentos do digital \nMarketing - Google Digital \nGaragem.\n• Conferência do ICIBM sobre CON-\nquestões temporárias em bus-\nGerenciamento de Ness - Organização \nMembro do Comitê. Resumo Profissional\nExecutivo experiente de desenvolvimento de negócios conhecido por impulsionar as vendas, aprimorando \norganizações e mercados em expansão. Um comunicador estratégico hábil na construção \nRelacionamentos do cliente e implementação de estratégias de crescimento inovadoras. Equipe comprometida \nJogador com fortes habilidades analíticas, excedendo consistentemente os alvos.\nHistórico de emprego\nExecutivo de Desenvolvimento de Negócios, Raheem Solutions Unip. Ltd., \nLahore, Paquistão\n0 9/2 0 2 2 - p re s e n t\n• Desenvolvido e mantido relacionamentos com o cliente, garantindo um cliente excepcional \nsatisfação e lealdade.\n• Colaborar com as equipes de vendas e marketing para alinhar estratégias e en-\nOportunidades de geração de receita de Hance.\n• Ajudei minha equipe de vendas a atingir seus objetivos, utilizando várias ferramentas, como \nComo Apollo, Lusha, entre em contato e o LinkedIn Sales Navigator.\n• Através de upwork e freelancer, eu gero e qualifique liderões com sucesso, \ncontribuindo para um pipeline consistente de clientes em potencial.\nRepresentante de Desenvolvimento de Vendas - Gerente de Estado, \nSeebiz Pvt. Ltd., Lahore, Paquistão.\n0 8/2 0 2 2 - 0 9/2 0 2 2\n• Lidar conosco com clientes por meio de chamadas, mensagens e e -mails. Aumenta o meu \nHabilidades de comunicação e gerenciamento de pessoas\n• Gerenciou um território, supervisionando as atividades de geração de leads e conversão e \nacordos fechados com sucesso.\n• participou de sessões de treinamento de produtos e utilizou o conhecimento do produto para \ncomunicar efetivamente proposições de valor a clientes em potencial.\nEducação\nMestre em Administração de Empresas (MBA) em Marketing, \nUniversidade de Punjab Central, Lahore, Paquistão\n0 3/2 0 1 9 - 0 7/2 0 2 2\n• Programa de MBA concluído com foco em estratégias de marketing, consumidor \ncomportamento e pesquisa de mercado.\n• Especializado em gerenciamento e vendas de marcas, alavancando a experiência para dirigir \ncrescimento nos negócios.\n• Graduado com proficiência em aplicar conceitos de marketing modernos a \ncenários do mundo real.\nBacharel em Comércio, Universidade do Punjab, Lahore, Paquistão.\n0 8/2 0 1 6 - 1 2/2 0 1 8\n• Adquiriu Fundação Forte em Business Essentials: Finanças, Contabilidade, Eco-\nNomics e gerenciamento.\n• Envolvido em projetos colaborativos, aprimorando o trabalho em equipe e as habilidades de comunicação.\n• Desenvolveu uma compreensão abrangente das operações comerciais.\nReferências\nDisponível mediante solicitação. de",
  "details": {
    "name": "Arslan Iqbal",
    "number": "9233336662181",
    "skills": [
      "Vendas e desenvolvimento organizacional",
      "Pesquisa e análise de mercado",
      "Email marketing e aquisição de clientes"
    ],
    "email_id": "arsllan.181@hotmail.com",
    "location": "Lahore, Paquistão",
    "projects": [],
    "education": [
      {
        "end_date": "07-2022",
        "university": "Universidade de Punjab Central",
        "degree_title": "Mestre em Administração de Empresas (MBA) em Marketing"
      },
      {
        "end_date": "12-2018",
        "university": "Universidade do Punjab",
        "degree_title": "Bacharel em Comércio"
      }
    ],
    "achievements": [
      "Melhor Prêmio de Geração de Leads, Marketing Gala 2022, UCP Business School."
    ],
    "publications": [],
    "certifications": [
      {
        "certification_name": "Os fundamentos do marketing digital",
        "issuing_organization": "Garagem digital do Google",
        "date_of_issuance": "01-2022"
      }
    ],
    "additional_urls": [
      {
        "url": "linkedin.com/in/ar-slan-iqbal1/",
        "website_name": "LinkedIn"
      }
    ],
    "executive_summary": "O Arslan Iqbal é um executivo de desenvolvimento de negócios experiente conhecido por impulsionar as vendas e aumentar o crescimento organizacional. Ele possui fortes habilidades técnicas em vendas e pesquisas de mercado, demonstrando um compromisso com a satisfação do cliente e as estratégias inovadoras.",
    "employment_history": [
      {
        "details": "Desenvolveu e manteve o relacionamento com os clientes, garantindo satisfação e lealdade excepcionais do cliente. Colaborou com as equipes de vendas e marketing para alinhar estratégias e aprimorar as oportunidades de geração de receita. Ajudou a equipe de vendas a alcançar suas metas, utilizando várias ferramentas, como Apollo, Lusha, entrar em contato e LinkedIn Sales Navigator. Leads com sucesso gerados e qualificados por meio de upwork e freelancer, contribuindo para um pipeline consistente de clientes em potencial.",
        "end_date": "Presente",
        "location": "Lahore, Paquistão",
        "job_title": "Executivo de Desenvolvimento de Negócios",
        "start_date": "09-2022",
        "company_name": "Raheem Solutions Unip. Ltd."
      },
      {
        "details": "Lidar com clientes dos EUA através de chamadas, mensagens e e -mails, aprimorando as habilidades de comunicação e gerenciamento de pessoas. Gerenciou um território, supervisionando as atividades de geração e conversão de leads e fechou com sucesso acordos. Participou de sessões de treinamento de produtos e utilizou o conhecimento do produto para comunicar efetivamente proposições de valor a clientes em potencial.",
        "end_date": "09-2022",
        "location": "Lahore, Paquistão",
        "job_title": "Representante de Desenvolvimento de Vendas - Gerente de Estado",
        "start_date": "08-2022",
        "company_name": "Seebiz Pvt. Ltd."
      }
    ]
  }
}