{
  "job_description": "Gerente de Desenvolvimento de Negócios\n\nJunte -se a ** Innovatecorp ** como gerente de desenvolvimento de negócios para contribuir com nossa crescente equipe e impulsionar iniciativas estratégicas no setor de serviços de tecnologia. O candidato ideal alavancará sua vasta experiência em desenvolvimento de negócios, relações com clientes e gerenciamento de projetos para expandir nossa presença no mercado e criar parcerias duradouras.\n\n#### Responsabilidades -chave:\n- Desenvolver e implementar planos de desenvolvimento estratégico de negócios para alcançar as metas da empresa.\n- Geração de leads e construção de relacionamentos com clientes em potencial.\n- Supervisionar estratégias de aquisição de clientes, incluindo exploração além dos mercados freelancers.\n- Colabore com equipes multifuncionais para garantir a entrega suave do projeto.\n- Utilize o software CRM para rastrear o engajamento do cliente e o progresso do desenvolvimento.\n- Realize pesquisas de mercado para permanecer a par das tendências da indústria e informar estratégias de negócios.\n- Gerenciar e relatar as métricas de desenvolvimento de negócios.\n\n#### Habilidades e competências:\n- Comunicação forte e habilidades interpessoais para envolvimento e colaboração do cliente.\n- Excelentes habilidades analíticas para informar propostas e decisões estratégicas.\n- Experiência no Microsoft Office para documentação e apresentações.\n- Proficiência no software CRM para gerenciar o relacionamento com os clientes.\n\n#### Benefícios:\n- Salário competitivo com incentivos de bônus.\n- Oportunidades de desenvolvimento profissional e avanço na carreira.\n- Pacotes de saúde e seguro odontológico.\n- Horário de trabalho flexível e um ambiente positivo e orientado para a equipe.",
  "additional_info": "A Innovatecorp prefere candidatos de escolas de negócios líderes, como o Comsats Institute of Information and Technology. Apoiamos a realocação para o candidato certo e oferecemos oportunidades de trabalho remotas. As habilidades são avaliadas através de uma combinação de entrevistas técnicas e estudos de caso práticos, garantindo que os candidatos atendam aos nossos altos padrões de desempenho antes de oferecer uma posição.",
  "resume": "Zarwa Shahid  \nExecutivo de Desenvolvimento de Negócios  \n \n \n \nContato  \nJohar Town,  \nLahore  \n0306 -1538612  \nshahidzarwa4@gmail.com  \nhttps://www.linkedin.com/in/zarwa - \nShahid -926986208/  \n \n \nEducação  \nUniversidade rápida (2022)  \nGrupo Superior de Faculdades (2017)  \n \n \n \nLicença e  \nCertificação  \nMarketing de afiliado de comércio eletrônico  \n(ECOMmerce Pro)  \nFunnels de vendas e marketing de comércio eletrônico  \n(ECOMmerce Pro)  \nPublicidade do Facebook para comércio eletrônico  \n(ECOMmerce Pro)  \nADS do comércio eletrônico do comércio eletrônico  \n(ECOMmerce Pro)  \nWordPress wooCommerce  \n(ECOMmerce Pro)  \n \n \n \nHabilidades -chave  \nMarketing  \nGeração de chumbo  \nEscrita da proposta  \nMídia social  \nPlanejamento  \nWordPress  \nExcelente comunicação  \nObjetivo de vendas de TI  \nEu sou um membro dedicado da equipe que tenta o seu melhor para obter receita  \nExpectativas e pretendem atingir seus objetivos. Eu tenho muito orgulho no meu  \nhabilidades de comunicação, atenção aos detalhes, capacidade de multitarefa e  \nconfiabilidade. Eu sou duro -trabalhando e pontual. Eu posso fazer problemas de solução  \ndecisões rapidamente. Estou procurando oportunidades para aprender e adquirir novos  \nHabilidades para que eu possa melhorar minhas habilidades para uma carreira próspera na indústria de TI.  \n \n \nExperiência  \n2022 - 2023  \nDesenvolvimento de Negócios Executive @ Software Pro \nO Software Pro faz parte de um grupo de tecnologia líder da Nova York EUA. \nComo executivo da BD, sou responsável por impulsionar as vendas da empresa por \nadquirir novos clientes e criar um valor longo de longo prazo para seus negócios via \nPlataformas BD.  \n \n2023 - (meio período)  \nExecutivo de Desenvolvimento de Negócios @ It Cado LLC  \n• Contratado como um experiente e promovido ao desenvolvimento de negócios  \nexecutivo como líder da equipe.  \n• Internos treinados para geração de leads e lances de trabalho  \n• Utilizou o HubSpot e o Salesforce para gerenciar leads  \n• Especialista em tela | Projetou várias propostas para clientes  \n• Responsável por projetar e gerenciar portfólios da empresa  \n• Skype usado, Slack, Basecamp e Jira para Cliente  \ncomunicação  \n \n     (2023 - em tempo integral)  \n    Executivo de Desenvolvimento de Negócios @tecspine  \n      \n• Contratado como um experiente e promovido ao desenvolvimento de negócios \nexecutivo como líder da equipe.  \n• Responsável por projetar e gerenciar portfólios da empresa  \n• Skype usado, Slack, Basecamp e Jira para Cliente",
  "details": {
    "name": "Zarwa Shahid",
    "number": "03061538612",
    "skills": [
      "WordPress",
      "HubSpot",
      "Salesforce",
      "Canva",
      "Skype",
      "Folga",
      "Basecamp",
      "Jira"
    ],
    "email_id": "shahidzarwa4@gmail.com",
    "location": "Johar Town, Lahore",
    "projects": [],
    "education": [
      {
        "end_date": "2022",
        "university": "Universidade rápida",
        "degree_title": ""
      },
      {
        "end_date": "2017",
        "university": "Grupo Superior de Faculdades",
        "degree_title": ""
      }
    ],
    "achievements": [],
    "publications": [],
    "certifications": [
      {
        "certification_name": "Marketing de afiliado de comércio eletrônico",
        "issuing_organization": "Comércio eletrônico Pro",
        "date_of_issuance": ""
      },
      {
        "certification_name": "Funnels de vendas e marketing de comércio eletrônico",
        "issuing_organization": "Comércio eletrônico Pro",
        "date_of_issuance": ""
      },
      {
        "certification_name": "Publicidade do Facebook para comércio eletrônico",
        "issuing_organization": "Comércio eletrônico Pro",
        "date_of_issuance": ""
      },
      {
        "certification_name": "ADS do comércio eletrônico do comércio eletrônico",
        "issuing_organization": "Comércio eletrônico Pro",
        "date_of_issuance": ""
      },
      {
        "certification_name": "WordPress wooCommerce",
        "issuing_organization": "Comércio eletrônico Pro",
        "date_of_issuance": ""
      }
    ],
    "additional_urls": [
      {
        "url": "Linkedin.com/in/zarwa-shahid-926986208/",
        "website_name": "LinkedIn"
      }
    ],
    "executive_summary": "Zarwa Shahid é um executivo de desenvolvimento de negócios dedicado, com experiência em impulsionar as vendas e gerenciar o relacionamento com os clientes. Ele possui fortes habilidades técnicas em várias ferramentas e plataformas de software, demonstrando um compromisso de atingir as metas de negócios e aprimorar os portfólios da empresa.",
    "employment_history": [
      {
        "details": "Responsável por impulsionar as vendas da empresa, adquirindo novos clientes e criando um valor de longo prazo para seus negócios por meio de plataformas BD.",
        "end_date": "2023",
        "location": "",
        "job_title": "Executivo de Desenvolvimento de Negócios",
        "start_date": "2022",
        "company_name": "Software Pro"
      },
      {
        "details": "Promovido a executivo de desenvolvimento de negócios como líder da equipe. Internos treinados para geração de leads e lances de trabalho. Utilizou o HubSpot e o Salesforce para gerenciar leads. Projetou várias propostas para os clientes.",
        "end_date": "",
        "location": "",
        "job_title": "Executivo de Desenvolvimento de Negócios",
        "start_date": "2023",
        "company_name": "It Cado LLC"
      },
      {
        "details": "Promovido a executivo de desenvolvimento de negócios como líder da equipe. Responsável por projetar e gerenciar portfólios da empresa.",
        "end_date": "",
        "location": "",
        "job_title": "Executivo de Desenvolvimento de Negócios",
        "start_date": "2023",
        "company_name": "Tecspine"
      }
    ]
  }
}