{
  "job_description": "Participe ** Techventures Inc. ** Como um gerente de projeto sênior **, onde você supervisionará a entrega de projetos de gerenciamento de dados e análise de dados. Estamos à procura de um líder inovador que possa estabelecer e defender os padrões de entrega, gerenciando equipes multifuncionais para alcançar os mais altos níveis de excelência em serviços. Sua experiência em pré-vendas, arquitetura de soluções e gerenciamento de relacionamento com clientes impulsionará nossa expansão para novos mercados e otimizará os processos existentes.\n\n### Responsabilidades -chave:\n- Liderar e gerenciar projetos complexos de análise de dados e gerenciamento desde o início até a conclusão.\n- Desenvolver e implementar sistemas de qualidade e gerenciamento de projetos para se alinhar com as metas organizacionais.\n- Coordenar as atividades de arquitetura de soluções e pré-vendas, incluindo a preparação de RFPs e EOIs.\n- Mentor e orientar os membros da equipe júnior em desenvolvimento profissional e execução do projeto.\n- Envolva -se com os clientes para fornecer soluções de negócios personalizadas e melhorar a satisfação do cliente.\n- Colabore com outros departamentos para identificar oportunidades de melhoria e otimizar processos.\n\n### Habilidades preferidas:\n- Proficiência em ferramentas de dados como Powerbi, Oracle DV e Tableau.\n- Forte entendimento das metodologias de desenvolvimento de software, incluindo Agile e Scrum.\n- Capacidade demonstrada de liderar grandes equipes técnicas e lidar com as comunicações das partes interessadas de maneira eficaz.\n- Especialização em implementação de inteligência de negócios e data warehousing corporativo.\n\n### Por que se juntar a nós?\n- Oportunidade de trabalhar em projetos impactantes com alcance global.\n- ambiente de trabalho colaborativo e inclusivo.\n- Aprendizagem contínua e oportunidades de desenvolvimento profissional.\n\nTorne -se parte de uma equipe que valorize a integridade, a excelência e a inovação e ajude -nos a redefinir o que é possível no setor de tecnologia.",
  "additional_info": "As universidades preferenciais incluem a Universidade Nacional de Computação e Ciências Emergentes no Paquistão e instituições equivalentes. Oferecemos apoio de realocação a candidatos baseados fora da cidade de contratação, sujeitos à aprovação da gerência. As habilidades são avaliadas através de uma combinação de testes técnicos, estudos de caso de gerenciamento de projetos e entrevistas com painéis que consistem em chefes departamentais e representantes de RH.",
  "resume": "Shahrukh Ali\nshahrukh.ali@descon.com 4618452\nLinkedIn.com/in/shahrukh-ali-3021ab24a\nResumo\nUm executivo de desenvolvimento de negócios altamente motivado e orientado a resultados, que também serviu como finanças &\nContas profissionais com 12 anos de experiência inestimável, incluindo ser qualificado em vários negócios\nCampos de desenvolvimento, financeiro e contábil. Eu tenho a capacidade de lidar com atribuições complexas de maneira eficaz e\nPossuindo a confiança para trabalhar como parte de uma equipe ou de forma independente. Uma reputação estabelecida de auto-\nMotivação, atenção aos detalhes excelentes habilidades organizacionais e alta conduta ética. Atualmente procurando o\nMelhor oportunidade com uma empresa orientada a objetivos, onde posso me destacar, entregar e alcançar de acordo com o meu potencial. EU\nEstou entusiasmado em aprender profundamente sobre desenvolvimentos emergentes em meu setor de trabalho.\nExperiência\nAssociado sênior\nKPMG no Paquistão\nAgosto de 2021 - fevereiro de 2022 (7 meses)\nSupervisão da equipe e treinamento\nAnalista de entrada de dados: Atualize o sistema conforme as faturas são recebidas.\nAnalista de pagamento bancário: Contas de processamento e pagamentos recebidos em conformidade.\nSAP ERP\nOráculo\nPolíticas e procedimentos financeiros.\nAnalista de exceções: abordar disputas e problemas de falha de pagamento.\nAnalista de manutenção de fornecedores: mantenha um banco de dados de fornecedor preciso.\nAnalista de finanças: realizando transações financeiras diárias, incluindo verificação, classificação,\nDados de computação, postagem e registro de contas a receber\nExecutivo de Desenvolvimento de Negócios\nInspecion (Private) Limited\nFevereiro de 2022 - presente (7 meses +)\nContabilidade, finanças e receita de desenvolvimento de negócios\nRelações com o cliente\nNegociação de clientes\nExecutivo de contas\nDescon Engineering Limited\nAgosto de 2009 - 2021 de julho (12 anos)\nAnalista de entrada de dados: Atualize o sistema conforme as faturas são recebidas.\nAnalista de pagamento bancário\nSAP ERP\nOráculo\nPolíticas e procedimentos financeiros.\nAnalista de exceções: abordar disputas e problemas de falha de pagamento.\nShahrukh Ali - Analista de manutenção do fornecedor: Mantenha um banco de dados de fornecedor preciso.\nAnalista de finanças: realizando transações financeiras diárias, incluindo verificação, classificação,\nDados de computação, postagem e registro de contas a receber\nEducação\nUniversidade de Punjab Central\nMBA\nUniversidade de Hajvery\nBacharel em Comércio\nHabilidades\nAbacus • Contabilidade • Contas a receber • ACCPAC • Análise • Lei de Negócios • CEO •  \nConsultoria • Entrada de dados • Administração de banco de dados\nShahrukh Ali - Página 2",
  "details": {
    "name": "Shahrukh Ali",
    "number": "4618452",
    "skills": [
      "SAP ERP",
      "Oráculo",
      "ábaco",
      "contabilidade",
      "contas a receber",
      "Accpac",
      "entrada de dados",
      "Administração de banco de dados"
    ],
    "email_id": "shahrukh.ali@descon.com",
    "location": "",
    "projects": [],
    "education": [
      {
        "end_date": "06-2010",
        "university": "Universidade de Hajvery",
        "degree_title": "Bacharel em Comércio"
      },
      {
        "end_date": "06-2012",
        "university": "Universidade de Punjab Central",
        "degree_title": "MBA"
      }
    ],
    "achievements": [],
    "publications": [],
    "certifications": [],
    "additional_urls": [
      {
        "url": "LinkedIn.com/in/shahrukh-ali-3021ab24a",
        "website_name": "LinkedIn"
      }
    ],
    "executive_summary": "Shahrukh Ali é um executivo de desenvolvimento de negócios altamente motivado e orientado a resultados, com 12 anos de experiência inestimável em desenvolvimento de negócios, finanças e contabilidade. Ele possui fortes habilidades técnicas no SAP ERP e Oracle e possui um histórico comprovado em lidar com atribuições complexas de maneira eficaz.",
    "employment_history": [
      {
        "details": "Supervisão e treinamento da equipe, analista de entrada de dados: Atualize o sistema conforme as faturas são recebidas, analista de pagamento bancário: processamento de contas e pagamentos recebidos em conformidade, analista de exceções: abordagem de disputas e problemas de falha de pagamento, analistas de manutenção de fornecedores: Manter um banco de dados de dados, com realização de transações financeiras, incluindo a classificação, a classificação, a classificação precisa, a classificação precisa.",
        "end_date": "02-2022",
        "location": "Paquistão",
        "job_title": "Associado sênior",
        "start_date": "08-2021",
        "company_name": "KPMG no Paquistão"
      },
      {
        "details": "Contabilidade, finanças e receita de desenvolvimento de negócios, relações com clientes, negociação de clientes.",
        "end_date": "",
        "location": "",
        "job_title": "Executivo de Desenvolvimento de Negócios",
        "start_date": "02-2022",
        "company_name": "Inspecion (Private) Limited"
      },
      {
        "details": "Analista de entrada de dados: Atualize o sistema conforme as faturas são recebidas, analista de pagamento bancário, analista de exceções: abordagem de disputas e problemas de falha de pagamento, analista de manutenção de fornecedores: mantenha um banco de dados preciso do fornecedor, analista de finanças: executando transações financeiras diárias, incluindo a verificação, classificação, computação e registro de contas de contas de contas.",
        "end_date": "07-2021",
        "location": "",
        "job_title": "Executivo de contas",
        "start_date": "08-2009",
        "company_name": "Descon Engineering Limited"
      }
    ]
  }
}