{
  "job_description": "## Título do trabalho: Especialista em gerenciamento de vendas e SEO  \n\n### Localização: Lahore, Paquistão  \n\n### Empresa: Innovate Digital Solutions Inc.  \n\nResumo do trabalho:  \nParticipe da Innovate Digital Solutions Inc. como especialista em gerenciamento de vendas e SEO. Você fará parte de uma equipe dinâmica responsável por impulsionar o envolvimento do cliente e garantir o desempenho ideal em estratégias de marketing digital. Sua função incluirá o gerenciamento do relacionamento com os clientes, a melhoria das estratégias de SEO e a liderança de sua equipe a atingir metas de vendas.  \n\n### Responsabilidades -chave:  \n- Envolva -se proativamente com clientes em potencial para entender suas necessidades de negócios e fornecer soluções inovadoras.  \n- Projete e execute estratégias de SEO em alinhamento com os objetivos de marketing do cliente.  \n- Gerenciar e otimizar as campanhas do PPC para maximizar o ROI e a visibilidade da marca.  \n- Desenvolva e mantenha um forte relacionamento com os clientes por meio de soluções de marketing personalizadas.  \n- Lidere uma equipe a alcançar e superar as metas de vendas, fornecendo um atendimento excepcional ao cliente.  \n- Analise as tendências e algoritmos do mercado para adaptar as estratégias de SEO de acordo.  \n- Produza relatórios que acompanham o progresso e medem o sucesso contra os KPIs.  \n\n### Perfil de candidato ideal:  \nVocê é um profissional qualificado de vendas e marketing, com fortes habilidades analíticas adequadas para identificar e executar oportunidades de SEO. Você se destaca nas interações do cliente, possuindo a capacidade de transformar possíveis leads em clientes satisfeitos por meio de iniciativas de marketing estratégicas e bem executadas. As habilidades de liderança e gerenciamento de equipes serão fundamentais para impulsionar as vendas e motivar sua equipe.  \n\n### benefícios:  \n- Pacote de salário competitivo  \n- Benefícios de saúde e bem -estar  \n- Bônus de desempenho  \n- Oportunidades de avanço na carreira  \n\nJunte -se a nós para redefinir o engajamento digital e liderar estratégias de mercado com agilidade e inovação.",
  "additional_info": "A Innovate Digital Solutions Inc. prefere candidatos de instituições respeitáveis ​​como [Universidade de Lahore], [Universidade de Punjab]. As opções de trabalho remotas estão disponíveis sujeitas a funções e responsabilidades. Avaliamos as habilidades por meio de uma combinação de testes técnicos, entrevistas e cenários de solução de problemas do mundo real para avaliar a competência prática em contextos estratégicos de marketing.",
  "resume": "Usman Hanif  \nUsman.hanif9@gmail.com  \nH# 878-C, Bloco de Usama, Nishter Colony, Lahore. \n+923214580128  \nhttps://www.linkedin.com/in/usman-hanif -53858460/  \n \nOBJETIVO  \n“Perseguir uma posição orientada ao desenvolvimento, onde minhas habilidades, conhecimentos e habilidades agregam valor significativo ao \norganização\"   \nEDUCAÇÃO  \nUniversidade Superior, Lahore  \n(2011 -2015) Bacharelado em Administração de Empresas  \n Major em marketing  \nStandard College, Lahore  \n(2010-2011) F.SC Pré -engenharia  \nEXPERIÊNCIA  \nSiddiq Agricoze (Pvt). Limitado | Muridke Punjab, pk  \nAnalista de desenvolvimento de negócios em janeiro de 2022 - presente  \n Relacionamento comercial engajado e formado com os clientes internacionais em EUA e UE etc. \n Geração de leads através de exposições e eventos internacionais.  \n Fez as exposições visitar planos e marcar reuniões com potenciais distribuidores internacionais e \nclientes.  \n Sugerido para montar Stand & exibir os produtos em exposições internacionais.  \n Comunicar -se com os clientes existentes e cumprir seus quartos de negócios.  \n Analisar a concorrência e elaborar as estratégias de acordo.  \n Prepare as amostras do produto e despachar para os clientes.  \n Desenou o contrato de vendas com agentes/fornecedores e compra as ofertas.  \n Coordenação com todos os departamentos internos para remessas suaves e aquisição de novos clientes.  \n   \n Executivo de Desenvolvimento de Negócios de fevereiro de 2021 - dezembro de 2021  \n Desenvolveu a rede de distribuição em todo o Paquistão.  \n Projetou os contratos de vendas com distribuidores e metas de vendas.  \n Link de vendas B2B estabelecido e também forneceu suporte de vendas.   \n Projetou o perfil da empresa e os abordagens de produtos.  \n Anote o script do vídeo do perfil da empresa e executou a filmagem de vídeo.  \no Link: https: // www.youtube.com/watch?v=J8JXDOJX1WW&t=5S  \n Provocou o sistema de armazém e logística da empresa.  \n Forneceu previsões de vendas em bases mensais/trimestrais para o Conselho de Administração e a equipe de produção.  \n relataram o desempenho das vendas em bases mensais para o Conselho de Declorcedores.  \nSRC Private Limited | Lahore Punjab, pk  \nOficial de Desenvolvimento de Negócios Janeiro de 2018 - Dezembro de 2021  \n Análise do mercado e sugere novos projetos/produtos para o crescimento da empresa.  \n Realizou pesquisas de mercado e explorou as novas oportunidades de mercado.  \n Estudou o mercado local e internacional de ingredientes à base de arroz  \no demanda/oferta de glicose líquida.  \no Análise dos concorrentes locais e internacionais.  \no compilou o base de dados de distribuidores/clientes locais e internacionais.  \no Identificou os principais desafios e fatores de mercado.  \no Estrutura proposta e funções de um departamento de vendas e marketing. \no Proposto ao Conselho de Administração para construir ingredientes de ingredientes à base de arroz.  \no Conselho de Di reitores aprovou o projeto e agora a empresa está vendendo produtos em local e \nmercado internacional.  \n Realizou análise de mercado de produtos químicos de construção.  \no Propôs o Conselho de Administração para adicionar produtos químicos do agente de redução de água no \nlinha de produtos.  \n Analisou o mercado de produtos FMCG de atendimento domiciliar que leva a empresa a introduzir novos \nMarca “Saaf & Safe” no Paquistão.  \nYorkshire Trading (Pvt). Limitado | Lahore Punjab, pk  \nOficial de vendas agosto de 2016 - janeiro de 2018  \n Vendas de folhas de placa, painéis de portas importados e podutos de madeira sólida no Punjab, \nPaquistão. \n Preparação e execução do plano de vendas e marketing.  \n Geração potencial de leads e engajamento de leads do cliente.  \n Desenvolvi um canal de vendas B2B (Haier, Chugtaiz, Móveis para Tocha e Móveis Mohkam etc.)  \n Também desenvolveu o canal de vendas de varejo em Punjab, Paquistão.  \n Introduzido folhas UV importadas (turcas) no mercado.  \n Recuperação de pagamentos contra vendas.   \n  Assuntos relacionados ao banco.  \nHABILIDADES  \n \nHabilidades de gestão e liderança  \n \n Gerenciamento de registros  \n Multi -tola  \n Capacidade de trabalhar com PEO de uma ampla gama de origens culturais e socioeconômicas  \n Construir e manter boas relações profissionais  \nComunicação e habilidades interpessoais  \n Forte experiência de gerenciar partes interessadas e parceiros  \n Comunicação de e -mail e escritório (tomando notas, desenvolvendo plantas e redação de relatórios)  \n Habilidades sociais (adaptabilidade, negociação e persuasão)  \nHabilidades digitais  \n Microsoft (Microsoft Excel, Microsoft PowerPoint, Microsoft Word, Microsoft Outlook)  \n Operador certificado CANDELA RMS  \n Gerenciamento de mídia social  \n \nIdiomas conhecidos  \n \n Urdu   \n Punjabi   \n Inglês  \n \nAlém dos acadêmicos  \n Serviço social  \n Turismo  \n Fotografia  \n Assistindo filmes",
  "details": {
    "name": "Usman Hanif",
    "number": "923214580128",
    "skills": [
      "Microsoft Excel",
      "Microsoft PowerPoint",
      "Microsoft Word",
      "Microsoft Outlook",
      "Gerenciamento de mídia social",
      "Operador Candella RMS certificado"
    ],
    "email_id": "Usman.hanif9@gmail.com",
    "location": "H# 878-C, Bloco de Usama, Nishter Colony, Lahore",
    "projects": [],
    "education": [
      {
        "end_date": "05-2015",
        "university": "Universidade Superior, Lahore",
        "degree_title": "Bacharelado em Administração de Empresas"
      },
      {
        "end_date": "05-2011",
        "university": "Standard College, Lahore",
        "degree_title": "F.SC pré-engenharia"
      }
    ],
    "achievements": [],
    "publications": [],
    "certifications": [
      {
        "certification_name": "Operador Candella RMS certificado",
        "issuing_organization": "Candela",
        "date_of_issuance": "01-2021"
      }
    ],
    "additional_urls": [
      {
        "url": "LinkedIn.com/in/usman-hanif-53858460/",
        "website_name": "LinkedIn"
      },
      {
        "url": "youtube.com/watch?v=J8JXDOJX1WW&t=5S",
        "website_name": "YouTube"
      }
    ],
    "executive_summary": "Usman Hanif é um analista de desenvolvimento de negócios dedicado, com uma forte formação em marketing e administração de empresas. Ele tem uma vasta experiência em se envolver com clientes internacionais e desenvolver relacionamentos estratégicos de negócios, mostrando suas habilidades técnicas em análise de mercado e desenvolvimento de estratégias de vendas.",
    "employment_history": [
      {
        "details": "Relacionamento comercial engajado e formado com os clientes internacionais nos EUA e na UE. Geração de leads através de exposições e eventos internacionais. Sugeriu estabelecer o Stand & exibir os produtos em exposições internacionais. Comunicar -se com os clientes existentes e cumprir suas consultas comerciais.",
        "end_date": "Presente",
        "location": "Muridke Punjab, pk",
        "job_title": "Analista de desenvolvimento de negócios",
        "start_date": "01-2022",
        "company_name": "Siddiq Agricoze (Pvt). Limitado"
      },
      {
        "details": "Desenvolveu a rede de distribuição em todo o Paquistão. Projetou os contratos de vendas com distribuidores e metas de vendas. Estabeleceu a ligação de vendas B2B e forneceu suporte de vendas.",
        "end_date": "12-2021",
        "location": "Lahore Punjab, pk",
        "job_title": "Executivo de Desenvolvimento de Negócios",
        "start_date": "02-2021",
        "company_name": "Siddiq Agricoze (Pvt). Limitado"
      },
      {
        "details": "Conduziu pesquisas de mercado e explorou novas oportunidades de mercado. Proposto ao Conselho de Administração para construir ingredientes de ingredientes à base de arroz.",
        "end_date": "12-2021",
        "location": "Lahore Punjab, pk",
        "job_title": "Oficial de Desenvolvimento de Negócios",
        "start_date": "01-2018",
        "company_name": "SRC Private Limited"
      },
      {
        "details": "Vendas de lençóis de folga, painéis de portas importados e produtos de madeira maciça em Punjab, Paquistão. Desenvolveu o canal de vendas B2B e introduziu folhas UV importadas no mercado.",
        "end_date": "01-2018",
        "location": "Lahore Punjab, pk",
        "job_title": "Oficial de vendas",
        "start_date": "08-2016",
        "company_name": "Yorkshire Trading (Pvt). Limitado"
      }
    ]
  }
}