{
  "job_description": "Participe ** Techventures Inc. ** Como um gerente de projeto sênior **, onde você supervisionará a entrega de projetos de gerenciamento de dados e análise de dados. Estamos à procura de um líder inovador que possa estabelecer e defender os padrões de entrega, gerenciando equipes multifuncionais para alcançar os mais altos níveis de excelência em serviços. Sua experiência em pré-vendas, arquitetura de soluções e gerenciamento de relacionamento com clientes impulsionará nossa expansão para novos mercados e otimizará os processos existentes.\n\n### Responsabilidades -chave:\n- Liderar e gerenciar projetos complexos de análise de dados e gerenciamento desde o início até a conclusão.\n- Desenvolver e implementar sistemas de qualidade e gerenciamento de projetos para se alinhar com as metas organizacionais.\n- Coordenar as atividades de arquitetura de soluções e pré-vendas, incluindo a preparação de RFPs e EOIs.\n- Mentor e orientar os membros da equipe júnior em desenvolvimento profissional e execução do projeto.\n- Envolva -se com os clientes para fornecer soluções de negócios personalizadas e melhorar a satisfação do cliente.\n- Colabore com outros departamentos para identificar oportunidades de melhoria e otimizar processos.\n\n### Habilidades preferidas:\n- Proficiência em ferramentas de dados como Powerbi, Oracle DV e Tableau.\n- Forte entendimento das metodologias de desenvolvimento de software, incluindo Agile e Scrum.\n- Capacidade demonstrada de liderar grandes equipes técnicas e lidar com as comunicações das partes interessadas de maneira eficaz.\n- Especialização em implementação de inteligência de negócios e data warehousing corporativo.\n\n### Por que se juntar a nós?\n- Oportunidade de trabalhar em projetos impactantes com alcance global.\n- ambiente de trabalho colaborativo e inclusivo.\n- Aprendizagem contínua e oportunidades de desenvolvimento profissional.\n\nTorne -se parte de uma equipe que valorize a integridade, a excelência e a inovação e ajude -nos a redefinir o que é possível no setor de tecnologia.",
  "additional_info": "As universidades preferenciais incluem a Universidade Nacional de Computação e Ciências Emergentes no Paquistão e instituições equivalentes. Oferecemos apoio de realocação a candidatos baseados fora da cidade de contratação, sujeitos à aprovação da gerência. As habilidades são avaliadas através de uma combinação de testes técnicos, estudos de caso de gerenciamento de projetos e entrevistas com painéis que consistem em chefes departamentais e representantes de RH.",
  "resume": "Muzamil Qamar  \n03091999966 Lahore /Paquistão  \nE -mail · muzamil qamar19@gmail.com ·  \n \nEu procuro trabalhar em um ambiente competitivo e desafiador, onde posso aprender e polir minhas habilidades \nResultado -indivíduo orientado, organizado e motivado que busca uma posição de gerenciamento disponível em um \nesforço para utilizar anos de experiência para atender aos requisitos estratégicos da empresa.  \n \nExperiência profissional  \nDados trans • Lahore  \nLíder de desenvolvimento de negócios - presente  \n \n• Aumento das vendas implementando um novo processo de vendas e criando novos materiais de vendas  \n• Revisou e avaliou os dados dos clientes em potencial e as técnicas de geração de leads, resultando em novas oportunidades de vendas  \n• Implementou um novo programa de treinamento de vendas para funcionários novos e existentes, aumentando as vendas médias  \nvolume  \n• Abordou proativamente os possíveis problemas de vendas, levando a uma redução na rotatividade da força de vendas  \n \nCarro primeiro (Lahore)  \nGerente C Ustomer Services. (22 de setembro)  \n \n• Garanta altos níveis de atendimento ao cliente na respectiva divisão/seção para obter uma imagem de marca positiva \ne experiência do cliente  \n• Apresentar sugestões e recomendações na maior decisão tomada pela gerência sênior com o \nem relação às atividades de vendas/ promoção  \n• Atingir/exceder as metas de organização designadas para manter a tendência de negócios lucrativa  \n• Envolvido nos movimentos da marca/desempenho de departamento/desempenho de vendas/custo/desempenho trimestral \nAnálise e engajada para solicitar os bancos de dados do consumidor e para um futuro lucrativo.  \n• executar e manter os padrões de atendimento ao cliente  \n• Coordenação com o controle de qualidade e definir o novo processo e política para obter o crescimento máximo em \no negócio de geração de leads  \n• Shift Plan's/Rotações/alocações de destino/segregação de equipes  \n• Envolvido no planejamento de uma nova estratégia e nova rotação que tenha um efeito imenso na marca \ntaxa de retenção  \n• Projetou os mecanismos de desenvolvimento e higiene de funcionários para garantir proficiência e números mais altos \nde produtividade  \n• Construir relações com os clientes e planejar novas iniciativas para aumentar a experiência do cliente com a correlação \ndo tema do mercado -alvo e dos negócios  \n• Projetou a estrutura P-O-L-C-A para fornecer orientações úteis. \n• Definir e revisar orçamentos e gerenciar custos. \n \nAbacus Consulting (Lahore)  \nCareem - Now Operations Lead (21 de outubro) \n \n• Produziu a maior classificação de satisfação do cliente do ano com a cooperação da minha equipe, fornecendo \nSeguir -se e atendimento personalizado.     \n• Trabalhou sob a supervisão direta do gerente de atendimento ao cliente.  \n• Apresentações de mercadorias de liderança sobre os recursos de produção.  \n• Utilizou o forte conhecimento do produto e as habilidades de solução de problemas para ajudar os clientes com suas preocupações.  \n• Garantiu a precisão dos dados, acompanhando todas as chamadas de clientes por meio de planilhas e empresa \nsoftware.  \n• Manter relacionamentos com fornecedores e clientes internos e externos.  \n 2 Resíduos Busters Gerenciamento de Resíduos Sólidos Pvt  \nExecutivo de Desenvolvimento de Negócios (19 de janeiro) \n \n• Siga os principais indicadores de desempenho e alcance os benchmarks de desempenho definidos pela empresa e \npartes interessadas  \n• Compreensão de problemas do cliente, propriedade de equipamentos e personalização com o cliente  \n• cumprir as políticas da empresa para garantir operações suaves.  \n• Analisando KPIs para identificar fraquezas, propondo e implementando soluções robustas e gerenciando \nExpectativas de equipe executiva e operacional, sob prazos apertados para oferecer mudanças transformacionais.  \n• Coordenação direta com a equipe de vendas para a segurança perfeita  \n \n \n \nHABILIDADES  \n• fortes habilidades interpessoais e de comunicação  \n• Possuir habilidades administrativas e organizacionais firmes  \n• Aberto aos desafios da mudança e aprendizado  \n• Capacidade de se adaptar às mudanças de amanhã  \n• ênfase no trabalho de alta qualidade e conclusão do trabalho • Proficiente no Microsoft Office (MS Word, \nPowerPoint, Excel)  \n• Altamente organizado e eficiente  \n• Capacidade de trabalhar de forma independente ou como parte do \nEquipe   \n• Capacidade de treinar um noivo para manter um \nambiente saudável   \nRealizações | Responsabilidades  \n• Bolsas de estudo.  \n• Honra a inclusão do rolo para notas altas.  \n• Prêmios de atendimento perfeito  \n• Prêmio de Excelência Ganhada por Obras de Arte, 20014 -2016  \n• IELTS marcou a banda 6.5, 2018  \n• Nível de idioma alemão (A1) na LUMS  \n \n EDUCAÇÃO  \n \n2021  \nBacharelado em Comércio  \n2018  \nHSSC, intermediário  \ni.com (intermediário em comércio)  \n \n2016  \nMATRÍCULA",
  "details": {
    "name": "Muzamil Qamar",
    "number": "03091999966",
    "skills": [
      "Microsoft Office (MS Word, PowerPoint, Excel)"
    ],
    "email_id": "muzamil qamar19@gmail.com",
    "location": "Lahore, Paquistão",
    "projects": [],
    "education": [
      {
        "end_date": "12-2021",
        "university": "",
        "degree_title": "Bacharelado em Comércio"
      },
      {
        "end_date": "05-2018",
        "university": "",
        "degree_title": "HSSC, intermediário"
      },
      {
        "end_date": "05-2016",
        "university": "",
        "degree_title": "Matrícula"
      }
    ],
    "achievements": [
      "Bolsas de estudo",
      "Honra Inclusão de rolos para notas altas",
      "Prêmios perfeitos de presença",
      "Prêmio de Excelência Ganhada por Obras de Arte, 2014-2016",
      "IELTS marcou a banda 6.5, 2018",
      "Nível de idioma alemão (A1) na Lums"
    ],
    "publications": [],
    "certifications": [],
    "additional_urls": [],
    "executive_summary": "Muzamil Qamar é um profissional dedicado, com vasta experiência em desenvolvimento de negócios e atendimento ao cliente. Ele tem uma forte formação na implementação de processos de vendas e programas de treinamento, demonstrando seu compromisso de melhorar o desempenho organizacional e a satisfação do cliente.",
    "employment_history": [
      {
        "details": "Aumento das vendas implementando um novo processo de vendas e criando novos materiais de vendas. Revisou e avaliou os dados dos clientes em potencial e as técnicas de geração de leads, resultando em novas oportunidades de vendas. Implementou um novo programa de treinamento de vendas para funcionários novos e existentes, aumentando o volume médio de vendas. Abordou proativamente possíveis questões de vendas, levando a uma redução no faturamento da força de vendas.",
        "end_date": "",
        "location": "Lahore",
        "job_title": "Líder de desenvolvimento de negócios",
        "start_date": "",
        "company_name": "Dados trans"
      },
      {
        "details": "Garantiu altos níveis de atendimento ao cliente na respectiva divisão/seção para obter uma imagem positiva da marca e experiência do cliente. Alvos da organização atingida/alcançada para manter a tendência de negócios lucrativa. Envolvido no planejamento de uma nova estratégia e uma nova rotação, que tem um efeito imenso na taxa de retenção da marca.",
        "end_date": "09-2022",
        "location": "Lahore",
        "job_title": "Gerente de atendimento ao cliente",
        "start_date": "",
        "company_name": "Carro primeiro"
      },
      {
        "details": "Produziu a maior classificação de satisfação do cliente do ano com a cooperação da minha equipe, fornecendo acompanhamento e serviço personalizados. Garantiu a precisão dos dados, acompanhando todas as chamadas de clientes por meio de planilhas e software da empresa.",
        "end_date": "10-2021",
        "location": "Lahore",
        "job_title": "Líder de operações",
        "start_date": "",
        "company_name": "Abacus Consulting"
      },
      {
        "details": "Seguiu os principais indicadores de desempenho e alcançou os benchmarks de desempenho definidos pela empresa e às partes interessadas. Analisou os KPIs para identificar fraquezas, propondo e implementando soluções robustas.",
        "end_date": "01-2019",
        "location": "",
        "job_title": "Executivo de Desenvolvimento de Negócios",
        "start_date": "",
        "company_name": "Resíduos Busters Gerenciamento de Resíduos Sólidos Pvt"
      }
    ]
  }
}