{
  "job_description": "Gerente de Desenvolvimento de Negócios\n\n** Empresa fictícia ** está buscando um gerente de desenvolvimento de negócios dinâmico e estratégico para ingressar em nossa equipe crescente. Nesta função, você desenvolverá e executará estratégias de vendas, gerenciará as principais contas e liderará iniciativas de desenvolvimento de negócios para impulsionar o crescimento organizacional.\n\nResponsabilidades ####:\n- Desenvolva e implemente estratégias para o desenvolvimento de negócios para atingir objetivos corporativos.\n- Supervisionar todo o ciclo de vendas, da geração de leads a acordos de fechamento.\n- Gerenciar e orientar uma equipe de executivos de desenvolvimento de negócios, aprimorando seu potencial para otimizar o sucesso da empresa.\n- Aprimore a presença da empresa por meio de engajamento ativo em plataformas on -line como o LinkedIn e os sites de rede profissional.\n-Envolva-se em negociações de alto risco e coordenam com as principais partes interessadas da conta para garantir a satisfação do cliente e as parcerias de longo prazo.\n\n#### Requisitos:\n- Utilize habilidades analíticas para identificar novas oportunidades e tendências de mercado.\n- Use o Microsoft Office Suite de maneira eficaz para planejar, relatar e apresentar estratégias de vendas.\n\nJunte -se a nós para desempenhar um papel fundamental na expansão de nossos negócios localmente e internacionalmente, trabalhando ao lado de uma equipe dinâmica em um ambiente inovador. Se você gosta de tomar iniciativas e liderar iniciativas de negócios impactantes, queremos ouvir você!",
  "additional_info": "Os candidatos preferidos terão se formado nas principais escolas de negócios, como núcleos rápidos ou Lums. A empresa apóia a realocação de funcionários no Paquistão com a assistência logística necessária. As habilidades são avaliadas por meio de uma combinação de entrevistas técnicas e estudos de caso práticos alinhados aos desafios do setor.",
  "resume": "Saad A. Mubarak \nExecutivo de BI e Marketing Digital \nsaadali.frt@gmail.com \n+92 323 4217884 \nLahore \nLinkedIn.com/in/saadmali346 \nSou um profissional de marketing experiente com os 3 anos de experiência em desenvolvimento de negócios, inteligência de negócios e marketing digital\nsetores. Acredito muito em trabalho em equipe, solução de problemas, liderança e adaptabilidade como um diretor de cinema que acredita no de alguém\nideia e adapta essa ideia; trabalha com a equipe na ideia; lidera a equipe, recebe instruções da equipe e resolve sua equipe\nproblema e complete a visão. \nEDUCAÇÃO \nMS Marketing \nFaculdade Nacional de Administração de Empresas\n& Economics \n03/2021 - presente\n, Assim, \n \nBacharel em Comércio em Informações\nTecnologia \nUniversidade do Punjab \n06/2017 - 10/2019\n, Assim, \n \nLahore \nExperiência de trabalho \nExecutivo de BI e Marketing Digital \nTOTHECHONDOWN TOTHOLOGIAS PVT. Ltd. \n12/2020 - presente\n, Assim, \n \nLahore \nEstou trabalhando na equipe de crescimento onde olho por cima\nPesquisa de mercado, que inclui sucata e\nVisualizando dados de diferentes negócios de acordo com o nicho. \nEstou trabalhando no final do marketing digital, onde principalmente eu\nColoque meus esforços em marketing por e -mail. Em marketing por e -mail,\nEu executo campanhas de e -mail automatizadas e campanhas de gotejamento\ndo HubSpot \nTambém estou olhando para a automação Martech, onde eu\nOlhe para o topo e o meio do funil de marketing. \nExecutivo de Desenvolvimento de Negócios \nMatrix Tech LLC \n11/2019 - 10/2020\n, Assim, \n \nLahore \nMatrix era um contact center que vendeu serviços de SEO para o\nMercado dos EUA. \nEnviei campanhas de marketing por e -mail para o seu prospectivo\nPúblico para dirigir trafeder e gerar leads. \nEu costumava trabalhar na pesquisa de palavras -chave dos clientes e também\nleads de contato através de diferentes meios e também eu fiz\nDiscando ali. \nExecutivo de processamento de documentos \nSystem Limited \n02/2019 - 11/2019\n, Assim, \n \nLahore \nEu estava no departamento de terceirização de processos de negócios,\nonde eu trabalhei em seu projeto terrestre. \nEu costumava compilar e completar os dados conforme a propriedade\ntipo. \nTambém realizei uma verificação de qualidade no arquivo de propriedade. \nHABILIDADES \nPesquisa de mercado \nDesenvolvimento de negócios \nVisualização de dados \nAutomação de marketing \nGeração de chumbo \nMarketing por e -mail \nHubSpot \nSendinBlue \nMailChimp \nScapping Web \nMarketing de mecanismo de pesquisa \nMarketing de mídia social \nOtimização do mecanismo de pesquisa (SEO) \nPesquisa de palavras -chave \nProjetos \nEspecialista em automação de marketing para revvlab\n (07/2022 - presente)\n \nEstou trabalhando no marketing deles como consultor para configurar o\nAutomação para suas diferentes marcas. \nProjeto de engajamento de negócios para alojamento falcões\n (04/2022 - presente)\n \nEstou trabalhando lá como executivo de engajamento de negócios com\nsua equipe. Eu lido com a conta de trabalho de trabalho e executei e -mail\ncampanhas de marketing para eles. \nProjeto de marketing por email para eclipse\n (09/2021 - 02/2022)\n \nEu trabalhei lá como executivo de marketing e costumava raspar dados\npara eles de acordo com o nicho deles. Eu executei campanhas de e -mail para eles,\nque incluíam e -mails de marketing e campanhas de gotejamento. \nCertificações \nOs fundamentos do marketing digital \nAnalítica avançada do Google \nGoogle Analytics para iniciantes \nIdiomas \nInglês \nProfiência profissional completa \nInteresses \nFilmes \nDireção \nGrilo \nTarefas \nTarefas \nTarefas",
  "details": {
    "name": "Saad A. Mubarak",
    "number": "923234217884",
    "skills": [
      "Pesquisa de mercado",
      "Visualização de dados",
      "Automação de marketing",
      "Geração de chumbo",
      "Marketing por e -mail",
      "HubSpot",
      "SendinBlue",
      "MailChimp",
      "Scapping Web",
      "Marketing de mecanismo de pesquisa",
      "Marketing de mídia social",
      "Otimização do mecanismo de pesquisa (SEO)",
      "Pesquisa de palavras -chave"
    ],
    "email_id": "saadali.frt@gmail.com",
    "location": "Lahore",
    "projects": [
      {
        "title": "Especialista em automação de marketing para revvlab",
        "description": "Consultor para configurar a automação de marketing para diferentes marcas."
      },
      {
        "title": "Projeto de engajamento de negócios para alojamento falcões",
        "description": "Lida com a conta de trabalho e executa campanhas de marketing por email."
      },
      {
        "title": "Projeto de marketing por email para eclipse",
        "description": "Dados raspados e executaram campanhas de email, incluindo e -mails de marketing e campanhas de gotejamento."
      }
    ],
    "education": [
      {
        "end_date": "Presente",
        "university": "Faculdade Nacional de Administração de Empresas e Economia",
        "degree_title": "MS Marketing"
      },
      {
        "end_date": "10-2019",
        "university": "Universidade do Punjab",
        "degree_title": "Bacharel em Comércio em Tecnologia da Informação"
      }
    ],
    "achievements": [],
    "publications": [],
    "certifications": [
      {
        "certification_name": "Os fundamentos do marketing digital",
        "issuing_organization": "Google",
        "date_of_issuance": "01-2021"
      },
      {
        "certification_name": "Analítica avançada do Google",
        "issuing_organization": "Google",
        "date_of_issuance": "01-2021"
      },
      {
        "certification_name": "Google Analytics para iniciantes",
        "issuing_organization": "Google",
        "date_of_issuance": "01-2021"
      }
    ],
    "additional_urls": [
      {
        "url": "LinkedIn.com/in/saadmali346",
        "website_name": "LinkedIn"
      }
    ],
    "executive_summary": "Saad A. Mubarak é um executivo qualificado de BI e de marketing digital, com mais de três anos de experiência em desenvolvimento de negócios, inteligência de negócios e marketing digital. Ele é especialista em pesquisa de mercado, visualização de dados e automação de marketing, demonstrando uma forte proficiência em ferramentas como HubSpot e MailChimp.",
    "employment_history": [
      {
        "details": "Trabalhando na equipe de crescimento com foco em pesquisas de mercado, raspagem de dados e visualização de dados. Responsável por campanhas de marketing por email e automação da Martech.",
        "end_date": "Presente",
        "location": "Lahore",
        "job_title": "Executivo de BI e Marketing Digital",
        "start_date": "12-2020",
        "company_name": "TOTHECHONDOWN TOTHOLOGIAS PVT. Ltd."
      },
      {
        "details": "Enviou campanhas de marketing por email para impulsionar o tráfego e gerar leads para serviços de SEO. Conduziu pesquisa de palavras -chave e entrou em contato com leads.",
        "end_date": "10-2020",
        "location": "Lahore",
        "job_title": "Executivo de Desenvolvimento de Negócios",
        "start_date": "11-2019",
        "company_name": "Matrix Tech LLC"
      },
      {
        "details": "Trabalhou no departamento de terceirização de processos de negócios, compilando e concluindo dados conforme tipo de propriedade e executando verificações de qualidade.",
        "end_date": "11-2019",
        "location": "Lahore",
        "job_title": "Executivo de processamento de documentos",
        "start_date": "02-2019",
        "company_name": "System Limited"
      }
    ]
  }
}