{
  "job_description": "** Título: Gerente de Desenvolvimento de Negócios **  \n\n** Empresa: MarketPros Enterprises **  \n\n** Localização: remoto com potencial viagens para locais de clientes **  \n\n**Sobre nós:**  \nA MarketPros Enterprises é um fornecedor global líder de soluções de negócios inovadoras, com o objetivo de maximizar o crescimento da marca. Trabalhamos com diversas indústrias para aprimorar sua infraestrutura de vendas e fornecer estratégias incomparáveis ​​de envolvimento do cliente.  \n\n** Visão geral da função: **  \nComo gerente de desenvolvimento de negócios da MarketPros Enterprises, você será responsável por liderar iniciativas estratégicas que impulsionam o crescimento dos negócios, aumentam a participação de mercado e fortalecem as relações com os clientes. Você gerenciará equipes multifuncionais para implementar estratégias de vendas, aproveitar as idéias do mercado e impulsionar a expansão da marca.  \n\n** Responsabilidades -chave: **  \n- Desenvolver e implementar estratégias de negócios abrangentes para aumentar o crescimento da receita.  \n- Liderar uma equipe na execução de campanhas de marketing e otimizar os pipelines de vendas.  \n- Utilize ferramentas de análise de dados para produzir informações acionáveis, melhorando o desempenho geral.  \n- Realize pesquisas de mercado para identificar tendências do setor e novas oportunidades de negócios.  \n- Envolva-se com clientes em potencial por meio de apresentações e promova relacionamentos de longo prazo.  \n- Gerenciar sistemas CRM (Salesforce, HubSpot) para otimizar as operações e aprimorar a produtividade.  \n\n** Habilidades preferidas: **  \n- Proficiência em planejamento estratégico e análise de mercado.  \n- Fortes habilidades de liderança com experiência comprovada no desenvolvimento de equipes.  \n- Conhecimento avançado de software CRM e ferramentas de marketing digital.  \n- Excelentes habilidades de comunicação e negociação.  \n\nJunte -se a nós para ultrapassar os limites da inovação de negócios e nos ajudar a alcançar nossos objetivos de expansão.",
  "additional_info": "A MarketPros Enterprises valoriza a diversidade na contratação e incentiva aplicativos de profissionais de negócios experientes com origens variadas. As universidades preferenciais incluem instituições da Ivy League e as principais escolas de negócios. Oferecemos benefícios de realocação para candidatos excepcionais e facilitamos os acordos de trabalho remotos. As competências técnicas e estratégicas são avaliadas através de uma mistura de avaliações psicométricas e entrevistas com estudos de caso.",
  "resume": "Afnan Faiz \n  \n  \n  \nResumo profissional  \nUm comunicador qualificado e direcionado para a meta, equipespitited, persuasiva, \nIndivíduo adaptável, auto -motivado e orientado para a carreira, buscando \nutilizar habilidades e experiência analíticas para contribuir com o seu \ncrescimento e objetivos da organização.  \n  \n  \n  \nHistória do trabalho  \n \nExecutivo de Desenvolvimento de Negócios (março de 202 2 a julho de 2022)   \nTechnerds Inc. - Lahore, Punjab   \n   \n· Gerenciamento de lances de upwork.  \n· LinkedIn com o Sales Navigator às perspectivas de destino.   \n· Análise de projetos e desenvolvimento de propostas.    \n· Relatórios de sucesso da equipe de desenvolvimento mensal e semanal.   \n· Marketing por e -mail.  \n \n \nOficial sênior de desenvolvimento de negócios (outubro de 2021 - fevereiro de 2022) \nCybexo Inc. - Lahore, Punjab  \n \n· Gerenciamento de lances de upwork.  \n· LinkedIn com o Sales Navigator às perspectivas de destino.  \n· Desenvolvimento de sites e Desenvolvimento de aplicativos Manuseio de clientes.   \n· Gerenciamento de desenvolvimento de projetos e reuniões de clientes \ngerenciamento.  \n· Análise de projetos e desenvolvimento de propostas.  \n· Relatórios de sucesso da equipe de desenvolvimento mensal e semanal.  \n· Colaborar com a equipe de desenvolvimento e fornecer a todos \nas informações para o desenvolvimento do projeto. \n· Marketing por e -mail via Sendy.  \n \n \nOficial de Desenvolvimento de Negócios (outubro de 2019 - outubro de 2021) \nWebsouls - Lahore, Punjab  \n \n· Desenvolvimento de sites, SEO e manuseio de clientes SMM.   \n· Gerenciamento de desenvolvimento de projetos e reuniões de clientes \ngerenciamento.  \n· Análise de projetos e desenvolvimento de propostas.  \n· Relatórios mensais da equipe de desenvolvimento semanal.  \n· Colaborar com a equipe de desenvolvimento e fornecer a todos \nas informações para o desenvolvimento do projeto. \n· Marketing por e -mail. \n· Coupa de cinco, upwork e freelancer CAs e gerenciamento de lances.  \n \nEmail Support Executive - Systems Limited (janeiro de 2019 - março de 2019):   \n· Manipulação de bate -papos e e -mails de clientes internacionais.     \nCONTATO  \nEndereço: Lahore, PB 54000   \nTelefone: +92 (304) (1418484)  \nE -mail: afnanfaiz273@gmail.com  \nLinkedIn: https://www.linkedin.com/in\n/Afnanfaiz/  \n  \n  \n  \nHABILIDADES  \n● Microsoft Office.  \n● Trabalho de pesquisa.  \n● Aprendiz rápido.  \n● Apresentações projetando e \ndesenvolvimento . \n● Desenvolvimento de negócios.  \n● Construindo relações com os clientes.  \n● Engajamento do cliente.  \n● Relatórios de análise.  \n● Gerenciamento de projetos. \n● Desenvolvimento da proposta.  \n● Marketing por e -mail.  \n  · Assistência inclui rastrear os pedidos dos clientes de diferentes correios \nportais e fornecendo as informações e soluções corretas para o \nclientes de acordo com as políticas da organização.  \n \nEmail Support Executive - Mindbridge (maio de 2017 - dezembro de 2018):  \n                 \n· Lidar com e -mails dos clientes internacionais da Uber.  \n· Assistência inclui rastrear os registros dos clientes e fornecer o direito \ninformações e soluções para os clientes, de acordo com os da organização \npolíticas.  \n \n \n  \n  \n  \nEDUCAÇÃO  \n(2020 -2022) Mestrado em Administração de Empresas (MBA) de  \nRápido -NUCE LAHORE.          \n(2015 -2019) Bacharelado em Administração de Empresas (BBA Hons) \nde NCBA & e. \n(2012-2014) Intermediário em ciências do computador (ICS) de \nGrupo de Faculdades Punjab. \n(2010-2012) Matrícula  \nGovt. Escola piloto de garotas secundárias piloto.",
  "details": {
    "name": "Afnan Faiz",
    "number": "923041418484",
    "skills": [
      "Microsoft Office",
      "Desenvolvimento de negócios",
      "Gerenciamento de projetos",
      "Desenvolvimento da proposta",
      "Marketing por e -mail"
    ],
    "email_id": "afnanfaiz273@gmail.com",
    "location": "Lahore, PB 54000",
    "projects": [],
    "education": [
      {
        "end_date": "06-2022",
        "university": "Rápido -NUCE LAHORE",
        "degree_title": "Mestrado em Administração de Empresas (MBA)"
      },
      {
        "end_date": "06-2019",
        "university": "NCBA & E.",
        "degree_title": "Bacharelado em Administração de Empresas (BBA Hons)"
      },
      {
        "end_date": "06-2014",
        "university": "Grupo de Faculdades Punjab",
        "degree_title": "Intermediário em ciências do computador (ICS)"
      },
      {
        "end_date": "06-2012",
        "university": "Govt. Escola piloto de garotas secundárias piloto",
        "degree_title": "Matrícula"
      }
    ],
    "achievements": [],
    "publications": [],
    "certifications": [],
    "additional_urls": [
      {
        "url": "linkedin.com/in/afnanfaiz/",
        "website_name": "LinkedIn"
      }
    ],
    "executive_summary": "Afnan Faiz é um profissional dedicado de desenvolvimento de negócios, com uma forte experiência no gerenciamento de projetos, no desenvolvimento de propostas e na execução de estratégias de marketing por email. Com experiência em várias funções, a Afnan demonstrou proficiência no Microsoft Office and Business Development, contribuindo efetivamente para o sucesso da equipe.",
    "employment_history": [
      {
        "details": "O Upwork Bids Management, LinkedIn com o Navigator de vendas a perspectivas de destino, análise de projetos e desenvolvimento de propostas, relatórios de sucesso da equipe de desenvolvimento mensal e semanal, marketing por email.",
        "end_date": "07-2022",
        "location": "Lahore, Punjab",
        "job_title": "Executivo de Desenvolvimento de Negócios",
        "start_date": "03-2022",
        "company_name": "Technerds Inc."
      },
      {
        "details": "A UPWORK BIDS Management, LinkedIn com o navegador de vendas a perspectivas de destino, desenvolvimento de sites e desenvolvimento de clientes de aplicativos, gerenciamento de gerenciamento de desenvolvimento de projetos e gerenciamento de reuniões de clientes, análise de projetos e desenvolvimento de propostas, reportagem de sucesso da equipe de desenvolvimento mensal e semanal, colabore com a equipe de desenvolvimento e forneça todas as informações para o desenvolvimento do projeto, marketing por email por meio de envio.",
        "end_date": "02-2022",
        "location": "Lahore, Punjab",
        "job_title": "Diretor de Desenvolvimento de Negócios Sênior",
        "start_date": "10-2021",
        "company_name": "Cybexo Inc."
      },
      {
        "details": "Desenvolvimento de sites, Manuseio de clientes SMM e SMM, Gerenciamento de desenvolvimento de projetos e Gerenciamento de reuniões de clientes, análise de projetos e desenvolvimento de propostas, Relatórios mensais da equipe de desenvolvimento semanal, colaboram com a equipe de desenvolvimento e fornecem todas as informações para o desenvolvimento do projeto, marketing por email, cinco, trabalhos e contas freelancers e gerenciamento de lances.",
        "end_date": "10-2021",
        "location": "Lahore, Punjab",
        "job_title": "Oficial de Desenvolvimento de Negócios",
        "start_date": "10-2019",
        "company_name": "Websouls"
      },
      {
        "details": "Manipulação de bate -papos e e -mails de clientes internacionais.",
        "end_date": "03-2019",
        "location": "",
        "job_title": "Email Support Executive",
        "start_date": "01-2019",
        "company_name": "Systems Limited"
      },
      {
        "details": "O manuseio de e -mails dos clientes internacionais da Uber, a assistência inclui rastrear os registros dos clientes e fornecer as informações e soluções corretas para os clientes, de acordo com as políticas da organização.",
        "end_date": "12-2018",
        "location": "",
        "job_title": "Email Support Executive",
        "start_date": "05-2017",
        "company_name": "Mindbridge"
      }
    ]
  }
}