{
  "job_description": "## Título do trabalho: Especialista em gerenciamento de vendas e SEO  \n\n### Localização: Lahore, Paquistão  \n\n### Empresa: Innovate Digital Solutions Inc.  \n\nResumo do trabalho:  \nParticipe da Innovate Digital Solutions Inc. como especialista em gerenciamento de vendas e SEO. Você fará parte de uma equipe dinâmica responsável por impulsionar o envolvimento do cliente e garantir o desempenho ideal em estratégias de marketing digital. Sua função incluirá o gerenciamento do relacionamento com os clientes, a melhoria das estratégias de SEO e a liderança de sua equipe a atingir metas de vendas.  \n\n### Responsabilidades -chave:  \n- Envolva -se proativamente com clientes em potencial para entender suas necessidades de negócios e fornecer soluções inovadoras.  \n- Projete e execute estratégias de SEO em alinhamento com os objetivos de marketing do cliente.  \n- Gerenciar e otimizar as campanhas do PPC para maximizar o ROI e a visibilidade da marca.  \n- Desenvolva e mantenha um forte relacionamento com os clientes por meio de soluções de marketing personalizadas.  \n- Lidere uma equipe a alcançar e superar as metas de vendas, fornecendo um atendimento excepcional ao cliente.  \n- Analise as tendências e algoritmos do mercado para adaptar as estratégias de SEO de acordo.  \n- Produza relatórios que acompanham o progresso e medem o sucesso contra os KPIs.  \n\n### Perfil de candidato ideal:  \nVocê é um profissional qualificado de vendas e marketing, com fortes habilidades analíticas adequadas para identificar e executar oportunidades de SEO. Você se destaca nas interações do cliente, possuindo a capacidade de transformar possíveis leads em clientes satisfeitos por meio de iniciativas de marketing estratégicas e bem executadas. As habilidades de liderança e gerenciamento de equipes serão fundamentais para impulsionar as vendas e motivar sua equipe.  \n\n### benefícios:  \n- Pacote de salário competitivo  \n- Benefícios de saúde e bem -estar  \n- Bônus de desempenho  \n- Oportunidades de avanço na carreira  \n\nJunte -se a nós para redefinir o engajamento digital e liderar estratégias de mercado com agilidade e inovação.",
  "additional_info": "A Innovate Digital Solutions Inc. prefere candidatos de instituições respeitáveis ​​como [Universidade de Lahore], [Universidade de Punjab]. As opções de trabalho remotas estão disponíveis sujeitas a funções e responsabilidades. Avaliamos as habilidades por meio de uma combinação de testes técnicos, entrevistas e cenários de solução de problemas do mundo real para avaliar a competência prática em contextos estratégicos de marketing.",
  "resume": "Contato\nDubai, Emirados Árabes Unidos \nNúmero dos Emirados Árabes Unidos: +971504680678\nNúmero PAK: +923108141420\nNúmero KSA: +966546978135\nyahyamalik1@outlook.com\nwww.linkedin.com/in/\nEngryahyamalik (LinkedIn)\nPrincipais habilidades\nAutomação\nInstrumentação\nOT Cyber ​​Security\nIdiomas\nInglês (trabalho profissional)\nCertificações\nISA 62443 Cibersegurança\nEspecialista em Fundamentos\nNSE 1,2,3 Segurança de rede\nAssociado\nProfissional de vendas certificado nozomi\n(NNCTSP) \nIelts General \nVendas certificadas da Honeywell\nProfissional no controle de processo\nSistemas\nHonors-Acwards\nOrganizador - Técnico anual\nConferência 2017\nOrganizador - Pogee 2018\nOrganizer-Ot Cybersecurity\nConferência de implementação por ISA\nSegurança do organizador para críticas\nAtivos MENA\nFuncionário do mês Awardyahya M.\nGerente de Desenvolvimento de Negócios | Líder de vendas | Industrial\nAutomação | Gerente de conta | OT Cybersecurity ISA 62443 CFS\n| Transformação digital | Integração IT/OT | Multimilionário fechado $\nProjetos nos últimos 5 anos\nDubai, Emirados Árabes Unidos\nResumo\nyahyamalik1@outlook.com \nYahya Malik é um engenheiro experiente que virou marketing, com 9+\nAnos de diversas experiência no campo das vendas B2B, negociação,\nGerenciamento de relações com clientes, processo de gerenciamento de produtos\nAutomação e segurança cibernética com um grande interesse em IIOT.\nTrabalhou com líderes do setor, como Nozomi Networks, Palo Alto,\nFortinet, ABB, Rockwell Automation, Yokogawa, Honeywell, General\nMonitores, Trend Micro, Txone e Schneider. Criando vitória para ganhar\nestratégia para minha organização e para meus clientes também\nAtualmente, estou trabalhando como gerente de desenvolvimento de negócios na ACET\nSoluções. Aqui, não estamos apenas ajudando as empresas com nosso AT e\nSoluções de ICS, mas também ajudando -os a garantir sua infraestrutura digital\nAtravés de nossas práticas aprofundadas de segurança cibernética. Com profunda experiência em\nmaduro e emergente OT/isso significa que estamos ajudando várias verticais\nautomatizar seus processos, proteger sua infraestrutura e aprimorar\nprodutividade operacional\nMeu forte variando de geração de leads, pesquisa de mercado, negócios\nDesenvolvimento, vendas internacionais, gerenciamento de contas -chave, vendas\nOperações, estratégia de vendas, gerenciamento de produtos, novos negócios\nDesenvolvimento e satisfação do cliente\nEntendimento fundamental dos princípios básicos de segurança cibernética do OT/ICS e\nconceitos modernos relacionados a;\n-Firewalls, detecção e prevenção de intrusões, DMZ's, remoto\nSoluções de acesso \n-Data Prevenção de vazamentos\n-Secure nuvem, segurança de dados, ferramentas de operações de segurança,\n  Página 1 de 3   \n-Isa 62443 e outros padrões de segurança cibernética OT\nTecnologias: \nAutomação industrial | Indústria 4.0 | IoT industrial | IT/OT\nIntegração | Sistema de Gerenciamento da Enterprise | Historiador de dados e\nnuvem | Segurança cibernética | Scada | Solar | Elétrico | Instrumentação |\nEnergia renovável | \nVerticais da indústria:\nPetróleo e gás | Processo | Utilitários e poder | Metais | Fmcg\nGeografias:\nPaquistão | Gcc | África Ocidental | Cingapura | EUA\nClientes: \nFortuna 100 | Governo | EPCS | OEMs \nCompetências funcionais: \nPlanejamento e execução da estratégia | Propostas de produtos e soluções\n| P&L Management | Gerenciamento de conta -chave | Negociações\n| Desenvolvimento de negócios | Gerenciamento de relacionamento com o cliente\n| Análise competitiva | Solução e Serviços Sales Demand\nGeração | Posicionamento da marca | Alianças e parcerias estratégicas |\nTransformação digital | Sistemas de controle (PLC, DCS, SCADA) | EPC\nConecte -se com Yahya:\nWatsapp Emirados Árabes Unidos: +971 50 468 0678\nWatsapp KSA: +966 54 697 8135\nWatsapp Pak: +92 310 814 1420 \nID oficial de e -mail: yahya.malik@acetsolutions.com\nExperiência\nSoluções ACET\nGerente de Desenvolvimento de Negócios\nJunho de 2021-presente (2 anos)\nEmirados Árabes Unidos\n  Página 2 de 3   \n-Olhando após as vendas e o desenvolvimento de negócios da automação, OT\nSoluções de Tecnologia Enterprise Digital de segurança cibernética no Paquistão e Médio\nMercado Leste\nSociedade Internacional de Automação (ISA)\n2 anos 5 meses\nPresidente eleito\nOutubro de 2022-presente (8 meses)\nMembro do conselho (webinars e seminários)\nJaneiro de 2021-outubro de 2022 (1 ano 10 meses)\nDescon\nGerente de Desenvolvimento de Negócios\nNovembro de 2017-maio ​​de 2021 (3 anos 7 meses)\nEmirados Árabes Unidos\nAutomação enxuta\nEngenheiro de Aplicativo de Design\nJaneiro de 2016-outubro de 2017 (1 ano 10 meses)\nEmirados Árabes Unidos\nBebidas Coca-Cola Pakistan Limited\nTrainee de gestão de pós -graduação\nJaneiro de 2015-dezembro de 2015 (1 ano)\nPaquistão\nEducação\nLahore University of Management Sciences\nArte de vender idéias-advertionar 101, impressão, ao ar livre e digital\nMarketing · (março de 2021)\nNebosh\nCertificado Geral Internacional de Nebosh em Saúde Ocupacional e\nSegurança, Saúde Ocupacional e Segurança · (janeiro de 2021)\nUniversidade de Comsats\nEngenheiro de Engenharia, Engenharia Elétrica e Eletrônica · (2010)\n  Página 3 de 3",
  "details": {
    "name": "Yahya Malik",
    "number": "971504680678",
    "skills": [
      "Automação",
      "Instrumentação",
      "OT Cyber ​​Security",
      "Automação industrial",
      "Indústria 4.0",
      "IoT industrial",
      "Integração IT/OT",
      "Sistema de gerenciamento corporativo",
      "Historiador de dados e nuvem",
      "Segurança cibernética",
      "Scada",
      "Solar",
      "Elétrica",
      "Instrumentação",
      "Energia renovável"
    ],
    "email_id": "yahyamalik1@outlook.com",
    "location": "Dubai, Emirados Árabes Unidos",
    "projects": [],
    "education": [
      {
        "end_date": "03-2021",
        "university": "Lahore University of Management Sciences",
        "degree_title": "Arte de vender idéias-advertirizar 101, impressão, marketing externo e digital"
      },
      {
        "end_date": "01-2021",
        "university": "Nebosh",
        "degree_title": "Certificado Geral Internacional de Nebosh em Saúde e Segurança Ocupacional"
      },
      {
        "end_date": "2010",
        "university": "Universidade de Comsats",
        "degree_title": "Engenheiro de Engenharia, Engenharia Elétrica e Eletrônica"
      }
    ],
    "achievements": [
      "Organizador - Conferência Técnica Anual 2017",
      "Organizador - Pogee 2018",
      "Organizador - Conferência de implementação de segurança cibernética da ISA",
      "Organizador - segurança cibernética para ativos críticos MENA",
      "Prêmio de funcionário do mês"
    ],
    "publications": [],
    "certifications": [
      {
        "certification_name": "Especialista em fundamentos de segurança cibernética do ISA 62443",
        "issuing_organization": "Isa",
        "date_of_issuance": "01-2021"
      },
      {
        "certification_name": "NSE 1,2,3 Associado de Segurança de Rede",
        "issuing_organization": "Fortinet",
        "date_of_issuance": "01-2021"
      },
      {
        "certification_name": "Profissional de vendas certificado nozomi (NNCTSP)",
        "issuing_organization": "Redes Nozomi",
        "date_of_issuance": "01-2021"
      },
      {
        "certification_name": "Ielts General",
        "issuing_organization": "Conselho Britânico",
        "date_of_issuance": "01-2021"
      },
      {
        "certification_name": "Profissional de vendas certificado pela Honeywell em sistemas de controle de processos",
        "issuing_organization": "Honeywell",
        "date_of_issuance": "01-2021"
      }
    ],
    "additional_urls": [
      {
        "url": "LinkedIn.com/in/engryahyamalik",
        "website_name": "LinkedIn"
      }
    ],
    "executive_summary": "Yahya Malik é um engenheiro experiente que virou marketing, com mais de 9 anos de experiência diversificada em vendas B2B, negociação, gerenciamento de relações com clientes, gerenciamento de produtos, automação de processos e segurança cibernética. Ele trabalhou com líderes do setor e atualmente é gerente de desenvolvimento de negócios da ACET Solutions, com foco em soluções de automação e segurança cibernética. Sua experiência inclui geração de leads, pesquisa de mercado e transformação digital, tornando -o um ativo valioso para aumentar a produtividade operacional em vários setores.",
    "employment_history": [
      {
        "details": "Olhando para as vendas e o desenvolvimento de negócios da automação, a OT Cybersecurity & Digital Enterprise Technology Solutions no Paquistão e no Oriente Médio Mercado",
        "end_date": "Presente",
        "location": "Emirados Árabes Unidos",
        "job_title": "Gerente de Desenvolvimento de Negócios",
        "start_date": "06-2021",
        "company_name": "Soluções ACET"
      },
      {
        "details": "Presidente eleito e membro do conselho (webinars e seminários)",
        "end_date": "Presente",
        "location": "Emirados Árabes Unidos",
        "job_title": "Presidente eleito",
        "start_date": "10-2022",
        "company_name": "Sociedade Internacional de Automação (ISA)"
      },
      {
        "details": "Gerente de Desenvolvimento de Negócios",
        "end_date": "05-2021",
        "location": "Emirados Árabes Unidos",
        "job_title": "Gerente de Desenvolvimento de Negócios",
        "start_date": "11-2017",
        "company_name": "Descon"
      },
      {
        "details": "Engenheiro de Aplicativo de Design",
        "end_date": "10-2017",
        "location": "Emirados Árabes Unidos",
        "job_title": "Engenheiro de Aplicativo de Design",
        "start_date": "01-2016",
        "company_name": "Automação enxuta"
      },
      {
        "details": "Trainee de gestão de pós -graduação",
        "end_date": "12-2015",
        "location": "Paquistão",
        "job_title": "Trainee de gestão de pós -graduação",
        "start_date": "01-2015",
        "company_name": "Bebidas Coca-Cola Pakistan Limited"
      }
    ]
  }
}