{
  "job_description": "** Título: Gerente de Desenvolvimento de Negócios **  \n\n** Empresa: MarketPros Enterprises **  \n\n** Localização: remoto com potencial viagens para locais de clientes **  \n\n**Sobre nós:**  \nA MarketPros Enterprises é um fornecedor global líder de soluções de negócios inovadoras, com o objetivo de maximizar o crescimento da marca. Trabalhamos com diversas indústrias para aprimorar sua infraestrutura de vendas e fornecer estratégias incomparáveis ​​de envolvimento do cliente.  \n\n** Visão geral da função: **  \nComo gerente de desenvolvimento de negócios da MarketPros Enterprises, você será responsável por liderar iniciativas estratégicas que impulsionam o crescimento dos negócios, aumentam a participação de mercado e fortalecem as relações com os clientes. Você gerenciará equipes multifuncionais para implementar estratégias de vendas, aproveitar as idéias do mercado e impulsionar a expansão da marca.  \n\n** Responsabilidades -chave: **  \n- Desenvolver e implementar estratégias de negócios abrangentes para aumentar o crescimento da receita.  \n- Liderar uma equipe na execução de campanhas de marketing e otimizar os pipelines de vendas.  \n- Utilize ferramentas de análise de dados para produzir informações acionáveis, melhorando o desempenho geral.  \n- Realize pesquisas de mercado para identificar tendências do setor e novas oportunidades de negócios.  \n- Envolva-se com clientes em potencial por meio de apresentações e promova relacionamentos de longo prazo.  \n- Gerenciar sistemas CRM (Salesforce, HubSpot) para otimizar as operações e aprimorar a produtividade.  \n\n** Habilidades preferidas: **  \n- Proficiência em planejamento estratégico e análise de mercado.  \n- Fortes habilidades de liderança com experiência comprovada no desenvolvimento de equipes.  \n- Conhecimento avançado de software CRM e ferramentas de marketing digital.  \n- Excelentes habilidades de comunicação e negociação.  \n\nJunte -se a nós para ultrapassar os limites da inovação de negócios e nos ajudar a alcançar nossos objetivos de expansão.",
  "additional_info": "A MarketPros Enterprises valoriza a diversidade na contratação e incentiva aplicativos de profissionais de negócios experientes com origens variadas. As universidades preferenciais incluem instituições da Ivy League e as principais escolas de negócios. Oferecemos benefícios de realocação para candidatos excepcionais e facilitamos os acordos de trabalho remotos. As competências técnicas e estratégicas são avaliadas através de uma mistura de avaliações psicométricas e entrevistas com estudos de caso.",
  "resume": "Ali Ahmad \nGerente de Desenvolvimento de Negócios \nEu sou um gerente de desenvolvimento de negócios qualificado com experiência em estratégia, vendas, negociações e\nGerenciando o ciclo de vendas completo. Também tenho experiência em gerenciamento de contas importantes. Estou procurando um\nposição desafiadora em uma organização onde posso contribuir para alcançar as metas organizacionais enquanto\ndesenvolvendo ainda mais minhas habilidades profissionais para alcançar todo o meu potencial. \naliahmed2312@gmail.com \n03128800078 \nLahore, Paquistão \nEDUCAÇÃO \nBacharel em Administração de Empresas \nNúcleos rápidos \n08/2016 - 08/2020\n, Assim, \n \nLahore \nExperiência de trabalho \nGerente de Desenvolvimento de Negócios \nIkonic \n04/2023 - Presente\n, Assim, \n \nMinha função inclui gerenciar a equipe de desenvolvimento de negócios,\nlidar com as reuniões que eles reservam e efetivação do\nciclo de vendas completo, além de lidar com o ativo do LinkedIn\ncampanhas. \nExecutivo de desenvolvimento de negócios sênior \nE-sparks \n01/2021 - 04/2023\n, Assim, \n \nMeu papel incluiu alcançar as perspectivas de freelancer\nSites (Upwork, Freelancer etc) e LinkedIn,\nsondando para entender seus pontos problemáticos. Gerenciamento de elementos\nde estratégia, vendas, negociações e efeito da\nciclo de vendas completo. \nWelcome Team Advisor \nGrupo gigante \n09/2020 - 12/2020\n, Assim, \n \nLahore, Paquistão \nMeu papel era responder a todas as consultas no limite via chamada ou ao vivo\nbater papo, \nfornecer os melhores conselhos e promover os benefícios de gigante\nGama de serviços do grupo de acordo com os parâmetros acordados como\nbem como acompanhar as perspectivas. \nIntern \nICI Pakistan Limited \n07/2019 - 08/2019\n, Assim, \n \nLahore \nInternado na ala de poliéster da ICI na finalização\ndepartamento e reconciliou seus balanços também\nAnálise financeira completa de seus concorrentes. \nIntern \nCoca Cola \n07/2018 - 08/2018\n, Assim, \n \nLahore \nInternado no departamento comercial e aprendeu sobre\nestratégias de campanha, incluindo campanhas específicas do produto como\nbem como a colocação do produto nos racks e o uso de\noutdoors \nHABILIDADES \nMicrosoft Office (Word/Excel/PowerPoint) \nLicitação do projeto \nRequisitos de coleta \nGerenciamento de contas \nDesenvolvimento de negócios \nProcesso de vendas \nLiderança \nEstratégias de vendas \nHabilidades de negociação \nHabilidades de resolução de problemas \nManuseio de pressão \nPesquisar \nIdiomas \nInglês \nProfiência profissional completa \nurdu \nProfiência profissional completa \nTarefas \nTarefas \nTarefas \nTarefas \nTarefas",
  "details": {
    "name": "Ali Ahmad",
    "number": "03128800078",
    "skills": [
      "Microsoft Office (Word/Excel/PowerPoint)",
      "Licitação do projeto",
      "Requisitos de coleta",
      "Gerenciamento de contas",
      "Desenvolvimento de negócios",
      "Processo de vendas",
      "Estratégias de vendas",
      "Habilidades de negociação",
      "Pesquisar"
    ],
    "email_id": "aliahmed2312@gmail.com",
    "location": "Lahore, Paquistão",
    "projects": [],
    "education": [
      {
        "end_date": "08-2020",
        "university": "Núcleos rápidos",
        "degree_title": "Bacharel em Administração de Empresas"
      }
    ],
    "achievements": [],
    "publications": [],
    "certifications": [],
    "additional_urls": [],
    "executive_summary": "Ali Ahmad é um gerente de desenvolvimento de negócios qualificado, com experiência em gerenciar ciclos de vendas, estratégia e negociações. Ele tem uma forte formação em desenvolvimento de negócios e gerenciamento de contas, buscando contribuir para as metas organizacionais e promover suas habilidades profissionais.",
    "employment_history": [
      {
        "details": "Gerenciando a equipe de desenvolvimento de negócios, lidando com reuniões e executando o ciclo de vendas completo, além de gerenciar campanhas ativas do LinkedIn.",
        "end_date": "Presente",
        "location": "Lahore, Paquistão",
        "job_title": "Gerente de Desenvolvimento de Negócios",
        "start_date": "04-2023",
        "company_name": "Ikonic"
      },
      {
        "details": "Procurando clientes em potencial em sites freelancers e LinkedIn, gerenciamento de estratégia, vendas, negociações e o ciclo completo de vendas.",
        "end_date": "04-2023",
        "location": "Lahore, Paquistão",
        "job_title": "Executivo de desenvolvimento de negócios sênior",
        "start_date": "01-2021",
        "company_name": "E-sparks"
      },
      {
        "details": "Respondendo às consultas de entrada por meio de chat de chamadas ou ao vivo, fornecendo conselhos e promovendo serviços.",
        "end_date": "12-2020",
        "location": "Lahore, Paquistão",
        "job_title": "Welcome Team Advisor",
        "start_date": "09-2020",
        "company_name": "Grupo gigante"
      },
      {
        "details": "Internado no departamento de finanças, reconciliando balanços e realizando análises financeiras.",
        "end_date": "08-2019",
        "location": "Lahore, Paquistão",
        "job_title": "Intern",
        "start_date": "07-2019",
        "company_name": "ICI Pakistan Limited"
      },
      {
        "details": "Internado no departamento comercial, aprendendo sobre estratégias de campanha e colocação de produtos.",
        "end_date": "08-2018",
        "location": "Lahore, Paquistão",
        "job_title": "Intern",
        "start_date": "07-2018",
        "company_name": "Coca Cola"
      }
    ]
  }
}