{
  "job_description": "Gerente de Desenvolvimento de Negócios\n\nJunte -se a ** Innovatecorp ** como gerente de desenvolvimento de negócios para contribuir com nossa crescente equipe e impulsionar iniciativas estratégicas no setor de serviços de tecnologia. O candidato ideal alavancará sua vasta experiência em desenvolvimento de negócios, relações com clientes e gerenciamento de projetos para expandir nossa presença no mercado e criar parcerias duradouras.\n\n#### Responsabilidades -chave:\n- Desenvolver e implementar planos de desenvolvimento estratégico de negócios para alcançar as metas da empresa.\n- Geração de leads e construção de relacionamentos com clientes em potencial.\n- Supervisionar estratégias de aquisição de clientes, incluindo exploração além dos mercados freelancers.\n- Colabore com equipes multifuncionais para garantir a entrega suave do projeto.\n- Utilize o software CRM para rastrear o engajamento do cliente e o progresso do desenvolvimento.\n- Realize pesquisas de mercado para permanecer a par das tendências da indústria e informar estratégias de negócios.\n- Gerenciar e relatar as métricas de desenvolvimento de negócios.\n\n#### Habilidades e competências:\n- Comunicação forte e habilidades interpessoais para envolvimento e colaboração do cliente.\n- Excelentes habilidades analíticas para informar propostas e decisões estratégicas.\n- Experiência no Microsoft Office para documentação e apresentações.\n- Proficiência no software CRM para gerenciar o relacionamento com os clientes.\n\n#### Benefícios:\n- Salário competitivo com incentivos de bônus.\n- Oportunidades de desenvolvimento profissional e avanço na carreira.\n- Pacotes de saúde e seguro odontológico.\n- Horário de trabalho flexível e um ambiente positivo e orientado para a equipe.",
  "additional_info": "A Innovatecorp prefere candidatos de escolas de negócios líderes, como o Comsats Institute of Information and Technology. Apoiamos a realocação para o candidato certo e oferecemos oportunidades de trabalho remotas. As habilidades são avaliadas através de uma combinação de entrevistas técnicas e estudos de caso práticos, garantindo que os candidatos atendam aos nossos altos padrões de desempenho antes de oferecer uma posição.",
  "resume": "Saad A. Mubarak \nExecutivo de BI e Marketing Digital \nsaadali.frt@gmail.com \n+92 323 4217884 \nLahore \nLinkedIn.com/in/saadmali346 \nSou um profissional de marketing experiente com os 3 anos de experiência em desenvolvimento de negócios, inteligência de negócios e marketing digital\nsetores. Acredito muito em trabalho em equipe, solução de problemas, liderança e adaptabilidade como um diretor de cinema que acredita no de alguém\nideia e adapta essa ideia; trabalha com a equipe na ideia; lidera a equipe, recebe instruções da equipe e resolve sua equipe\nproblema e complete a visão. \nEDUCAÇÃO \nMS Marketing \nFaculdade Nacional de Administração de Empresas\n& Economics \n03/2021 - presente\n, Assim, \n \nBacharel em Comércio em Informações\nTecnologia \nUniversidade do Punjab \n06/2017 - 10/2019\n, Assim, \n \nLahore \nExperiência de trabalho \nExecutivo de BI e Marketing Digital \nTOTHECHONDOWN TOTHOLOGIAS PVT. Ltd. \n12/2020 - presente\n, Assim, \n \nLahore \nEstou trabalhando na equipe de crescimento onde olho por cima\nPesquisa de mercado, que inclui sucata e\nVisualizando dados de diferentes negócios de acordo com o nicho. \nEstou trabalhando no final do marketing digital, onde principalmente eu\nColoque meus esforços em marketing por e -mail. Em marketing por e -mail,\nEu executo campanhas de e -mail automatizadas e campanhas de gotejamento\ndo HubSpot \nTambém estou olhando para a automação Martech, onde eu\nOlhe para o topo e o meio do funil de marketing. \nExecutivo de Desenvolvimento de Negócios \nMatrix Tech LLC \n11/2019 - 10/2020\n, Assim, \n \nLahore \nMatrix era um contact center que vendeu serviços de SEO para o\nMercado dos EUA. \nEnviei campanhas de marketing por e -mail para o seu prospectivo\nPúblico para dirigir trafeder e gerar leads. \nEu costumava trabalhar na pesquisa de palavras -chave dos clientes e também\nleads de contato através de diferentes meios e também eu fiz\nDiscando ali. \nExecutivo de processamento de documentos \nSystem Limited \n02/2019 - 11/2019\n, Assim, \n \nLahore \nEu estava no departamento de terceirização de processos de negócios,\nonde eu trabalhei em seu projeto terrestre. \nEu costumava compilar e completar os dados conforme a propriedade\ntipo. \nTambém realizei uma verificação de qualidade no arquivo de propriedade. \nHABILIDADES \nPesquisa de mercado \nDesenvolvimento de negócios \nVisualização de dados \nAutomação de marketing \nGeração de chumbo \nMarketing por e -mail \nHubSpot \nSendinBlue \nMailChimp \nScapping Web \nMarketing de mecanismo de pesquisa \nMarketing de mídia social \nOtimização do mecanismo de pesquisa (SEO) \nPesquisa de palavras -chave \nProjetos \nEspecialista em automação de marketing para revvlab\n (07/2022 - presente)\n \nEstou trabalhando no marketing deles como consultor para configurar o\nAutomação para suas diferentes marcas. \nProjeto de engajamento de negócios para alojamento falcões\n (04/2022 - presente)\n \nEstou trabalhando lá como executivo de engajamento de negócios com\nsua equipe. Eu lido com a conta de trabalho de trabalho e executei e -mail\ncampanhas de marketing para eles. \nProjeto de marketing por email para eclipse\n (09/2021 - 02/2022)\n \nEu trabalhei lá como executivo de marketing e costumava raspar dados\npara eles de acordo com o nicho deles. Eu executei campanhas de e -mail para eles,\nque incluíam e -mails de marketing e campanhas de gotejamento. \nCertificações \nOs fundamentos do marketing digital \nAnalítica avançada do Google \nGoogle Analytics para iniciantes \nIdiomas \nInglês \nProfiência profissional completa \nInteresses \nFilmes \nDireção \nGrilo \nTarefas \nTarefas \nTarefas",
  "details": {
    "name": "Saad A. Mubarak",
    "number": "923234217884",
    "skills": [
      "Pesquisa de mercado",
      "Visualização de dados",
      "Automação de marketing",
      "Geração de chumbo",
      "Marketing por e -mail",
      "HubSpot",
      "SendinBlue",
      "MailChimp",
      "Scapping Web",
      "Marketing de mecanismo de pesquisa",
      "Marketing de mídia social",
      "Otimização do mecanismo de pesquisa (SEO)",
      "Pesquisa de palavras -chave"
    ],
    "email_id": "saadali.frt@gmail.com",
    "location": "Lahore",
    "projects": [
      {
        "title": "Especialista em automação de marketing para revvlab",
        "description": "Consultor para configurar a automação de marketing para diferentes marcas."
      },
      {
        "title": "Projeto de engajamento de negócios para alojamento falcões",
        "description": "Lida com a conta de trabalho e executa campanhas de marketing por email."
      },
      {
        "title": "Projeto de marketing por email para eclipse",
        "description": "Dados raspados e executaram campanhas de email, incluindo e -mails de marketing e campanhas de gotejamento."
      }
    ],
    "education": [
      {
        "end_date": "10-2019",
        "university": "Universidade do Punjab",
        "degree_title": "Bacharel em Comércio em Tecnologia da Informação"
      },
      {
        "end_date": "Presente",
        "university": "Faculdade Nacional de Administração de Empresas e Economia",
        "degree_title": "MS Marketing"
      }
    ],
    "achievements": [],
    "publications": [],
    "certifications": [
      {
        "certification_name": "Os fundamentos do marketing digital",
        "issuing_organization": "Google",
        "date_of_issuance": "Mm-yyyy"
      },
      {
        "certification_name": "Analítica avançada do Google",
        "issuing_organization": "Google",
        "date_of_issuance": "Mm-yyyy"
      },
      {
        "certification_name": "Google Analytics para iniciantes",
        "issuing_organization": "Google",
        "date_of_issuance": "Mm-yyyy"
      }
    ],
    "additional_urls": [
      {
        "url": "LinkedIn.com/in/saadmali346",
        "website_name": "LinkedIn"
      }
    ],
    "executive_summary": "Saad A. Mubarak é um executivo de marketing digital e de BI e mais de três anos de experiência em desenvolvimento de negócios, inteligência de negócios e marketing digital. Ele é especialista em pesquisa de mercado, visualização de dados e automação de marketing, demonstrando um forte conjunto de habilidades técnicas em marketing por e -mail e várias ferramentas de marketing.",
    "employment_history": [
      {
        "details": "Trabalhando na equipe de crescimento com foco em pesquisas de mercado, raspagem de dados e visualização de dados. Responsável por campanhas de marketing por email e automação da Martech.",
        "end_date": "Presente",
        "location": "Lahore",
        "job_title": "Executivo de BI e Marketing Digital",
        "start_date": "12-2020",
        "company_name": "TOTHECHONDOWN TOTHOLOGIAS PVT. Ltd."
      },
      {
        "details": "Enviou campanhas de marketing por email para impulsionar o tráfego e gerar leads para serviços de SEO. Conduziu pesquisa de palavras -chave e entrou em contato com leads.",
        "end_date": "10-2020",
        "location": "Lahore",
        "job_title": "Executivo de Desenvolvimento de Negócios",
        "start_date": "11-2019",
        "company_name": "Matrix Tech LLC"
      },
      {
        "details": "Trabalhou no departamento de terceirização de processos de negócios, compilando e concluindo dados conforme tipo de propriedade e executando verificações de qualidade.",
        "end_date": "11-2019",
        "location": "Lahore",
        "job_title": "Executivo de processamento de documentos",
        "start_date": "02-2019",
        "company_name": "System Limited"
      }
    ]
  }
}