{
  "job_description": "** Título: Gerente de Desenvolvimento de Negócios **  \n\n** Empresa: MarketPros Enterprises **  \n\n** Localização: remoto com potencial viagens para locais de clientes **  \n\n**Sobre nós:**  \nA MarketPros Enterprises é um fornecedor global líder de soluções de negócios inovadoras, com o objetivo de maximizar o crescimento da marca. Trabalhamos com diversas indústrias para aprimorar sua infraestrutura de vendas e fornecer estratégias incomparáveis ​​de envolvimento do cliente.  \n\n** Visão geral da função: **  \nComo gerente de desenvolvimento de negócios da MarketPros Enterprises, você será responsável por liderar iniciativas estratégicas que impulsionam o crescimento dos negócios, aumentam a participação de mercado e fortalecem as relações com os clientes. Você gerenciará equipes multifuncionais para implementar estratégias de vendas, aproveitar as idéias do mercado e impulsionar a expansão da marca.  \n\n** Responsabilidades -chave: **  \n- Desenvolver e implementar estratégias de negócios abrangentes para aumentar o crescimento da receita.  \n- Liderar uma equipe na execução de campanhas de marketing e otimizar os pipelines de vendas.  \n- Utilize ferramentas de análise de dados para produzir informações acionáveis, melhorando o desempenho geral.  \n- Realize pesquisas de mercado para identificar tendências do setor e novas oportunidades de negócios.  \n- Envolva-se com clientes em potencial por meio de apresentações e promova relacionamentos de longo prazo.  \n- Gerenciar sistemas CRM (Salesforce, HubSpot) para otimizar as operações e aprimorar a produtividade.  \n\n** Habilidades preferidas: **  \n- Proficiência em planejamento estratégico e análise de mercado.  \n- Fortes habilidades de liderança com experiência comprovada no desenvolvimento de equipes.  \n- Conhecimento avançado de software CRM e ferramentas de marketing digital.  \n- Excelentes habilidades de comunicação e negociação.  \n\nJunte -se a nós para ultrapassar os limites da inovação de negócios e nos ajudar a alcançar nossos objetivos de expansão.",
  "additional_info": "A MarketPros Enterprises valoriza a diversidade na contratação e incentiva aplicativos de profissionais de negócios experientes com origens variadas. As universidades preferenciais incluem instituições da Ivy League e as principais escolas de negócios. Oferecemos benefícios de realocação para candidatos excepcionais e facilitamos os acordos de trabalho remotos. As competências técnicas e estratégicas são avaliadas através de uma mistura de avaliações psicométricas e entrevistas com estudos de caso.",
  "resume": "Shahrukh Ali\nshahrukh.ali@descon.com 4618452\nLinkedIn.com/in/shahrukh-ali-3021ab24a\nResumo\nUm executivo de desenvolvimento de negócios altamente motivado e orientado a resultados, que também serviu como finanças &\nContas profissionais com 12 anos de experiência inestimável, incluindo ser qualificado em vários negócios\nCampos de desenvolvimento, financeiro e contábil. Eu tenho a capacidade de lidar com atribuições complexas de maneira eficaz e\nPossuindo a confiança para trabalhar como parte de uma equipe ou de forma independente. Uma reputação estabelecida de auto-\nMotivação, atenção aos detalhes excelentes habilidades organizacionais e alta conduta ética. Atualmente procurando o\nMelhor oportunidade com uma empresa orientada a objetivos, onde posso me destacar, entregar e alcançar de acordo com o meu potencial. EU\nEstou entusiasmado em aprender profundamente sobre desenvolvimentos emergentes em meu setor de trabalho.\nExperiência\nAssociado sênior\nKPMG no Paquistão\nAgosto de 2021 - fevereiro de 2022 (7 meses)\nSupervisão da equipe e treinamento\nAnalista de entrada de dados: Atualize o sistema conforme as faturas são recebidas.\nAnalista de pagamento bancário: Contas de processamento e pagamentos recebidos em conformidade.\nSAP ERP\nOráculo\nPolíticas e procedimentos financeiros.\nAnalista de exceções: abordar disputas e problemas de falha de pagamento.\nAnalista de manutenção de fornecedores: mantenha um banco de dados de fornecedor preciso.\nAnalista de finanças: realizando transações financeiras diárias, incluindo verificação, classificação,\nDados de computação, postagem e registro de contas a receber\nExecutivo de Desenvolvimento de Negócios\nInspecion (Private) Limited\nFevereiro de 2022 - presente (7 meses +)\nContabilidade, finanças e receita de desenvolvimento de negócios\nRelações com o cliente\nNegociação de clientes\nExecutivo de contas\nDescon Engineering Limited\nAgosto de 2009 - 2021 de julho (12 anos)\nAnalista de entrada de dados: Atualize o sistema conforme as faturas são recebidas.\nAnalista de pagamento bancário\nSAP ERP\nOráculo\nPolíticas e procedimentos financeiros.\nAnalista de exceções: abordar disputas e problemas de falha de pagamento.\nShahrukh Ali - Analista de manutenção do fornecedor: Mantenha um banco de dados de fornecedor preciso.\nAnalista de finanças: realizando transações financeiras diárias, incluindo verificação, classificação,\nDados de computação, postagem e registro de contas a receber\nEducação\nUniversidade de Punjab Central\nMBA\nUniversidade de Hajvery\nBacharel em Comércio\nHabilidades\nAbacus • Contabilidade • Contas a receber • ACCPAC • Análise • Lei de Negócios • CEO •  \nConsultoria • Entrada de dados • Administração de banco de dados\nShahrukh Ali - Página 2",
  "details": {
    "name": "Shahrukh Ali",
    "number": "4618452",
    "skills": [
      "SAP ERP",
      "Oráculo",
      "ábaco",
      "contabilidade",
      "contas a receber",
      "Accpac",
      "entrada de dados",
      "Administração de banco de dados"
    ],
    "email_id": "shahrukh.ali@descon.com",
    "location": "",
    "projects": [],
    "education": [
      {
        "end_date": "06-2010",
        "university": "Universidade de Hajvery",
        "degree_title": "Bacharel em Comércio"
      },
      {
        "end_date": "06-2012",
        "university": "Universidade de Punjab Central",
        "degree_title": "MBA"
      }
    ],
    "achievements": [],
    "publications": [],
    "certifications": [],
    "additional_urls": [
      {
        "url": "LinkedIn.com/in/shahrukh-ali-3021ab24a",
        "website_name": "LinkedIn"
      }
    ],
    "executive_summary": "Shahrukh Ali é um executivo de desenvolvimento de negócios altamente motivado e orientado a resultados, com 12 anos de experiência inestimável em desenvolvimento de negócios, finanças e contabilidade. Ele possui fortes habilidades técnicas no SAP ERP e Oracle e possui um histórico comprovado em lidar com atribuições complexas de maneira eficaz.",
    "employment_history": [
      {
        "details": "Supervisão e treinamento da equipe, analista de entrada de dados: Atualize o sistema conforme as faturas são recebidas, analista de pagamento bancário: processamento de contas e pagamentos recebidos em conformidade, analista de exceções: abordagem de disputas e problemas de falha de pagamento, analista de manutenção de fornecedores: mantenha um banco de dados de fornecedores preciso, analista de finanças: realizar transações financeiras diárias.",
        "end_date": "02-2022",
        "location": "Paquistão",
        "job_title": "Associado sênior",
        "start_date": "08-2021",
        "company_name": "KPMG no Paquistão"
      },
      {
        "details": "Contabilidade, finanças e receita de desenvolvimento de negócios, relações com clientes, negociação de clientes.",
        "end_date": "",
        "location": "",
        "job_title": "Executivo de Desenvolvimento de Negócios",
        "start_date": "02-2022",
        "company_name": "Inspecion (Private) Limited"
      },
      {
        "details": "Analista de entrada de dados: Atualize o sistema conforme as faturas são recebidas, analista de pagamento bancário, analista de exceções: endereços de disputas e problemas de falha de pagamento, analista de manutenção de fornecedores: mantenha um banco de dados de fornecedores preciso, analista de finanças: executando transações financeiras diárias.",
        "end_date": "07-2021",
        "location": "",
        "job_title": "Executivo de contas",
        "start_date": "08-2009",
        "company_name": "Descon Engineering Limited"
      }
    ]
  }
}