{
  "job_description": "** Título: Gerente de Desenvolvimento de Negócios **  \n\n** Empresa: MarketPros Enterprises **  \n\n** Localização: remoto com potencial viagens para locais de clientes **  \n\n**Sobre nós:**  \nA MarketPros Enterprises é um fornecedor global líder de soluções de negócios inovadoras, com o objetivo de maximizar o crescimento da marca. Trabalhamos com diversas indústrias para aprimorar sua infraestrutura de vendas e fornecer estratégias incomparáveis ​​de envolvimento do cliente.  \n\n** Visão geral da função: **  \nComo gerente de desenvolvimento de negócios da MarketPros Enterprises, você será responsável por liderar iniciativas estratégicas que impulsionam o crescimento dos negócios, aumentam a participação de mercado e fortalecem as relações com os clientes. Você gerenciará equipes multifuncionais para implementar estratégias de vendas, aproveitar as idéias do mercado e impulsionar a expansão da marca.  \n\n** Responsabilidades -chave: **  \n- Desenvolver e implementar estratégias de negócios abrangentes para aumentar o crescimento da receita.  \n- Liderar uma equipe na execução de campanhas de marketing e otimizar os pipelines de vendas.  \n- Utilize ferramentas de análise de dados para produzir informações acionáveis, melhorando o desempenho geral.  \n- Realize pesquisas de mercado para identificar tendências do setor e novas oportunidades de negócios.  \n- Envolva-se com clientes em potencial por meio de apresentações e promova relacionamentos de longo prazo.  \n- Gerenciar sistemas CRM (Salesforce, HubSpot) para otimizar as operações e aprimorar a produtividade.  \n\n** Habilidades preferidas: **  \n- Proficiência em planejamento estratégico e análise de mercado.  \n- Fortes habilidades de liderança com experiência comprovada no desenvolvimento de equipes.  \n- Conhecimento avançado de software CRM e ferramentas de marketing digital.  \n- Excelentes habilidades de comunicação e negociação.  \n\nJunte -se a nós para ultrapassar os limites da inovação de negócios e nos ajudar a alcançar nossos objetivos de expansão.",
  "additional_info": "A MarketPros Enterprises valoriza a diversidade na contratação e incentiva aplicativos de profissionais de negócios experientes com origens variadas. As universidades preferenciais incluem instituições da Ivy League e as principais escolas de negócios. Oferecemos benefícios de realocação para candidatos excepcionais e facilitamos os acordos de trabalho remotos. As competências técnicas e estratégicas são avaliadas através de uma mistura de avaliações psicométricas e entrevistas com estudos de caso.",
  "resume": "Askari Xi, Lahore\nE-mail\n:\n \nmaham.ahmad581@gmail.com\nTelefone\n:\n \n+92 333 1425589\nDESCRIÇÃO\nAnalista de Bioinformatician/ Business\nBuscando uma posição como um analista bioinformático/de negócios onde posso\naplicar minhas habilidades e conhecimentos neste campo em direção ao crescimento e\nprosperidade do país.\nMeu objetivo é o crescimento intelectual contínuo, buscando conquistas mais altas\ne aceitar os novos empreendimentos com alto moral e persistência. Como um bioinformático,\nSerei obrigado a colocar minha paixão e trabalho duro no terreno para o sucesso de estimado\nOrganizações e, como analista de negócios, serei dedicado ao sucesso\nConclusão de projetos usando histórias de usuário direcionadas.\nEDUCAÇÃO\nMestre em \nBioinformática\n(Design de medicamentos computacionais)\n2019 - 2021\nBacharel em Bioinformática\n2015 - 2019\nUniversidade Nacional de Ciências e Tecnologia (NUST) - Islamabad\nCGPA = 3,89/4,00\nProjeto: Ligante combinado e protocolos guiados para atingir o ganho de\nMutações de função do canal de Gardos na deformabilidade de células vermelhas. \nUniversidade da faculdade do governo Faisalabad\nCGPA = 3,97/4,00\nMedalhista de ouro\nProjeto:\n In-Silico\n \nidentificação\n de novos alvos putativos de drogas contra\nBordetella pertussis\n. \nTRABALHAR\nEXPERIÊNCIA\nSoliton Technologies (Persivia)\nJunho de 2022 - presente\nUniversidade de Administração de Lahore\nCiências (Lums)\nAbril de 2022 - maio de 2022\nUniversidade de Agricultura,\nFaisalabad.\n2018 - 2018\nAnalista de negócios\nRa Intern\nEstágio - Curso de Treinamento de Bioinformática\nTreinado em:\nFormatos de arquivo bioinformática\nAcessando e interpretando dados biológicos (bancos de dados públicos)\nAnálise filogenética\nMaham Ahmad\nMaham Ahmad\n1UPWORK, Fiverr\n2017 - presente\nFerramentas de bioinformática\nLinux e Perl para bioinformática\nServiço freelancer como bioinformático\nPerfis:\nhttps://www.fiverr.com/maham_ahmad/do-bioinformatics-analysis-relatou-se-\nDesign de drogas computacionais\nhttps://www.upwork.com/freelancers/~019A12C465CC8262DC\nHABILIDADES\nBA Skills\nJira\nBacklog Manutera\nPlanejamento de sprint\nRequisitos do cliente\nPO Revisão de histórias\nHabilidades de informática\nMicrosoft Office\nFerramentas e bancos de dados online (Bioinformática)\nRecuperação de dados\nEncaixe e simulações\nProgramação\nSoftware/Ferramentas: Autodock, Gold, Moe, Vina, Schrodinger, Descubra\nEstúdio, pymol, quimera, grind, weka, modeller, etc.\nHabilidades adicionais\nSEO e marketing de conteúdo\nWordPress Site Design/Personalização e Otimização\nConteúdo e redação técnica\nRealizações\nParticipação da competição de pôsteres \n\"Sociedade do Paquistão para Biologia Computacional\nPSCB \"\n - 2015 e 2016\nParticipação \n\"1º episódio de IEEE LSYWTC\" \n(Universidade Superior Lahore) -\n2016\nParticipação \n\"Workshop nacional sobre ferramentas básicas em bioinformática\" \n(Gcul) -\n2017\n2ª posição na competição de modelos em \n\"Dia Mundial de DNA\"\n (GCUF) - 2017\nParticipação em \n\"16ª cúpula do jovem líder\"\n \n- 2018\nParticipação do seminário \n\"Cultura de células e inovações de biologia de proteínas\"\n \n(GCUF) - 2018\nCertificado de gerente de mídia social em \nNust Biorreach Society\n (NUST) - 2019\nCertificado de eventos de administração em\n \nClube do Quiz\n (NUST) - 2019\nParticipação no \n\"Abordagens racionais de design de medicamentos computacionais\"\nnuvem\nworkshop prático baseado, co-organizado pela Universidade Nacional de Ciências e\nTECNOLOGIA (NUST) - Paquistão e Schrödinger - 2021\nVice-campeão para\n \n\"Projeto de sinal inteligente\" \nno FICS 2021.\nIdiomas\nInglês\nurdu\nMaham Ahmad\n2 interiores\nPesquisar\nComunicação/interação\nEsportes (badminton)\nMaham Ahmad\n3",
  "details": {
    "name": "Maham Ahmad",
    "number": "9233331425589",
    "skills": [
      "Bioinformática",
      "Linux",
      "Perl",
      "Autodock",
      "OURO",
      "Moe",
      "Vina",
      "Schrodinger",
      "Discover Studio",
      "Pymol",
      "Quimera",
      "MOER",
      "Weka",
      "Modeller",
      "Jira",
      "Microsoft Office",
      "Ferramentas e bancos de dados online (Bioinformática)",
      "Recuperação de dados",
      "Encaixe e simulações"
    ],
    "email_id": "maham.ahmad581@gmail.com",
    "location": "Lahore",
    "projects": [
      {
        "title": "Protocolos guiados de ligante e estrutura combinados para direcionar as mutações de ganho de função do canal de Gardos na deformabilidade de células vermelhas",
        "description": "Projeto de mestre em bioinformática."
      },
      {
        "title": "Identificação in silico de novos alvos putativos de drogas contra Bordetella Pertussis",
        "description": "Projeto de Bacharel em Bioinformática."
      }
    ],
    "education": [
      {
        "end_date": "12-2021",
        "university": "Universidade Nacional de Ciências e Tecnologia (NUST) - Islamabad",
        "degree_title": "Mestrado em bioinformática (design de medicamentos computacionais)"
      },
      {
        "end_date": "05-2019",
        "university": "Universidade da faculdade do governo Faisalabad",
        "degree_title": "Bacharel em Bioinformática"
      }
    ],
    "achievements": [
      "Medalhista de Ouro em Bacharelado em Bioinformática",
      "Segundo Crocinador para Projeto de Sinal Inteligente no FICS 2021",
      "Certificado de Gerente de Mídia Social na Nust Biorreach Society - 2019",
      "Certificado de eventos administrativos no Nust Quiz Club - 2019"
    ],
    "publications": [],
    "certifications": [
      {
        "certification_name": "Gerente de mídia social",
        "issuing_organization": "Nust Biorreach Society",
        "date_of_issuance": "2019"
      },
      {
        "certification_name": "Eventos de administrador",
        "issuing_organization": "Clube do Quiz",
        "date_of_issuance": "2019"
      }
    ],
    "additional_urls": [
      {
        "url": "fiverr.com/maham_ahmad/do-bioinformatics-analysis-relatou-se-computacional-DRUG-DESign",
        "website_name": "Fiverr"
      },
      {
        "url": "upwork.com/freelancers/~019A12C465CC8262DC",
        "website_name": "Upwork"
      }
    ],
    "executive_summary": "Maham Ahmad é um analista bioinformático e de negócios dedicado, com uma forte formação acadêmica em bioinformática. Ela demonstrou experiência em várias ferramentas de bioinformática e linguagens de programação, contribuindo para projetos significativos no design de medicamentos computacionais. Maham está comprometida em alavancar suas habilidades para o avanço da pesquisa científica e do sucesso do projeto.",
    "employment_history": [
      {
        "details": "Analista de Negócios da Soliton Technologies (Persivia)",
        "end_date": "Presente",
        "location": "Lahore",
        "job_title": "Analista de negócios",
        "start_date": "06-2022",
        "company_name": "Soliton Technologies"
      },
      {
        "details": "Estagiário de RA na Universidade de Ciências da Administração de Lahore (LUMS)",
        "end_date": "05-2022",
        "location": "Lahore",
        "job_title": "Internatário Assistente de Pesquisa",
        "start_date": "04-2022",
        "company_name": "Lums"
      },
      {
        "details": "Estágio - Curso de Treinamento de Bioinformática na Universidade de Agricultura, Faisalabad",
        "end_date": "12-2018",
        "location": "Faisalabad",
        "job_title": "Intern",
        "start_date": "2018",
        "company_name": "Universidade de Agricultura, Faisalabad"
      }
    ]
  }
}