{
  "job_description": "## Generação de leads e especialista em inteligência de negócios\n\nJunte -se a ** Innovate Connections Inc. ** Como uma geração de leads e especialista em inteligência de negócios. Você desempenhará um papel fundamental na condução do crescimento dos negócios, liderando iniciativas de geração de leads e fornecendo informações estratégicas por meio da análise de dados. Estamos à procura de um profissional altamente qualificado, com uma forte experiência em geração de leads, gerenciamento de dados e inteligência de negócios.\n\n### Responsabilidades -chave:\n- Desenvolva e execute estratégias de geração de leads usando técnicas de marketing digital, chamadas a frio e ferramentas de raspagem de dados.\n- Colabore com equipes multifuncionais para otimizar estratégias de aquisição de clientes.\n- Utilize sistemas de CRM para gerenciar e analisar os dados do cliente para obter a qualificação do lead.\n- Crie e gerencie cronogramas e planos de trabalho detalhados, utilizando as melhores práticas e padrões para a execução do projeto.\n- Desenvolva modelos financeiros e estratégias de crescimento de negócios com base em insights de dados.\n- Utilize ferramentas como Power BI, SQL e Tableau para desenvolver relatórios e painéis abrangentes de dados.\n\n### Habilidades e experiência desejadas:\n- Fortes habilidades de programação em C ++, HTML e CSS.\n- Proficiência em plataformas de marketing digital, marketing por e -mail e mídia social.\n- Experiência no gerenciamento de grandes conjuntos de dados e no uso de ferramentas de BI (Power BI, Excel, Tableau).\n- Excelentes habilidades de comunicação e capacidade de desenvolver relacionamentos fortes do cliente.\n- Capacidade de trabalhar de forma independente e gerenciar vários projetos simultaneamente.\n\n### Por que a Inovate Connections Inc.?\n- Innovamos na vanguarda da tecnologia e permitimos que os membros da nossa equipe cresçam ao lado da empresa.\n-Valorizamos a tomada de decisão orientada a dados e capacitamos nossas equipes com as ferramentas certas para ter sucesso.\n- Oferecendo um ambiente de trabalho de apoio e oportunidades de avanço na carreira.\n\n### Como se inscrever:\nEnvie seu currículo e carta de apresentação detalhando sua experiência relevante e por que você está interessado em ingressar na Innovate Connections Inc.",
  "additional_info": "A Innovate Connections Inc. prefere candidatos de universidades reconhecidas, como a Universidade de Gerenciamento e Tecnologia e a Lahore School of Economics. Incentivamos um ambiente de trabalho remoto, mas exige presença física para sessões de construção de equipes e estratégicas duas vezes por trimestre. A assistência à realocação está disponível para candidatos excepcionais. Nossa avaliação abrangente inclui um teste técnico seguido de entrevistas estruturadas para avaliar as habilidades técnicas e sociais de forma abrangente.",
  "resume": "Ali Ahmad \nGerente de Desenvolvimento de Negócios \nEu sou um gerente de desenvolvimento de negócios qualificado com experiência em estratégia, vendas, negociações e\nGerenciando o ciclo de vendas completo. Também tenho experiência em gerenciamento de contas importantes. Estou procurando um\nposição desafiadora em uma organização onde posso contribuir para alcançar as metas organizacionais enquanto\ndesenvolvendo ainda mais minhas habilidades profissionais para alcançar todo o meu potencial. \naliahmed2312@gmail.com \n03128800078 \nLahore, Paquistão \nEDUCAÇÃO \nBacharel em Administração de Empresas \nNúcleos rápidos \n08/2016 - 08/2020\n, Assim, \n \nLahore \nExperiência de trabalho \nGerente de Desenvolvimento de Negócios \nIkonic \n04/2023 - Presente\n, Assim, \n \nMinha função inclui gerenciar a equipe de desenvolvimento de negócios,\nlidar com as reuniões que eles reservam e efetivação do\nciclo de vendas completo, além de lidar com o ativo do LinkedIn\ncampanhas. \nExecutivo de desenvolvimento de negócios sênior \nE-sparks \n01/2021 - 04/2023\n, Assim, \n \nMeu papel incluiu alcançar as perspectivas de freelancer\nSites (Upwork, Freelancer etc) e LinkedIn,\nsondando para entender seus pontos problemáticos. Gerenciamento de elementos\nde estratégia, vendas, negociações e efeito da\nciclo de vendas completo. \nWelcome Team Advisor \nGrupo gigante \n09/2020 - 12/2020\n, Assim, \n \nLahore, Paquistão \nMeu papel era responder a todas as consultas no limite via chamada ou ao vivo\nbater papo, \nfornecer os melhores conselhos e promover os benefícios de gigante\nGama de serviços do grupo de acordo com os parâmetros acordados como\nbem como acompanhar as perspectivas. \nIntern \nICI Pakistan Limited \n07/2019 - 08/2019\n, Assim, \n \nLahore \nInternado na ala de poliéster da ICI na finalização\ndepartamento e reconciliou seus balanços também\nAnálise financeira completa de seus concorrentes. \nIntern \nCoca Cola \n07/2018 - 08/2018\n, Assim, \n \nLahore \nInternado no departamento comercial e aprendeu sobre\nestratégias de campanha, incluindo campanhas específicas do produto como\nbem como a colocação do produto nos racks e o uso de\noutdoors \nHABILIDADES \nMicrosoft Office (Word/Excel/PowerPoint) \nLicitação do projeto \nRequisitos de coleta \nGerenciamento de contas \nDesenvolvimento de negócios \nProcesso de vendas \nLiderança \nEstratégias de vendas \nHabilidades de negociação \nHabilidades de resolução de problemas \nManuseio de pressão \nPesquisar \nIdiomas \nInglês \nProfiência profissional completa \nurdu \nProfiência profissional completa \nTarefas \nTarefas \nTarefas \nTarefas \nTarefas",
  "details": {
    "name": "Ali Ahmad",
    "number": "03128800078",
    "skills": [
      "Microsoft Office (Word/Excel/PowerPoint)",
      "Licitação do projeto",
      "Requisitos de coleta",
      "Gerenciamento de contas",
      "Desenvolvimento de negócios",
      "Processo de vendas",
      "Estratégias de vendas",
      "Habilidades de negociação",
      "Pesquisar"
    ],
    "email_id": "aliahmed2312@gmail.com",
    "location": "Lahore, Paquistão",
    "projects": [],
    "education": [
      {
        "end_date": "08-2020",
        "university": "Núcleos rápidos",
        "degree_title": "Bacharel em Administração de Empresas"
      }
    ],
    "achievements": [],
    "publications": [],
    "certifications": [],
    "additional_urls": [
      {
        "url": "LinkedIn.com/in/ali-ahmad",
        "website_name": "LinkedIn"
      }
    ],
    "executive_summary": "Ali Ahmad é um gerente de desenvolvimento de negócios qualificado com experiência em estratégia, vendas e negociações, hábil no gerenciamento do ciclo de vendas completo e gerenciamento de contas. Atualmente, ele está buscando uma posição desafiadora para contribuir com os objetivos organizacionais, desenvolvendo ainda mais suas habilidades profissionais.",
    "employment_history": [
      {
        "details": "Gerenciando a equipe de desenvolvimento de negócios, lidando com reuniões e executando o ciclo de vendas completo, além de gerenciar campanhas ativas do LinkedIn.",
        "end_date": "Presente",
        "location": "Lahore, Paquistão",
        "job_title": "Gerente de Desenvolvimento de Negócios",
        "start_date": "04-2023",
        "company_name": "Ikonic"
      },
      {
        "details": "Procurando clientes em potencial em sites freelancers e LinkedIn, gerenciamento de estratégia, vendas, negociações e o ciclo completo de vendas.",
        "end_date": "04-2023",
        "location": "Lahore, Paquistão",
        "job_title": "Executivo de desenvolvimento de negócios sênior",
        "start_date": "01-2021",
        "company_name": "E-sparks"
      },
      {
        "details": "Respondendo às consultas de entrada por meio de chat de chamadas ou ao vivo, fornecendo conselhos e promovendo serviços.",
        "end_date": "12-2020",
        "location": "Lahore, Paquistão",
        "job_title": "Welcome Team Advisor",
        "start_date": "09-2020",
        "company_name": "Grupo gigante"
      },
      {
        "details": "Internado no departamento de finanças, reconciliando balanços e realizando análises financeiras.",
        "end_date": "08-2019",
        "location": "Lahore, Paquistão",
        "job_title": "Intern",
        "start_date": "07-2019",
        "company_name": "ICI Pakistan Limited"
      },
      {
        "details": "Internado no departamento comercial, aprendendo sobre estratégias de campanha e colocação de produtos.",
        "end_date": "08-2018",
        "location": "Lahore, Paquistão",
        "job_title": "Intern",
        "start_date": "07-2018",
        "company_name": "Coca Cola"
      }
    ]
  }
}