{
  "job_description": "## Título do trabalho: Especialista em gerenciamento de vendas e SEO  \n\n### Localização: Lahore, Paquistão  \n\n### Empresa: Innovate Digital Solutions Inc.  \n\nResumo do trabalho:  \nParticipe da Innovate Digital Solutions Inc. como especialista em gerenciamento de vendas e SEO. Você fará parte de uma equipe dinâmica responsável por impulsionar o envolvimento do cliente e garantir o desempenho ideal em estratégias de marketing digital. Sua função incluirá o gerenciamento do relacionamento com os clientes, a melhoria das estratégias de SEO e a liderança de sua equipe a atingir metas de vendas.  \n\n### Responsabilidades -chave:  \n- Envolva -se proativamente com clientes em potencial para entender suas necessidades de negócios e fornecer soluções inovadoras.  \n- Projete e execute estratégias de SEO em alinhamento com os objetivos de marketing do cliente.  \n- Gerenciar e otimizar as campanhas do PPC para maximizar o ROI e a visibilidade da marca.  \n- Desenvolva e mantenha um forte relacionamento com os clientes por meio de soluções de marketing personalizadas.  \n- Lidere uma equipe a alcançar e superar as metas de vendas, fornecendo um atendimento excepcional ao cliente.  \n- Analise as tendências e algoritmos do mercado para adaptar as estratégias de SEO de acordo.  \n- Produza relatórios que acompanham o progresso e medem o sucesso contra os KPIs.  \n\n### Perfil de candidato ideal:  \nVocê é um profissional qualificado de vendas e marketing, com fortes habilidades analíticas adequadas para identificar e executar oportunidades de SEO. Você se destaca nas interações do cliente, possuindo a capacidade de transformar possíveis leads em clientes satisfeitos por meio de iniciativas de marketing estratégicas e bem executadas. As habilidades de liderança e gerenciamento de equipes serão fundamentais para impulsionar as vendas e motivar sua equipe.  \n\n### benefícios:  \n- Pacote de salário competitivo  \n- Benefícios de saúde e bem -estar  \n- Bônus de desempenho  \n- Oportunidades de avanço na carreira  \n\nJunte -se a nós para redefinir o engajamento digital e liderar estratégias de mercado com agilidade e inovação.",
  "additional_info": "A Innovate Digital Solutions Inc. prefere candidatos de instituições respeitáveis ​​como [Universidade de Lahore], [Universidade de Punjab]. As opções de trabalho remotas estão disponíveis sujeitas a funções e responsabilidades. Avaliamos as habilidades por meio de uma combinação de testes técnicos, entrevistas e cenários de solução de problemas do mundo real para avaliar a competência prática em contextos estratégicos de marketing.",
  "resume": "Mubashar Fayyaz\nDesenvolvimento de negócios e gerenciamento de operação, B2B, B2C, TI, Treinamento\nLahore\nmubashar.fayyaz@yahoo.com\n+92 331 4393771\nExperiência profissional em desenvolvimento e gerenciamento de negócios, gerenciamento de operações, técnico\nLiderança e supervisão de vendas. Valioso para operações comerciais iniciantes e em andamento; excelente\nCapacidade de desenvolver novos projetos. Bem equipado para gerenciar multi-departamentos como RH, vendas, finanças,\ne compras. A experiência de gerenciamento de TI é uma vantagem adicional para analisar funções de negócios e\nimplantando novas tecnologias. Fortes habilidades analíticas e de solução de problemas com a capacidade de trabalhar com\nsupervisão limitada.\nExperiência de trabalho\nOficial de Desenvolvimento de Negócios\nFastech Pvt. Ltd - Lahore\nJaneiro de 2019 para apresentar\n• Minhas responsabilidades principais são pegar projetos de Upwork, Freelancer, etc.\n• Comunicação com clientes.\n• Gerando leads e compartilhamento de atribuições de leads com nosso departamento na costa.\n• Trabalhe com nosso departamento de vendas para convertê -lo em uma oportunidade que leva ao fechamento da venda.\n• Mantenha contato e acompanhe rigorosamente o cliente em potencial até o fechamento da venda.\n• Estamos encontrando KPIs semanais e adicionando -os ao CRM.\n• Treinar os recém -chegados do departamento de vendas interno, desde a sucata de dados até a geração de leads e a partir de\nPesquisa de dados para relatórios.\n• cumprir a meta anual do fechamento de vendas.\n• Acompanhamentos com os clientes.\n• Entenda o escopo do projeto.\n• Atribuir a tarefa ao assistente e ao BDE.\n• Decida os termos e elucidar os requisitos para o custo e o prazo do projeto.\n• Lidar com contas de trabalho e freelancer.\n• Gerenciando negócios e leads usando o HubSpot.\n• Gere leads através do LinkedIn Sales Navigator, AngelList, etc.\n• Executando a campanha de e -mail através do Appolo.io\nGerente de TI e operações\nFundo de Apoio ao Agrades\nSetembro de 2013 a janeiro de 2019\n• O gerenciamento e os projetos de TI e operações levam a facilitar as partes interessadas.\n• Análise de orçamento e custo para a infraestrutura de TI e a implantação de sistemas, preparando o escopo do trabalho.\n• Os requisitos reuniram e implementaram várias soluções como ERP, comércio eletrônico, LMS e Web\nAplicações.\n• Supervisionar as equipes de TI/MIS para operações suaves de TI, incluindo LAN/WAN e Security.Manager Operations\nFundo de Apoio ao Agrades\nOutubro de 2010 a setembro de 2013\n• Preparar relatórios, apresentações, atas de reuniões e conduzir pesquisas para\nInformação.\n• Acordos de cumprimento, cuidando de acordos de viagens ao exterior, incluindo segurança.\n• Experiência do membro do comitê de compras das regras dos EUA e da PPRA.\n• Contratação do fornecedor (SLA) conforme as necessidades organizacionais.\n• Trabalhou com o departamento de RH para preparar descrições de cargos, anúncios de posição e contratação de funcionários.\nOperações de gerente/desenvolvimento de negócios\nWateen Telecom\nDezembro de 2007 a setembro de 2010\n• Desenvolvimento de negócios e gerenciamento definido no escopo do projeto e estabelecem metas e entregas para\ncrescimento nos negócios.\n• Planejou e implementou atividades promocionais de negócios para atingir metas definidas.\n• Supervisão da equipe e alcançou mais de 6000 clientes a bordo.\n• Gerenciamento de vendas para quatro pontos de vendas (POS), seguiu a hierarquia de gerentes de vendas e equipe\nmembros para atingir metas definidas.\n• Crie um roteiro para o sucesso para gerenciar revendedores e distribuidores para garantir o funcional\neficácia do negócio.\n• Prepare os custos de terra, estabeleça um orçamento e meta para sustentabilidade e lucratividade dos negócios.\n• Contratação e treinamento de funcionários em tecnologia como WiMax, TCP/IP, configuração de VoIP e solução de problemas,\nPortal de CRM, incluindo sistema de gerenciamento de registros financeiros.\nEducação\nMestre de ciências nele\nUniversidade de Preston\n2005\nB. com\nFaculdade de Comércio Punjab\n1996\nHabilidades\n• Gerenciamento de projetos (3 anos)\n• Gerenciamento de operações (4 anos)\n• Compras (2 anos)\n• Desenvolvimento e Gerenciamento de Negócios (5 anos)\n• Vendas e atendimento ao cliente (3 anos)\n• Contratação e treinamento da equipe (4 anos)\n• Controle de inventário (3 anos)\n• Orçamento (3 anos) • Melhoria do processo (5 anos)\n• Gerenciamento (5 anos)\n• folha de pagamento (3 anos)\n• Análise de negócios (3 anos)\n• Asana (menos de 1 ano)\n• SQL (3 anos)\n• ágil (menos de 1 ano)\n• VoIP (2 anos)\n• TCP/IP (3 anos)\n• Licitação (4 anos)\n• Geração de leads (4 anos)\n• Escrita da proposta (4 anos)\nIdiomas\n• Inglês - Fluente\n• Chinês - iniciante\n• urdu - fluente",
  "details": {
    "name": "Mubashar Fayyaz",
    "number": "923314393771",
    "skills": [
      "Gerenciamento de projetos",
      "Gerenciamento de operações",
      "Compras",
      "Desenvolvimento de Negócios e Gerenciamento",
      "Vendas e atendimento ao cliente",
      "Contratação e treinamento de funcionários",
      "Controle de inventário",
      "Orçamento",
      "Melhoria do processo",
      "Gerenciamento",
      "Folha de pagamento",
      "Análise de negócios",
      "Asana",
      "SQL",
      "Ágil",
      "VoIP",
      "TCP/IP",
      "Licitação",
      "Geração de chumbo",
      "Escrita da proposta"
    ],
    "email_id": "mubashar.fayyaz@yahoo.com",
    "location": "Lahore",
    "projects": [],
    "education": [
      {
        "end_date": "12-2005",
        "university": "Universidade de Preston",
        "degree_title": "Mestre de ciências nele"
      },
      {
        "end_date": "06-1996",
        "university": "Faculdade de Comércio Punjab",
        "degree_title": "B. com"
      }
    ],
    "achievements": [],
    "publications": [],
    "certifications": [],
    "additional_urls": [
      {
        "url": "LinkedIn.com/in/mubasharfayyaz",
        "website_name": "LinkedIn"
      }
    ],
    "executive_summary": "Mubashar Fayyaz é um profissional qualificado em desenvolvimento de negócios e gerenciamento de operações, com vasta experiência em TI e treinamento. Ele tem um histórico comprovado no gerenciamento de funções multi-departamentais e nos principais projetos técnicos, demonstrando uma forte capacidade de impulsionar o crescimento dos negócios e a eficiência operacional.",
    "employment_history": [
      {
        "details": "Minhas principais responsabilidades são pegar projetos da Upwork, Freelancer, etc. Comunicação com os clientes. Gerando leads e compartilhamento de atribuições de leads com nosso departamento na costa. Trabalhe com nosso departamento de vendas para convertê -lo em uma oportunidade que leva ao fechamento da venda. Fique em contato e acompanhe rigorosamente o cliente em potencial até o fechamento da venda. Estamos encontrando KPIs semanais e adicionando -os ao CRM. Treinar os recém -chegados do departamento de vendas interno, desde a sucção de dados até a geração de leads e da pesquisa de dados até os relatórios. Cumprindo a meta anual do fechamento de vendas. Acompanhamento com os clientes. Entenda o escopo do projeto. Atribuir a tarefa ao assistente e ao BDE. Decida os termos e elucidar os requisitos para o custo e o prazo do projeto. Lidar com contas de trabalho e freelancer. Gerenciando negócios e leads usando o HubSpot. Gerar leads através do LinkedIn Sales Navigator, AngelList, etc. Executando a campanha por e -mail através do Appolo.io",
        "end_date": "Presente",
        "location": "Lahore",
        "job_title": "Oficial de Desenvolvimento de Negócios",
        "start_date": "01-2019",
        "company_name": "Fastech Pvt. Ltd"
      },
      {
        "details": "O gerenciamento e os projetos de TI e operações levam a facilitar as partes interessadas. Análise de orçamento e custo para a infraestrutura de TI e a implantação de sistemas, preparando o escopo do trabalho. Os requisitos reuniram e implementaram várias soluções como ERP, comércio eletrônico, LMS e aplicativos da Web. Supervisionar as equipes de TI/MIS para operações suaves de TI, incluindo LAN/WAN e segurança.",
        "end_date": "01-2019",
        "location": "Lahore",
        "job_title": "Gerente de TI e operações",
        "start_date": "09-2013",
        "company_name": "Fundo de Apoio ao Agrades"
      },
      {
        "details": "Prepare relatórios, apresentações, atas de reuniões e conduz a pesquisa para obter informações. Acordos de cumprimento, cuidando de acordos de viagens ao exterior, incluindo segurança. Comitê de compras Experiência do Comitê das Regras dos EUA e da PPRA. Contratação do fornecedor (SLA) conforme as necessidades organizacionais. Trabalhou com o departamento de RH para preparar descrições de cargos, anúncios de posição e contratação de funcionários.",
        "end_date": "09-2013",
        "location": "Lahore",
        "job_title": "Operações de gerente",
        "start_date": "10-2010",
        "company_name": "Fundo de Apoio ao Agrades"
      },
      {
        "details": "O desenvolvimento de negócios e o gerenciamento definiram o escopo do projeto e estabelecem metas e entregas para o crescimento dos negócios. Planejou e implementou atividades promocionais de negócios para atingir metas definidas. Supervisão da equipe e alcançou mais de 6000 clientes a bordo. O gerenciamento de vendas para quatro pontos de vendas (POS), seguiu a hierarquia de gerentes de vendas e membros da equipe para atingir as metas definidas. Crie um roteiro para o sucesso para gerenciar revendedores e distribuidores para garantir a eficácia funcional dos negócios. Prepare os custos de terra, estabeleça um orçamento e meta para sustentabilidade e lucratividade dos negócios. Contratação e treinamento de funcionários em tecnologia como WiMAX, TCP/IP, Configuração e solução de problemas VoIP, portal de CRM, incluindo o sistema de gerenciamento de registros financeiros.",
        "end_date": "09-2010",
        "location": "Lahore",
        "job_title": "Operações de gerente/desenvolvimento de negócios",
        "start_date": "12-2007",
        "company_name": "Wateen Telecom"
      }
    ]
  }
}