{
  "job_description": "Gerente de Desenvolvimento de Negócios\n\nJunte -se a ** Innovatecorp ** como gerente de desenvolvimento de negócios para contribuir com nossa crescente equipe e impulsionar iniciativas estratégicas no setor de serviços de tecnologia. O candidato ideal alavancará sua vasta experiência em desenvolvimento de negócios, relações com clientes e gerenciamento de projetos para expandir nossa presença no mercado e criar parcerias duradouras.\n\n#### Responsabilidades -chave:\n- Desenvolver e implementar planos de desenvolvimento estratégico de negócios para alcançar as metas da empresa.\n- Geração de leads e construção de relacionamentos com clientes em potencial.\n- Supervisionar estratégias de aquisição de clientes, incluindo exploração além dos mercados freelancers.\n- Colabore com equipes multifuncionais para garantir a entrega suave do projeto.\n- Utilize o software CRM para rastrear o engajamento do cliente e o progresso do desenvolvimento.\n- Realize pesquisas de mercado para permanecer a par das tendências da indústria e informar estratégias de negócios.\n- Gerenciar e relatar as métricas de desenvolvimento de negócios.\n\n#### Habilidades e competências:\n- Comunicação forte e habilidades interpessoais para envolvimento e colaboração do cliente.\n- Excelentes habilidades analíticas para informar propostas e decisões estratégicas.\n- Experiência no Microsoft Office para documentação e apresentações.\n- Proficiência no software CRM para gerenciar o relacionamento com os clientes.\n\n#### Benefícios:\n- Salário competitivo com incentivos de bônus.\n- Oportunidades de desenvolvimento profissional e avanço na carreira.\n- Pacotes de saúde e seguro odontológico.\n- Horário de trabalho flexível e um ambiente positivo e orientado para a equipe.",
  "additional_info": "A Innovatecorp prefere candidatos de escolas de negócios líderes, como o Comsats Institute of Information and Technology. Apoiamos a realocação para o candidato certo e oferecemos oportunidades de trabalho remotas. As habilidades são avaliadas através de uma combinação de entrevistas técnicas e estudos de caso práticos, garantindo que os candidatos atendam aos nossos altos padrões de desempenho antes de oferecer uma posição.",
  "resume": "Syed Ali Sher Rizvi \nGerente de Desenvolvimento de Negócios \nUm profissional organizado e criativo com habilidades de marketing comprovadas e um desejo de aprender mais. Possuir\nMais de 4 anos de experiência trabalhando para um grupo diversificado de organizações e clientes. Ganhou experiência em dados\nAnálise, marketing de publicação e publicidade baseada na Web. Procurando utilizar meu conjunto de habilidades existentes para\nAumentar a lucratividade da empresa na SPLEEN MANUFACTURAÇÃO (PVT) LTD. \nsahibzadaali66@gmail.com \n03015062755 \nLahore, Paquistão \nLinkedIn.com/in/syed-ali-hair-rizvi-7bb859171 \nExperiência de trabalho \nGerente de Desenvolvimento de Negócios \nFeliztanent \n01/2022 - presente\n, Assim, \n \nLahore/Dubai, Emirados Árabes Unidos \nHappytenant é uma empresa base dos Emirados Árabes Unidos, estou trabalhando aqui (remotamente) para desenvolver seus\nNegócios no Paquistão, EUA e Emirados Árabes Unidos também. \nDefinindo metas e desenvolvendo planos para negócios e receita\ncrescimento. \nPlanejando e supervisionando novas iniciativas de marketing. \nAumentando o valor dos clientes atuais enquanto atrai novos\nuns. \nParticipando de conferências, reuniões e eventos do setor. \nCoordenador de mídia social \nCarrinho de minoras \n01/2022 - presente\n, Assim, \n \nLahore/Dubai, Emirados Árabes Unidos \nhttps://www.minoracart.com/ \nAnalisou e relatou presença de mídia social, engajamento e\neficiência em todas as plataformas \nEnvolvido em interações consistentes com clientes, doadores e fãs \nDoubled Website Trafil de 15.000 visitantes médios para 31.000 \nAsst. Gerente Marketing \nSPLEEN MANUFACTURAÇÃO (PVT) LTD 08/2018 - Presente, \n10/2018 - 02/2022\n, Assim, \n \nLahore, Paquistão \nFornecendo soluções de engenharia para todos os tipos de fabricações leves e pesadas \nCampanhas de ponta de lança com sucesso em plataformas de mídia social\nincluindo Facebook, Twitter e Instagram \nContato \n:\n-\nRana Shahbaz Ahmed (cabeça BD & Marketing) \n0300 8463927 \nEDUCAÇÃO \nMSC Marketing \nColagem Nacional de Administração de Empresas e\nEconomia \n2020 - presente\n, Assim, \n \nLahore. Paquistão \nTerceirização global \nGerenciamento de contratos \nEmpreendedorismo \nGerenciamento Final \nBacharel em Comércio \nUniversidade de Punjab \n12/2016 - 05/05/2018\n, Assim, \n \nLahore Paquistão \nHABILIDADES \nMS OFICE \nZoho CRM \nMailChimp \nNegociação \nCapacidade de se envolver \nExcelente comunicação verbal e escrita \nCapacidade de persuadir \nMarketing por e -mail \nGeração de chumbo \nNavigador de vendas \nSignalhire \nApollo.io \nBUFE \nPublicidade digital \nRealizações \nCurso de marketing digital do PNY Institute\n (09/2021)\n \nMarketing de mídia social, palavras de anúncio do Google, SMM, celular\nMarketing \nGerenciamento da Huawei\n (2018 - presente)\n \nPortal Huawei de manuseio completo \ntotalmente coordenado com sua equipe para\ncontratos recentes e negociação futura em cotractos \nERP (SARP) \nSoftware ERP de manipulação completa e tem consciência suficiente que pode\nlidar com cada departamento através dele. \nAchiever do ano (fabricação de baço)\n (2019 - 2020)\n \nProjetos da empresa \nCarrinho de minoras\n (06/2022 - presente)\n \nAnúncio de mídia social \nNome do projeto \nDelux - Serviços de Controle de Pragas\n (12/2022 - presente)\n \nMarketing de mídia social (baixo CPC - Altas conversões) \n220 KV DHABJI LINHA DE PROJETOS DE LINHA\n (09/2021 - 11/2021)\n \nProjetos da Huawei (CMPAK, Jazz, Ufone Telenor)\n (02/2021 - presente)\n \nCertificados \nMarketing digital\n (2021 - presente)\n \nMarketing do YouTube\n (2021 - presente)\n \nRealizações/tarefas \nRealizações/tarefas \nRealizações/tarefas \nCursos",
  "details": {
    "name": "Syed Ali Sher Rizvi",
    "number": "03015062755",
    "skills": [
      "MS Office",
      "Zoho CRM",
      "MailChimp",
      "Marketing por e -mail",
      "Geração de chumbo",
      "Navigador de vendas",
      "Signalhire",
      "Apollo.io",
      "Buffer",
      "Publicidade digital"
    ],
    "email_id": "sahibzadaali66@gmail.com",
    "location": "Lahore, Paquistão",
    "projects": [
      {
        "title": "Carrinho de minoras",
        "description": "Anúncio de mídia social"
      },
      {
        "title": "Delux - Serviços de Controle de Pragas",
        "description": "Marketing de mídia social (baixo CPC - Altas conversões)"
      },
      {
        "title": "220 KV DHABJI LINHA DE PROJETOS DE LINHA",
        "description": ""
      },
      {
        "title": "Projetos da Huawei (CMPAK, Jazz, Ufone Telenor)",
        "description": ""
      }
    ],
    "education": [
      {
        "end_date": "05-2018",
        "university": "Universidade de Punjab",
        "degree_title": "Bacharel em Comércio"
      },
      {
        "end_date": "Presente",
        "university": "Colagem Nacional de Administração de Empresas e Economia",
        "degree_title": "MSC Marketing"
      }
    ],
    "achievements": [
      "Curso de marketing digital do PNY Institute (09-2021)",
      "Achiever of the Year (Manufacturing) (2019 - 2020)"
    ],
    "publications": [],
    "certifications": [
      {
        "certification_name": "Marketing digital",
        "issuing_organization": "Não especificado",
        "date_of_issuance": "2021"
      },
      {
        "certification_name": "Marketing do YouTube",
        "issuing_organization": "Não especificado",
        "date_of_issuance": "2021"
      }
    ],
    "additional_urls": [
      {
        "url": "LinkedIn.com/in/syed-ali-hair-rizvi-7bb859171",
        "website_name": "LinkedIn"
      }
    ],
    "executive_summary": "Syed Ali Sher Rizvi é gerente de desenvolvimento de negócios com mais de 4 anos de experiência em estratégias de marketing e crescimento de negócios. Ele tem uma forte formação em análise de dados, marketing de publicação e publicidade baseada na Web e atualmente está focada em melhorar a lucratividade para a Sleen Manufacturing (PVT) Ltd.",
    "employment_history": [
      {
        "details": "Desenvolvimento de negócios no Paquistão, EUA e Emirados Árabes Unidos, estabelecendo metas e desenvolvendo planos para crescimento de negócios e receita.",
        "end_date": "Presente",
        "location": "Lahore/Dubai, Emirados Árabes Unidos",
        "job_title": "Gerente de Desenvolvimento de Negócios",
        "start_date": "01-2022",
        "company_name": "Feliztanent"
      },
      {
        "details": "Analisou e relatou presença, engajamento e eficácia da mídia social em todas as plataformas, dobrou o tráfego do site.",
        "end_date": "Presente",
        "location": "Lahore/Dubai, Emirados Árabes Unidos",
        "job_title": "Coordenador de mídia social",
        "start_date": "01-2022",
        "company_name": "Carrinho de minoras"
      },
      {
        "details": "Com êxito, liderou campanhas em plataformas de mídia social, incluindo Facebook, Twitter e Instagram.",
        "end_date": "02-2022",
        "location": "Lahore, Paquistão",
        "job_title": "Asst. Gerente Marketing",
        "start_date": "10-2018",
        "company_name": "SPLEEN MANUFACTURAÇÃO (PVT) LTD"
      }
    ]
  }
}