{
  "job_description": "### Gerente de contas -chave na Luxotech Solutions\n\n** Localização: ** Karachi, Paquistão\n\n** Departamento: ** Vendas e marketing\n\n** Relatórios para: ** Diretor de vendas\n\n** Visão geral da função: **\nJunte -se à Luxotech Solutions como gerente de contas importantes, onde você será responsável pelo gerenciamento das principais contas nos segmentos de varejo e hospitalidade em todo o Paquistão. Você impulsionará o crescimento das vendas, gerenciando contas existentes e desenvolvendo estratégias para novas contas. Sua função envolverá coordenar com equipes multifuncionais, analisar tendências do mercado e liderar iniciativas para cumprir as metas de receita.\n\nResponsabilidades ####:\n- Gerencie um portfólio de mais de 15 contas principais, compreendendo usuários finais e parceiros de canal.\n- Dirija a expansão para novos segmentos de mercado, identificando e se envolvendo com possíveis leads.\n- Desenvolva e execute estratégias de gerenciamento de contas para alcançar 110% de obtenção alvo de receita.\n- Utilize ferramentas de análise de dados, como o Power BI, para avaliar as tendências do mercado e gerar insights.\n- Coordenar com equipes internas, incluindo marketing e operações, para garantir o alinhamento estratégico.\n- Liderar negociações contratadas e gerenciar estratégias de preços para otimizar a lucratividade.\n- Relatório sobre o desempenho da conta e as oportunidades de mercado para a gerência sênior regularmente.\n\n#### habilidades essenciais:\n- Fortes habilidades de liderança e gerenciamento de partes interessadas.\n- Proficiência na análise de dados e previsão para informar a tomada de decisão.\n- Experiência em ferramentas como Salesforce, Vistex e SAP ERP para gerenciar funções de vendas.\n- Excelentes habilidades de comunicação para interações com clientes e colaborações internas.\n\n#### qualificações:\n- Mestre de preferência; É necessário um diploma de bacharel em administração de empresas ou campo relacionado.\n- Mais de 5 anos de experiência em gerenciamento de vendas ou desenvolvimento de negócios, com foco no gerenciamento de contas principais.\n- O sucesso demonstrado em contas crescentes e atingindo metas de receita.\n\n#### Benefícios:\n- Salário competitivo com bônus de desempenho.\n- Oportunidades de desenvolvimento profissional e acesso a seminários da indústria.\n- Horário de trabalho flexível.",
  "additional_info": "A Luxotech Solutions valoriza a diversidade e busca candidatos de uma variedade de origens e experiências. As instituições preferidas incluem o Instituto de Administração de Empresas, Karachi e Nuces Fast. A empresa suporta acordos de trabalho híbridos e oferece assistência de realocação para candidatos excepcionais. As habilidades são avaliadas através de uma combinação de testes técnicos, estudos de caso e entrevistas estruturadas com membros do painel de vários departamentos.",
  "resume": "Ahsin yousaf\nDesenvolvimento de negócios / geração de leads\nEspecialista na Technology\nEstou trabalhando como executivo de desenvolvimento de negócios na Invozone Technologies. Eu tenho forte\nConhecimento sobre tecnologias como Elixir, Phoenix, estruturas (JavaScript, Python, Php) e\nDiferentes plataformas freelancers (Upwork & Freelancer) e experiência prática em desenvolvimento.\nEu quero seguir uma carreira em uma organização orientada ao crescimento que oferece oportunidades para\naprendizagem pessoal e desenvolvimento profissional.\n03032548705\nahsiny4@gmail.com✉\nhttps://www.linkedin.com/in/ahsin-yousaf-\nBB3147145\nMansoora, perto de Cakes & Bakes Lahore\nLahore, Paquistão\n Pontos fortes e habilidades\n✔b2b ✔ desenvolvimento de negócios ✔ marketing digital\n✔fiverr ✔freelancer ✔ Google AdWords\n✔ Propoções Writer ✔ Otimização do mecanismo de pesquisa (SEO) ✔Social Media Marketing\n✔Upwork ✔WordPress\n Acadêmicos\nData de pontuação do Instituto do Título\nMSC-IT University of Central Punjab (UCP), Lahore 3.4 CGPA 2019\nUniversidade ADP-IT da Central Punjab (UCP), Lahore 2.9 CGPA 2017\n Certificações\nData da autoridade do título\nUniversidade de Desenvolvimento da Web de Lahore a partir de agosto de 2019\nFreelancing & WordPress E-Rozgaar a partir de janeiro de 2019\nSEO WSCUBE TECH\nSMM WSCUBE TECH\n Experimente menos de 1 ano \n2 meses\n7 meses\n11 meses\n8 meses\n2,3 anos Duração da designação de compras\nInvozone Business Development Executive / BDE em outubro de 2020 - presente\nTRYNGO TECHNOLOGIES DESENVOLVIMENTO DE NEVISÃO DE NEGÓCIOS / BDE ABRA 2020 - NOV 2020\nUpwork Freelancer Jan 2020 - presente\nDesenvolvedor do MaxSify WordPress agosto de 2019 - abril de 2020\nFiverr Freelancer agosto de 2018 - presente\n História do trabalho\nInvozone em outubro de 2020 - presente (2 meses)\nExecutivo de Desenvolvimento de Negócios / BDE Lahore, Paquistão\nDescrição do meu trabalho é\n* Trabalhando em conta freelancer preferida com recrutador\n* Geração de leads.\n* Escrita da proposta.\n* Escrevendo carta de apresentação para todo emprego.\n* Agende uma reunião.\n* Criando currículos para todo trabalho.\n* Criando perfis em diferentes plataformas.\n* Suporte de bate -papo por e -mail e Skype.\n* Desenvolvimento do LinkedIn.\n* Buscar e -mails e dados.\n* Crie e atribuindo a tarefa no HubSpot.\n* Gerenciamento de projetos.\n* Desenvolvedor de Recursos Humanos para Projeto e Job.\n* Serviços de TI\nTRYNGO TECHNOLOGIES APR 2020 - NOV 2020 (7 meses)\nExecutivo de Desenvolvimento de Negócios / BDE Lahore, Paquistão\n- Lives em diferentes plataformas (Upwork, Freelancer).\n- Pesquisando clientes em potencial usando o Google e diretórios diferentes\n- Marketing por email para terceirizar nossos serviços\n- Entrada de dados\n- direcionando o mercado estrangeiro\n- marketing interno\n- Marketing de mídia social \n- Marketing digital \n \nUpwork de janeiro de 2020 - presente (11 meses)\nFreelancer Lahore, Paquistão\nOFERINAÇÃO SERVIÇOS:\nDesenvolvimento do WordPress \nMarketing digital\nMaxSify Ago 2019 - abril de 2020 (8 meses)\nDesenvolvedor WordPress Lahore, Paquistão\nAtualmente, estou trabalhando na MaxSify Technology como desenvolvedor júnior do WordPress. Meu principal responsável é converter html para o WordPress e construir\nsite usando temas e construtores premium.\nFiverr agosto de 2018 - presente (2,3 anos)\nFreelancer Lahore, Paquistão\nTenho uma ótima experiência em freelancer. Ofereci WordPress, Wix, PSD para HTML, WordPress Speed ​​Optimization, Data Entry and Product Listing\n Indústrias\nTecnologia da informação Áreas funcionais*\nMarketing\nGerenciamento de projetos\nVendas e desenvolvimento de negócios\n Idiomas\nUrdu - nativo\nInglês - Hobbies para iniciantes\nNavegando\nViajando",
  "details": {
    "name": "Ahsin yousaf",
    "number": "03032548705",
    "skills": [
      "Elixir",
      "Fênix",
      "JavaScript",
      "Python",
      "Php",
      "Upwork",
      "Freelancer",
      "Fiverr",
      "Google AdWords",
      "Otimização do mecanismo de pesquisa (SEO)",
      "Marketing de mídia social",
      "WordPress"
    ],
    "email_id": "ahsiny4@gmail.com",
    "location": "Mansoora, perto de Cakes & Bakes Lahore, Lahore, Paquistão",
    "projects": [],
    "education": [
      {
        "end_date": "2019",
        "university": "Universidade de Punjab Central (UCP), Lahore",
        "degree_title": "MSC-IT"
      },
      {
        "end_date": "2017",
        "university": "Universidade de Punjab Central (UCP), Lahore",
        "degree_title": "ADP-IT"
      }
    ],
    "achievements": [],
    "publications": [],
    "certifications": [
      {
        "certification_name": "Desenvolvimento da Web",
        "issuing_organization": "Universidade de Lahore",
        "date_of_issuance": "08-2019"
      },
      {
        "certification_name": "Freelancing & WordPress",
        "issuing_organization": "E-rozgaar",
        "date_of_issuance": "01-2019"
      },
      {
        "certification_name": "SEO",
        "issuing_organization": "WSCUBE TECH",
        "date_of_issuance": ""
      },
      {
        "certification_name": "SMM",
        "issuing_organization": "WSCUBE TECH",
        "date_of_issuance": ""
      }
    ],
    "additional_urls": [
      {
        "url": "LinkedIn.com/in/ahsin-yousaf-bb3147145",
        "website_name": "LinkedIn"
      }
    ],
    "executive_summary": "Ahsin Yousaf é um executivo de desenvolvimento de negócios qualificado com experiência em várias tecnologias, incluindo Elixir e Phoenix, bem como proficiência em várias estruturas de programação, como JavaScript, Python e PHP. Ele tem experiência prática em plataformas de desenvolvimento e freelancer, demonstrando um forte compromisso com o crescimento e o desenvolvimento profissional.",
    "employment_history": [
      {
        "details": "Trabalhando em uma conta freelancer preferida com recrutador, geração de leads, redação de propostas, escrita de cartas de cobertura, agendamento de reuniões, criação de currículos, criação de perfis em diferentes plataformas, suporte de bate -papo em e -mail e skype, desenvolvimento do LinkedIn, buscando e -mails e dados, criação e atribuição de tarefas no HubSpot, gerenciamento de projetos, desenvolvimento de recursos humanos para projetos e trabalhos, serviços de TI.",
        "end_date": "Presente",
        "location": "Lahore, Paquistão",
        "job_title": "Executivo de Desenvolvimento de Negócios / BDE",
        "start_date": "10-2020",
        "company_name": "Invozone"
      },
      {
        "details": "Lives em diferentes plataformas (Upwork, Freelancer), pesquisando clientes em potencial usando o Google e diferentes diretórios, email marketing para serviços de terceirização, entrada de dados, direcionamento de mercados estrangeiros, marketing interno, marketing de mídia social, marketing digital.",
        "end_date": "11-2020",
        "location": "Lahore, Paquistão",
        "job_title": "Executivo de Desenvolvimento de Negócios / BDE",
        "start_date": "04-2020",
        "company_name": "Tecnologias Tryngo"
      },
      {
        "details": "Oferecendo serviços no desenvolvimento do WordPress e marketing digital.",
        "end_date": "Presente",
        "location": "Lahore, Paquistão",
        "job_title": "Freelancer",
        "start_date": "01-2020",
        "company_name": "Upwork"
      },
      {
        "details": "Convertendo HTML em WordPress e criando sites usando temas e construtores premium.",
        "end_date": "04-2020",
        "location": "Lahore, Paquistão",
        "job_title": "Desenvolvedor do WordPress",
        "start_date": "08-2019",
        "company_name": "MaxSify"
      },
      {
        "details": "Oferecendo serviços em WordPress, Wix, PSD para HTML, WordPress Speed ​​Optimization, Data Entrada e Listagem de Produtos.",
        "end_date": "Presente",
        "location": "Lahore, Paquistão",
        "job_title": "Freelancer",
        "start_date": "08-2018",
        "company_name": "Fiverr"
      }
    ]
  }
}