{
  "job_description": "### Executivo de Desenvolvimento de Negócios\n\n** Empresa: ** Innovate Dynamics Ltd.\n\n** Localização: ** Hyderabad, Índia\n\n** Visão geral da função: **\nParticipe da Innovate Dynamics Ltd. como executivo de desenvolvimento de negócios, onde você desempenhará um papel fundamental na condução do crescimento dos negócios, gerando leads e gerenciando as principais contas do cliente. Aproveite sua experiência em análise econômica e estratégias de marketing para aprimorar nossa presença no mercado e criar relacionamentos fortes dos clientes.\n\n** Responsabilidades: **\n- Desenvolver e executar planos abrangentes de desenvolvimento de negócios para alcançar os objetivos da empresa.\n- Identifique e envolva clientes em potencial em diversos nichos, incluindo desenvolvimento e terceirização de software.\n- Gerenciar e aumentar as relações com as principais contas para impulsionar o sucesso a longo prazo.\n- Utilize estratégias de marketing digital para aumentar o envolvimento e a retenção do cliente.\n- Colabore com equipes multifuncionais para desenvolver soluções de clientes personalizados.\n- Utilize o LinkedIn Sales Navigator para identificar e abordar novos leads de negócios.\n\n** Qualificações: **\n- Bacharel em Administração de Empresas, Economia ou Campo Relacionado.\n- 3-5 anos de experiência em desenvolvimento de negócios ou campos relacionados.\n- Forte proficiência com as ferramentas de MS Office Suite e Análise de Dados como o STATA.\n- Excelentes habilidades de comunicação verbal e escrita.\n- Capacidade de multitarefa e gerenciar vários projetos simultaneamente.",
  "additional_info": "A Innovate Dynamics Ltd. prioriza os candidatos de universidades de primeira linha, como [University X] e [University Y]. A assistência à realocação está disponível para candidatos dispostos a se mudar para Hyderabad. As habilidades técnicas são avaliadas através de testes padronizados e uma série de entrevistas. Nossa empresa incentiva a diversidade e a inclusão no processo de contratação.",
  "resume": "Samha\nAhmed\nEndereço: Lahore, Paquistão - Telefone: +923324817353\nE-mail:\nsamhaahmed39@gmail.com\nOBJETIVO\nTrabalhar em um ambiente desafiador, onde posso utilizar melhor minhas habilidades e aprimorar minha experiência em\no domínio de vendas e desenvolvimento de negócios.\nExperiência de trabalho\nExecutivo de Desenvolvimento de Negócios\nRolustech\n(Setembro de 2021 - presente)\nExecutivo de Desenvolvimento de Negócios\nTxlabz\n(Maio de 2021 - setembro de 2021)\nGerente de Projeto Associado\nTxlabz\n(Junho de 2021 - setembro de 2021)\nEDUCAÇÃO\nBS Tecnologia da Informação\n(2017-2021)\nFaculdade de Tecnologia da Informação da Universidade de Punjab, Lahore\n(OOP, DSA, DB, Web, Android, SQA)\nF.SC pré-engenharia\n(2015 - 2017)\nPunjab College of Science, Lahore\n(Química, Física, Matemática)\nPorcentagem: 80%\nMATRÍCULA\n(2013 - 2015)\nWapda Girls High School, Lahore\n(Computador, matemática, física, química)\nPorcentagem: 93%de habilidades pessoais\n●\nFortes habilidades interpessoais\n●\nOução eficaz\n●\nCapacidade de negociar\n●\nCapacidade de multitarefa\n●\nAtenção aos detalhes\n●\nComportamento profissional\n●\nTempo e recurso \ngerenciamento\n●\nTomada de decisão eficaz\nHabilidades organizacionais/ gerenciais\n●\nHabilidades de inteligência de negócios e habilidades de marketing\n●\nExperiência prática em lances de trabalho e utilização de plataformas freelancers para chumbo\ngeração\n●\nConhecimento de todos os estágios de um ciclo de vendas\n●\nExperiência com sistemas de CRM\n●\nForte conhecimento da geração de leads usando campanhas de email e ferramentas de marketing popular\n●\nCapacidade de analisar tendências de mercado e sugerir novas idéias/estratégias para melhorar as vendas\n●\nCapacidade de interagir e se comunicar efetivamente com pessoas de diversas origens\n●\nFortes habilidades de persuasão que ajudam a maximizar a satisfação do cliente\n●\nBom em criar e estabelecer metas e atingir metas, tomada de decisão, gerenciamento\ncompromissos, gerenciamento de equipes e pensamento estratégico\nProjetos semestrais\nSistema de gerenciamento do campus\nAssunto: Fundamentos de programação, foi desenvolvido em C ++.\nSistema de banco de dados de ONGs\nAssunto: Sistema de banco de dados. Foi desenvolvido no Oracle usando PHP, HTML e CSS.\nLudo Game\nAssunto: OOAD (análise e design orientados a objetos). Foi desenvolvido em Java.\nGaleria de arte online\nAssunto: Desenvolvimento da Web. Foi desenvolvido usando HTML, CSS, Bootstrap, JavaScript, Ajax,\nJQuery e JSON. Projeto do ano final\nAplicação de rastreamento de e-bus PU\nÉ um aplicativo que fornecerá locais de ônibus em tempo real aos alunos. É um\nProjeto baseado em Android. O aplicativo possui dois módulos; um é para motoristas, o outro para\nalunos. Quando um motorista abre o aplicativo, sua localização em tempo real na Firebase é salva. Quando\nUm aluno abre o aplicativo, ônibus próximos a 3 km de raio são mostrados ao aluno.\nTambém desenvolvemos um site para administradores que podem remover ou adicionar ônibus.\nFerramentas para Android: Java, XML, Gradle e Firebase Database.\nFerramentas para Web: HTML5, CSS3, JavaScript, JQuery, React, Python e MySQL.",
  "details": {
    "name": "Samha Ahmed",
    "number": "923324817353",
    "skills": [
      "C ++",
      "ORÁCULO",
      "Php",
      "Html",
      "CSS",
      "JAVA",
      "Html5",
      "CSS3",
      "JavaScript",
      "jQuery",
      "Reagir",
      "Python",
      "Mysql",
      "Xml",
      "Gradle",
      "Banco de dados de Firebase"
    ],
    "email_id": "samhaahmed39@gmail.com",
    "location": "Lahore, Paquistão",
    "projects": [
      {
        "title": "Sistema de gerenciamento do campus",
        "description": "Desenvolvido em C ++."
      },
      {
        "title": "Sistema de banco de dados de ONGs",
        "description": "Desenvolvido no Oracle usando PHP, HTML e CSS."
      },
      {
        "title": "Ludo Game",
        "description": "Desenvolvido em Java."
      },
      {
        "title": "Galeria de arte online",
        "description": "Desenvolvido usando HTML, CSS, Bootstrap, JavaScript, Ajax, JQuery e JSON."
      },
      {
        "title": "Aplicação de rastreamento de e-bus PU",
        "description": "Aplicativo baseado em Android, fornecendo locais de ônibus em tempo real."
      }
    ],
    "education": [
      {
        "end_date": "06-2021",
        "university": "Faculdade de Tecnologia da Informação da Universidade de Punjab, Lahore",
        "degree_title": "BS Tecnologia da Informação"
      },
      {
        "end_date": "05-2017",
        "university": "Punjab College of Science, Lahore",
        "degree_title": "F.SC pré-engenharia"
      },
      {
        "end_date": "05-2015",
        "university": "Wapda Girls High School, Lahore",
        "degree_title": "Matrícula"
      }
    ],
    "achievements": [],
    "publications": [],
    "certifications": [],
    "additional_urls": [],
    "executive_summary": "Samha Ahmed é uma executiva qualificada de desenvolvimento de negócios, com uma forte formação em tecnologia da informação. Ela tem experiência em várias linguagens e tecnologias de programação, demonstrando sua proficiência técnica no desenvolvimento de software e gerenciamento de projetos.",
    "employment_history": [
      {
        "details": "Executivo de Desenvolvimento de Negócios da Rolustech.",
        "end_date": "Presente",
        "location": "Lahore, Paquistão",
        "job_title": "Executivo de Desenvolvimento de Negócios",
        "start_date": "09-2021",
        "company_name": "Rolustech"
      },
      {
        "details": "Executivo de Desenvolvimento de Negócios na TXLABZ.",
        "end_date": "09-2021",
        "location": "Lahore, Paquistão",
        "job_title": "Executivo de Desenvolvimento de Negócios",
        "start_date": "05-2021",
        "company_name": "Txlabz"
      },
      {
        "details": "Gerente de Projeto Associado em Txlabz.",
        "end_date": "09-2021",
        "location": "Lahore, Paquistão",
        "job_title": "Gerente de Projeto Associado",
        "start_date": "06-2021",
        "company_name": "Txlabz"
      }
    ]
  }
}