{
  "job_description": "Gerente de Desenvolvimento de Negócios\n\n** Empresa fictícia ** está buscando um gerente de desenvolvimento de negócios dinâmico e estratégico para ingressar em nossa equipe crescente. Nesta função, você desenvolverá e executará estratégias de vendas, gerenciará as principais contas e liderará iniciativas de desenvolvimento de negócios para impulsionar o crescimento organizacional.\n\nResponsabilidades ####:\n- Desenvolva e implemente estratégias para o desenvolvimento de negócios para atingir objetivos corporativos.\n- Supervisionar todo o ciclo de vendas, da geração de leads a acordos de fechamento.\n- Gerenciar e orientar uma equipe de executivos de desenvolvimento de negócios, aprimorando seu potencial para otimizar o sucesso da empresa.\n- Aprimore a presença da empresa por meio de engajamento ativo em plataformas on -line como o LinkedIn e os sites de rede profissional.\n-Envolva-se em negociações de alto risco e coordenam com as principais partes interessadas da conta para garantir a satisfação do cliente e as parcerias de longo prazo.\n\n#### Requisitos:\n- Utilize habilidades analíticas para identificar novas oportunidades e tendências de mercado.\n- Use o Microsoft Office Suite de maneira eficaz para planejar, relatar e apresentar estratégias de vendas.\n\nJunte -se a nós para desempenhar um papel fundamental na expansão de nossos negócios localmente e internacionalmente, trabalhando ao lado de uma equipe dinâmica em um ambiente inovador. Se você gosta de tomar iniciativas e liderar iniciativas de negócios impactantes, queremos ouvir você!",
  "additional_info": "Os candidatos preferidos terão se formado nas principais escolas de negócios, como núcleos rápidos ou Lums. A empresa apóia a realocação de funcionários no Paquistão com a assistência logística necessária. As habilidades são avaliadas por meio de uma combinação de entrevistas técnicas e estudos de caso práticos alinhados aos desafios do setor.",
  "resume": "Shahrukh Ali\nshahrukh.ali@descon.com 4618452\nLinkedIn.com/in/shahrukh-ali-3021ab24a\nResumo\nUm executivo de desenvolvimento de negócios altamente motivado e orientado a resultados, que também serviu como finanças &\nContas profissionais com 12 anos de experiência inestimável, incluindo ser qualificado em vários negócios\nCampos de desenvolvimento, financeiro e contábil. Eu tenho a capacidade de lidar com atribuições complexas de maneira eficaz e\nPossuindo a confiança para trabalhar como parte de uma equipe ou de forma independente. Uma reputação estabelecida de auto-\nMotivação, atenção aos detalhes excelentes habilidades organizacionais e alta conduta ética. Atualmente procurando o\nMelhor oportunidade com uma empresa orientada a objetivos, onde posso me destacar, entregar e alcançar de acordo com o meu potencial. EU\nEstou entusiasmado em aprender profundamente sobre desenvolvimentos emergentes em meu setor de trabalho.\nExperiência\nAssociado sênior\nKPMG no Paquistão\nAgosto de 2021 - fevereiro de 2022 (7 meses)\nSupervisão da equipe e treinamento\nAnalista de entrada de dados: Atualize o sistema conforme as faturas são recebidas.\nAnalista de pagamento bancário: Contas de processamento e pagamentos recebidos em conformidade.\nSAP ERP\nOráculo\nPolíticas e procedimentos financeiros.\nAnalista de exceções: abordar disputas e problemas de falha de pagamento.\nAnalista de manutenção de fornecedores: mantenha um banco de dados de fornecedor preciso.\nAnalista de finanças: realizando transações financeiras diárias, incluindo verificação, classificação,\nDados de computação, postagem e registro de contas a receber\nExecutivo de Desenvolvimento de Negócios\nInspecion (Private) Limited\nFevereiro de 2022 - presente (7 meses +)\nContabilidade, finanças e receita de desenvolvimento de negócios\nRelações com o cliente\nNegociação de clientes\nExecutivo de contas\nDescon Engineering Limited\nAgosto de 2009 - 2021 de julho (12 anos)\nAnalista de entrada de dados: Atualize o sistema conforme as faturas são recebidas.\nAnalista de pagamento bancário\nSAP ERP\nOráculo\nPolíticas e procedimentos financeiros.\nAnalista de exceções: abordar disputas e problemas de falha de pagamento.\nShahrukh Ali - Analista de manutenção do fornecedor: Mantenha um banco de dados de fornecedor preciso.\nAnalista de finanças: realizando transações financeiras diárias, incluindo verificação, classificação,\nDados de computação, postagem e registro de contas a receber\nEducação\nUniversidade de Punjab Central\nMBA\nUniversidade de Hajvery\nBacharel em Comércio\nHabilidades\nAbacus • Contabilidade • Contas a receber • ACCPAC • Análise • Lei de Negócios • CEO •  \nConsultoria • Entrada de dados • Administração de banco de dados\nShahrukh Ali - Página 2",
  "details": {
    "name": "Shahrukh Ali",
    "number": "4618452",
    "skills": [
      "SAP ERP",
      "Oráculo",
      "ábaco",
      "contabilidade",
      "contas a receber",
      "Accpac",
      "entrada de dados",
      "Administração de banco de dados"
    ],
    "email_id": "shahrukh.ali@descon.com",
    "location": "",
    "projects": [],
    "education": [
      {
        "end_date": "06-2010",
        "university": "Universidade de Hajvery",
        "degree_title": "Bacharel em Comércio"
      },
      {
        "end_date": "06-2012",
        "university": "Universidade de Punjab Central",
        "degree_title": "MBA"
      }
    ],
    "achievements": [],
    "publications": [],
    "certifications": [],
    "additional_urls": [
      {
        "url": "LinkedIn.com/in/shahrukh-ali-3021ab24a",
        "website_name": "LinkedIn"
      }
    ],
    "executive_summary": "Shahrukh Ali é um executivo de desenvolvimento de negócios altamente motivado e orientado a resultados, com 12 anos de experiência inestimável em desenvolvimento de negócios, finanças e contabilidade. Ele possui fortes habilidades técnicas no SAP ERP e Oracle e possui um histórico comprovado em lidar com atribuições complexas de maneira eficaz.",
    "employment_history": [
      {
        "details": "Supervisão e treinamento da equipe, analista de entrada de dados: Atualize o sistema conforme as faturas são recebidas, analista de pagamento bancário: processamento de contas e pagamentos recebidos em conformidade, analista de exceções: abordagem de disputas e problemas de falha de pagamento, analistas de manutenção de fornecedores: Manter um banco de dados de dados, com realização de transações financeiras, incluindo a classificação, a classificação, a classificação precisa, a classificação precisa.",
        "end_date": "02-2022",
        "location": "Paquistão",
        "job_title": "Associado sênior",
        "start_date": "08-2021",
        "company_name": "KPMG no Paquistão"
      },
      {
        "details": "Contabilidade, finanças e receita de desenvolvimento de negócios, relações com clientes, negociação de clientes.",
        "end_date": "",
        "location": "",
        "job_title": "Executivo de Desenvolvimento de Negócios",
        "start_date": "02-2022",
        "company_name": "Inspecion (Private) Limited"
      },
      {
        "details": "Analista de entrada de dados: Atualize o sistema conforme as faturas são recebidas, analista de pagamento bancário, analista de exceções: abordagem de disputas e problemas de falha de pagamento, analista de manutenção de fornecedores: mantenha um banco de dados preciso do fornecedor, analista de finanças: executando transações financeiras diárias, incluindo a verificação, classificação, computação e registro de contas de contas de contas.",
        "end_date": "07-2021",
        "location": "",
        "job_title": "Executivo de contas",
        "start_date": "08-2009",
        "company_name": "Descon Engineering Limited"
      }
    ]
  }
}