{
  "job_description": "## Junte -se à nossa equipe dinâmica como executivo de vendas e marketing sênior\n\nVisão geral da posição\n\n[ACME Corp], líder no fornecimento de soluções de marketing digital de ponta, está em busca de um executivo de vendas e marketing sênior ** para desempenhar um papel fundamental em nossa equipe em crescimento. Você aproveitará suas habilidades em gerenciamento de vendas, desenvolvimento de negócios e marketing digital para impulsionar o crescimento dos negócios e maximizar a satisfação do cliente. Use seu talento em liderança para orientar nossa equipe jovem, garantindo que atinjam as principais metas de negócios enquanto estabelecem novos padrões no setor.\n\n### Responsabilidades -chave\n- Dirija estratégias de vendas para atingir as metas de desempenho e expandir nosso alcance no mercado.\n-Gerenciar processos de vendas de ponta a ponta, incluindo prospecção de clientes, geração de leads e fechamento de vendas. \n- Trabalhe em colaboração com a equipe de marketing digital para conceber, gerenciar e executar campanhas de marketing.\n- Utilize ferramentas de CRM, como o HubSpot para rastreamento e análise, para aumentar a eficiência de vendas.\n- Realizar pesquisas de mercado e análise de dados para informar estratégias de negócios.\n- Mentor Novos contratados e facilite o desenvolvimento profissional contínuo.\n\n### habilidades e experiência essenciais\n- Experiência comprovada em gerenciamento de vendas e marketing digital (mais de 5 anos de preferência).\n- Comando forte sobre ferramentas de automação de marketing e CRMs como HubSpot e Salesforce.\n- Capacidade de definir metas estratégicas com excelentes habilidades de solução de problemas e comunicação.\n- Aptidão para visualização e análise de dados para conduzir decisões de marketing informadas.\n- Familiaridade com SEO, SEM, campanhas de marketing por email e ferramentas de inteligência de negócios.\n- Proficiência demonstrou liderar e supervisionar um ambiente de equipe dinâmica.\n\n### o que oferecemos\n- Salário competitivo e um pacote abrangente de benefícios.\n- Oportunidade de trabalhar com uma equipe e um ambiente inovadores.\n- Oportunidades contínuas de aprendizado e potencial de crescimento dentro da empresa.\n\nJunte -se a nós para causar impacto no cenário digital e impulsionar o sucesso!",
  "additional_info": "Na Acme Corp, priorizamos candidatos de diversas origens educacionais com experiência comprovada em ambientes de vendas de alta pressão. Congratulamo -nos com os graduados de instituições respeitáveis, mas não temos preferência específica por nenhuma universidade. O suporte à realocação está disponível caso a caso. A avaliação de habilidades incluirá um projeto de marketing prático para avaliar a capacidade de capacidade em cenários do mundo real, complementados por entrevistas pessoais para avaliar o ajuste cultural e o potencial de crescimento.",
  "resume": "Samha\nAhmed\nEndereço: Lahore, Paquistão - Telefone: +923324817353\nE-mail:\nsamhaahmed39@gmail.com\nOBJETIVO\nTrabalhar em um ambiente desafiador, onde posso utilizar melhor minhas habilidades e aprimorar minha experiência em\no domínio de vendas e desenvolvimento de negócios.\nExperiência de trabalho\nExecutivo de Desenvolvimento de Negócios\nRolustech\n(Setembro de 2021 - presente)\nExecutivo de Desenvolvimento de Negócios\nTxlabz\n(Maio de 2021 - setembro de 2021)\nGerente de Projeto Associado\nTxlabz\n(Junho de 2021 - setembro de 2021)\nEDUCAÇÃO\nBS Tecnologia da Informação\n(2017-2021)\nFaculdade de Tecnologia da Informação da Universidade de Punjab, Lahore\n(OOP, DSA, DB, Web, Android, SQA)\nF.SC pré-engenharia\n(2015 - 2017)\nPunjab College of Science, Lahore\n(Química, Física, Matemática)\nPorcentagem: 80%\nMATRÍCULA\n(2013 - 2015)\nWapda Girls High School, Lahore\n(Computador, matemática, física, química)\nPorcentagem: 93%de habilidades pessoais\n●\nFortes habilidades interpessoais\n●\nOução eficaz\n●\nCapacidade de negociar\n●\nCapacidade de multitarefa\n●\nAtenção aos detalhes\n●\nComportamento profissional\n●\nTempo e recurso \ngerenciamento\n●\nTomada de decisão eficaz\nHabilidades organizacionais/ gerenciais\n●\nHabilidades de inteligência de negócios e habilidades de marketing\n●\nExperiência prática em lances de trabalho e utilização de plataformas freelancers para chumbo\ngeração\n●\nConhecimento de todos os estágios de um ciclo de vendas\n●\nExperiência com sistemas de CRM\n●\nForte conhecimento da geração de leads usando campanhas de email e ferramentas de marketing popular\n●\nCapacidade de analisar tendências de mercado e sugerir novas idéias/estratégias para melhorar as vendas\n●\nCapacidade de interagir e se comunicar efetivamente com pessoas de diversas origens\n●\nFortes habilidades de persuasão que ajudam a maximizar a satisfação do cliente\n●\nBom em criar e estabelecer metas e atingir metas, tomada de decisão, gerenciamento\ncompromissos, gerenciamento de equipes e pensamento estratégico\nProjetos semestrais\nSistema de gerenciamento do campus\nAssunto: Fundamentos de programação, foi desenvolvido em C ++.\nSistema de banco de dados de ONGs\nAssunto: Sistema de banco de dados. Foi desenvolvido no Oracle usando PHP, HTML e CSS.\nLudo Game\nAssunto: OOAD (análise e design orientados a objetos). Foi desenvolvido em Java.\nGaleria de arte online\nAssunto: Desenvolvimento da Web. Foi desenvolvido usando HTML, CSS, Bootstrap, JavaScript, Ajax,\nJQuery e JSON. Projeto do ano final\nAplicação de rastreamento de e-bus PU\nÉ um aplicativo que fornecerá locais de ônibus em tempo real aos alunos. É um\nProjeto baseado em Android. O aplicativo possui dois módulos; um é para motoristas, o outro para\nalunos. Quando um motorista abre o aplicativo, sua localização em tempo real na Firebase é salva. Quando\nUm aluno abre o aplicativo, ônibus próximos a 3 km de raio são mostrados ao aluno.\nTambém desenvolvemos um site para administradores que podem remover ou adicionar ônibus.\nFerramentas para Android: Java, XML, Gradle e Firebase Database.\nFerramentas para Web: HTML5, CSS3, JavaScript, JQuery, React, Python e MySQL.",
  "details": {
    "name": "Samha Ahmed",
    "number": "923324817353",
    "skills": [
      "C ++",
      "ORÁCULO",
      "Php",
      "Html",
      "CSS",
      "JAVA",
      "Html5",
      "CSS3",
      "JavaScript",
      "jQuery",
      "Reagir",
      "Python",
      "Mysql",
      "Xml",
      "Gradle",
      "Banco de dados de Firebase"
    ],
    "email_id": "samhaahmed39@gmail.com",
    "location": "Lahore, Paquistão",
    "projects": [
      {
        "title": "Sistema de gerenciamento do campus",
        "description": "Desenvolvido em C ++."
      },
      {
        "title": "Sistema de banco de dados de ONGs",
        "description": "Desenvolvido no Oracle usando PHP, HTML e CSS."
      },
      {
        "title": "Ludo Game",
        "description": "Desenvolvido em Java."
      },
      {
        "title": "Galeria de arte online",
        "description": "Desenvolvido usando HTML, CSS, Bootstrap, JavaScript, Ajax, JQuery e JSON."
      },
      {
        "title": "Aplicação de rastreamento de e-bus PU",
        "description": "Aplicativo baseado em Android, fornecendo locais de ônibus em tempo real."
      }
    ],
    "education": [
      {
        "end_date": "06-2021",
        "university": "Faculdade de Tecnologia da Informação da Universidade de Punjab, Lahore",
        "degree_title": "BS Tecnologia da Informação"
      },
      {
        "end_date": "05-2017",
        "university": "Punjab College of Science, Lahore",
        "degree_title": "F.SC pré-engenharia"
      },
      {
        "end_date": "05-2015",
        "university": "Wapda Girls High School, Lahore",
        "degree_title": "Matrícula"
      }
    ],
    "achievements": [],
    "publications": [],
    "certifications": [],
    "additional_urls": [],
    "executive_summary": "Samha Ahmed é uma executiva qualificada de desenvolvimento de negócios, com uma forte formação em tecnologia da informação. Ela tem experiência em várias linguagens e tecnologias de programação, demonstrando sua proficiência técnica no desenvolvimento de software e gerenciamento de projetos.",
    "employment_history": [
      {
        "details": "Executivo de Desenvolvimento de Negócios da Rolustech.",
        "end_date": "Presente",
        "location": "Lahore, Paquistão",
        "job_title": "Executivo de Desenvolvimento de Negócios",
        "start_date": "09-2021",
        "company_name": "Rolustech"
      },
      {
        "details": "Executivo de Desenvolvimento de Negócios na TXLABZ.",
        "end_date": "09-2021",
        "location": "Lahore, Paquistão",
        "job_title": "Executivo de Desenvolvimento de Negócios",
        "start_date": "05-2021",
        "company_name": "Txlabz"
      },
      {
        "details": "Gerente de Projeto Associado em Txlabz.",
        "end_date": "09-2021",
        "location": "Lahore, Paquistão",
        "job_title": "Gerente de Projeto Associado",
        "start_date": "06-2021",
        "company_name": "Txlabz"
      }
    ]
  }
}