{
  "job_description": "## Título do trabalho: Especialista em gerenciamento de vendas e SEO  \n\n### Localização: Lahore, Paquistão  \n\n### Empresa: Innovate Digital Solutions Inc.  \n\nResumo do trabalho:  \nParticipe da Innovate Digital Solutions Inc. como especialista em gerenciamento de vendas e SEO. Você fará parte de uma equipe dinâmica responsável por impulsionar o envolvimento do cliente e garantir o desempenho ideal em estratégias de marketing digital. Sua função incluirá o gerenciamento do relacionamento com os clientes, a melhoria das estratégias de SEO e a liderança de sua equipe a atingir metas de vendas.  \n\n### Responsabilidades -chave:  \n- Envolva -se proativamente com clientes em potencial para entender suas necessidades de negócios e fornecer soluções inovadoras.  \n- Projete e execute estratégias de SEO em alinhamento com os objetivos de marketing do cliente.  \n- Gerenciar e otimizar as campanhas do PPC para maximizar o ROI e a visibilidade da marca.  \n- Desenvolva e mantenha um forte relacionamento com os clientes por meio de soluções de marketing personalizadas.  \n- Lidere uma equipe a alcançar e superar as metas de vendas, fornecendo um atendimento excepcional ao cliente.  \n- Analise as tendências e algoritmos do mercado para adaptar as estratégias de SEO de acordo.  \n- Produza relatórios que acompanham o progresso e medem o sucesso contra os KPIs.  \n\n### Perfil de candidato ideal:  \nVocê é um profissional qualificado de vendas e marketing, com fortes habilidades analíticas adequadas para identificar e executar oportunidades de SEO. Você se destaca nas interações do cliente, possuindo a capacidade de transformar possíveis leads em clientes satisfeitos por meio de iniciativas de marketing estratégicas e bem executadas. As habilidades de liderança e gerenciamento de equipes serão fundamentais para impulsionar as vendas e motivar sua equipe.  \n\n### benefícios:  \n- Pacote de salário competitivo  \n- Benefícios de saúde e bem -estar  \n- Bônus de desempenho  \n- Oportunidades de avanço na carreira  \n\nJunte -se a nós para redefinir o engajamento digital e liderar estratégias de mercado com agilidade e inovação.",
  "additional_info": "A Innovate Digital Solutions Inc. prefere candidatos de instituições respeitáveis ​​como [Universidade de Lahore], [Universidade de Punjab]. As opções de trabalho remotas estão disponíveis sujeitas a funções e responsabilidades. Avaliamos as habilidades por meio de uma combinação de testes técnicos, entrevistas e cenários de solução de problemas do mundo real para avaliar a competência prática em contextos estratégicos de marketing.",
  "resume": "Izma bint-e-atif\nAnalista de negócios\nPensamento crítico\nManter confidencialidade\nControle de qualidade\nDistribuição\nHabilidades organizacionais\nSolução de problemas\nAnálise Estatística\nComunicação verbal/virtual\nFortes habilidades analíticas\nAuxiliar de gerenciamento de produtos técnicos\nDesigningskills de circuito+92 331 0483113\nCasa nº 530, Bloco J3, Johar\nTown, Lahore izma.b.atif@gmail.com Antecedentes Trabalhando com clientes internos e externos para reunir\ne providenciar requisitos, fornecer análise, auxiliar na criação de usuário\ninterfaces e desenvolva prazos de implementação em ambiente ágil.\nBuscando uma oportunidade desafiadora, onde poderei utilizar meu\nfortes habilidades organizacionais, formação educacional e capacidade de trabalhar\nbem com as pessoas, o que me permitirá crescer pessoalmente e\nPerfil profissionalmente de carros\nEXPERIÊNCIAS\nNextbridge Unip. Ltd. \nRed Communication Arts Pvt. LTD2021 - Presente\n2020 - 2021 Business Development Executive\nConduzir análises de mercado para as linhas de produtos e para o geral\nlucratividade do negócio\nAuxiliar no planejamento e execução dos planos de teste para integração\ne teste de processo, incluindo o aumento de logs de falhas.\nDesenvolva conceitos de projeto e mantenha o fluxo de trabalho ideal.\nComunicação forte e habilidades interpessoais para construir significativas\nrelacionamentos com clientes. \nAtenção aos detalhes para aprimorar cada tarefa necessária. \nTomada de decisão avançada e habilidades de solução de problemas.\nAnalista de negócios júnior\nAnalisar e priorizar os requisitos do cliente. \nTraduzir os requisitos do cliente em resumos de projeto especificados por\nEntendendo o ciclo de vida do desenvolvimento de software.\nTrabalhando diretamente com usuários/clientes e entendendo problemas de negócios,\nEstabelecendo solução e apresentando de volta às principais partes interessadas\nCriando uma análise de negócios detalhada, descrevendo problemas, oportunidades\ne soluções para um negócio\nAnálise de processo e produção de artefato acordado adequado para internos\nuse e/ou revisão do cliente e assinatura.educação\nFastNuces2020 - Bacharel em\nEngenharia Elétrica\nQueen Mary College for Women2015 - FSC pré -engenharia\nEscola do Convento do Coração Sagrado2013 - MatriculationBalsamiq \nMatlab \nCAD automático\nSketchup \nSoftware do Visual Studio \nProjetos\nImpressora 3D com mecanismo cartesiano (FYP) \nProjetou uma impressora 3D com mecanismo cartesiano usando deposição fundida\nTecnologia de modelagem (FDM) seguindo o método de fabricação aditiva. \nInglês\nUrdulanguagesmicrosoft Office \nLinguagens de programação (c ++, c, linguagem de montagem,\nOOP) \nSQL \nProjeto de circuito, plc\nPrograma de gerenciamento hospitalar\nProjetou um código OPD (departamento de paciente ao ar livre) em C ++.\nReferências\nPode ser fornecido mediante necessidade. Desenvolvimento de negócios\nAnálise de negócios \nLiderança \nSolução de problemas \nNegociação \nPensador crítico \nCompetências de Habilidades de Apresentação e Negociação de Apresentação e Negociação\nViajando\nEsportes \nEscrita \nAssistindo a filmes interincores e\nHobbies",
  "details": {
    "name": "Izma bint-e-atif",
    "number": "923310483113",
    "skills": [
      "Projeto de circuito",
      "Balsamiq",
      "Matlab",
      "CAD automático",
      "Sketchup",
      "Visual Studio",
      "C ++",
      "C",
      "Linguagem de montagem",
      "OOP",
      "SQL",
      "Plc"
    ],
    "email_id": "izma.b.atif@gmail.com",
    "location": "Casa nº 530, Bloco J3, Johar Town, Lahore",
    "projects": [
      {
        "title": "Impressora 3D com mecanismo cartesiano",
        "description": "Projetou uma impressora 3D com mecanismo cartesiano usando a tecnologia de modelagem de deposição fundida (FDM) seguindo o método de fabricação aditiva."
      },
      {
        "title": "Programa de gerenciamento hospitalar",
        "description": "Projetou um código OPD (departamento de paciente ao ar livre) em C ++."
      }
    ],
    "education": [
      {
        "end_date": "06-2020",
        "university": "FastNuces",
        "degree_title": "Bacharel em Engenharia Elétrica"
      },
      {
        "end_date": "06-2015",
        "university": "Queen Mary College for Women",
        "degree_title": "FSC pré -engenharia"
      },
      {
        "end_date": "06-2013",
        "university": "Escola de Convento do Coração Sagrado",
        "degree_title": "Matrícula"
      }
    ],
    "achievements": [],
    "publications": [],
    "certifications": [],
    "additional_urls": [
      {
        "url": "LinkedIn.com/in/izma-bint-e-atif",
        "website_name": "LinkedIn"
      }
    ],
    "executive_summary": "A IZMA Bint-E-ATIF é um analista de negócios qualificado com uma forte experiência em engenharia elétrica e vasta experiência em análise de mercado, gerenciamento de projetos e desenvolvimento de software. Ela demonstrou proficiência em várias linguagens de programação e ferramentas de software, contribuindo para resultados bem -sucedidos de projetos em ambientes ágeis. Sua experiência técnica é complementada por sua capacidade de comunicar e colaborar efetivamente com clientes e partes interessadas.",
    "employment_history": [
      {
        "details": "Realize análises de mercado para as linhas de produtos e a lucratividade geral dos negócios. Auxiliar no planejamento e execução dos planos de teste para integração e teste de processo, incluindo o aumento de logs de falhas. Desenvolva conceitos de projeto e mantenha o fluxo de trabalho ideal.",
        "end_date": "Presente",
        "location": "Nextbridge Unip. Ltd.",
        "job_title": "Executivo de Desenvolvimento de Negócios",
        "start_date": "01-2021",
        "company_name": "Nextbridge Unip. Ltd."
      },
      {
        "details": "Analisar e priorizar os requisitos do cliente. Traduzir os requisitos do cliente em resumos especificados do projeto, compreendendo o ciclo de vida do desenvolvimento de software. Trabalhando diretamente com usuários/clientes e compreendendo problemas de negócios, estabelecendo solução e apresentando de volta às principais partes interessadas. Criando uma análise de negócios detalhada, descrevendo problemas, oportunidades e soluções para um negócio. Análise de processo e produção de artefato acordado adequado para uso interno e/ou revisão e assinatura do cliente.",
        "end_date": "12-2021",
        "location": "Red Communication Arts Pvt. Ltd.",
        "job_title": "Analista de negócios júnior",
        "start_date": "01-2020",
        "company_name": "Red Communication Arts Pvt. Ltd."
      }
    ]
  }
}