{
  "job_description": "Gerente de Desenvolvimento de Negócios\n\nJunte -se a ** Innovatecorp ** como gerente de desenvolvimento de negócios para contribuir com nossa crescente equipe e impulsionar iniciativas estratégicas no setor de serviços de tecnologia. O candidato ideal alavancará sua vasta experiência em desenvolvimento de negócios, relações com clientes e gerenciamento de projetos para expandir nossa presença no mercado e criar parcerias duradouras.\n\n#### Responsabilidades -chave:\n- Desenvolver e implementar planos de desenvolvimento estratégico de negócios para alcançar as metas da empresa.\n- Geração de leads e construção de relacionamentos com clientes em potencial.\n- Supervisionar estratégias de aquisição de clientes, incluindo exploração além dos mercados freelancers.\n- Colabore com equipes multifuncionais para garantir a entrega suave do projeto.\n- Utilize o software CRM para rastrear o engajamento do cliente e o progresso do desenvolvimento.\n- Realize pesquisas de mercado para permanecer a par das tendências da indústria e informar estratégias de negócios.\n- Gerenciar e relatar as métricas de desenvolvimento de negócios.\n\n#### Habilidades e competências:\n- Comunicação forte e habilidades interpessoais para envolvimento e colaboração do cliente.\n- Excelentes habilidades analíticas para informar propostas e decisões estratégicas.\n- Experiência no Microsoft Office para documentação e apresentações.\n- Proficiência no software CRM para gerenciar o relacionamento com os clientes.\n\n#### Benefícios:\n- Salário competitivo com incentivos de bônus.\n- Oportunidades de desenvolvimento profissional e avanço na carreira.\n- Pacotes de saúde e seguro odontológico.\n- Horário de trabalho flexível e um ambiente positivo e orientado para a equipe.",
  "additional_info": "A Innovatecorp prefere candidatos de escolas de negócios líderes, como o Comsats Institute of Information and Technology. Apoiamos a realocação para o candidato certo e oferecemos oportunidades de trabalho remotas. As habilidades são avaliadas através de uma combinação de entrevistas técnicas e estudos de caso práticos, garantindo que os candidatos atendam aos nossos altos padrões de desempenho antes de oferecer uma posição.",
  "resume": "Mubashar Fayyaz\nDesenvolvimento de negócios e gerenciamento de operação, B2B, B2C, TI, Treinamento\nLahore\nmubashar.fayyaz@yahoo.com\n+92 331 4393771\nExperiência profissional em desenvolvimento e gerenciamento de negócios, gerenciamento de operações, técnico\nLiderança e supervisão de vendas. Valioso para operações comerciais iniciantes e em andamento; excelente\nCapacidade de desenvolver novos projetos. Bem equipado para gerenciar multi-departamentos como RH, vendas, finanças,\ne compras. A experiência de gerenciamento de TI é uma vantagem adicional para analisar funções de negócios e\nimplantando novas tecnologias. Fortes habilidades analíticas e de solução de problemas com a capacidade de trabalhar com\nsupervisão limitada.\nExperiência de trabalho\nOficial de Desenvolvimento de Negócios\nFastech Pvt. Ltd - Lahore\nJaneiro de 2019 para apresentar\n• Minhas responsabilidades principais são pegar projetos de Upwork, Freelancer, etc.\n• Comunicação com clientes.\n• Gerando leads e compartilhamento de atribuições de leads com nosso departamento na costa.\n• Trabalhe com nosso departamento de vendas para convertê -lo em uma oportunidade que leva ao fechamento da venda.\n• Mantenha contato e acompanhe rigorosamente o cliente em potencial até o fechamento da venda.\n• Estamos encontrando KPIs semanais e adicionando -os ao CRM.\n• Treinar os recém -chegados do departamento de vendas interno, desde a sucata de dados até a geração de leads e a partir de\nPesquisa de dados para relatórios.\n• cumprir a meta anual do fechamento de vendas.\n• Acompanhamentos com os clientes.\n• Entenda o escopo do projeto.\n• Atribuir a tarefa ao assistente e ao BDE.\n• Decida os termos e elucidar os requisitos para o custo e o prazo do projeto.\n• Lidar com contas de trabalho e freelancer.\n• Gerenciando negócios e leads usando o HubSpot.\n• Gere leads através do LinkedIn Sales Navigator, AngelList, etc.\n• Executando a campanha de e -mail através do Appolo.io\nGerente de TI e operações\nFundo de Apoio ao Agrades\nSetembro de 2013 a janeiro de 2019\n• O gerenciamento e os projetos de TI e operações levam a facilitar as partes interessadas.\n• Análise de orçamento e custo para a infraestrutura de TI e a implantação de sistemas, preparando o escopo do trabalho.\n• Os requisitos reuniram e implementaram várias soluções como ERP, comércio eletrônico, LMS e Web\nAplicações.\n• Supervisionar as equipes de TI/MIS para operações suaves de TI, incluindo LAN/WAN e Security.Manager Operations\nFundo de Apoio ao Agrades\nOutubro de 2010 a setembro de 2013\n• Preparar relatórios, apresentações, atas de reuniões e conduzir pesquisas para\nInformação.\n• Acordos de cumprimento, cuidando de acordos de viagens ao exterior, incluindo segurança.\n• Experiência do membro do comitê de compras das regras dos EUA e da PPRA.\n• Contratação do fornecedor (SLA) conforme as necessidades organizacionais.\n• Trabalhou com o departamento de RH para preparar descrições de cargos, anúncios de posição e contratação de funcionários.\nOperações de gerente/desenvolvimento de negócios\nWateen Telecom\nDezembro de 2007 a setembro de 2010\n• Desenvolvimento de negócios e gerenciamento definido no escopo do projeto e estabelecem metas e entregas para\ncrescimento nos negócios.\n• Planejou e implementou atividades promocionais de negócios para atingir metas definidas.\n• Supervisão da equipe e alcançou mais de 6000 clientes a bordo.\n• Gerenciamento de vendas para quatro pontos de vendas (POS), seguiu a hierarquia de gerentes de vendas e equipe\nmembros para atingir metas definidas.\n• Crie um roteiro para o sucesso para gerenciar revendedores e distribuidores para garantir o funcional\neficácia do negócio.\n• Prepare os custos de terra, estabeleça um orçamento e meta para sustentabilidade e lucratividade dos negócios.\n• Contratação e treinamento de funcionários em tecnologia como WiMax, TCP/IP, configuração de VoIP e solução de problemas,\nPortal de CRM, incluindo sistema de gerenciamento de registros financeiros.\nEducação\nMestre de ciências nele\nUniversidade de Preston\n2005\nB. com\nFaculdade de Comércio Punjab\n1996\nHabilidades\n• Gerenciamento de projetos (3 anos)\n• Gerenciamento de operações (4 anos)\n• Compras (2 anos)\n• Desenvolvimento e Gerenciamento de Negócios (5 anos)\n• Vendas e atendimento ao cliente (3 anos)\n• Contratação e treinamento da equipe (4 anos)\n• Controle de inventário (3 anos)\n• Orçamento (3 anos) • Melhoria do processo (5 anos)\n• Gerenciamento (5 anos)\n• folha de pagamento (3 anos)\n• Análise de negócios (3 anos)\n• Asana (menos de 1 ano)\n• SQL (3 anos)\n• ágil (menos de 1 ano)\n• VoIP (2 anos)\n• TCP/IP (3 anos)\n• Licitação (4 anos)\n• Geração de leads (4 anos)\n• Escrita da proposta (4 anos)\nIdiomas\n• Inglês - Fluente\n• Chinês - iniciante\n• urdu - fluente",
  "details": {
    "name": "Mubashar Fayyaz",
    "number": "923314393771",
    "skills": [
      "Gerenciamento de projetos",
      "Gerenciamento de operações",
      "Compras",
      "Desenvolvimento de Negócios e Gerenciamento",
      "Vendas e atendimento ao cliente",
      "Contratação e treinamento de funcionários",
      "Controle de inventário",
      "Orçamento",
      "Melhoria do processo",
      "Gerenciamento",
      "Folha de pagamento",
      "Análise de negócios",
      "Asana",
      "SQL",
      "Ágil",
      "VoIP",
      "TCP/IP",
      "Licitação",
      "Geração de chumbo",
      "Escrita da proposta"
    ],
    "email_id": "mubashar.fayyaz@yahoo.com",
    "location": "Lahore",
    "projects": [],
    "education": [
      {
        "end_date": "12-2005",
        "university": "Universidade de Preston",
        "degree_title": "Mestre de ciências nele"
      },
      {
        "end_date": "06-1996",
        "university": "Faculdade de Comércio Punjab",
        "degree_title": "B. com"
      }
    ],
    "achievements": [],
    "publications": [],
    "certifications": [],
    "additional_urls": [
      {
        "url": "LinkedIn.com/in/mubasharfayyaz",
        "website_name": "LinkedIn"
      }
    ],
    "executive_summary": "Mubashar Fayyaz é um profissional qualificado em desenvolvimento de negócios e gerenciamento de operações, com vasta experiência em TI e treinamento. Ele tem um histórico comprovado no gerenciamento de funções multi-departamentais e nos principais projetos técnicos, demonstrando uma forte capacidade de impulsionar o crescimento dos negócios e a eficiência operacional.",
    "employment_history": [
      {
        "details": "Minhas principais responsabilidades são pegar projetos da Upwork, Freelancer, etc. Comunicação com os clientes. Gerando leads e compartilhamento de atribuições de leads com nosso departamento na costa. Trabalhe com nosso departamento de vendas para convertê -lo em uma oportunidade que leva ao fechamento da venda. Fique em contato e acompanhe rigorosamente o cliente em potencial até o fechamento da venda. Estamos encontrando KPIs semanais e adicionando -os ao CRM. Treinar os recém -chegados do departamento de vendas interno, desde a sucção de dados até a geração de leads e da pesquisa de dados até os relatórios. Cumprindo a meta anual do fechamento de vendas. Acompanhamento com os clientes. Entenda o escopo do projeto. Atribuir a tarefa ao assistente e ao BDE. Decida os termos e elucidar os requisitos para o custo e o prazo do projeto. Lidar com contas de trabalho e freelancer. Gerenciando negócios e leads usando o HubSpot. Gerar leads através do LinkedIn Sales Navigator, AngelList, etc. Executando a campanha por e -mail através do Appolo.io",
        "end_date": "Presente",
        "location": "Lahore",
        "job_title": "Oficial de Desenvolvimento de Negócios",
        "start_date": "01-2019",
        "company_name": "Fastech Pvt. Ltd"
      },
      {
        "details": "O gerenciamento e os projetos de TI e operações levam a facilitar as partes interessadas. Análise de orçamento e custo para a infraestrutura de TI e a implantação de sistemas, preparando o escopo do trabalho. Os requisitos reuniram e implementaram várias soluções como ERP, comércio eletrônico, LMS e aplicativos da Web. Supervisionar as equipes de TI/MIS para operações suaves de TI, incluindo LAN/WAN e segurança.",
        "end_date": "01-2019",
        "location": "Lahore",
        "job_title": "Gerente de TI e operações",
        "start_date": "09-2013",
        "company_name": "Fundo de Apoio ao Agrades"
      },
      {
        "details": "Prepare relatórios, apresentações, atas de reuniões e conduz a pesquisa para obter informações. Acordos de cumprimento, cuidando de acordos de viagens ao exterior, incluindo segurança. Comitê de compras Experiência do Comitê das Regras dos EUA e da PPRA. Contratação do fornecedor (SLA) conforme as necessidades organizacionais. Trabalhou com o departamento de RH para preparar descrições de cargos, anúncios de posição e contratação de funcionários.",
        "end_date": "09-2013",
        "location": "Lahore",
        "job_title": "Operações de gerente",
        "start_date": "10-2010",
        "company_name": "Fundo de Apoio ao Agrades"
      },
      {
        "details": "O desenvolvimento de negócios e o gerenciamento definiram o escopo do projeto e estabelecem metas e entregas para o crescimento dos negócios. Planejou e implementou atividades promocionais de negócios para atingir metas definidas. Supervisão da equipe e alcançou mais de 6000 clientes a bordo. O gerenciamento de vendas para quatro pontos de vendas (POS), seguiu a hierarquia de gerentes de vendas e membros da equipe para atingir as metas definidas. Crie um roteiro para o sucesso para gerenciar revendedores e distribuidores para garantir a eficácia funcional dos negócios. Prepare os custos de terra, estabeleça um orçamento e meta para sustentabilidade e lucratividade dos negócios. Contratação e treinamento de funcionários em tecnologia como WiMAX, TCP/IP, Configuração e solução de problemas VoIP, portal de CRM, incluindo o sistema de gerenciamento de registros financeiros.",
        "end_date": "09-2010",
        "location": "Lahore",
        "job_title": "Operações de gerente/desenvolvimento de negócios",
        "start_date": "12-2007",
        "company_name": "Wateen Telecom"
      }
    ]
  }
}