{
  "job_description": "Gerente de Desenvolvimento de Negócios\n\n** Empresa fictícia ** está buscando um gerente de desenvolvimento de negócios dinâmico e estratégico para ingressar em nossa equipe crescente. Nesta função, você desenvolverá e executará estratégias de vendas, gerenciará as principais contas e liderará iniciativas de desenvolvimento de negócios para impulsionar o crescimento organizacional.\n\nResponsabilidades ####:\n- Desenvolva e implemente estratégias para o desenvolvimento de negócios para atingir objetivos corporativos.\n- Supervisionar todo o ciclo de vendas, da geração de leads a acordos de fechamento.\n- Gerenciar e orientar uma equipe de executivos de desenvolvimento de negócios, aprimorando seu potencial para otimizar o sucesso da empresa.\n- Aprimore a presença da empresa por meio de engajamento ativo em plataformas on -line como o LinkedIn e os sites de rede profissional.\n-Envolva-se em negociações de alto risco e coordenam com as principais partes interessadas da conta para garantir a satisfação do cliente e as parcerias de longo prazo.\n\n#### Requisitos:\n- Utilize habilidades analíticas para identificar novas oportunidades e tendências de mercado.\n- Use o Microsoft Office Suite de maneira eficaz para planejar, relatar e apresentar estratégias de vendas.\n\nJunte -se a nós para desempenhar um papel fundamental na expansão de nossos negócios localmente e internacionalmente, trabalhando ao lado de uma equipe dinâmica em um ambiente inovador. Se você gosta de tomar iniciativas e liderar iniciativas de negócios impactantes, queremos ouvir você!",
  "additional_info": "Os candidatos preferidos terão se formado nas principais escolas de negócios, como núcleos rápidos ou Lums. A empresa apóia a realocação de funcionários no Paquistão com a assistência logística necessária. As habilidades são avaliadas por meio de uma combinação de entrevistas técnicas e estudos de caso práticos alinhados aos desafios do setor.",
  "resume": "Faique Ali Raza House # 392, K Block, Model Town, Lahore, Pakistan 03143631941 linkedin.com/in/FaiqueAliRaza faiquealiraza@gmail.com Profile • An individual who is focused, honest, team-oriented, deliberate, determined, and most importantly, who makes use of his grey matter. • Vários anos de experiência em desenvolvimento de negócios, geração de vendas e campos de marketing. • Freelancer com melhor classificação no Upwork. • Experiência prática em geração de leads, marketing por email, tele-vendas, navegador de vendas, Salesforce, documentação e CRM. • 1 ano de experiência em marketing de comunicação e tele-sales. • Mais de 9 anos de experiência no campo da música e gerenciamento de eventos. Experiência de trabalho educacional • Matric | Ciência | Autoridade de Aviação Civil LAHORE LAHORE • Intermediário | Pre Eng. | Government College Gulberg Lahore • Bacharel em Ciência da Computação | Os prêmios de habilidades da Universidade de Lahore, realizações e certificações raspam dados | Extração de dados | Leads | E -mails upwork | Fiverr | Freelancer | Guru | Toptal Musician | Produção | Live | Gravações de estúdio • Curso de cinema e documentário | Hunerkada College of Visual & Performing Arts | Lahore | 2020  \n Design de produção para filme e tela | Escola de televisão e rádio australiana de cinema e rádio | 2020 \n Programa Nacional de Alfabetização Financeira para Juventude | Instituto Nacional de Bancos e Finanças (NIBAF) -Paquistão | 2020 \n Certificação em pensamento crítico - tomada de decisão mestre e resolução de problemas. \n Ganhou muitas batalhas musicais no Paquistão. \n Tendo muitas certificações em diferentes atividades e cursos.  • Marketing de conteúdo e publicidade | Universidade de Punjab | E-rozgaar | Lahore | 2020 \nSrs | GDD | Wbd | Marcos | Linhas de tempo • Gerente de Desenvolvimento de Negócios | CrewLogicx Tech | Studios de origami | Abril de 2022 - cont. • Desenvolvimento de negócios e gerente de projetos digitais | Firtle Tech | Meio período | Junho de 2019 - cont. • Executivo de Desenvolvimento de Negócios | Tech de argônio | Lahore | Maio de 2021 - abril de 2022. • Executivo de Desenvolvimento de Negócios | Kodex Technologies | Dezembro de 2020 - maio de 2021. • Executivo de Desenvolvimento de Negócios | Growhawk | Agosto - dezembro de 2020. • Executivo de Desenvolvimento de Negócios | Bizzclan | Lahore | Maio - agosto de 2020. • Agente de telemarketing | Solução nixxe | 2019. Desenvolvedor de Negócios | Especialista no LinkedIn | Leads/Gerador de vendas | Freelancer de upwork com melhor classificação",
  "details": {
    "name": "Faique Ali Raza",
    "number": "03143631941",
    "skills": [
      "Raspagem de dados",
      "Extração de dados",
      "Pistas",
      "E -mails",
      "Salesforce",
      "Documentação",
      "CRM"
    ],
    "email_id": "faiquealiraza@gmail.com",
    "location": "Lahore, Paquistão",
    "projects": [],
    "education": [
      {
        "end_date": "06-2020",
        "university": "Autoridade de aviação civil LAHORE",
        "degree_title": "Matric | Ciência"
      },
      {
        "end_date": "06-2020",
        "university": "Faculdade de governo Gulberg Lahore",
        "degree_title": "Intermediário | Pre Eng."
      },
      {
        "end_date": "06-2020",
        "university": "A Universidade de Lahore",
        "degree_title": "Bacharel em Ciência da Computação"
      }
    ],
    "achievements": [
      "Freelancer de primeira classificação no Upwork",
      "Ganhou muitas batalhas musicais no Paquistão"
    ],
    "publications": [],
    "certifications": [
      {
        "certification_name": "Curso de cinema e documentário",
        "issuing_organization": "Hunerkada College of Visual & Performing Arts",
        "date_of_issuance": "06-2020"
      },
      {
        "certification_name": "Design de produção para cinema e tela",
        "issuing_organization": "Escola de televisão e rádio australiana",
        "date_of_issuance": "06-2020"
      },
      {
        "certification_name": "Programa Nacional de Alfabetização Financeira para Juventude",
        "issuing_organization": "Instituto Nacional de Bancos e Finanças (NIBAF) -Paquistão",
        "date_of_issuance": "06-2020"
      },
      {
        "certification_name": "Marketing de conteúdo e publicidade",
        "issuing_organization": "Universidade de Punjab | E-rozgaar",
        "date_of_issuance": "06-2020"
      }
    ],
    "additional_urls": [
      {
        "url": "LinkedIn.com/in/faiquealiraza",
        "website_name": "LinkedIn"
      }
    ],
    "executive_summary": "Faique Ali Raza é um profissional dedicado, com vasta experiência em desenvolvimento de negócios, geração de vendas e marketing. Ele tem uma forte formação técnica em sistemas de raspagem de dados, geração de leads e CRM, complementados por uma base educacional sólida na ciência da computação. Faique é reconhecido como um freelancer de melhor classificação no Upwork e alcançou um sucesso notável em batalhas musicais em todo o Paquistão.",
    "employment_history": [
      {
        "details": "Gerente de Desenvolvimento de Negócios Responsável por impulsionar as vendas e gerenciar o relacionamento com os clientes.",
        "end_date": "Presente",
        "location": "Lahore",
        "job_title": "Gerente de Desenvolvimento de Negócios",
        "start_date": "04-2022",
        "company_name": "CrewLogicx Tech"
      },
      {
        "details": "Desenvolvimento de negócios em período parcial e gerente de projetos digitais que supervisionam a execução do projeto e o envolvimento do cliente.",
        "end_date": "Presente",
        "location": "Lahore",
        "job_title": "Desenvolvimento de negócios e gerente de projetos digitais",
        "start_date": "06-2019",
        "company_name": "Firtle Tech"
      },
      {
        "details": "O Executivo de Desenvolvimento de Negócios se concentrou na geração de leads e fechamento de vendas.",
        "end_date": "04-2022",
        "location": "Lahore",
        "job_title": "Executivo de Desenvolvimento de Negócios",
        "start_date": "05-2021",
        "company_name": "Tecnologia de Argon"
      },
      {
        "details": "Executivo de desenvolvimento de negócios responsável pela aquisição de clientes e gerenciamento de relacionamento.",
        "end_date": "05-2021",
        "location": "Lahore",
        "job_title": "Executivo de Desenvolvimento de Negócios",
        "start_date": "12-2020",
        "company_name": "Kodex Technologies"
      },
      {
        "details": "Executivo de desenvolvimento de negócios encarregado de geração de leads e estratégias de vendas.",
        "end_date": "12-2020",
        "location": "Lahore",
        "job_title": "Executivo de Desenvolvimento de Negócios",
        "start_date": "08-2020",
        "company_name": "Growhawk"
      },
      {
        "details": "Agente de telemarketing envolvido em vendas diretas e divulgação de clientes.",
        "end_date": "12-2019",
        "location": "Lahore",
        "job_title": "Agente de telemarketing",
        "start_date": "01-2019",
        "company_name": "Solução nixxe"
      }
    ]
  }
}