{
  "job_description": "Gerente de Desenvolvimento de Negócios\n\nJunte -se a ** Innovatecorp ** como gerente de desenvolvimento de negócios para contribuir com nossa crescente equipe e impulsionar iniciativas estratégicas no setor de serviços de tecnologia. O candidato ideal alavancará sua vasta experiência em desenvolvimento de negócios, relações com clientes e gerenciamento de projetos para expandir nossa presença no mercado e criar parcerias duradouras.\n\n#### Responsabilidades -chave:\n- Desenvolver e implementar planos de desenvolvimento estratégico de negócios para alcançar as metas da empresa.\n- Geração de leads e construção de relacionamentos com clientes em potencial.\n- Supervisionar estratégias de aquisição de clientes, incluindo exploração além dos mercados freelancers.\n- Colabore com equipes multifuncionais para garantir a entrega suave do projeto.\n- Utilize o software CRM para rastrear o engajamento do cliente e o progresso do desenvolvimento.\n- Realize pesquisas de mercado para permanecer a par das tendências da indústria e informar estratégias de negócios.\n- Gerenciar e relatar as métricas de desenvolvimento de negócios.\n\n#### Habilidades e competências:\n- Comunicação forte e habilidades interpessoais para envolvimento e colaboração do cliente.\n- Excelentes habilidades analíticas para informar propostas e decisões estratégicas.\n- Experiência no Microsoft Office para documentação e apresentações.\n- Proficiência no software CRM para gerenciar o relacionamento com os clientes.\n\n#### Benefícios:\n- Salário competitivo com incentivos de bônus.\n- Oportunidades de desenvolvimento profissional e avanço na carreira.\n- Pacotes de saúde e seguro odontológico.\n- Horário de trabalho flexível e um ambiente positivo e orientado para a equipe.",
  "additional_info": "A Innovatecorp prefere candidatos de escolas de negócios líderes, como o Comsats Institute of Information and Technology. Apoiamos a realocação para o candidato certo e oferecemos oportunidades de trabalho remotas. As habilidades são avaliadas através de uma combinação de entrevistas técnicas e estudos de caso práticos, garantindo que os candidatos atendam aos nossos altos padrões de desempenho antes de oferecer uma posição.",
  "resume": "Hassan Saeed\nGerente de Business De Velropment\nCONTATO\nEndereço: Sadiq Abad\nNúmero do celular: +923053328700\nID do email: hassansaeed3328@gmail.com\nData de nascimento: 02-Sep-1996\nGênero: Masculino\nNacionalidade: Paquistão\nEstado civil: casado\nIdiomas: inglês\nHABILIDADES\nGerenciamento de projetos freelancers\nDesenvolvimento de negócios\nREFERÊNCIA\nNome: Oneeb Arif\nDetalhe: Invozone - Líder de Desenvolvimento\nE -mail: oneeb@invozone.com\nMobile: 03051234640\nNome: Raheel Ahmed\nDetalhe: Codfelix - Gerente de Projeto\nE -mail: raheelahmed121@gmail.com\nMobile: 03053661152\nExperiência de trabalho\nSoluções Homi\nGerente de Desenvolvimento de Negócios\nDuração: 06-2022 - Até hoje\nDevbunch\nEquipe de Desenvolvimento de Negócios Líder\nDuração: 09-2021-06-2022\nPrincipais executivos e gerenciamento de todos os clientes de negócios\nInvozone\nExecutivo de Desenvolvimento de Negócios\nDuração: 03-2021-08-2021\nMinhas responsabilidades centrais eram bloquear o cliente de várias plataformas freelancers,\nComunicação com os clientes, acompanhe o cliente, escopo do projeto, cronograma\nencontrando -se com a pessoa técnica, gerencie o lead usando folga\nCodfelix\nDesenvolvedor de negócios\nDuração: 05-2020-02-2021\nEnviando propostas ao cliente em trabalho, responda ao cliente, chamadas não técnicas,\nEngajamento do desenvolvedor, travamento do cliente\nEDUCAÇÃO\nBise Bahawalpur\nEscola MTB H/S, SDK - Matrícula\nNotas - 74 %\nAno de aprovação: 2011\nPBTE LAHORE\nGCT College, Ryk. - Intermediário\nNotas - 75 %\nAno de aprovação: 2014\nKfueit, Ryk\n- Tecnologia da informação BS\nNotas - 3,00 cGPA\nAno da passagem: 2020\nProjetos\nAPI do mapa do custome\nDesenvolvedor de negócios\nDuração: 01-2022 -\nTamanho da equipe - 4\nMetaverse da NFT\nDesenvolvedor de negócios\nDuração: 01-2022 -\nTamanho da equipe - 4\nRealizações\nMOS 2013\nCaça ao projeto",
  "details": {
    "name": "Hassan Saeed",
    "number": "923053328700",
    "skills": [
      "Freelancer",
      "Gerenciamento de projetos",
      "Desenvolvimento de negócios"
    ],
    "email_id": "hassansaeed3328@gmail.com",
    "location": "Sadiq Abad",
    "projects": [
      {
        "title": "API do mapa do custome",
        "description": "Desenvolvedor de negócios"
      },
      {
        "title": "Metaverse da NFT",
        "description": "Desenvolvedor de negócios"
      }
    ],
    "education": [
      {
        "end_date": "2011",
        "university": "Escola MTB H/S, SDK",
        "degree_title": "Matrícula"
      },
      {
        "end_date": "2014",
        "university": "GCT College, Ryk",
        "degree_title": "Intermediário"
      },
      {
        "end_date": "2020",
        "university": "Kfueit, Ryk",
        "degree_title": "BS Tecnologia da Informação"
      }
    ],
    "achievements": [
      "MOS 2013",
      "Caça ao projeto"
    ],
    "publications": [],
    "certifications": [],
    "additional_urls": [],
    "executive_summary": "Hassan Saeed é um gerente de desenvolvimento de negócios qualificado, com vasta experiência em freelancer e gerenciamento de projetos. Ele tem uma forte formação em desenvolvimento de negócios, tendo trabalhado com várias organizações para aprimorar o envolvimento do cliente e a execução do projeto.",
    "employment_history": [
      {
        "details": "Principais executivos e gerenciamento de todos os clientes de negócios",
        "end_date": "Até hoje",
        "location": "",
        "job_title": "Gerente de Desenvolvimento de Negócios",
        "start_date": "06-2022",
        "company_name": "Soluções Homi"
      },
      {
        "details": "Principais executivos e gerenciamento de todos os clientes de negócios",
        "end_date": "06-2022",
        "location": "",
        "job_title": "Equipe de Desenvolvimento de Negócios Líder",
        "start_date": "09-2021",
        "company_name": "Devbunch"
      },
      {
        "details": "Bloquear clientes de várias plataformas freelancers, comunicar -se com clientes, acompanhar, entender o escopo do projeto, agendar reuniões com pessoal técnico, gerenciar leads usando o Slack",
        "end_date": "08-2021",
        "location": "",
        "job_title": "Executivo de Desenvolvimento de Negócios",
        "start_date": "03-2021",
        "company_name": "Invozone"
      },
      {
        "details": "Enviando propostas para os clientes em trabalho, respondendo a clientes, chamadas não técnicas, engajamento do desenvolvedor, travamento de clientes",
        "end_date": "02-2021",
        "location": "",
        "job_title": "Desenvolvedor de negócios",
        "start_date": "05-2020",
        "company_name": "Codfelix"
      }
    ]
  }
}