{
  "job_description": "Participe ** Techventures Inc. ** Como um gerente de projeto sênior **, onde você supervisionará a entrega de projetos de gerenciamento de dados e análise de dados. Estamos à procura de um líder inovador que possa estabelecer e defender os padrões de entrega, gerenciando equipes multifuncionais para alcançar os mais altos níveis de excelência em serviços. Sua experiência em pré-vendas, arquitetura de soluções e gerenciamento de relacionamento com clientes impulsionará nossa expansão para novos mercados e otimizará os processos existentes.\n\n### Responsabilidades -chave:\n- Liderar e gerenciar projetos complexos de análise de dados e gerenciamento desde o início até a conclusão.\n- Desenvolver e implementar sistemas de qualidade e gerenciamento de projetos para se alinhar com as metas organizacionais.\n- Coordenar as atividades de arquitetura de soluções e pré-vendas, incluindo a preparação de RFPs e EOIs.\n- Mentor e orientar os membros da equipe júnior em desenvolvimento profissional e execução do projeto.\n- Envolva -se com os clientes para fornecer soluções de negócios personalizadas e melhorar a satisfação do cliente.\n- Colabore com outros departamentos para identificar oportunidades de melhoria e otimizar processos.\n\n### Habilidades preferidas:\n- Proficiência em ferramentas de dados como Powerbi, Oracle DV e Tableau.\n- Forte entendimento das metodologias de desenvolvimento de software, incluindo Agile e Scrum.\n- Capacidade demonstrada de liderar grandes equipes técnicas e lidar com as comunicações das partes interessadas de maneira eficaz.\n- Especialização em implementação de inteligência de negócios e data warehousing corporativo.\n\n### Por que se juntar a nós?\n- Oportunidade de trabalhar em projetos impactantes com alcance global.\n- ambiente de trabalho colaborativo e inclusivo.\n- Aprendizagem contínua e oportunidades de desenvolvimento profissional.\n\nTorne -se parte de uma equipe que valorize a integridade, a excelência e a inovação e ajude -nos a redefinir o que é possível no setor de tecnologia.",
  "additional_info": "As universidades preferenciais incluem a Universidade Nacional de Computação e Ciências Emergentes no Paquistão e instituições equivalentes. Oferecemos apoio de realocação a candidatos baseados fora da cidade de contratação, sujeitos à aprovação da gerência. As habilidades são avaliadas através de uma combinação de testes técnicos, estudos de caso de gerenciamento de projetos e entrevistas com painéis que consistem em chefes departamentais e representantes de RH.",
  "resume": "Idiomas SpokenProspecting, Qualificação, Desenvolvimento de Pipeline de Vendas.\nDemonstrações de produtos.\nProprietário do produto.\nGeração de chumbo e promovendo -os: gerar o novo líder e\npromove -os.\nExaminar o requisito do cliente e, mantendo o\ndocumentos de requisito.\nPerspectivas de vendas, mantendo perspectivas saudáveis ​​de vendas. Agindo como um\nligação entre a equipe de desenvolvimento e a equipe de negócios,\npermanecendo conectado com o cliente.\nDemonstração mensal de MVPs aos clientes.\nChamada a frio - e -mail frio: alcançando novos clientes e tomando acompanhamento\nUPS para perspectivas futuras.\nIniciar o relacionamento com as perspectivas saudáveis ​​através\nLinkedIn.\nDemonstrações de produtos para os clientes depois de definir bem -sucedido\nreuniões.\nEspecialista sênior de suporte ao cliente Suporte contratado | Julho de 2020 - Jan\n2021\nEntrei para o apoio contratado como especialista sênior de suporte ao cliente\nPara promover minhas habilidades escritas.\nReceba e responda prontamente às consultas do cliente.\nDocumentar problemas e resoluções.\nAprenda sobre novos produtos e serviços. Keep Truckin\nExecutivo de contas | Novembro de 2021 - presente\nQuadrado viral\nOficial de Desenvolvimento de Negócios | Fevereiro de 2021- novembro de 2021\nSuporte contratado\nUniversidade de Punjab Central\nMestrado em Administração de Empresas 2021 - Presente\nComecei meu mestrado em administração de empresas da universidade\ndo Punjab central para promover minha experiência ainda mais conforme a necessidade do\nmercado, para entender melhor as perspectivas de vendas.\nUniversidade Hazara\nBacharelado em Administração de Empresas 2014 - 2018\nEu fiz meus solteiros da Universidade de Hazara, garantindo coloridos\nnotas, escolheu as finanças como minha principal área de pesquisa. Experiência de trabalho\nDestaques da educação: +923475130731\nUmersaleemzaman1308@gmail.com\nLinkedIn.com/in/umersaleemzaman/ \nJohar Town, Lahore, Paquistanumer Saleem\nOficial de Desenvolvimento de Negócios\nNegócios experientes\nDesenvolvimento e cliente\nExecutivo com um\nHistória demonstrada de\nTrabalhando como contato de vendas\nentre o cliente e o\nEmpresa. Eu tenho acuminado\nhabilidades em gerenciamento de clientes,\nRequisitos de coleta e\nPotencial convincente\nClientes, um pensamento que\nimpulsiona a execução, muito\nconhecedor em uma ampla\nVariedade de profissional\ndisciplinas que maximizam\ncrescimento da marca, incluindo\nfinanças, marketing e tudo\nFacetas de operações comerciais\ndo desenvolvimento de produtos para\nengajamento do cliente. Resumo executivo\nGeração de chumbo\nSalesFroce\nSalloft\nMicrosoft Office\nZendesk\nTawlk.to\nPipeline de vendas\nDesenvolvimento de vendas\nDemonstrações de produtos\nINGLÊS\nURDU \nHINDI",
  "details": {
    "name": "Umer Saleem",
    "number": "923475130731",
    "skills": [
      "Geração de chumbo",
      "SalesFroce",
      "Salloft",
      "Microsoft Office",
      "Zendesk",
      "Tawlk.to",
      "Pipeline de vendas",
      "Desenvolvimento de vendas",
      "Demonstrações de produtos"
    ],
    "email_id": "Umersaleemzaman1308@gmail.com",
    "location": "Johar Town, Lahore, Paquistão",
    "projects": [],
    "education": [
      {
        "end_date": "12-2021",
        "university": "Universidade de Punjab Central",
        "degree_title": "Mestrado em Administração de Empresas"
      },
      {
        "end_date": "05-2018",
        "university": "Universidade Hazara",
        "degree_title": "Bacharelado em Administração de Empresas"
      }
    ],
    "achievements": [],
    "publications": [],
    "certifications": [],
    "additional_urls": [
      {
        "url": "LinkedIn.com/in/umersaleemzaman/",
        "website_name": "LinkedIn"
      }
    ],
    "executive_summary": "A UMER Saleem é um oficial de desenvolvimento de negócios experiente, com uma forte experiência em gerenciamento e vendas de clientes. Ele demonstrou experiência em geração de leads, demonstrações de produtos e manutenção de perspectivas de vendas saudáveis, atuando efetivamente como uma ligação entre os clientes e a empresa.",
    "employment_history": [
      {
        "details": "Atuando como uma ligação entre a equipe de desenvolvimento e a equipe de negócios, mantendo -se conectado ao cliente. Demonstração mensal de MVPs aos clientes. Chamada a frio - e -mail frio: alcançando novos clientes e aceitando acompanhamentos para futuras perspectivas.",
        "end_date": "Presente",
        "location": "",
        "job_title": "Executivo de contas",
        "start_date": "11-2021",
        "company_name": "Mantenha o caminhão"
      },
      {
        "details": "Promover habilidades escritas e responder prontamente às consultas do cliente. Documentando problemas e resoluções.",
        "end_date": "01-2021",
        "location": "",
        "job_title": "Especialista sênior de suporte ao cliente",
        "start_date": "07-2020",
        "company_name": "Suporte contratado"
      },
      {
        "details": "Responsável pelo desenvolvimento de negócios e gerenciamento de clientes, concentrando -se em gerar novos leads e manter relacionamentos com clientes em potencial.",
        "end_date": "11-2021",
        "location": "",
        "job_title": "Oficial de Desenvolvimento de Negócios",
        "start_date": "02-2021",
        "company_name": "Quadrado viral"
      }
    ]
  }
}