{
  "job_description": "## Generação de leads e especialista em inteligência de negócios\n\nJunte -se a ** Innovate Connections Inc. ** Como uma geração de leads e especialista em inteligência de negócios. Você desempenhará um papel fundamental na condução do crescimento dos negócios, liderando iniciativas de geração de leads e fornecendo informações estratégicas por meio da análise de dados. Estamos à procura de um profissional altamente qualificado, com uma forte experiência em geração de leads, gerenciamento de dados e inteligência de negócios.\n\n### Responsabilidades -chave:\n- Desenvolva e execute estratégias de geração de leads usando técnicas de marketing digital, chamadas a frio e ferramentas de raspagem de dados.\n- Colabore com equipes multifuncionais para otimizar estratégias de aquisição de clientes.\n- Utilize sistemas de CRM para gerenciar e analisar os dados do cliente para obter a qualificação do lead.\n- Crie e gerencie cronogramas e planos de trabalho detalhados, utilizando as melhores práticas e padrões para a execução do projeto.\n- Desenvolva modelos financeiros e estratégias de crescimento de negócios com base em insights de dados.\n- Utilize ferramentas como Power BI, SQL e Tableau para desenvolver relatórios e painéis abrangentes de dados.\n\n### Habilidades e experiência desejadas:\n- Fortes habilidades de programação em C ++, HTML e CSS.\n- Proficiência em plataformas de marketing digital, marketing por e -mail e mídia social.\n- Experiência no gerenciamento de grandes conjuntos de dados e no uso de ferramentas de BI (Power BI, Excel, Tableau).\n- Excelentes habilidades de comunicação e capacidade de desenvolver relacionamentos fortes do cliente.\n- Capacidade de trabalhar de forma independente e gerenciar vários projetos simultaneamente.\n\n### Por que a Inovate Connections Inc.?\n- Innovamos na vanguarda da tecnologia e permitimos que os membros da nossa equipe cresçam ao lado da empresa.\n-Valorizamos a tomada de decisão orientada a dados e capacitamos nossas equipes com as ferramentas certas para ter sucesso.\n- Oferecendo um ambiente de trabalho de apoio e oportunidades de avanço na carreira.\n\n### Como se inscrever:\nEnvie seu currículo e carta de apresentação detalhando sua experiência relevante e por que você está interessado em ingressar na Innovate Connections Inc.",
  "additional_info": "A Innovate Connections Inc. prefere candidatos de universidades reconhecidas, como a Universidade de Gerenciamento e Tecnologia e a Lahore School of Economics. Incentivamos um ambiente de trabalho remoto, mas exige presença física para sessões de construção de equipes e estratégicas duas vezes por trimestre. A assistência à realocação está disponível para candidatos excepcionais. Nossa avaliação abrangente inclui um teste técnico seguido de entrevistas estruturadas para avaliar as habilidades técnicas e sociais de forma abrangente.",
  "resume": "Zarwa Shahid  \nExecutivo de Desenvolvimento de Negócios  \n \n \n \nContato  \nJohar Town,  \nLahore  \n0306 -1538612  \nshahidzarwa4@gmail.com  \nhttps://www.linkedin.com/in/zarwa - \nShahid -926986208/  \n \n \nEducação  \nUniversidade rápida (2022)  \nGrupo Superior de Faculdades (2017)  \n \n \n \nLicença e  \nCertificação  \nMarketing de afiliado de comércio eletrônico  \n(ECOMmerce Pro)  \nFunnels de vendas e marketing de comércio eletrônico  \n(ECOMmerce Pro)  \nPublicidade do Facebook para comércio eletrônico  \n(ECOMmerce Pro)  \nADS do comércio eletrônico do comércio eletrônico  \n(ECOMmerce Pro)  \nWordPress wooCommerce  \n(ECOMmerce Pro)  \n \n \n \nHabilidades -chave  \nMarketing  \nGeração de chumbo  \nEscrita da proposta  \nMídia social  \nPlanejamento  \nWordPress  \nExcelente comunicação  \nObjetivo de vendas de TI  \nEu sou um membro dedicado da equipe que tenta o seu melhor para obter receita  \nExpectativas e pretendem atingir seus objetivos. Eu tenho muito orgulho no meu  \nhabilidades de comunicação, atenção aos detalhes, capacidade de multitarefa e  \nconfiabilidade. Eu sou duro -trabalhando e pontual. Eu posso fazer problemas de solução  \ndecisões rapidamente. Estou procurando oportunidades para aprender e adquirir novos  \nHabilidades para que eu possa melhorar minhas habilidades para uma carreira próspera na indústria de TI.  \n \n \nExperiência  \n2022 - 2023  \nDesenvolvimento de Negócios Executive @ Software Pro \nO Software Pro faz parte de um grupo de tecnologia líder da Nova York EUA. \nComo executivo da BD, sou responsável por impulsionar as vendas da empresa por \nadquirir novos clientes e criar um valor longo de longo prazo para seus negócios via \nPlataformas BD.  \n \n2023 - (meio período)  \nExecutivo de Desenvolvimento de Negócios @ It Cado LLC  \n• Contratado como um experiente e promovido ao desenvolvimento de negócios  \nexecutivo como líder da equipe.  \n• Internos treinados para geração de leads e lances de trabalho  \n• Utilizou o HubSpot e o Salesforce para gerenciar leads  \n• Especialista em tela | Projetou várias propostas para clientes  \n• Responsável por projetar e gerenciar portfólios da empresa  \n• Skype usado, Slack, Basecamp e Jira para Cliente  \ncomunicação  \n \n     (2023 - em tempo integral)  \n    Executivo de Desenvolvimento de Negócios @tecspine  \n      \n• Contratado como um experiente e promovido ao desenvolvimento de negócios \nexecutivo como líder da equipe.  \n• Responsável por projetar e gerenciar portfólios da empresa  \n• Skype usado, Slack, Basecamp e Jira para Cliente",
  "details": {
    "name": "Zarwa Shahid",
    "number": "03061538612",
    "skills": [
      "WordPress",
      "HubSpot",
      "Salesforce",
      "Canva",
      "Skype",
      "Folga",
      "Basecamp",
      "Jira"
    ],
    "email_id": "shahidzarwa4@gmail.com",
    "location": "Johar Town, Lahore",
    "projects": [],
    "education": [
      {
        "end_date": "2022",
        "university": "Universidade rápida",
        "degree_title": ""
      },
      {
        "end_date": "2017",
        "university": "Grupo Superior de Faculdades",
        "degree_title": ""
      }
    ],
    "achievements": [],
    "publications": [],
    "certifications": [
      {
        "certification_name": "Marketing de afiliado de comércio eletrônico",
        "issuing_organization": "Comércio eletrônico Pro",
        "date_of_issuance": ""
      },
      {
        "certification_name": "Funnels de vendas e marketing de comércio eletrônico",
        "issuing_organization": "Comércio eletrônico Pro",
        "date_of_issuance": ""
      },
      {
        "certification_name": "Publicidade do Facebook para comércio eletrônico",
        "issuing_organization": "Comércio eletrônico Pro",
        "date_of_issuance": ""
      },
      {
        "certification_name": "ADS do comércio eletrônico do comércio eletrônico",
        "issuing_organization": "Comércio eletrônico Pro",
        "date_of_issuance": ""
      },
      {
        "certification_name": "WordPress wooCommerce",
        "issuing_organization": "Comércio eletrônico Pro",
        "date_of_issuance": ""
      }
    ],
    "additional_urls": [
      {
        "url": "Linkedin.com/in/zarwa-shahid-926986208/",
        "website_name": "LinkedIn"
      }
    ],
    "executive_summary": "Zarwa Shahid é um executivo de desenvolvimento de negócios dedicado, com experiência em impulsionar as vendas e gerenciar o relacionamento com os clientes. Ele possui fortes habilidades técnicas em várias ferramentas e plataformas de software, demonstrando um compromisso de atingir as metas de negócios e aprimorar os portfólios da empresa.",
    "employment_history": [
      {
        "details": "Responsável por impulsionar as vendas da empresa, adquirindo novos clientes e criando um valor de longo prazo para seus negócios por meio de plataformas BD.",
        "end_date": "2023",
        "location": "",
        "job_title": "Executivo de Desenvolvimento de Negócios",
        "start_date": "2022",
        "company_name": "Software Pro"
      },
      {
        "details": "Promovido a executivo de desenvolvimento de negócios como líder da equipe. Internos treinados para geração de leads e lances de trabalho. Utilizou o HubSpot e o Salesforce para gerenciar leads. Projetou várias propostas para os clientes.",
        "end_date": "",
        "location": "",
        "job_title": "Executivo de Desenvolvimento de Negócios",
        "start_date": "2023",
        "company_name": "It Cado LLC"
      },
      {
        "details": "Promovido a executivo de desenvolvimento de negócios como líder da equipe. Responsável por projetar e gerenciar portfólios da empresa.",
        "end_date": "",
        "location": "",
        "job_title": "Executivo de Desenvolvimento de Negócios",
        "start_date": "2023",
        "company_name": "Tecspine"
      }
    ]
  }
}