{
  "job_description": "Participe ** Techventures Inc. ** Como um gerente de projeto sênior **, onde você supervisionará a entrega de projetos de gerenciamento de dados e análise de dados. Estamos à procura de um líder inovador que possa estabelecer e defender os padrões de entrega, gerenciando equipes multifuncionais para alcançar os mais altos níveis de excelência em serviços. Sua experiência em pré-vendas, arquitetura de soluções e gerenciamento de relacionamento com clientes impulsionará nossa expansão para novos mercados e otimizará os processos existentes.\n\n### Responsabilidades -chave:\n- Liderar e gerenciar projetos complexos de análise de dados e gerenciamento desde o início até a conclusão.\n- Desenvolver e implementar sistemas de qualidade e gerenciamento de projetos para se alinhar com as metas organizacionais.\n- Coordenar as atividades de arquitetura de soluções e pré-vendas, incluindo a preparação de RFPs e EOIs.\n- Mentor e orientar os membros da equipe júnior em desenvolvimento profissional e execução do projeto.\n- Envolva -se com os clientes para fornecer soluções de negócios personalizadas e melhorar a satisfação do cliente.\n- Colabore com outros departamentos para identificar oportunidades de melhoria e otimizar processos.\n\n### Habilidades preferidas:\n- Proficiência em ferramentas de dados como Powerbi, Oracle DV e Tableau.\n- Forte entendimento das metodologias de desenvolvimento de software, incluindo Agile e Scrum.\n- Capacidade demonstrada de liderar grandes equipes técnicas e lidar com as comunicações das partes interessadas de maneira eficaz.\n- Especialização em implementação de inteligência de negócios e data warehousing corporativo.\n\n### Por que se juntar a nós?\n- Oportunidade de trabalhar em projetos impactantes com alcance global.\n- ambiente de trabalho colaborativo e inclusivo.\n- Aprendizagem contínua e oportunidades de desenvolvimento profissional.\n\nTorne -se parte de uma equipe que valorize a integridade, a excelência e a inovação e ajude -nos a redefinir o que é possível no setor de tecnologia.",
  "additional_info": "As universidades preferenciais incluem a Universidade Nacional de Computação e Ciências Emergentes no Paquistão e instituições equivalentes. Oferecemos apoio de realocação a candidatos baseados fora da cidade de contratação, sujeitos à aprovação da gerência. As habilidades são avaliadas através de uma combinação de testes técnicos, estudos de caso de gerenciamento de projetos e entrevistas com painéis que consistem em chefes departamentais e representantes de RH.",
  "resume": "Shahbaz Joiya \nExecutivo de Desenvolvimento de Negócios \nPara obter uma posição desafiadora em crescimento e organização orientada para a carreira, onde os desafios são um\ntrabalho de rotina e onde eu mostro o melhor de minhas habilidades e qualificação para o progresso daquele\norganização e atualize minha carreira. \nShahbazjoiya07@gmail.com \n+923070504083 \nJohar Town R1 Fase 2,\nLahore, Paquistão \nHABILIDADES \nDesenvolvimento de negócios \nGerenciamento de projetos \nComunicação \nHtml \nCSS \nJavaScript \nBootstrap \nAprendiz rápido \nResolução de problemas \nIdiomas \nurdu \nProficiência nativa ou bilíngue \nInglês \nProfiência profissional de trabalho \nInteresses \nViajando \nColeção de filmes \nEDUCAÇÃO \nBacharel em Ciência em Ciência da Computação \nGovt. Universidade College Faisalabad, Sahiwal Campus \n09/2017 - 07/2021\n, Assim, \n \nIntrodução à administração \nDesenvolvimento de negócios \nEngenharia de software \nProgramação orientada a objetos \nEstrutura de dados e algoritmo \nSistema operacional \nIntermediário em ciência da computação \nPunjab College Haronabad \n04/2015 - 07/2017\n, Assim, \n \nExperiência de trabalho \nLíder da equipe (Amazon Drop Shipping e Product Hunting) \nADH Sahiwal \n01/2022 - presente\n, Assim, \n \nProjetos pessoais \nAutomação residencial usando sensores (FYP)\n (09/2020 - 06/2021)\n \nCaracterísticas:- \nÉ um controle centralizado da iluminação, aquecimento, ventilação e aparelhos de ar condicionado e\nOutros sistemas, para proporcionar maior conveniência, conforto, eficiência energética e segurança. \nSensores:-\n Inclui \nSensores de temperatura e termostatos inteligentes, \nSensores de luz, \nSensores de movimento, \nJanela\ne sensores de porta, e \nSensores de fumaça inteligente e CO. \nSite de comércio eletrônico \nFerramentas:- \nCódigo do Visual Studio, HTML, CSS, JavaScript, Sistema de Gerenciamento SQL e ASP.NET MVC. \nSite de comércio eletrônico baseado na Web desenvolvido no ASP.NET MVC. \nCaracterísticas:-\n Verifique a lista do item com a categoria, veja os detalhes do item e a lista do mais recente item \nRealizações \nO fundo de doação da educação do Punjab - PEEF\n (2017 - 2021)\n \nCursos",
  "details": {
    "name": "Shahbaz Joiya",
    "number": "923070504083",
    "skills": [
      "Html",
      "CSS",
      "JavaScript",
      "Bootstrap"
    ],
    "email_id": "Shahbazjoiya07@gmail.com",
    "location": "Johar Town R1 Fase 2, Lahore, Paquistão",
    "projects": [
      {
        "title": "Automação residencial usando sensores (FYP)",
        "description": "É um controle centralizado de aparelhos de iluminação, aquecimento, ventilação e ar condicionado e outros sistemas, para proporcionar uma conveniência, conforto, conforto, eficiência energética e segurança."
      },
      {
        "title": "Site de comércio eletrônico",
        "description": "Site de comércio eletrônico baseado na Web desenvolvido no ASP.NET MVC."
      }
    ],
    "education": [
      {
        "end_date": "07-2021",
        "university": "Govt. Universidade College Faisalabad, Sahiwal Campus",
        "degree_title": "Bacharel em Ciência em Ciência da Computação"
      },
      {
        "end_date": "07-2017",
        "university": "Punjab College Haronabad",
        "degree_title": "Intermediário em ciência da computação"
      }
    ],
    "achievements": [
      "O Fundo de Doação de Educação Punjab - Peef (2017 - 2021)"
    ],
    "publications": [],
    "certifications": [],
    "additional_urls": [],
    "executive_summary": "Shahbaz Joiya é um executivo de desenvolvimento de negócios dedicado, com forte experiência em ciência da computação e habilidades técnicas em tecnologias de desenvolvimento da Web, como HTML, CSS, JavaScript e Bootstrap. Ele demonstrou suas capacidades através de vários projetos, incluindo um sistema de automação residencial e um site de comércio eletrônico.",
    "employment_history": [
      {
        "details": "Líder da equipe (Amazon Drop Shipping e Product Hunting)",
        "end_date": "Presente",
        "location": "ADH Sahiwal",
        "job_title": "Líder da equipe",
        "start_date": "01-2022",
        "company_name": "ADH Sahiwal"
      }
    ]
  }
}