{
  "job_description": "### Gerente de contas -chave na Luxotech Solutions\n\n** Localização: ** Karachi, Paquistão\n\n** Departamento: ** Vendas e marketing\n\n** Relatórios para: ** Diretor de vendas\n\n** Visão geral da função: **\nJunte -se à Luxotech Solutions como gerente de contas importantes, onde você será responsável pelo gerenciamento das principais contas nos segmentos de varejo e hospitalidade em todo o Paquistão. Você impulsionará o crescimento das vendas, gerenciando contas existentes e desenvolvendo estratégias para novas contas. Sua função envolverá coordenar com equipes multifuncionais, analisar tendências do mercado e liderar iniciativas para cumprir as metas de receita.\n\nResponsabilidades ####:\n- Gerencie um portfólio de mais de 15 contas principais, compreendendo usuários finais e parceiros de canal.\n- Dirija a expansão para novos segmentos de mercado, identificando e se envolvendo com possíveis leads.\n- Desenvolva e execute estratégias de gerenciamento de contas para alcançar 110% de obtenção alvo de receita.\n- Utilize ferramentas de análise de dados, como o Power BI, para avaliar as tendências do mercado e gerar insights.\n- Coordenar com equipes internas, incluindo marketing e operações, para garantir o alinhamento estratégico.\n- Liderar negociações contratadas e gerenciar estratégias de preços para otimizar a lucratividade.\n- Relatório sobre o desempenho da conta e as oportunidades de mercado para a gerência sênior regularmente.\n\n#### habilidades essenciais:\n- Fortes habilidades de liderança e gerenciamento de partes interessadas.\n- Proficiência na análise de dados e previsão para informar a tomada de decisão.\n- Experiência em ferramentas como Salesforce, Vistex e SAP ERP para gerenciar funções de vendas.\n- Excelentes habilidades de comunicação para interações com clientes e colaborações internas.\n\n#### qualificações:\n- Mestre de preferência; É necessário um diploma de bacharel em administração de empresas ou campo relacionado.\n- Mais de 5 anos de experiência em gerenciamento de vendas ou desenvolvimento de negócios, com foco no gerenciamento de contas principais.\n- O sucesso demonstrado em contas crescentes e atingindo metas de receita.\n\n#### Benefícios:\n- Salário competitivo com bônus de desempenho.\n- Oportunidades de desenvolvimento profissional e acesso a seminários da indústria.\n- Horário de trabalho flexível.",
  "additional_info": "A Luxotech Solutions valoriza a diversidade e busca candidatos de uma variedade de origens e experiências. As instituições preferidas incluem o Instituto de Administração de Empresas, Karachi e Nuces Fast. A empresa suporta acordos de trabalho híbridos e oferece assistência de realocação para candidatos excepcionais. As habilidades são avaliadas através de uma combinação de testes técnicos, estudos de caso e entrevistas estruturadas com membros do painel de vários departamentos.",
  "resume": "MBA 2023 Muhammad Kalim  \n+92-321-9474340 | mkalim70@gmail.com | www.linkedin.com/in/mkalim70  \n \nEducação   \nSciences da Universidade de Gerenciamento de Lahore Lahore, Paquistão  \nMestre em Administração de Empresas 2021 -2023  \nUniversidade do Punjab Lahore, Paquistão  \nBacharel em Ciências em Engenharia Química 2014-2018  \nHabilidades   \n \nVisualização de dados e relatórios Microsoft Office, Tableau  \nSoft Skills Comunicação eficaz, resolução de problemas e liderança  \nOutros SQL e R  \n \nExperiência de trabalho   \nAkzonobel Paquistão Lahore, Paquistão  \nConculadora de pesquisa de mercado: janeiro de 2023 - maio de 2023 \n- pesquisado, entrevistado e analisou os dados coletados sobre a demanda potencial para a marca Interpon de \nAkzonobel e os requisitos de revestimento em pó dos fabricantes de eletrônicos de consumo.  \n- Forneceu informações acionáveis ​​para Akzonobel sobre a exploração da vertical do revestimento em pó.  \nGrupo Fatima Lahore, Paquistão  \nEstagiário de vendas: julho de 2022 - agosto de 2022  \n- Desenvolveu planos de evacuação de emergência para dez grupos de Fátima armazéns localizados na zona norte do Paquistão para reduzir o \nIncidentes de segurança que podem afetar mais de 20 funcionários. Esta foi uma iniciativa combinada do departamento de vendas e corporativo  \nHSE.  \n- Realizou o treinamento dos 10 oficiais de armazém em colaboração com o Departamento de HSE para garantir a implementação do \nPlano de evacuação.  \n- Auditorias observadas e conduzidas das operações do armazém.  \nPak Elektron Limited Lahore, Paquistão  \nEstagiário de marketing: junho de 2022 - julho de 2022  \n- Liderou uma equipe de cinco pessoas a conduzir pesquisas sobre a redução das vendas de aparelhos PEL no principal aparelho \nmercado de Lahore e proposto soluções de possibilidades para melhorar as vendas.  \n- Realizou visitas de rotina aos varejistas para entender os desafios enfrentados pelos varejistas.  \n     Fauji Fertilizer bin Qasim Limited Karachi, Paquistão  \nAssociado de Gerenciamento (Operações: Utilitários): abril de 2019 - maio de 2020  \n- realizado em análise em profundidade da torre de resfriamento que resultou em uma economia de 14% em termos de dosagem química no resfriamento \ntorre.  A dose de produtos químicos na torre de resfriamento estava aumentando, o que era um ônus financeiro.  Para combater o problema \ndo aumento da dosagem, avaliou a condição da torre de resfriamento preenche e criou uma estratégia de substituição após alternativa \nano.  \n- Trabalhou como líder de turno, gerenciando uma equipe de 12 pessoas em campo, realizou tarefas de rotina, como a preparação de permissões de trabalho  \ne relatórios de atividades diárias de status e manutenção no SAP.  \n- Realizou negociações semanais de segurança com os operadores de turno sobre como executar tarefas de acordo com os princípios de HSE.  \n-Realizou sessões de treinamento para os 12 associados não administrados e 4 estagiários de verão.  \n \nTrabalho do projeto   \nLivro branco sobre o estabelecimento da marca de equipamentos esportivos locais  \n- Realizou pesquisas sobre o mercado de equipamentos esportivos locais e deu recomendações aos fabricantes de esportes locais \nDurante o aprendizado experimental de MBA -i. \n. \nCertificações e treinamento W O R K S H O P S  \n- Google Data Analytics Certificado por Coursera  \n- MBA Business Games 2023 (simulação de marketing estratégico por Markstrat) na LUMS  \n- Participou do treinamento da SAP Realizado pelos Serviços de TI pela FFCL (outubro de 2020)",
  "details": {
    "name": "Muhammad Kalim",
    "number": "923219474340",
    "skills": [
      "Visualização de dados e relatórios",
      "Microsoft Office",
      "Quadro",
      "SQL",
      "R"
    ],
    "email_id": "mkalim70@gmail.com",
    "location": "Lahore, Paquistão",
    "projects": [
      {
        "title": "Livro branco sobre o estabelecimento da marca de equipamentos esportivos locais",
        "description": "Realizou pesquisas sobre o mercado de equipamentos esportivos locais e deu recomendações aos fabricantes de esportes locais durante o aprendizado experimental de MBA -i."
      }
    ],
    "education": [
      {
        "end_date": "05-2023",
        "university": "Lahore University of Management Sciences",
        "degree_title": "Mestre em Administração de Empresas"
      },
      {
        "end_date": "05-2018",
        "university": "Universidade do Punjab",
        "degree_title": "Bacharel em Ciências em Engenharia Química"
      }
    ],
    "achievements": [],
    "publications": [],
    "certifications": [
      {
        "certification_name": "Google Data Analytics Certificado",
        "issuing_organization": "Coursera",
        "date_of_issuance": "01-2023"
      },
      {
        "certification_name": "MBA Business Games 2023 (simulação de marketing estratégico por Markstrat)",
        "issuing_organization": "Lums",
        "date_of_issuance": "01-2023"
      },
      {
        "certification_name": "Treinamento da SAP",
        "issuing_organization": "Serviços de TI por FFCL",
        "date_of_issuance": "10-2020"
      }
    ],
    "additional_urls": [
      {
        "url": "LinkedIn.com/in/mkalim70",
        "website_name": "LinkedIn"
      }
    ],
    "executive_summary": "Muhammad Kalim é um profissional qualificado, com uma forte experiência em visualização e relatórios de dados, proficiente em ferramentas como o Microsoft Office e o Tableau, além de programar linguagens SQL e R. Ele tem experiência em pesquisa de mercado e gerenciamento de operações, demonstrando um compromisso de fornecer insights acionáveis ​​e melhorar a eficiência operacional.",
    "employment_history": [
      {
        "details": "Pesquisou, entrevistou e analisou os dados coletados sobre a demanda potencial da marca Interpon de Akzonobel e os requisitos de revestimento em pó dos fabricantes de eletrônicos de consumo. Forneceu informações acionáveis ​​para Akzonobel sobre a exploração da vertical do revestimento em pó.",
        "end_date": "05-2023",
        "location": "Lahore, Paquistão",
        "job_title": "Consultor de pesquisa de mercado",
        "start_date": "01-2023",
        "company_name": "Akzonobel Paquistão"
      },
      {
        "details": "Desenvolveu planos de evacuação de emergência para dez grupos de Fátima armazéns localizados na zona norte do Paquistão para reduzir os incidentes de segurança que podem afetar mais de 20 funcionários. Conduziu o treinamento dos 10 oficiais de armazém em colaboração com o Departamento de HSE para garantir a implementação do plano de evacuação. Observou e conduziu auditorias das operações do armazém.",
        "end_date": "08-2022",
        "location": "Lahore, Paquistão",
        "job_title": "Estagiário de vendas",
        "start_date": "07-2022",
        "company_name": "Grupo Fátima"
      },
      {
        "details": "Liderou uma equipe de cinco pessoas a conduzir pesquisas sobre a redução das vendas de aparelhos PEL no mercado principal de eletrodomésticos de Lahore e propuseram possíveis soluções para melhorar as vendas. Conduziu visitas de rotina aos varejistas para entender os desafios enfrentados pelos varejistas.",
        "end_date": "07-2022",
        "location": "Lahore, Paquistão",
        "job_title": "Estagiário de marketing",
        "start_date": "06-2022",
        "company_name": "Pak Elektron Limited"
      },
      {
        "details": "Realizada em análise em profundidade da torre de resfriamento que resultou em uma economia de 14% em termos de dosagem química na torre de resfriamento. Trabalhou como líder de turno, gerenciando uma equipe de 12 pessoas em campo, realizou tarefas de rotina, como a preparação de permissões de trabalho e o relatório de atividades diárias de status e manutenção no SAP. Realizou negociações semanais de segurança com os operadores de turno sobre como executar tarefas de acordo com os princípios de HSE. Realizou sessões de treinamento para os 12 associados não-gerentes e 4 estagiários de verão.",
        "end_date": "05-2020",
        "location": "Karachi, Paquistão",
        "job_title": "Associado de Gerenciamento (Operações: Utilitários)",
        "start_date": "04-2019",
        "company_name": "Fauji Fertilizer bin Qasim Limited"
      }
    ]
  }
}