{
  "job_description": "Gerente de Desenvolvimento de Negócios\n\nJunte -se a ** Innovatecorp ** como gerente de desenvolvimento de negócios para contribuir com nossa crescente equipe e impulsionar iniciativas estratégicas no setor de serviços de tecnologia. O candidato ideal alavancará sua vasta experiência em desenvolvimento de negócios, relações com clientes e gerenciamento de projetos para expandir nossa presença no mercado e criar parcerias duradouras.\n\n#### Responsabilidades -chave:\n- Desenvolver e implementar planos de desenvolvimento estratégico de negócios para alcançar as metas da empresa.\n- Geração de leads e construção de relacionamentos com clientes em potencial.\n- Supervisionar estratégias de aquisição de clientes, incluindo exploração além dos mercados freelancers.\n- Colabore com equipes multifuncionais para garantir a entrega suave do projeto.\n- Utilize o software CRM para rastrear o engajamento do cliente e o progresso do desenvolvimento.\n- Realize pesquisas de mercado para permanecer a par das tendências da indústria e informar estratégias de negócios.\n- Gerenciar e relatar as métricas de desenvolvimento de negócios.\n\n#### Habilidades e competências:\n- Comunicação forte e habilidades interpessoais para envolvimento e colaboração do cliente.\n- Excelentes habilidades analíticas para informar propostas e decisões estratégicas.\n- Experiência no Microsoft Office para documentação e apresentações.\n- Proficiência no software CRM para gerenciar o relacionamento com os clientes.\n\n#### Benefícios:\n- Salário competitivo com incentivos de bônus.\n- Oportunidades de desenvolvimento profissional e avanço na carreira.\n- Pacotes de saúde e seguro odontológico.\n- Horário de trabalho flexível e um ambiente positivo e orientado para a equipe.",
  "additional_info": "A Innovatecorp prefere candidatos de escolas de negócios líderes, como o Comsats Institute of Information and Technology. Apoiamos a realocação para o candidato certo e oferecemos oportunidades de trabalho remotas. As habilidades são avaliadas através de uma combinação de entrevistas técnicas e estudos de caso práticos, garantindo que os candidatos atendam aos nossos altos padrões de desempenho antes de oferecer uma posição.",
  "resume": "Idiomas SpokenProspecting, Qualificação, Desenvolvimento de Pipeline de Vendas.\nDemonstrações de produtos.\nProprietário do produto.\nGeração de chumbo e promovendo -os: gerar o novo líder e\npromove -os.\nExaminar o requisito do cliente e, mantendo o\ndocumentos de requisito.\nPerspectivas de vendas, mantendo perspectivas saudáveis ​​de vendas. Agindo como um\nligação entre a equipe de desenvolvimento e a equipe de negócios,\npermanecendo conectado com o cliente.\nDemonstração mensal de MVPs aos clientes.\nChamada a frio - e -mail frio: alcançando novos clientes e tomando acompanhamento\nUPS para perspectivas futuras.\nIniciar o relacionamento com as perspectivas saudáveis ​​através\nLinkedIn.\nDemonstrações de produtos para os clientes depois de definir bem -sucedido\nreuniões.\nEspecialista sênior de suporte ao cliente Suporte contratado | Julho de 2020 - Jan\n2021\nEntrei para o apoio contratado como especialista sênior de suporte ao cliente\nPara promover minhas habilidades escritas.\nReceba e responda prontamente às consultas do cliente.\nDocumentar problemas e resoluções.\nAprenda sobre novos produtos e serviços. Keep Truckin\nExecutivo de contas | Novembro de 2021 - presente\nQuadrado viral\nOficial de Desenvolvimento de Negócios | Fevereiro de 2021- novembro de 2021\nSuporte contratado\nUniversidade de Punjab Central\nMestrado em Administração de Empresas 2021 - Presente\nComecei meu mestrado em administração de empresas da universidade\ndo Punjab central para promover minha experiência ainda mais conforme a necessidade do\nmercado, para entender melhor as perspectivas de vendas.\nUniversidade Hazara\nBacharelado em Administração de Empresas 2014 - 2018\nEu fiz meus solteiros da Universidade de Hazara, garantindo coloridos\nnotas, escolheu as finanças como minha principal área de pesquisa. Experiência de trabalho\nDestaques da educação: +923475130731\nUmersaleemzaman1308@gmail.com\nLinkedIn.com/in/umersaleemzaman/ \nJohar Town, Lahore, Paquistanumer Saleem\nOficial de Desenvolvimento de Negócios\nNegócios experientes\nDesenvolvimento e cliente\nExecutivo com um\nHistória demonstrada de\nTrabalhando como contato de vendas\nentre o cliente e o\nEmpresa. Eu tenho acuminado\nhabilidades em gerenciamento de clientes,\nRequisitos de coleta e\nPotencial convincente\nClientes, um pensamento que\nimpulsiona a execução, muito\nconhecedor em uma ampla\nVariedade de profissional\ndisciplinas que maximizam\ncrescimento da marca, incluindo\nfinanças, marketing e tudo\nFacetas de operações comerciais\ndo desenvolvimento de produtos para\nengajamento do cliente. Resumo executivo\nGeração de chumbo\nSalesFroce\nSalloft\nMicrosoft Office\nZendesk\nTawlk.to\nPipeline de vendas\nDesenvolvimento de vendas\nDemonstrações de produtos\nINGLÊS\nURDU \nHINDI",
  "details": {
    "name": "Umer Saleem",
    "number": "923475130731",
    "skills": [
      "Geração de chumbo",
      "SalesFroce",
      "Salloft",
      "Microsoft Office",
      "Zendesk",
      "Tawlk.to",
      "Pipeline de vendas",
      "Desenvolvimento de vendas",
      "Demonstrações de produtos"
    ],
    "email_id": "Umersaleemzaman1308@gmail.com",
    "location": "Johar Town, Lahore, Paquistão",
    "projects": [],
    "education": [
      {
        "end_date": "12-2021",
        "university": "Universidade de Punjab Central",
        "degree_title": "Mestrado em Administração de Empresas"
      },
      {
        "end_date": "05-2018",
        "university": "Universidade Hazara",
        "degree_title": "Bacharelado em Administração de Empresas"
      }
    ],
    "achievements": [],
    "publications": [],
    "certifications": [],
    "additional_urls": [
      {
        "url": "LinkedIn.com/in/umersaleemzaman/",
        "website_name": "LinkedIn"
      }
    ],
    "executive_summary": "A UMER Saleem é um oficial de desenvolvimento de negócios experiente, com uma forte experiência em gerenciamento e vendas de clientes. Ele demonstrou experiência em geração de leads, demonstrações de produtos e manutenção de perspectivas de vendas saudáveis, atuando efetivamente como uma ligação entre os clientes e a empresa.",
    "employment_history": [
      {
        "details": "Atuando como uma ligação entre a equipe de desenvolvimento e a equipe de negócios, mantendo -se conectado ao cliente. Demonstração mensal de MVPs aos clientes. Chamada a frio - e -mail frio: alcançando novos clientes e aceitando acompanhamentos para futuras perspectivas.",
        "end_date": "Presente",
        "location": "",
        "job_title": "Executivo de contas",
        "start_date": "11-2021",
        "company_name": "Mantenha o caminhão"
      },
      {
        "details": "Promover habilidades escritas e responder prontamente às consultas do cliente. Documentando problemas e resoluções.",
        "end_date": "01-2021",
        "location": "",
        "job_title": "Especialista sênior de suporte ao cliente",
        "start_date": "07-2020",
        "company_name": "Suporte contratado"
      },
      {
        "details": "Responsável pelo desenvolvimento de negócios e gerenciamento de clientes, concentrando -se em gerar novos leads e manter relacionamentos com clientes em potencial.",
        "end_date": "11-2021",
        "location": "",
        "job_title": "Oficial de Desenvolvimento de Negócios",
        "start_date": "02-2021",
        "company_name": "Quadrado viral"
      }
    ]
  }
}