{
  "job_description": "### Executivo de Desenvolvimento de Negócios\n\n** Empresa: ** Innovate Dynamics Ltd.\n\n** Localização: ** Hyderabad, Índia\n\n** Visão geral da função: **\nParticipe da Innovate Dynamics Ltd. como executivo de desenvolvimento de negócios, onde você desempenhará um papel fundamental na condução do crescimento dos negócios, gerando leads e gerenciando as principais contas do cliente. Aproveite sua experiência em análise econômica e estratégias de marketing para aprimorar nossa presença no mercado e criar relacionamentos fortes dos clientes.\n\n** Responsabilidades: **\n- Desenvolver e executar planos abrangentes de desenvolvimento de negócios para alcançar os objetivos da empresa.\n- Identifique e envolva clientes em potencial em diversos nichos, incluindo desenvolvimento e terceirização de software.\n- Gerenciar e aumentar as relações com as principais contas para impulsionar o sucesso a longo prazo.\n- Utilize estratégias de marketing digital para aumentar o envolvimento e a retenção do cliente.\n- Colabore com equipes multifuncionais para desenvolver soluções de clientes personalizados.\n- Utilize o LinkedIn Sales Navigator para identificar e abordar novos leads de negócios.\n\n** Qualificações: **\n- Bacharel em Administração de Empresas, Economia ou Campo Relacionado.\n- 3-5 anos de experiência em desenvolvimento de negócios ou campos relacionados.\n- Forte proficiência com as ferramentas de MS Office Suite e Análise de Dados como o STATA.\n- Excelentes habilidades de comunicação verbal e escrita.\n- Capacidade de multitarefa e gerenciar vários projetos simultaneamente.",
  "additional_info": "A Innovate Dynamics Ltd. prioriza os candidatos de universidades de primeira linha, como [University X] e [University Y]. A assistência à realocação está disponível para candidatos dispostos a se mudar para Hyderabad. As habilidades técnicas são avaliadas através de testes padronizados e uma série de entrevistas. Nossa empresa incentiva a diversidade e a inclusão no processo de contratação.",
  "resume": "Idiomas SpokenProspecting, Qualificação, Desenvolvimento de Pipeline de Vendas.\nDemonstrações de produtos.\nProprietário do produto.\nGeração de chumbo e promovendo -os: gerar o novo líder e\npromove -os.\nExaminar o requisito do cliente e, mantendo o\ndocumentos de requisito.\nPerspectivas de vendas, mantendo perspectivas saudáveis ​​de vendas. Agindo como um\nligação entre a equipe de desenvolvimento e a equipe de negócios,\npermanecendo conectado com o cliente.\nDemonstração mensal de MVPs aos clientes.\nChamada a frio - e -mail frio: alcançando novos clientes e tomando acompanhamento\nUPS para perspectivas futuras.\nIniciar o relacionamento com as perspectivas saudáveis ​​através\nLinkedIn.\nDemonstrações de produtos para os clientes depois de definir bem -sucedido\nreuniões.\nEspecialista sênior de suporte ao cliente Suporte contratado | Julho de 2020 - Jan\n2021\nEntrei para o apoio contratado como especialista sênior de suporte ao cliente\nPara promover minhas habilidades escritas.\nReceba e responda prontamente às consultas do cliente.\nDocumentar problemas e resoluções.\nAprenda sobre novos produtos e serviços. Keep Truckin\nExecutivo de contas | Novembro de 2021 - presente\nQuadrado viral\nOficial de Desenvolvimento de Negócios | Fevereiro de 2021- novembro de 2021\nSuporte contratado\nUniversidade de Punjab Central\nMestrado em Administração de Empresas 2021 - Presente\nComecei meu mestrado em administração de empresas da universidade\ndo Punjab central para promover minha experiência ainda mais conforme a necessidade do\nmercado, para entender melhor as perspectivas de vendas.\nUniversidade Hazara\nBacharelado em Administração de Empresas 2014 - 2018\nEu fiz meus solteiros da Universidade de Hazara, garantindo coloridos\nnotas, escolheu as finanças como minha principal área de pesquisa. Experiência de trabalho\nDestaques da educação: +923475130731\nUmersaleemzaman1308@gmail.com\nLinkedIn.com/in/umersaleemzaman/ \nJohar Town, Lahore, Paquistanumer Saleem\nOficial de Desenvolvimento de Negócios\nNegócios experientes\nDesenvolvimento e cliente\nExecutivo com um\nHistória demonstrada de\nTrabalhando como contato de vendas\nentre o cliente e o\nEmpresa. Eu tenho acuminado\nhabilidades em gerenciamento de clientes,\nRequisitos de coleta e\nPotencial convincente\nClientes, um pensamento que\nimpulsiona a execução, muito\nconhecedor em uma ampla\nVariedade de profissional\ndisciplinas que maximizam\ncrescimento da marca, incluindo\nfinanças, marketing e tudo\nFacetas de operações comerciais\ndo desenvolvimento de produtos para\nengajamento do cliente. Resumo executivo\nGeração de chumbo\nSalesFroce\nSalloft\nMicrosoft Office\nZendesk\nTawlk.to\nPipeline de vendas\nDesenvolvimento de vendas\nDemonstrações de produtos\nINGLÊS\nURDU \nHINDI",
  "details": {
    "name": "Umer Saleem",
    "number": "923475130731",
    "skills": [
      "Geração de chumbo",
      "SalesFroce",
      "Salloft",
      "Microsoft Office",
      "Zendesk",
      "Tawlk.to",
      "Pipeline de vendas",
      "Desenvolvimento de vendas",
      "Demonstrações de produtos"
    ],
    "email_id": "Umersaleemzaman1308@gmail.com",
    "location": "Johar Town, Lahore, Paquistão",
    "projects": [],
    "education": [
      {
        "end_date": "12-2021",
        "university": "Universidade de Punjab Central",
        "degree_title": "Mestrado em Administração de Empresas"
      },
      {
        "end_date": "05-2018",
        "university": "Universidade Hazara",
        "degree_title": "Bacharelado em Administração de Empresas"
      }
    ],
    "achievements": [],
    "publications": [],
    "certifications": [],
    "additional_urls": [
      {
        "url": "LinkedIn.com/in/umersaleemzaman/",
        "website_name": "LinkedIn"
      }
    ],
    "executive_summary": "A UMER Saleem é um oficial de desenvolvimento de negócios experiente, com uma forte experiência em gerenciamento e vendas de clientes. Ele demonstrou experiência em geração de leads, demonstrações de produtos e manutenção de perspectivas de vendas saudáveis, atuando efetivamente como uma ligação entre os clientes e a empresa.",
    "employment_history": [
      {
        "details": "Atuando como uma ligação entre a equipe de desenvolvimento e a equipe de negócios, mantendo -se conectado ao cliente. Demonstração mensal de MVPs aos clientes. Chamada a frio - e -mail frio: alcançando novos clientes e aceitando acompanhamentos para futuras perspectivas.",
        "end_date": "Presente",
        "location": "",
        "job_title": "Executivo de contas",
        "start_date": "11-2021",
        "company_name": "Mantenha o caminhão"
      },
      {
        "details": "Promover habilidades escritas e responder prontamente às consultas do cliente. Documentando problemas e resoluções.",
        "end_date": "01-2021",
        "location": "",
        "job_title": "Especialista sênior de suporte ao cliente",
        "start_date": "07-2020",
        "company_name": "Suporte contratado"
      },
      {
        "details": "Responsável pelo desenvolvimento de negócios e gerenciamento de clientes, concentrando -se em gerar novos leads e manter relacionamentos com clientes em potencial.",
        "end_date": "11-2021",
        "location": "",
        "job_title": "Oficial de Desenvolvimento de Negócios",
        "start_date": "02-2021",
        "company_name": "Quadrado viral"
      }
    ]
  }
}