{
  "job_description": "## Título do trabalho: Especialista em gerenciamento de vendas e SEO  \n\n### Localização: Lahore, Paquistão  \n\n### Empresa: Innovate Digital Solutions Inc.  \n\nResumo do trabalho:  \nParticipe da Innovate Digital Solutions Inc. como especialista em gerenciamento de vendas e SEO. Você fará parte de uma equipe dinâmica responsável por impulsionar o envolvimento do cliente e garantir o desempenho ideal em estratégias de marketing digital. Sua função incluirá o gerenciamento do relacionamento com os clientes, a melhoria das estratégias de SEO e a liderança de sua equipe a atingir metas de vendas.  \n\n### Responsabilidades -chave:  \n- Envolva -se proativamente com clientes em potencial para entender suas necessidades de negócios e fornecer soluções inovadoras.  \n- Projete e execute estratégias de SEO em alinhamento com os objetivos de marketing do cliente.  \n- Gerenciar e otimizar as campanhas do PPC para maximizar o ROI e a visibilidade da marca.  \n- Desenvolva e mantenha um forte relacionamento com os clientes por meio de soluções de marketing personalizadas.  \n- Lidere uma equipe a alcançar e superar as metas de vendas, fornecendo um atendimento excepcional ao cliente.  \n- Analise as tendências e algoritmos do mercado para adaptar as estratégias de SEO de acordo.  \n- Produza relatórios que acompanham o progresso e medem o sucesso contra os KPIs.  \n\n### Perfil de candidato ideal:  \nVocê é um profissional qualificado de vendas e marketing, com fortes habilidades analíticas adequadas para identificar e executar oportunidades de SEO. Você se destaca nas interações do cliente, possuindo a capacidade de transformar possíveis leads em clientes satisfeitos por meio de iniciativas de marketing estratégicas e bem executadas. As habilidades de liderança e gerenciamento de equipes serão fundamentais para impulsionar as vendas e motivar sua equipe.  \n\n### benefícios:  \n- Pacote de salário competitivo  \n- Benefícios de saúde e bem -estar  \n- Bônus de desempenho  \n- Oportunidades de avanço na carreira  \n\nJunte -se a nós para redefinir o engajamento digital e liderar estratégias de mercado com agilidade e inovação.",
  "additional_info": "A Innovate Digital Solutions Inc. prefere candidatos de instituições respeitáveis ​​como [Universidade de Lahore], [Universidade de Punjab]. As opções de trabalho remotas estão disponíveis sujeitas a funções e responsabilidades. Avaliamos as habilidades por meio de uma combinação de testes técnicos, entrevistas e cenários de solução de problemas do mundo real para avaliar a competência prática em contextos estratégicos de marketing.",
  "resume": "Ali Ahmad \nGerente de Desenvolvimento de Negócios \nEu sou um gerente de desenvolvimento de negócios qualificado com experiência em estratégia, vendas, negociações e\nGerenciando o ciclo de vendas completo. Também tenho experiência em gerenciamento de contas importantes. Estou procurando um\nposição desafiadora em uma organização onde posso contribuir para alcançar as metas organizacionais enquanto\ndesenvolvendo ainda mais minhas habilidades profissionais para alcançar todo o meu potencial. \naliahmed2312@gmail.com \n03128800078 \nLahore, Paquistão \nEDUCAÇÃO \nBacharel em Administração de Empresas \nNúcleos rápidos \n08/2016 - 08/2020\n, Assim, \n \nLahore \nExperiência de trabalho \nGerente de Desenvolvimento de Negócios \nIkonic \n04/2023 - Presente\n, Assim, \n \nMinha função inclui gerenciar a equipe de desenvolvimento de negócios,\nlidar com as reuniões que eles reservam e efetivação do\nciclo de vendas completo, além de lidar com o ativo do LinkedIn\ncampanhas. \nExecutivo de desenvolvimento de negócios sênior \nE-sparks \n01/2021 - 04/2023\n, Assim, \n \nMeu papel incluiu alcançar as perspectivas de freelancer\nSites (Upwork, Freelancer etc) e LinkedIn,\nsondando para entender seus pontos problemáticos. Gerenciamento de elementos\nde estratégia, vendas, negociações e efeito da\nciclo de vendas completo. \nWelcome Team Advisor \nGrupo gigante \n09/2020 - 12/2020\n, Assim, \n \nLahore, Paquistão \nMeu papel era responder a todas as consultas no limite via chamada ou ao vivo\nbater papo, \nfornecer os melhores conselhos e promover os benefícios de gigante\nGama de serviços do grupo de acordo com os parâmetros acordados como\nbem como acompanhar as perspectivas. \nIntern \nICI Pakistan Limited \n07/2019 - 08/2019\n, Assim, \n \nLahore \nInternado na ala de poliéster da ICI na finalização\ndepartamento e reconciliou seus balanços também\nAnálise financeira completa de seus concorrentes. \nIntern \nCoca Cola \n07/2018 - 08/2018\n, Assim, \n \nLahore \nInternado no departamento comercial e aprendeu sobre\nestratégias de campanha, incluindo campanhas específicas do produto como\nbem como a colocação do produto nos racks e o uso de\noutdoors \nHABILIDADES \nMicrosoft Office (Word/Excel/PowerPoint) \nLicitação do projeto \nRequisitos de coleta \nGerenciamento de contas \nDesenvolvimento de negócios \nProcesso de vendas \nLiderança \nEstratégias de vendas \nHabilidades de negociação \nHabilidades de resolução de problemas \nManuseio de pressão \nPesquisar \nIdiomas \nInglês \nProfiência profissional completa \nurdu \nProfiência profissional completa \nTarefas \nTarefas \nTarefas \nTarefas \nTarefas",
  "details": {
    "name": "Ali Ahmad",
    "number": "03128800078",
    "skills": [
      "Microsoft Office (Word/Excel/PowerPoint)",
      "Licitação do projeto",
      "Requisitos de coleta",
      "Gerenciamento de contas",
      "Desenvolvimento de negócios",
      "Processo de vendas",
      "Estratégias de vendas",
      "Habilidades de negociação",
      "Pesquisar"
    ],
    "email_id": "aliahmed2312@gmail.com",
    "location": "Lahore, Paquistão",
    "projects": [],
    "education": [
      {
        "end_date": "08-2020",
        "university": "Núcleos rápidos",
        "degree_title": "Bacharel em Administração de Empresas"
      }
    ],
    "achievements": [],
    "publications": [],
    "certifications": [],
    "additional_urls": [
      {
        "url": "LinkedIn.com/in/ali-ahmad",
        "website_name": "LinkedIn"
      }
    ],
    "executive_summary": "Ali Ahmad é um gerente de desenvolvimento de negócios qualificado com experiência em estratégia, vendas e negociações, hábil no gerenciamento do ciclo de vendas completo e gerenciamento de contas. Atualmente, ele está buscando uma posição desafiadora para contribuir com os objetivos organizacionais, desenvolvendo ainda mais suas habilidades profissionais.",
    "employment_history": [
      {
        "details": "Gerenciando a equipe de desenvolvimento de negócios, lidando com reuniões e executando o ciclo de vendas completo, além de gerenciar campanhas ativas do LinkedIn.",
        "end_date": "Presente",
        "location": "Lahore, Paquistão",
        "job_title": "Gerente de Desenvolvimento de Negócios",
        "start_date": "04-2023",
        "company_name": "Ikonic"
      },
      {
        "details": "Procurando clientes em potencial em sites freelancers e LinkedIn, gerenciamento de estratégia, vendas, negociações e o ciclo completo de vendas.",
        "end_date": "04-2023",
        "location": "Lahore, Paquistão",
        "job_title": "Executivo de desenvolvimento de negócios sênior",
        "start_date": "01-2021",
        "company_name": "E-sparks"
      },
      {
        "details": "Respondendo às consultas de entrada por meio de chat de chamadas ou ao vivo, fornecendo conselhos e promovendo serviços.",
        "end_date": "12-2020",
        "location": "Lahore, Paquistão",
        "job_title": "Welcome Team Advisor",
        "start_date": "09-2020",
        "company_name": "Grupo gigante"
      },
      {
        "details": "Internado no departamento de finanças, reconciliando balanços e realizando análises financeiras.",
        "end_date": "08-2019",
        "location": "Lahore, Paquistão",
        "job_title": "Intern",
        "start_date": "07-2019",
        "company_name": "ICI Pakistan Limited"
      },
      {
        "details": "Internado no departamento comercial, aprendendo sobre estratégias de campanha e colocação de produtos.",
        "end_date": "08-2018",
        "location": "Lahore, Paquistão",
        "job_title": "Intern",
        "start_date": "07-2018",
        "company_name": "Coca Cola"
      }
    ]
  }
}