{
  "job_description": "** Título: Gerente de Desenvolvimento de Negócios **  \n\n** Empresa: MarketPros Enterprises **  \n\n** Localização: remoto com potencial viagens para locais de clientes **  \n\n**Sobre nós:**  \nA MarketPros Enterprises é um fornecedor global líder de soluções de negócios inovadoras, com o objetivo de maximizar o crescimento da marca. Trabalhamos com diversas indústrias para aprimorar sua infraestrutura de vendas e fornecer estratégias incomparáveis ​​de envolvimento do cliente.  \n\n** Visão geral da função: **  \nComo gerente de desenvolvimento de negócios da MarketPros Enterprises, você será responsável por liderar iniciativas estratégicas que impulsionam o crescimento dos negócios, aumentam a participação de mercado e fortalecem as relações com os clientes. Você gerenciará equipes multifuncionais para implementar estratégias de vendas, aproveitar as idéias do mercado e impulsionar a expansão da marca.  \n\n** Responsabilidades -chave: **  \n- Desenvolver e implementar estratégias de negócios abrangentes para aumentar o crescimento da receita.  \n- Liderar uma equipe na execução de campanhas de marketing e otimizar os pipelines de vendas.  \n- Utilize ferramentas de análise de dados para produzir informações acionáveis, melhorando o desempenho geral.  \n- Realize pesquisas de mercado para identificar tendências do setor e novas oportunidades de negócios.  \n- Envolva-se com clientes em potencial por meio de apresentações e promova relacionamentos de longo prazo.  \n- Gerenciar sistemas CRM (Salesforce, HubSpot) para otimizar as operações e aprimorar a produtividade.  \n\n** Habilidades preferidas: **  \n- Proficiência em planejamento estratégico e análise de mercado.  \n- Fortes habilidades de liderança com experiência comprovada no desenvolvimento de equipes.  \n- Conhecimento avançado de software CRM e ferramentas de marketing digital.  \n- Excelentes habilidades de comunicação e negociação.  \n\nJunte -se a nós para ultrapassar os limites da inovação de negócios e nos ajudar a alcançar nossos objetivos de expansão.",
  "additional_info": "A MarketPros Enterprises valoriza a diversidade na contratação e incentiva aplicativos de profissionais de negócios experientes com origens variadas. As universidades preferenciais incluem instituições da Ivy League e as principais escolas de negócios. Oferecemos benefícios de realocação para candidatos excepcionais e facilitamos os acordos de trabalho remotos. As competências técnicas e estratégicas são avaliadas através de uma mistura de avaliações psicométricas e entrevistas com estudos de caso.",
  "resume": "Shahbaz Joiya \nExecutivo de Desenvolvimento de Negócios \nPara obter uma posição desafiadora em crescimento e organização orientada para a carreira, onde os desafios são um\ntrabalho de rotina e onde eu mostro o melhor de minhas habilidades e qualificação para o progresso daquele\norganização e atualize minha carreira. \nShahbazjoiya07@gmail.com \n+923070504083 \nJohar Town R1 Fase 2,\nLahore, Paquistão \nHABILIDADES \nDesenvolvimento de negócios \nGerenciamento de projetos \nComunicação \nHtml \nCSS \nJavaScript \nBootstrap \nAprendiz rápido \nResolução de problemas \nIdiomas \nurdu \nProficiência nativa ou bilíngue \nInglês \nProfiência profissional de trabalho \nInteresses \nViajando \nColeção de filmes \nEDUCAÇÃO \nBacharel em Ciência em Ciência da Computação \nGovt. Universidade College Faisalabad, Sahiwal Campus \n09/2017 - 07/2021\n, Assim, \n \nIntrodução à administração \nDesenvolvimento de negócios \nEngenharia de software \nProgramação orientada a objetos \nEstrutura de dados e algoritmo \nSistema operacional \nIntermediário em ciência da computação \nPunjab College Haronabad \n04/2015 - 07/2017\n, Assim, \n \nExperiência de trabalho \nLíder da equipe (Amazon Drop Shipping e Product Hunting) \nADH Sahiwal \n01/2022 - presente\n, Assim, \n \nProjetos pessoais \nAutomação residencial usando sensores (FYP)\n (09/2020 - 06/2021)\n \nCaracterísticas:- \nÉ um controle centralizado da iluminação, aquecimento, ventilação e aparelhos de ar condicionado e\nOutros sistemas, para proporcionar maior conveniência, conforto, eficiência energética e segurança. \nSensores:-\n Inclui \nSensores de temperatura e termostatos inteligentes, \nSensores de luz, \nSensores de movimento, \nJanela\ne sensores de porta, e \nSensores de fumaça inteligente e CO. \nSite de comércio eletrônico \nFerramentas:- \nCódigo do Visual Studio, HTML, CSS, JavaScript, Sistema de Gerenciamento SQL e ASP.NET MVC. \nSite de comércio eletrônico baseado na Web desenvolvido no ASP.NET MVC. \nCaracterísticas:-\n Verifique a lista do item com a categoria, veja os detalhes do item e a lista do mais recente item \nRealizações \nO fundo de doação da educação do Punjab - PEEF\n (2017 - 2021)\n \nCursos",
  "details": {
    "name": "Shahbaz Joiya",
    "number": "923070504083",
    "skills": [
      "Html",
      "CSS",
      "JavaScript",
      "Bootstrap"
    ],
    "email_id": "Shahbazjoiya07@gmail.com",
    "location": "Johar Town R1 Fase 2, Lahore, Paquistão",
    "projects": [
      {
        "title": "Automação residencial usando sensores (FYP)",
        "description": "É um controle centralizado de aparelhos de iluminação, aquecimento, ventilação e ar condicionado e outros sistemas, para proporcionar uma conveniência, conforto, conforto, eficiência energética e segurança."
      },
      {
        "title": "Site de comércio eletrônico",
        "description": "Site de comércio eletrônico baseado na Web desenvolvido no ASP.NET MVC."
      }
    ],
    "education": [
      {
        "end_date": "07-2021",
        "university": "Govt. Universidade College Faisalabad, Sahiwal Campus",
        "degree_title": "Bacharel em Ciência em Ciência da Computação"
      },
      {
        "end_date": "07-2017",
        "university": "Punjab College Haronabad",
        "degree_title": "Intermediário em ciência da computação"
      }
    ],
    "achievements": [
      "O Fundo de Doação de Educação Punjab - Peef (2017 - 2021)"
    ],
    "publications": [],
    "certifications": [],
    "additional_urls": [],
    "executive_summary": "Shahbaz Joiya é um executivo de desenvolvimento de negócios dedicado, com forte experiência em ciência da computação e habilidades técnicas em tecnologias de desenvolvimento da Web, como HTML, CSS, JavaScript e Bootstrap. Ele demonstrou suas capacidades através de vários projetos, incluindo um sistema de automação residencial e um site de comércio eletrônico.",
    "employment_history": [
      {
        "details": "Líder da equipe (Amazon Drop Shipping e Product Hunting)",
        "end_date": "Presente",
        "location": "ADH Sahiwal",
        "job_title": "Líder da equipe",
        "start_date": "01-2022",
        "company_name": "ADH Sahiwal"
      }
    ]
  }
}