{
  "job_description": "Participe ** Techventures Inc. ** Como um gerente de projeto sênior **, onde você supervisionará a entrega de projetos de gerenciamento de dados e análise de dados. Estamos à procura de um líder inovador que possa estabelecer e defender os padrões de entrega, gerenciando equipes multifuncionais para alcançar os mais altos níveis de excelência em serviços. Sua experiência em pré-vendas, arquitetura de soluções e gerenciamento de relacionamento com clientes impulsionará nossa expansão para novos mercados e otimizará os processos existentes.\n\n### Responsabilidades -chave:\n- Liderar e gerenciar projetos complexos de análise de dados e gerenciamento desde o início até a conclusão.\n- Desenvolver e implementar sistemas de qualidade e gerenciamento de projetos para se alinhar com as metas organizacionais.\n- Coordenar as atividades de arquitetura de soluções e pré-vendas, incluindo a preparação de RFPs e EOIs.\n- Mentor e orientar os membros da equipe júnior em desenvolvimento profissional e execução do projeto.\n- Envolva -se com os clientes para fornecer soluções de negócios personalizadas e melhorar a satisfação do cliente.\n- Colabore com outros departamentos para identificar oportunidades de melhoria e otimizar processos.\n\n### Habilidades preferidas:\n- Proficiência em ferramentas de dados como Powerbi, Oracle DV e Tableau.\n- Forte entendimento das metodologias de desenvolvimento de software, incluindo Agile e Scrum.\n- Capacidade demonstrada de liderar grandes equipes técnicas e lidar com as comunicações das partes interessadas de maneira eficaz.\n- Especialização em implementação de inteligência de negócios e data warehousing corporativo.\n\n### Por que se juntar a nós?\n- Oportunidade de trabalhar em projetos impactantes com alcance global.\n- ambiente de trabalho colaborativo e inclusivo.\n- Aprendizagem contínua e oportunidades de desenvolvimento profissional.\n\nTorne -se parte de uma equipe que valorize a integridade, a excelência e a inovação e ajude -nos a redefinir o que é possível no setor de tecnologia.",
  "additional_info": "As universidades preferenciais incluem a Universidade Nacional de Computação e Ciências Emergentes no Paquistão e instituições equivalentes. Oferecemos apoio de realocação a candidatos baseados fora da cidade de contratação, sujeitos à aprovação da gerência. As habilidades são avaliadas através de uma combinação de testes técnicos, estudos de caso de gerenciamento de projetos e entrevistas com painéis que consistem em chefes departamentais e representantes de RH.",
  "resume": "Ali Rehman Bhutta  \n+923451030599 | 23110213@lums.edu.pk | https://www.linkedin.com/in/alirehmanbhutta/  \nEDUCAÇÃO  \nLahore University of Management Sciences                                                     \nBSC (honras) em ciências da gestão            \n- Cursos -chave: comunicação de marketing integrada, gerenciamento da cadeia de suprimentos, gerenciamento de operações, estratégico \nGerenciamento de negócios, gerenciamento de forças de vendas, lixeira de negócios, comportamento do consumidor. \nUniversidade do Baltistão (UOBs)                                                                                                                            \nSemestre de troca de verão  \n• Curso: Introdução ao Comércio E  \nIntermediário (fsc.)-pré-engenharia                                                                                  \n• Matemática de Engenharia, Física, Química  \nExperiência profissional  \nDripssterz-co-fundador 20 de outubro 22-fevereiro de 2023  \n• Co -fundou uma marca de tênis de qualidade premium de premium chamada Dripssterz, adotando uma abordagem proativa para fazer moda \ne qualidade acessível a todos.  \n• Simplificou a cadeia de suprimentos e estabelecida parcerias com 10 fornecedores, adquirindo 400 pares exclusivos de prêmio \ntênis nos dois primeiros meses de operações.  \n• aumentou as vendas em 30% através da utilização eficaz dos canais de mídia social, alavancando estratégias direcionadas para se envolver \no público -alvo.  \nVarejo E -Commerce Venture (Rev) -Estagiário de Desenvolvimento de Negócios de 2022 -junho de 2022  \n• Relacionamentos de ponta a ponta gerenciados e aumento da satisfação do cliente pré -aquisição em 20% através da eficaz \nGerenciamento de partes interessadas e práticas de engajamento.  \n• Desenvolveu o mapa ideal de jornada do cliente para a função de marketing para aumentar a flexibilidade do marketing \nEstratégia de engajamento, levando a um aumento de 25% na geração de leads e um aumento de 5% na aquisição de clientes.  \nConsultor de Marketing e Vendas Independente-Central de comércio eletrônico 20 de setembro 20-março de 2023  \n• Aumento das vendas médias em 20% para um cliente de comércio eletrônico focado no varejo, fornecendo soluções de ponta a ponta sob demanda e \nPlanejamento de suprimentos, gerenciamento de operações e vendas de produtos para impulsionar.   \n• Ajudou meus clientes a encontrar novos produtos, gerar anúncios de mídia social e criar lojas que mais tarde escalaram para mais \nde US $ 20.000 individualmente.  \n• Operações automatizadas da empresa para 4 clientes, aprimorando as taxas de conclusão de tarefas em 60%, fazendo parceria com Trello, Slack, \ne clique em software de funil.  \n• Melhorou a taxa de conversão da loja para 4 % (1-2 % em idade média), adotando uma abordagem centrada no cliente-usando o Google Analytics \ne teste A/B em portfólio de produtos otimizado da loja.   \nExperiência de liderança  \nFundação Sahara - co -fundador de junho de 2020 - presente  \n• O Sahara é uma ONG com o objetivo de preencher a lacuna entre os pobres e os ricos.  \n• Lançou a fundação durante a pandemia e a ração distribuída para mais de 100 famílias de servir.  \n• Criou 1,5 milhão de PKR através do desenvolvimento de propostas de marketing e patrocínios, aumentando o aumento de fundos históricos em 30%.  \nFórum de Ação Ambiental da Lums (Leaf) - Líder do projeto em outubro de 2022 - março de 2023  \n• LED duas equipes de engajamento para PMEs locais, realizando análise de portfólio de produtos e desenvolvendo estratégia de crescimento \nTrazendo 0,1 milhão em PKR para folhas.  \nProjetos e experiência de pesquisa  \n• EcoSprings -Campanha de marketing para garrafas de água e ecologicamente corretas: escreveu um estudo de caso para entrada de produto de um ecológico \nmarca de água engarrafada chamada ecossprings. Demanda de nível de entrada prevista usando modelo de difusão de baixo e projetado \nlucratividade para os próximos dois metros.  \n• Avaliação de estoque - HONDA CARS PAKISTAN: Projetou as vendas de carros Honda Paquistão pelos próximos cinco anos com base em seu passado \nVariação com inflação, crescimento do PIB, taxa de câmbio e crescimento da indústria automobilística. As idéias foram usadas para \nperspectivas de investimento.  \nHabilidades e pessoal  \nIdiomas: urdu (nativo), inglês (fluente), punjabi (nativo)  \nIT: MS Office (completo), publicidade no Facebook, Marketing Digital, Power Bi - Intermediário, JIRA, SQL - Avançado. \nInteresses: caminhada e montanhismo, música folclórica, canto (hip-hop/rap), viajando",
  "details": {
    "name": "Ali Rehman Bhutta",
    "number": "923451030599",
    "skills": [
      "MS Office (completo)",
      "Publicidade no Facebook",
      "Marketing digital",
      "Power BI - Intermediário",
      "Jira",
      "SQL - Avançado"
    ],
    "email_id": "23110213@lums.edu.pk",
    "location": "",
    "projects": [],
    "education": [
      {
        "end_date": "06-2023",
        "university": "Lahore University of Management Sciences",
        "degree_title": "BSC (honras) em ciências da gestão"
      },
      {
        "end_date": "06-2022",
        "university": "Universidade do Baltistão (UOBs)",
        "degree_title": "Semestre de troca de verão"
      }
    ],
    "achievements": [],
    "publications": [],
    "certifications": [],
    "additional_urls": [
      {
        "url": "LinkedIn.com/in/alirehmanbhutta",
        "website_name": "LinkedIn"
      }
    ],
    "executive_summary": "Ali Rehman Bhutta é um empreendedor dinâmico e profissional de desenvolvimento de negócios, com uma forte formação em ciências da gestão e comércio eletrônico. Ele co-fundou uma marca de tênis bem-sucedida e tem experiência em aprimorar o relacionamento com os clientes e impulsionar as vendas por meio de estratégias de marketing inovadoras. Suas habilidades técnicas incluem proficiência em vários softwares e ferramentas essenciais para marketing digital e análise de dados.",
    "employment_history": [
      {
        "details": "Co-fundou uma marca de tênis de qualidade premium premium chamada Dripssterz, simplificando a cadeia de suprimentos e estabelecendo parcerias com fornecedores.",
        "end_date": "02-2023",
        "location": "",
        "job_title": "Co-fundador",
        "start_date": "10-2022",
        "company_name": "Dripssterz"
      },
      {
        "details": "Relacionamentos de ponta a ponta gerenciados e aumento da satisfação do cliente antes da aquisição por meio de uma gestão eficaz das partes interessadas.",
        "end_date": "06-2022",
        "location": "",
        "job_title": "Estagiário de desenvolvimento de negócios",
        "start_date": "05-2022",
        "company_name": "Venture de comércio eletrônico de varejo (Rev)"
      },
      {
        "details": "Maior vendas médias para um cliente de comércio eletrônico focado no varejo, fornecendo soluções de ponta a ponta sobre o planejamento da demanda e da oferta, gerenciamento de operações e vendas de produtos.",
        "end_date": "03-2023",
        "location": "",
        "job_title": "Consultor de marketing e vendas independente",
        "start_date": "09-2020",
        "company_name": "Centrado no comércio eletrônico"
      }
    ]
  }
}