{
  "job_description": "### Executivo de Desenvolvimento de Negócios\n\n** Empresa: ** Innovate Dynamics Ltd.\n\n** Localização: ** Hyderabad, Índia\n\n** Visão geral da função: **\nParticipe da Innovate Dynamics Ltd. como executivo de desenvolvimento de negócios, onde você desempenhará um papel fundamental na condução do crescimento dos negócios, gerando leads e gerenciando as principais contas do cliente. Aproveite sua experiência em análise econômica e estratégias de marketing para aprimorar nossa presença no mercado e criar relacionamentos fortes dos clientes.\n\n** Responsabilidades: **\n- Desenvolver e executar planos abrangentes de desenvolvimento de negócios para alcançar os objetivos da empresa.\n- Identifique e envolva clientes em potencial em diversos nichos, incluindo desenvolvimento e terceirização de software.\n- Gerenciar e aumentar as relações com as principais contas para impulsionar o sucesso a longo prazo.\n- Utilize estratégias de marketing digital para aumentar o envolvimento e a retenção do cliente.\n- Colabore com equipes multifuncionais para desenvolver soluções de clientes personalizados.\n- Utilize o LinkedIn Sales Navigator para identificar e abordar novos leads de negócios.\n\n** Qualificações: **\n- Bacharel em Administração de Empresas, Economia ou Campo Relacionado.\n- 3-5 anos de experiência em desenvolvimento de negócios ou campos relacionados.\n- Forte proficiência com as ferramentas de MS Office Suite e Análise de Dados como o STATA.\n- Excelentes habilidades de comunicação verbal e escrita.\n- Capacidade de multitarefa e gerenciar vários projetos simultaneamente.",
  "additional_info": "A Innovate Dynamics Ltd. prioriza os candidatos de universidades de primeira linha, como [University X] e [University Y]. A assistência à realocação está disponível para candidatos dispostos a se mudar para Hyderabad. As habilidades técnicas são avaliadas através de testes padronizados e uma série de entrevistas. Nossa empresa incentiva a diversidade e a inclusão no processo de contratação.",
  "resume": "Objetivos  \n \n \n \nExperiência  \n \n \n \n \n \n \n \n \n \n \n \nQualificação  \nSayyed Muhammad Ali Shah  \n03344899892  \nE -mail: alishah14619@gmail.com  \nVila e correios Jalalpur Sharif, Tehsil \nPinddadan Khan, distrito Jhelum. \n \nPara se envolver em uma carreira que permitirá o progresso em termos de \nespecialistas, desenvolvimentos socioeconômicos e em novação \nAtravés da Expo, com certeza até novas idéias para o crescimento profissional também \ncomo crescimento para a empresa.  \n \nBanqueiro de Desenvolvimento de Negócios no Bank Al Habib Ltd  \nAbril de 2022 - presente  \nResponsabilidades:  \n• Traga novos negócios no banco  \n• Abra novas contas  \n• Traga um novo depósito  \nGerente de relacionamento na MCB Bank Ltd  \nOutubro de 2020 - abril de 2022  \nResponsabilidades:  \n• Traga novos negócios no banco convertendo a remessa \nClientes para clientes bancários  \n• CHECK LOOK e Balanceamento de caixas eletrônicos  \n• Prepare relatórios mensais para livros de cheques.  \n• Abertura da conta  \nOficial de Desenvolvimento de Negócios da Bankislami Pakistan Ltd  \nAgosto de 2018 - outubro de 2020  \nResponsabilidades:  \n• Traga novos clientes em Bank & Cross Selling  \n• Venda automóveis e lide com todos os problemas relacionados ao automóvel  \n• lidar com problemas de seguro de cliente  \nCMA  \nApresentando ICMAP Islamabad  \nMestre do comércio  \n2018 NCBA & E.  \nSolteiro do comércio  \n2015 Universidade Punjab  \n Habilidades  \n• Relatórios financeiros  \n• Análise de dados   \n• Gerenciamento de tempo   \n• Jogador de equipe  \n• Cálculos  \n• Habilidade contábil  \n• MS Word, Excel & Power \napontar  \n \nIdiomas  \n• Inglês  \n• urdu",
  "details": {
    "name": "Sayyed Muhammad Ali Shah",
    "number": "03344899892",
    "skills": [
      "Relatórios financeiros",
      "Análise de dados",
      "Habilidade contábil",
      "MS Word",
      "MS Excel",
      "MS PowerPoint"
    ],
    "email_id": "alishah14619@gmail.com",
    "location": "Village and Post Office Jalalpur Sharif, Tehsil Pinddadan Khan, distrito Jhelum",
    "projects": [],
    "education": [
      {
        "end_date": "12-2018",
        "university": "NCBA & E.",
        "degree_title": "Mestre do Comércio"
      },
      {
        "end_date": "12-2015",
        "university": "Universidade de Punjab",
        "degree_title": "Bacharel em Comércio"
      }
    ],
    "achievements": [],
    "publications": [],
    "certifications": [],
    "additional_urls": [],
    "executive_summary": "O Sayyed Muhammad Ali Shah é um profissional bancário qualificado, com experiência em desenvolvimento de negócios e gerenciamento de relacionamento. Ele tem uma forte formação em relatórios financeiros e análise de dados, complementada por proficiência nos aplicativos do Microsoft Office.",
    "employment_history": [
      {
        "details": "Traga novos negócios no banco",
        "end_date": "Presente",
        "location": "Bank Al Habib Ltd",
        "job_title": "Banqueiro de desenvolvimento de negócios",
        "start_date": "04-2022",
        "company_name": "Bank Al Habib Ltd"
      },
      {
        "details": "Traga novos negócios no banco convertendo clientes de remessas em clientes bancários",
        "end_date": "04-2022",
        "location": "MCB BANK LTD",
        "job_title": "Gerente de relacionamento",
        "start_date": "10-2020",
        "company_name": "MCB BANK LTD"
      },
      {
        "details": "Traga novos clientes em Bank & Cross Selling",
        "end_date": "10-2020",
        "location": "Bankislami Pakistan Ltd",
        "job_title": "Oficial de Desenvolvimento de Negócios",
        "start_date": "08-2018",
        "company_name": "Bankislami Pakistan Ltd"
      }
    ]
  }
}