{
  "job_description": "### Gerente de contas -chave na Luxotech Solutions\n\n** Localização: ** Karachi, Paquistão\n\n** Departamento: ** Vendas e marketing\n\n** Relatórios para: ** Diretor de vendas\n\n** Visão geral da função: **\nJunte -se à Luxotech Solutions como gerente de contas importantes, onde você será responsável pelo gerenciamento das principais contas nos segmentos de varejo e hospitalidade em todo o Paquistão. Você impulsionará o crescimento das vendas, gerenciando contas existentes e desenvolvendo estratégias para novas contas. Sua função envolverá coordenar com equipes multifuncionais, analisar tendências do mercado e liderar iniciativas para cumprir as metas de receita.\n\nResponsabilidades ####:\n- Gerencie um portfólio de mais de 15 contas principais, compreendendo usuários finais e parceiros de canal.\n- Dirija a expansão para novos segmentos de mercado, identificando e se envolvendo com possíveis leads.\n- Desenvolva e execute estratégias de gerenciamento de contas para alcançar 110% de obtenção alvo de receita.\n- Utilize ferramentas de análise de dados, como o Power BI, para avaliar as tendências do mercado e gerar insights.\n- Coordenar com equipes internas, incluindo marketing e operações, para garantir o alinhamento estratégico.\n- Liderar negociações contratadas e gerenciar estratégias de preços para otimizar a lucratividade.\n- Relatório sobre o desempenho da conta e as oportunidades de mercado para a gerência sênior regularmente.\n\n#### habilidades essenciais:\n- Fortes habilidades de liderança e gerenciamento de partes interessadas.\n- Proficiência na análise de dados e previsão para informar a tomada de decisão.\n- Experiência em ferramentas como Salesforce, Vistex e SAP ERP para gerenciar funções de vendas.\n- Excelentes habilidades de comunicação para interações com clientes e colaborações internas.\n\n#### qualificações:\n- Mestre de preferência; É necessário um diploma de bacharel em administração de empresas ou campo relacionado.\n- Mais de 5 anos de experiência em gerenciamento de vendas ou desenvolvimento de negócios, com foco no gerenciamento de contas principais.\n- O sucesso demonstrado em contas crescentes e atingindo metas de receita.\n\n#### Benefícios:\n- Salário competitivo com bônus de desempenho.\n- Oportunidades de desenvolvimento profissional e acesso a seminários da indústria.\n- Horário de trabalho flexível.",
  "additional_info": "A Luxotech Solutions valoriza a diversidade e busca candidatos de uma variedade de origens e experiências. As instituições preferidas incluem o Instituto de Administração de Empresas, Karachi e Nuces Fast. A empresa suporta acordos de trabalho híbridos e oferece assistência de realocação para candidatos excepcionais. As habilidades são avaliadas através de uma combinação de testes técnicos, estudos de caso e entrevistas estruturadas com membros do painel de vários departamentos.",
  "resume": "Arslan Iqbal\nExecutivo de Desenvolvimento de Negócios \nPerfil pessoal\nLahore, \nPaquistão\n+9233336662181\narsllan.181@hotmail.com\nLinks\nhttps://www.linkedin.com/in/ar-\nslan-iqbal1/\nHabilidades\nVendas e desenvolvimento organizacional \nAtendimento ao Cliente\nPesquisa e análise de mercado \nEmail marketing e aquisição de clientes\nPensamento crítico e resolução de problemas\nPrêmios e certificação\n• Prêmio de melhor geração de leads  \n Gala de Marketing 2022, UCP \nEscola de Negócios.\n• Os fundamentos do digital \nMarketing - Google Digital \nGaragem.\n• Conferência do ICIBM sobre CON-\nquestões temporárias em bus-\nGerenciamento de Ness - Organização \nMembro do Comitê. Resumo Profissional\nExecutivo experiente de desenvolvimento de negócios conhecido por impulsionar as vendas, aprimorando \norganizações e mercados em expansão. Um comunicador estratégico hábil na construção \nRelacionamentos do cliente e implementação de estratégias de crescimento inovadoras. Equipe comprometida \nJogador com fortes habilidades analíticas, excedendo consistentemente os alvos.\nHistórico de emprego\nExecutivo de Desenvolvimento de Negócios, Raheem Solutions Unip. Ltd., \nLahore, Paquistão\n0 9/2 0 2 2 - p re s e n t\n• Desenvolvido e mantido relacionamentos com o cliente, garantindo um cliente excepcional \nsatisfação e lealdade.\n• Colaborar com as equipes de vendas e marketing para alinhar estratégias e en-\nOportunidades de geração de receita de Hance.\n• Ajudei minha equipe de vendas a atingir seus objetivos, utilizando várias ferramentas, como \nComo Apollo, Lusha, entre em contato e o LinkedIn Sales Navigator.\n• Através de upwork e freelancer, eu gero e qualifique liderões com sucesso, \ncontribuindo para um pipeline consistente de clientes em potencial.\nRepresentante de Desenvolvimento de Vendas - Gerente de Estado, \nSeebiz Pvt. Ltd., Lahore, Paquistão.\n0 8/2 0 2 2 - 0 9/2 0 2 2\n• Lidar conosco com clientes por meio de chamadas, mensagens e e -mails. Aumenta o meu \nHabilidades de comunicação e gerenciamento de pessoas\n• Gerenciou um território, supervisionando as atividades de geração de leads e conversão e \nacordos fechados com sucesso.\n• participou de sessões de treinamento de produtos e utilizou o conhecimento do produto para \ncomunicar efetivamente proposições de valor a clientes em potencial.\nEducação\nMestre em Administração de Empresas (MBA) em Marketing, \nUniversidade de Punjab Central, Lahore, Paquistão\n0 3/2 0 1 9 - 0 7/2 0 2 2\n• Programa de MBA concluído com foco em estratégias de marketing, consumidor \ncomportamento e pesquisa de mercado.\n• Especializado em gerenciamento e vendas de marcas, alavancando a experiência para dirigir \ncrescimento nos negócios.\n• Graduado com proficiência em aplicar conceitos de marketing modernos a \ncenários do mundo real.\nBacharel em Comércio, Universidade do Punjab, Lahore, Paquistão.\n0 8/2 0 1 6 - 1 2/2 0 1 8\n• Adquiriu Fundação Forte em Business Essentials: Finanças, Contabilidade, Eco-\nNomics e gerenciamento.\n• Envolvido em projetos colaborativos, aprimorando o trabalho em equipe e as habilidades de comunicação.\n• Desenvolveu uma compreensão abrangente das operações comerciais.\nReferências\nDisponível mediante solicitação. de",
  "details": {
    "name": "Arslan Iqbal",
    "number": "9233336662181",
    "skills": [
      "Vendas e desenvolvimento organizacional",
      "Pesquisa e análise de mercado",
      "Email marketing e aquisição de clientes"
    ],
    "email_id": "arsllan.181@hotmail.com",
    "location": "Lahore, Paquistão",
    "projects": [],
    "education": [
      {
        "end_date": "07-2022",
        "university": "Universidade de Punjab Central",
        "degree_title": "Mestre em Administração de Empresas (MBA) em Marketing"
      },
      {
        "end_date": "12-2018",
        "university": "Universidade do Punjab",
        "degree_title": "Bacharel em Comércio"
      }
    ],
    "achievements": [
      "Melhor Prêmio de Geração de Leads, Marketing Gala 2022, UCP Business School."
    ],
    "publications": [],
    "certifications": [
      {
        "certification_name": "Os fundamentos do marketing digital",
        "issuing_organization": "Garagem digital do Google",
        "date_of_issuance": "01-2022"
      }
    ],
    "additional_urls": [
      {
        "url": "linkedin.com/in/ar-slan-iqbal1/",
        "website_name": "LinkedIn"
      }
    ],
    "executive_summary": "O Arslan Iqbal é um executivo de desenvolvimento de negócios experiente conhecido por impulsionar as vendas e aumentar o crescimento organizacional. Ele possui fortes habilidades técnicas em vendas e pesquisas de mercado, demonstrando um compromisso com a satisfação do cliente e as estratégias inovadoras.",
    "employment_history": [
      {
        "details": "Desenvolveu e manteve o relacionamento com os clientes, garantindo satisfação e lealdade excepcionais do cliente. Colaborou com as equipes de vendas e marketing para alinhar estratégias e aprimorar as oportunidades de geração de receita. Ajudou a equipe de vendas a alcançar suas metas, utilizando várias ferramentas, como Apollo, Lusha, entrar em contato e LinkedIn Sales Navigator. Leads com sucesso gerados e qualificados por meio de upwork e freelancer, contribuindo para um pipeline consistente de clientes em potencial.",
        "end_date": "Presente",
        "location": "Lahore, Paquistão",
        "job_title": "Executivo de Desenvolvimento de Negócios",
        "start_date": "09-2022",
        "company_name": "Raheem Solutions Unip. Ltd."
      },
      {
        "details": "Lidar com clientes dos EUA através de chamadas, mensagens e e -mails, aprimorando as habilidades de comunicação e gerenciamento de pessoas. Gerenciou um território, supervisionando as atividades de geração e conversão de leads e fechou com sucesso acordos. Participou de sessões de treinamento de produtos e utilizou o conhecimento do produto para comunicar efetivamente proposições de valor a clientes em potencial.",
        "end_date": "09-2022",
        "location": "Lahore, Paquistão",
        "job_title": "Representante de Desenvolvimento de Vendas - Gerente de Estado",
        "start_date": "08-2022",
        "company_name": "Seebiz Pvt. Ltd."
      }
    ]
  }
}