{
  "job_description": "** Título: Gerente de Desenvolvimento de Negócios **  \n\n** Empresa: MarketPros Enterprises **  \n\n** Localização: remoto com potencial viagens para locais de clientes **  \n\n**Sobre nós:**  \nA MarketPros Enterprises é um fornecedor global líder de soluções de negócios inovadoras, com o objetivo de maximizar o crescimento da marca. Trabalhamos com diversas indústrias para aprimorar sua infraestrutura de vendas e fornecer estratégias incomparáveis ​​de envolvimento do cliente.  \n\n** Visão geral da função: **  \nComo gerente de desenvolvimento de negócios da MarketPros Enterprises, você será responsável por liderar iniciativas estratégicas que impulsionam o crescimento dos negócios, aumentam a participação de mercado e fortalecem as relações com os clientes. Você gerenciará equipes multifuncionais para implementar estratégias de vendas, aproveitar as idéias do mercado e impulsionar a expansão da marca.  \n\n** Responsabilidades -chave: **  \n- Desenvolver e implementar estratégias de negócios abrangentes para aumentar o crescimento da receita.  \n- Liderar uma equipe na execução de campanhas de marketing e otimizar os pipelines de vendas.  \n- Utilize ferramentas de análise de dados para produzir informações acionáveis, melhorando o desempenho geral.  \n- Realize pesquisas de mercado para identificar tendências do setor e novas oportunidades de negócios.  \n- Envolva-se com clientes em potencial por meio de apresentações e promova relacionamentos de longo prazo.  \n- Gerenciar sistemas CRM (Salesforce, HubSpot) para otimizar as operações e aprimorar a produtividade.  \n\n** Habilidades preferidas: **  \n- Proficiência em planejamento estratégico e análise de mercado.  \n- Fortes habilidades de liderança com experiência comprovada no desenvolvimento de equipes.  \n- Conhecimento avançado de software CRM e ferramentas de marketing digital.  \n- Excelentes habilidades de comunicação e negociação.  \n\nJunte -se a nós para ultrapassar os limites da inovação de negócios e nos ajudar a alcançar nossos objetivos de expansão.",
  "additional_info": "A MarketPros Enterprises valoriza a diversidade na contratação e incentiva aplicativos de profissionais de negócios experientes com origens variadas. As universidades preferenciais incluem instituições da Ivy League e as principais escolas de negócios. Oferecemos benefícios de realocação para candidatos excepcionais e facilitamos os acordos de trabalho remotos. As competências técnicas e estratégicas são avaliadas através de uma mistura de avaliações psicométricas e entrevistas com estudos de caso.",
  "resume": "Ahsin yousaf\nDesenvolvimento de negócios / geração de leads\nEspecialista na Technology\nEstou trabalhando como executivo de desenvolvimento de negócios na Invozone Technologies. Eu tenho forte\nConhecimento sobre tecnologias como Elixir, Phoenix, estruturas (JavaScript, Python, Php) e\nDiferentes plataformas freelancers (Upwork & Freelancer) e experiência prática em desenvolvimento.\nEu quero seguir uma carreira em uma organização orientada ao crescimento que oferece oportunidades para\naprendizagem pessoal e desenvolvimento profissional.\n03032548705\nahsiny4@gmail.com✉\nhttps://www.linkedin.com/in/ahsin-yousaf-\nBB3147145\nMansoora, perto de Cakes & Bakes Lahore\nLahore, Paquistão\n Pontos fortes e habilidades\n✔b2b ✔ desenvolvimento de negócios ✔ marketing digital\n✔fiverr ✔freelancer ✔ Google AdWords\n✔ Propoções Writer ✔ Otimização do mecanismo de pesquisa (SEO) ✔Social Media Marketing\n✔Upwork ✔WordPress\n Acadêmicos\nData de pontuação do Instituto do Título\nMSC-IT University of Central Punjab (UCP), Lahore 3.4 CGPA 2019\nUniversidade ADP-IT da Central Punjab (UCP), Lahore 2.9 CGPA 2017\n Certificações\nData da autoridade do título\nUniversidade de Desenvolvimento da Web de Lahore a partir de agosto de 2019\nFreelancing & WordPress E-Rozgaar a partir de janeiro de 2019\nSEO WSCUBE TECH\nSMM WSCUBE TECH\n Experimente menos de 1 ano \n2 meses\n7 meses\n11 meses\n8 meses\n2,3 anos Duração da designação de compras\nInvozone Business Development Executive / BDE em outubro de 2020 - presente\nTRYNGO TECHNOLOGIES DESENVOLVIMENTO DE NEVISÃO DE NEGÓCIOS / BDE ABRA 2020 - NOV 2020\nUpwork Freelancer Jan 2020 - presente\nDesenvolvedor do MaxSify WordPress agosto de 2019 - abril de 2020\nFiverr Freelancer agosto de 2018 - presente\n História do trabalho\nInvozone em outubro de 2020 - presente (2 meses)\nExecutivo de Desenvolvimento de Negócios / BDE Lahore, Paquistão\nDescrição do meu trabalho é\n* Trabalhando em conta freelancer preferida com recrutador\n* Geração de leads.\n* Escrita da proposta.\n* Escrevendo carta de apresentação para todo emprego.\n* Agende uma reunião.\n* Criando currículos para todo trabalho.\n* Criando perfis em diferentes plataformas.\n* Suporte de bate -papo por e -mail e Skype.\n* Desenvolvimento do LinkedIn.\n* Buscar e -mails e dados.\n* Crie e atribuindo a tarefa no HubSpot.\n* Gerenciamento de projetos.\n* Desenvolvedor de Recursos Humanos para Projeto e Job.\n* Serviços de TI\nTRYNGO TECHNOLOGIES APR 2020 - NOV 2020 (7 meses)\nExecutivo de Desenvolvimento de Negócios / BDE Lahore, Paquistão\n- Lives em diferentes plataformas (Upwork, Freelancer).\n- Pesquisando clientes em potencial usando o Google e diretórios diferentes\n- Marketing por email para terceirizar nossos serviços\n- Entrada de dados\n- direcionando o mercado estrangeiro\n- marketing interno\n- Marketing de mídia social \n- Marketing digital \n \nUpwork de janeiro de 2020 - presente (11 meses)\nFreelancer Lahore, Paquistão\nOFERINAÇÃO SERVIÇOS:\nDesenvolvimento do WordPress \nMarketing digital\nMaxSify Ago 2019 - abril de 2020 (8 meses)\nDesenvolvedor WordPress Lahore, Paquistão\nAtualmente, estou trabalhando na MaxSify Technology como desenvolvedor júnior do WordPress. Meu principal responsável é converter html para o WordPress e construir\nsite usando temas e construtores premium.\nFiverr agosto de 2018 - presente (2,3 anos)\nFreelancer Lahore, Paquistão\nTenho uma ótima experiência em freelancer. Ofereci WordPress, Wix, PSD para HTML, WordPress Speed ​​Optimization, Data Entry and Product Listing\n Indústrias\nTecnologia da informação Áreas funcionais*\nMarketing\nGerenciamento de projetos\nVendas e desenvolvimento de negócios\n Idiomas\nUrdu - nativo\nInglês - Hobbies para iniciantes\nNavegando\nViajando",
  "details": {
    "name": "Ahsin yousaf",
    "number": "03032548705",
    "skills": [
      "Elixir",
      "Fênix",
      "JavaScript",
      "Python",
      "Php",
      "Upwork",
      "Freelancer",
      "Fiverr",
      "Google AdWords",
      "Otimização do mecanismo de pesquisa (SEO)",
      "Marketing de mídia social",
      "WordPress"
    ],
    "email_id": "ahsiny4@gmail.com",
    "location": "Mansoora, perto de Cakes & Bakes Lahore, Lahore, Paquistão",
    "projects": [],
    "education": [
      {
        "end_date": "2019",
        "university": "Universidade do Punjab Central (UCP)",
        "degree_title": "MSC-IT"
      },
      {
        "end_date": "2017",
        "university": "Universidade do Punjab Central (UCP)",
        "degree_title": "ADP-IT"
      }
    ],
    "achievements": [],
    "publications": [],
    "certifications": [
      {
        "certification_name": "Desenvolvimento da Web",
        "issuing_organization": "Universidade de Lahore",
        "date_of_issuance": "08-2019"
      },
      {
        "certification_name": "Freelancing & WordPress",
        "issuing_organization": "E-rozgaar",
        "date_of_issuance": "01-2019"
      },
      {
        "certification_name": "SEO",
        "issuing_organization": "WSCUBE TECH",
        "date_of_issuance": ""
      },
      {
        "certification_name": "SMM",
        "issuing_organization": "WSCUBE TECH",
        "date_of_issuance": ""
      }
    ],
    "additional_urls": [
      {
        "url": "LinkedIn.com/in/ahsin-yousaf-bb3147145",
        "website_name": "LinkedIn"
      }
    ],
    "executive_summary": "Ahsin Yousaf é um executivo de desenvolvimento de negócios qualificado com experiência em várias tecnologias, incluindo Elixir e Phoenix, bem como proficiência em várias estruturas de programação, como JavaScript, Python e PHP. Ele tem experiência prática em plataformas de desenvolvimento e freelancer, demonstrando um forte compromisso com o crescimento e o desenvolvimento profissional.",
    "employment_history": [
      {
        "details": "Trabalhando em uma conta freelancer preferida com recrutador, geração de leads, redação de propostas, escrita de cartas de cobertura, agendamento de reuniões, criação de currículos, criação de perfis em diferentes plataformas, suporte de bate -papo em e -mail e skype, desenvolvimento do LinkedIn, buscando e -mails e dados, criação e atribuição de tarefas no HubSpot, gerenciamento de projetos, desenvolvimento de recursos humanos para projetos e trabalhos, serviços de TI.",
        "end_date": "Presente",
        "location": "Lahore, Paquistão",
        "job_title": "Executivo de Desenvolvimento de Negócios / BDE",
        "start_date": "10-2020",
        "company_name": "Invozone"
      },
      {
        "details": "Lives em diferentes plataformas (Upwork, Freelancer), pesquisando clientes em potencial usando o Google e diferentes diretórios, email marketing para serviços de terceirização, entrada de dados, direcionamento de mercados estrangeiros, marketing interno, marketing de mídia social, marketing digital.",
        "end_date": "11-2020",
        "location": "Lahore, Paquistão",
        "job_title": "Executivo de Desenvolvimento de Negócios / BDE",
        "start_date": "04-2020",
        "company_name": "Tecnologias Tryngo"
      },
      {
        "details": "Oferecendo serviços no desenvolvimento do WordPress e marketing digital.",
        "end_date": "Presente",
        "location": "Lahore, Paquistão",
        "job_title": "Freelancer",
        "start_date": "01-2020",
        "company_name": "Upwork"
      },
      {
        "details": "Convertendo HTML em WordPress e criando sites usando temas e construtores premium.",
        "end_date": "04-2020",
        "location": "Lahore, Paquistão",
        "job_title": "Desenvolvedor do WordPress",
        "start_date": "08-2019",
        "company_name": "MaxSify"
      },
      {
        "details": "Oferecendo serviços em WordPress, Wix, PSD para HTML, WordPress Speed ​​Optimization, Data Entrada e Listagem de Produtos.",
        "end_date": "Presente",
        "location": "Lahore, Paquistão",
        "job_title": "Freelancer",
        "start_date": "08-2018",
        "company_name": "Fiverr"
      }
    ]
  }
}