{
  "job_description": "### Gerente de contas -chave na Luxotech Solutions\n\n** Localização: ** Karachi, Paquistão\n\n** Departamento: ** Vendas e marketing\n\n** Relatórios para: ** Diretor de vendas\n\n** Visão geral da função: **\nJunte -se à Luxotech Solutions como gerente de contas importantes, onde você será responsável pelo gerenciamento das principais contas nos segmentos de varejo e hospitalidade em todo o Paquistão. Você impulsionará o crescimento das vendas, gerenciando contas existentes e desenvolvendo estratégias para novas contas. Sua função envolverá coordenar com equipes multifuncionais, analisar tendências do mercado e liderar iniciativas para cumprir as metas de receita.\n\nResponsabilidades ####:\n- Gerencie um portfólio de mais de 15 contas principais, compreendendo usuários finais e parceiros de canal.\n- Dirija a expansão para novos segmentos de mercado, identificando e se envolvendo com possíveis leads.\n- Desenvolva e execute estratégias de gerenciamento de contas para alcançar 110% de obtenção alvo de receita.\n- Utilize ferramentas de análise de dados, como o Power BI, para avaliar as tendências do mercado e gerar insights.\n- Coordenar com equipes internas, incluindo marketing e operações, para garantir o alinhamento estratégico.\n- Liderar negociações contratadas e gerenciar estratégias de preços para otimizar a lucratividade.\n- Relatório sobre o desempenho da conta e as oportunidades de mercado para a gerência sênior regularmente.\n\n#### habilidades essenciais:\n- Fortes habilidades de liderança e gerenciamento de partes interessadas.\n- Proficiência na análise de dados e previsão para informar a tomada de decisão.\n- Experiência em ferramentas como Salesforce, Vistex e SAP ERP para gerenciar funções de vendas.\n- Excelentes habilidades de comunicação para interações com clientes e colaborações internas.\n\n#### qualificações:\n- Mestre de preferência; É necessário um diploma de bacharel em administração de empresas ou campo relacionado.\n- Mais de 5 anos de experiência em gerenciamento de vendas ou desenvolvimento de negócios, com foco no gerenciamento de contas principais.\n- O sucesso demonstrado em contas crescentes e atingindo metas de receita.\n\n#### Benefícios:\n- Salário competitivo com bônus de desempenho.\n- Oportunidades de desenvolvimento profissional e acesso a seminários da indústria.\n- Horário de trabalho flexível.",
  "additional_info": "A Luxotech Solutions valoriza a diversidade e busca candidatos de uma variedade de origens e experiências. As instituições preferidas incluem o Instituto de Administração de Empresas, Karachi e Nuces Fast. A empresa suporta acordos de trabalho híbridos e oferece assistência de realocação para candidatos excepcionais. As habilidades são avaliadas através de uma combinação de testes técnicos, estudos de caso e entrevistas estruturadas com membros do painel de vários departamentos.",
  "resume": "Izma bint-e-atif\nAnalista de negócios\nPensamento crítico\nManter confidencialidade\nControle de qualidade\nDistribuição\nHabilidades organizacionais\nSolução de problemas\nAnálise Estatística\nComunicação verbal/virtual\nFortes habilidades analíticas\nAuxiliar de gerenciamento de produtos técnicos\nDesigningskills de circuito+92 331 0483113\nCasa nº 530, Bloco J3, Johar\nTown, Lahore izma.b.atif@gmail.com Antecedentes Trabalhando com clientes internos e externos para reunir\ne providenciar requisitos, fornecer análise, auxiliar na criação de usuário\ninterfaces e desenvolva prazos de implementação em ambiente ágil.\nBuscando uma oportunidade desafiadora, onde poderei utilizar meu\nfortes habilidades organizacionais, formação educacional e capacidade de trabalhar\nbem com as pessoas, o que me permitirá crescer pessoalmente e\nPerfil profissionalmente de carros\nEXPERIÊNCIAS\nNextbridge Unip. Ltd. \nRed Communication Arts Pvt. LTD2021 - Presente\n2020 - 2021 Business Development Executive\nConduzir análises de mercado para as linhas de produtos e para o geral\nlucratividade do negócio\nAuxiliar no planejamento e execução dos planos de teste para integração\ne teste de processo, incluindo o aumento de logs de falhas.\nDesenvolva conceitos de projeto e mantenha o fluxo de trabalho ideal.\nComunicação forte e habilidades interpessoais para construir significativas\nrelacionamentos com clientes. \nAtenção aos detalhes para aprimorar cada tarefa necessária. \nTomada de decisão avançada e habilidades de solução de problemas.\nAnalista de negócios júnior\nAnalisar e priorizar os requisitos do cliente. \nTraduzir os requisitos do cliente em resumos de projeto especificados por\nEntendendo o ciclo de vida do desenvolvimento de software.\nTrabalhando diretamente com usuários/clientes e entendendo problemas de negócios,\nEstabelecendo solução e apresentando de volta às principais partes interessadas\nCriando uma análise de negócios detalhada, descrevendo problemas, oportunidades\ne soluções para um negócio\nAnálise de processo e produção de artefato acordado adequado para internos\nuse e/ou revisão do cliente e assinatura.educação\nFastNuces2020 - Bacharel em\nEngenharia Elétrica\nQueen Mary College for Women2015 - FSC pré -engenharia\nEscola do Convento do Coração Sagrado2013 - MatriculationBalsamiq \nMatlab \nCAD automático\nSketchup \nSoftware do Visual Studio \nProjetos\nImpressora 3D com mecanismo cartesiano (FYP) \nProjetou uma impressora 3D com mecanismo cartesiano usando deposição fundida\nTecnologia de modelagem (FDM) seguindo o método de fabricação aditiva. \nInglês\nUrdulanguagesmicrosoft Office \nLinguagens de programação (c ++, c, linguagem de montagem,\nOOP) \nSQL \nProjeto de circuito, plc\nPrograma de gerenciamento hospitalar\nProjetou um código OPD (departamento de paciente ao ar livre) em C ++.\nReferências\nPode ser fornecido mediante necessidade. Desenvolvimento de negócios\nAnálise de negócios \nLiderança \nSolução de problemas \nNegociação \nPensador crítico \nCompetências de Habilidades de Apresentação e Negociação de Apresentação e Negociação\nViajando\nEsportes \nEscrita \nAssistindo a filmes interincores e\nHobbies",
  "details": {
    "name": "Izma bint-e-atif",
    "number": "923310483113",
    "skills": [
      "Projeto de circuito",
      "Balsamiq",
      "Matlab",
      "CAD automático",
      "Sketchup",
      "Visual Studio",
      "C ++",
      "C",
      "Linguagem de montagem",
      "OOP",
      "SQL",
      "Plc"
    ],
    "email_id": "izma.b.atif@gmail.com",
    "location": "Casa nº 530, Bloco J3, Johar Town, Lahore",
    "projects": [
      {
        "title": "Impressora 3D com mecanismo cartesiano",
        "description": "Projetou uma impressora 3D com mecanismo cartesiano usando a tecnologia de modelagem de deposição fundida (FDM) seguindo o método de fabricação aditiva."
      },
      {
        "title": "Programa de gerenciamento hospitalar",
        "description": "Projetou um código OPD (departamento de paciente ao ar livre) em C ++."
      }
    ],
    "education": [
      {
        "end_date": "06-2020",
        "university": "FastNuces",
        "degree_title": "Bacharel em Engenharia Elétrica"
      },
      {
        "end_date": "06-2015",
        "university": "Queen Mary College for Women",
        "degree_title": "FSC pré -engenharia"
      },
      {
        "end_date": "06-2013",
        "university": "Escola de Convento do Coração Sagrado",
        "degree_title": "Matrícula"
      }
    ],
    "achievements": [],
    "publications": [],
    "certifications": [],
    "additional_urls": [
      {
        "url": "LinkedIn.com/in/izma-bint-e-atif",
        "website_name": "LinkedIn"
      }
    ],
    "executive_summary": "A IZMA Bint-E-ATIF é um analista de negócios qualificado com uma forte experiência em engenharia elétrica e vasta experiência em análise de mercado, gerenciamento de projetos e desenvolvimento de software. Ela demonstrou proficiência em várias linguagens de programação e ferramentas de software, contribuindo para resultados bem -sucedidos de projetos em ambientes ágeis. Sua experiência técnica é complementada por sua capacidade de comunicar e colaborar efetivamente com clientes e partes interessadas.",
    "employment_history": [
      {
        "details": "Realize análises de mercado para as linhas de produtos e a lucratividade geral dos negócios. Auxiliar no planejamento e execução dos planos de teste para integração e teste de processo, incluindo o aumento de logs de falhas. Desenvolva conceitos de projeto e mantenha o fluxo de trabalho ideal.",
        "end_date": "Presente",
        "location": "Nextbridge Unip. Ltd.",
        "job_title": "Executivo de Desenvolvimento de Negócios",
        "start_date": "01-2021",
        "company_name": "Nextbridge Unip. Ltd."
      },
      {
        "details": "Analisar e priorizar os requisitos do cliente. Traduzir os requisitos do cliente em resumos especificados do projeto, compreendendo o ciclo de vida do desenvolvimento de software. Trabalhando diretamente com usuários/clientes e compreendendo problemas de negócios, estabelecendo solução e apresentando de volta às principais partes interessadas. Criando uma análise de negócios detalhada, descrevendo problemas, oportunidades e soluções para um negócio. Análise de processo e produção de artefato acordado adequado para uso interno e/ou revisão e assinatura do cliente.",
        "end_date": "12-2021",
        "location": "Red Communication Arts Pvt. Ltd.",
        "job_title": "Analista de negócios júnior",
        "start_date": "01-2020",
        "company_name": "Red Communication Arts Pvt. Ltd."
      }
    ]
  }
}