{
  "job_description": "### Executivo de Desenvolvimento de Negócios\n\n** Empresa: ** Innovate Dynamics Ltd.\n\n** Localização: ** Hyderabad, Índia\n\n** Visão geral da função: **\nParticipe da Innovate Dynamics Ltd. como executivo de desenvolvimento de negócios, onde você desempenhará um papel fundamental na condução do crescimento dos negócios, gerando leads e gerenciando as principais contas do cliente. Aproveite sua experiência em análise econômica e estratégias de marketing para aprimorar nossa presença no mercado e criar relacionamentos fortes dos clientes.\n\n** Responsabilidades: **\n- Desenvolver e executar planos abrangentes de desenvolvimento de negócios para alcançar os objetivos da empresa.\n- Identifique e envolva clientes em potencial em diversos nichos, incluindo desenvolvimento e terceirização de software.\n- Gerenciar e aumentar as relações com as principais contas para impulsionar o sucesso a longo prazo.\n- Utilize estratégias de marketing digital para aumentar o envolvimento e a retenção do cliente.\n- Colabore com equipes multifuncionais para desenvolver soluções de clientes personalizados.\n- Utilize o LinkedIn Sales Navigator para identificar e abordar novos leads de negócios.\n\n** Qualificações: **\n- Bacharel em Administração de Empresas, Economia ou Campo Relacionado.\n- 3-5 anos de experiência em desenvolvimento de negócios ou campos relacionados.\n- Forte proficiência com as ferramentas de MS Office Suite e Análise de Dados como o STATA.\n- Excelentes habilidades de comunicação verbal e escrita.\n- Capacidade de multitarefa e gerenciar vários projetos simultaneamente.",
  "additional_info": "A Innovate Dynamics Ltd. prioriza os candidatos de universidades de primeira linha, como [University X] e [University Y]. A assistência à realocação está disponível para candidatos dispostos a se mudar para Hyderabad. As habilidades técnicas são avaliadas através de testes padronizados e uma série de entrevistas. Nossa empresa incentiva a diversidade e a inclusão no processo de contratação.",
  "resume": "Shahbaz Joiya \nExecutivo de Desenvolvimento de Negócios \nPara obter uma posição desafiadora em crescimento e organização orientada para a carreira, onde os desafios são um\ntrabalho de rotina e onde eu mostro o melhor de minhas habilidades e qualificação para o progresso daquele\norganização e atualize minha carreira. \nShahbazjoiya07@gmail.com \n+923070504083 \nJohar Town R1 Fase 2,\nLahore, Paquistão \nHABILIDADES \nDesenvolvimento de negócios \nGerenciamento de projetos \nComunicação \nHtml \nCSS \nJavaScript \nBootstrap \nAprendiz rápido \nResolução de problemas \nIdiomas \nurdu \nProficiência nativa ou bilíngue \nInglês \nProfiência profissional de trabalho \nInteresses \nViajando \nColeção de filmes \nEDUCAÇÃO \nBacharel em Ciência em Ciência da Computação \nGovt. Universidade College Faisalabad, Sahiwal Campus \n09/2017 - 07/2021\n, Assim, \n \nIntrodução à administração \nDesenvolvimento de negócios \nEngenharia de software \nProgramação orientada a objetos \nEstrutura de dados e algoritmo \nSistema operacional \nIntermediário em ciência da computação \nPunjab College Haronabad \n04/2015 - 07/2017\n, Assim, \n \nExperiência de trabalho \nLíder da equipe (Amazon Drop Shipping e Product Hunting) \nADH Sahiwal \n01/2022 - presente\n, Assim, \n \nProjetos pessoais \nAutomação residencial usando sensores (FYP)\n (09/2020 - 06/2021)\n \nCaracterísticas:- \nÉ um controle centralizado da iluminação, aquecimento, ventilação e aparelhos de ar condicionado e\nOutros sistemas, para proporcionar maior conveniência, conforto, eficiência energética e segurança. \nSensores:-\n Inclui \nSensores de temperatura e termostatos inteligentes, \nSensores de luz, \nSensores de movimento, \nJanela\ne sensores de porta, e \nSensores de fumaça inteligente e CO. \nSite de comércio eletrônico \nFerramentas:- \nCódigo do Visual Studio, HTML, CSS, JavaScript, Sistema de Gerenciamento SQL e ASP.NET MVC. \nSite de comércio eletrônico baseado na Web desenvolvido no ASP.NET MVC. \nCaracterísticas:-\n Verifique a lista do item com a categoria, veja os detalhes do item e a lista do mais recente item \nRealizações \nO fundo de doação da educação do Punjab - PEEF\n (2017 - 2021)\n \nCursos",
  "details": {
    "name": "Shahbaz Joiya",
    "number": "923070504083",
    "skills": [
      "Html",
      "CSS",
      "JavaScript",
      "Bootstrap"
    ],
    "email_id": "Shahbazjoiya07@gmail.com",
    "location": "Johar Town R1 Fase 2, Lahore, Paquistão",
    "projects": [
      {
        "title": "Automação residencial usando sensores (FYP)",
        "description": "É um controle centralizado de aparelhos de iluminação, aquecimento, ventilação e ar condicionado e outros sistemas, para proporcionar uma conveniência, conforto, conforto, eficiência energética e segurança."
      },
      {
        "title": "Site de comércio eletrônico",
        "description": "Site de comércio eletrônico baseado na Web desenvolvido no ASP.NET MVC."
      }
    ],
    "education": [
      {
        "end_date": "07-2021",
        "university": "Govt. Universidade College Faisalabad, Sahiwal Campus",
        "degree_title": "Bacharel em Ciência em Ciência da Computação"
      },
      {
        "end_date": "07-2017",
        "university": "Punjab College Haronabad",
        "degree_title": "Intermediário em ciência da computação"
      }
    ],
    "achievements": [
      "O Fundo de Doação de Educação Punjab - Peef (2017 - 2021)"
    ],
    "publications": [],
    "certifications": [],
    "additional_urls": [],
    "executive_summary": "Shahbaz Joiya é um executivo de desenvolvimento de negócios dedicado, com forte experiência em ciência da computação e habilidades técnicas em tecnologias de desenvolvimento da Web, como HTML, CSS, JavaScript e Bootstrap. Ele demonstrou suas capacidades através de vários projetos, incluindo um sistema de automação residencial e um site de comércio eletrônico.",
    "employment_history": [
      {
        "details": "Líder da equipe (Amazon Drop Shipping e Product Hunting)",
        "end_date": "Presente",
        "location": "ADH Sahiwal",
        "job_title": "Líder da equipe",
        "start_date": "01-2022",
        "company_name": "ADH Sahiwal"
      }
    ]
  }
}