{
  "job_description": "### Executivo de Desenvolvimento de Negócios\n\n** Empresa: ** Innovate Dynamics Ltd.\n\n** Localização: ** Hyderabad, Índia\n\n** Visão geral da função: **\nParticipe da Innovate Dynamics Ltd. como executivo de desenvolvimento de negócios, onde você desempenhará um papel fundamental na condução do crescimento dos negócios, gerando leads e gerenciando as principais contas do cliente. Aproveite sua experiência em análise econômica e estratégias de marketing para aprimorar nossa presença no mercado e criar relacionamentos fortes dos clientes.\n\n** Responsabilidades: **\n- Desenvolver e executar planos abrangentes de desenvolvimento de negócios para alcançar os objetivos da empresa.\n- Identifique e envolva clientes em potencial em diversos nichos, incluindo desenvolvimento e terceirização de software.\n- Gerenciar e aumentar as relações com as principais contas para impulsionar o sucesso a longo prazo.\n- Utilize estratégias de marketing digital para aumentar o envolvimento e a retenção do cliente.\n- Colabore com equipes multifuncionais para desenvolver soluções de clientes personalizados.\n- Utilize o LinkedIn Sales Navigator para identificar e abordar novos leads de negócios.\n\n** Qualificações: **\n- Bacharel em Administração de Empresas, Economia ou Campo Relacionado.\n- 3-5 anos de experiência em desenvolvimento de negócios ou campos relacionados.\n- Forte proficiência com as ferramentas de MS Office Suite e Análise de Dados como o STATA.\n- Excelentes habilidades de comunicação verbal e escrita.\n- Capacidade de multitarefa e gerenciar vários projetos simultaneamente.",
  "additional_info": "A Innovate Dynamics Ltd. prioriza os candidatos de universidades de primeira linha, como [University X] e [University Y]. A assistência à realocação está disponível para candidatos dispostos a se mudar para Hyderabad. As habilidades técnicas são avaliadas através de testes padronizados e uma série de entrevistas. Nossa empresa incentiva a diversidade e a inclusão no processo de contratação.",
  "resume": "Hafsa Naeem \nDesenvolvimento de negócios\nProfissional \nProfissional dinâmico de BD com uma mentalidade de crescimento\n& B2B Expertise nas startups de tecnologia dos EUA \nhafsa.naeem1024@gmail.com \n+92 307 7089974 \nLahore, Paquistão \nLinkedIn.com/in/hafsanaeem92 \nExperiência de trabalho \nDesenvolvimento de negócios \nOdetta.ai \n11/2018 - presente\n, Assim, \n \nLahore, Paquistão \nOdetta é uma plataforma de terceirização on-line com sede nos EUA com a missão de capacitar\nmulheres em Mesa \nTrabalhando com líderes da indústria de tecnologia dos EUA em vários setores, como\nComo software de computador, Ed-Tech, FinTech, Healthcare, E-Commerce &\nVCs \nVendendo soluções de dados como geração de leads, anotação de dados,\nAutomação de marketing, fornecimento de candidatos e muito mais \nFechando acordos com as empresas da Fortune 500 dos EUA e o crescimento de nosso\nBase de clientes de 35 a 150+ em 2020-2021 \nLíder de recrutamento \nOdetta.ai \n03/2019 - 12/2021\n, Assim, \n \nLahore, Paquistão \nOdetta ocupa o #25 na Forbes Melhores Empregadores de Startups dos EUA em 2022,\nsob minha liderança \nUnidades de recrutamento de chumbo; Explorando, lista mais curta e entrevista\ntalento de camada de toda a região de Mesa \nOrientação e treinamento de nossa equipe \nAssistente virtual principal \nOdetta.ai \n05/2019 - 12/2020\n, Assim, \n \nLahore, Paquistão \nPrimeiro funcionário a ser promovido a função de VA \nLidere uma equipe de 2 vas para o nosso CEO \nControlador de qualidade/gerente de projeto \nOdetta.ai \n12/2018 - 12/2020\n, Assim, \n \nLahore, Paquistão \nLidere uma equipe de 15 a 20 pessoas para coleta/enriquecimento de dados\nProjetos para nós, capital de risco \nProjetos de categorização de dados gerenciados para empresas de software \nLidere uma equipe de 50 anotadores para projetos de anotação de dados da IA\nempresas \nRun Ran Campanhas de Vendas e CRM para startups em saúde, aeroespacial,\nFinChs de FinCh e consultoria \nEDUCAÇÃO \nMestrado em Administração de Empresas \nUniversidade Nacional de Computador e Emergente\nCiências \n09/2021 - Presente\n, Assim, \n \nLahore, Paquistão \nMarketing \nAnálise de negócios \nHABILIDADES \nGerenciamento de projetos \nPower bi \nLiderança \nMarketing digital \nCRM \nExtensão fria \nGeração de chumbo \nFornecimento de candidatos \nVendas B2B \nRealizações \nFuncionário da estrela \nSomente funcionário da Odetta como líder de vendas, First VA, VA\nLíder de chumbo e recrutamento por 2 anos \nCertificados \nFundamentos de análise de negócios: competências\n (07/2022 - presente)\n \nEmitido pelo Instituto Internacional de Análise de Negócios ™ \nAnálise de negócios: dados de vendas\n (07/2022 - presente)\n \nEmitido pelo Instituto Internacional de Análise de Negócios ™ \nEstratégias de tomada de decisão\n (07/2022 - presente)\n \nEmitido pela Associação Nacional de Conselhos Estaduais de\nContabilidade \nAnálise de dados para profissionais de negócios\n (07/2022 - presente)\n \nEmitido pelo LinkedIn Learning \nProjeto pessoal \nTecnologia da juventude\n (10/2021 - presente)\n \nCo-fundador e consultor de negócios @ Youth Tech, um crescente\nStartup oferecendo soluções de terceirização para empresas de tecnologia. \nIdiomas \nInglês \nProfiência profissional completa \nurdu \nProficiência nativa ou bilíngue \nInteresses \nAnálise de dados \nEmpreendedorismo \nOrientação de negócios \nFotografia \nSaúde e Fitness \nTecnologia e inovação \nRealizações/tarefas \nRealizações/tarefas \nRealizações/tarefas \nRealizações/tarefas \nCursos",
  "details": {
    "name": "Hafsa Naeem",
    "number": "923077089974",
    "skills": [
      "Gerenciamento de projetos",
      "Power bi",
      "Marketing digital",
      "CRM",
      "Extensão fria",
      "Geração de chumbo",
      "Fornecimento de candidatos",
      "Vendas B2B"
    ],
    "email_id": "hafsa.naeem1024@gmail.com",
    "location": "Lahore, Paquistão",
    "projects": [
      {
        "title": "Tecnologia da juventude",
        "description": "Co-fundador e consultor de negócios @ Youth Tech, uma startup em crescimento que oferece soluções de terceirização para empresas de tecnologia."
      }
    ],
    "education": [
      {
        "end_date": "Presente",
        "university": "Universidade Nacional de Computador e Ciências Emergentes",
        "degree_title": "Mestrado em Administração de Empresas"
      }
    ],
    "achievements": [
      "Funcionário da estrela",
      "Somente funcionário da Odetta como líder de vendas, First VA, VA líder e líder de recrutamento por 2 anos"
    ],
    "publications": [],
    "certifications": [
      {
        "certification_name": "Fundamentos de análise de negócios: competências",
        "issuing_organization": "O Instituto Internacional de Análise de Negócios ™",
        "date_of_issuance": "07-2022"
      },
      {
        "certification_name": "Análise de negócios: dados de vendas",
        "issuing_organization": "O Instituto Internacional de Análise de Negócios ™",
        "date_of_issuance": "07-2022"
      },
      {
        "certification_name": "Estratégias de tomada de decisão",
        "issuing_organization": "Associação Nacional de Conselhos Estaduais de Contabilidade",
        "date_of_issuance": "07-2022"
      },
      {
        "certification_name": "Análise de dados para profissionais de negócios",
        "issuing_organization": "Aprendizagem do LinkedIn",
        "date_of_issuance": "07-2022"
      }
    ],
    "additional_urls": [
      {
        "url": "LinkedIn.com/in/hafsanaeem92",
        "website_name": "LinkedIn"
      }
    ],
    "executive_summary": "A HAFSA NAEEM é um profissional dinâmico de desenvolvimento de negócios, com vasta experiência em vendas B2B e gerenciamento de projetos, particularmente no ecossistema de startups de tecnologia dos EUA. Ela demonstrou uma forte capacidade de liderar equipes e impulsionar o crescimento, expandindo significativamente as bases de clientes e aumentando a eficiência operacional.",
    "employment_history": [
      {
        "details": "Trabalhando com líderes da indústria de tecnologia dos EUA em vários setores, como software de computador, ED-Tech, Fintech, Healthcare, E-Commerce e VCs. Venda soluções de dados como geração de leads, anotação de dados, automação de marketing, fornecimento de candidatos e muito mais. O fechamento de acordos com as empresas da Fortune 500 e o crescimento de nossa base de clientes de 35 para 150+ em 2020-2021.",
        "end_date": "Presente",
        "location": "Lahore, Paquistão",
        "job_title": "Desenvolvimento de negócios",
        "start_date": "11-2018",
        "company_name": "Odetta.ai"
      },
      {
        "details": "Unidades de recrutamento de chumbo; Explorando, lista restante e entrevistando os melhores talentos de camadas de toda a região de Mesa. Orientação e treinamento de nossa equipe.",
        "end_date": "12-2021",
        "location": "Lahore, Paquistão",
        "job_title": "Líder de recrutamento",
        "start_date": "03-2019",
        "company_name": "Odetta.ai"
      },
      {
        "details": "Primeiro funcionário a ser promovido a função de VA. Lidere uma equipe de 2 VAs para o nosso CEO.",
        "end_date": "12-2020",
        "location": "Lahore, Paquistão",
        "job_title": "Assistente virtual principal",
        "start_date": "05-2019",
        "company_name": "Odetta.ai"
      },
      {
        "details": "Lidere uma equipe de 15 a 20 pessoas para projetos de coleta/enriquecimento de dados para empresas de capital de risco dos EUA. Projetos de categorização de dados gerenciados para empresas de software. Lidere uma equipe de 50 anotadores para projetos de anotação de dados das empresas de IA. Execute campanhas de vendas e CRM para startups em empresas de saúde, aeroespacial, fintech e consultoria.",
        "end_date": "12-2020",
        "location": "Lahore, Paquistão",
        "job_title": "Controlador de qualidade/gerente de projeto",
        "start_date": "12-2018",
        "company_name": "Odetta.ai"
      }
    ]
  }
}