{
  "job_description": "Gerente de Desenvolvimento de Negócios\n\n** Empresa fictícia ** está buscando um gerente de desenvolvimento de negócios dinâmico e estratégico para ingressar em nossa equipe crescente. Nesta função, você desenvolverá e executará estratégias de vendas, gerenciará as principais contas e liderará iniciativas de desenvolvimento de negócios para impulsionar o crescimento organizacional.\n\nResponsabilidades ####:\n- Desenvolva e implemente estratégias para o desenvolvimento de negócios para atingir objetivos corporativos.\n- Supervisionar todo o ciclo de vendas, da geração de leads a acordos de fechamento.\n- Gerenciar e orientar uma equipe de executivos de desenvolvimento de negócios, aprimorando seu potencial para otimizar o sucesso da empresa.\n- Aprimore a presença da empresa por meio de engajamento ativo em plataformas on -line como o LinkedIn e os sites de rede profissional.\n-Envolva-se em negociações de alto risco e coordenam com as principais partes interessadas da conta para garantir a satisfação do cliente e as parcerias de longo prazo.\n\n#### Requisitos:\n- Utilize habilidades analíticas para identificar novas oportunidades e tendências de mercado.\n- Use o Microsoft Office Suite de maneira eficaz para planejar, relatar e apresentar estratégias de vendas.\n\nJunte -se a nós para desempenhar um papel fundamental na expansão de nossos negócios localmente e internacionalmente, trabalhando ao lado de uma equipe dinâmica em um ambiente inovador. Se você gosta de tomar iniciativas e liderar iniciativas de negócios impactantes, queremos ouvir você!",
  "additional_info": "Os candidatos preferidos terão se formado nas principais escolas de negócios, como núcleos rápidos ou Lums. A empresa apóia a realocação de funcionários no Paquistão com a assistência logística necessária. As habilidades são avaliadas por meio de uma combinação de entrevistas técnicas e estudos de caso práticos alinhados aos desafios do setor.",
  "resume": "Zarwa Shahid  \nExecutivo de Desenvolvimento de Negócios  \n \n \n \nContato  \nJohar Town,  \nLahore  \n0306 -1538612  \nshahidzarwa4@gmail.com  \nhttps://www.linkedin.com/in/zarwa - \nShahid -926986208/  \n \n \nEducação  \nUniversidade rápida (2022)  \nGrupo Superior de Faculdades (2017)  \n \n \n \nLicença e  \nCertificação  \nMarketing de afiliado de comércio eletrônico  \n(ECOMmerce Pro)  \nFunnels de vendas e marketing de comércio eletrônico  \n(ECOMmerce Pro)  \nPublicidade do Facebook para comércio eletrônico  \n(ECOMmerce Pro)  \nADS do comércio eletrônico do comércio eletrônico  \n(ECOMmerce Pro)  \nWordPress wooCommerce  \n(ECOMmerce Pro)  \n \n \n \nHabilidades -chave  \nMarketing  \nGeração de chumbo  \nEscrita da proposta  \nMídia social  \nPlanejamento  \nWordPress  \nExcelente comunicação  \nObjetivo de vendas de TI  \nEu sou um membro dedicado da equipe que tenta o seu melhor para obter receita  \nExpectativas e pretendem atingir seus objetivos. Eu tenho muito orgulho no meu  \nhabilidades de comunicação, atenção aos detalhes, capacidade de multitarefa e  \nconfiabilidade. Eu sou duro -trabalhando e pontual. Eu posso fazer problemas de solução  \ndecisões rapidamente. Estou procurando oportunidades para aprender e adquirir novos  \nHabilidades para que eu possa melhorar minhas habilidades para uma carreira próspera na indústria de TI.  \n \n \nExperiência  \n2022 - 2023  \nDesenvolvimento de Negócios Executive @ Software Pro \nO Software Pro faz parte de um grupo de tecnologia líder da Nova York EUA. \nComo executivo da BD, sou responsável por impulsionar as vendas da empresa por \nadquirir novos clientes e criar um valor longo de longo prazo para seus negócios via \nPlataformas BD.  \n \n2023 - (meio período)  \nExecutivo de Desenvolvimento de Negócios @ It Cado LLC  \n• Contratado como um experiente e promovido ao desenvolvimento de negócios  \nexecutivo como líder da equipe.  \n• Internos treinados para geração de leads e lances de trabalho  \n• Utilizou o HubSpot e o Salesforce para gerenciar leads  \n• Especialista em tela | Projetou várias propostas para clientes  \n• Responsável por projetar e gerenciar portfólios da empresa  \n• Skype usado, Slack, Basecamp e Jira para Cliente  \ncomunicação  \n \n     (2023 - em tempo integral)  \n    Executivo de Desenvolvimento de Negócios @tecspine  \n      \n• Contratado como um experiente e promovido ao desenvolvimento de negócios \nexecutivo como líder da equipe.  \n• Responsável por projetar e gerenciar portfólios da empresa  \n• Skype usado, Slack, Basecamp e Jira para Cliente",
  "details": {
    "name": "Zarwa Shahid",
    "number": "03061538612",
    "skills": [
      "WordPress",
      "HubSpot",
      "Salesforce",
      "Canva",
      "Skype",
      "Folga",
      "Basecamp",
      "Jira"
    ],
    "email_id": "shahidzarwa4@gmail.com",
    "location": "Johar Town, Lahore",
    "projects": [],
    "education": [
      {
        "end_date": "2022",
        "university": "Universidade rápida",
        "degree_title": ""
      },
      {
        "end_date": "2017",
        "university": "Grupo Superior de Faculdades",
        "degree_title": ""
      }
    ],
    "achievements": [],
    "publications": [],
    "certifications": [
      {
        "certification_name": "Marketing de afiliado de comércio eletrônico",
        "issuing_organization": "Comércio eletrônico Pro",
        "date_of_issuance": ""
      },
      {
        "certification_name": "Funnels de vendas e marketing de comércio eletrônico",
        "issuing_organization": "Comércio eletrônico Pro",
        "date_of_issuance": ""
      },
      {
        "certification_name": "Publicidade do Facebook para comércio eletrônico",
        "issuing_organization": "Comércio eletrônico Pro",
        "date_of_issuance": ""
      },
      {
        "certification_name": "ADS do comércio eletrônico do comércio eletrônico",
        "issuing_organization": "Comércio eletrônico Pro",
        "date_of_issuance": ""
      },
      {
        "certification_name": "WordPress wooCommerce",
        "issuing_organization": "Comércio eletrônico Pro",
        "date_of_issuance": ""
      }
    ],
    "additional_urls": [
      {
        "url": "Linkedin.com/in/zarwa-shahid-926986208/",
        "website_name": "LinkedIn"
      }
    ],
    "executive_summary": "Zarwa Shahid é um executivo de desenvolvimento de negócios dedicado, com experiência em impulsionar as vendas e gerenciar o relacionamento com os clientes. Ele tem um forte conjunto de habilidades técnicas, incluindo proficiência no WordPress, HubSpot e Salesforce, e está comprometido em alcançar as metas de negócios por meio de estratégias eficazes de geração de leads e marketing.",
    "employment_history": [
      {
        "details": "Responsável por impulsionar as vendas da empresa, adquirindo novos clientes e criando um valor de longo prazo para seus negócios por meio de plataformas BD.",
        "end_date": "2023",
        "location": "",
        "job_title": "Executivo de Desenvolvimento de Negócios",
        "start_date": "2022",
        "company_name": "Software Pro"
      },
      {
        "details": "Promovido a executivo de desenvolvimento de negócios como líder da equipe. Internos treinados para geração de leads e lances de trabalho. Utilizou o HubSpot e o Salesforce para gerenciar leads. Projetou várias propostas para os clientes.",
        "end_date": "",
        "location": "",
        "job_title": "Executivo de Desenvolvimento de Negócios",
        "start_date": "2023",
        "company_name": "It Cado LLC"
      },
      {
        "details": "Promovido a executivo de desenvolvimento de negócios como líder da equipe. Responsável por projetar e gerenciar portfólios da empresa.",
        "end_date": "",
        "location": "",
        "job_title": "Executivo de Desenvolvimento de Negócios",
        "start_date": "2023",
        "company_name": "Tecspine"
      }
    ]
  }
}