{
  "job_description": "Gerente de Desenvolvimento de Negócios\n\n** Empresa fictícia ** está buscando um gerente de desenvolvimento de negócios dinâmico e estratégico para ingressar em nossa equipe crescente. Nesta função, você desenvolverá e executará estratégias de vendas, gerenciará as principais contas e liderará iniciativas de desenvolvimento de negócios para impulsionar o crescimento organizacional.\n\nResponsabilidades ####:\n- Desenvolva e implemente estratégias para o desenvolvimento de negócios para atingir objetivos corporativos.\n- Supervisionar todo o ciclo de vendas, da geração de leads a acordos de fechamento.\n- Gerenciar e orientar uma equipe de executivos de desenvolvimento de negócios, aprimorando seu potencial para otimizar o sucesso da empresa.\n- Aprimore a presença da empresa por meio de engajamento ativo em plataformas on -line como o LinkedIn e os sites de rede profissional.\n-Envolva-se em negociações de alto risco e coordenam com as principais partes interessadas da conta para garantir a satisfação do cliente e as parcerias de longo prazo.\n\n#### Requisitos:\n- Utilize habilidades analíticas para identificar novas oportunidades e tendências de mercado.\n- Use o Microsoft Office Suite de maneira eficaz para planejar, relatar e apresentar estratégias de vendas.\n\nJunte -se a nós para desempenhar um papel fundamental na expansão de nossos negócios localmente e internacionalmente, trabalhando ao lado de uma equipe dinâmica em um ambiente inovador. Se você gosta de tomar iniciativas e liderar iniciativas de negócios impactantes, queremos ouvir você!",
  "additional_info": "Os candidatos preferidos terão se formado nas principais escolas de negócios, como núcleos rápidos ou Lums. A empresa apóia a realocação de funcionários no Paquistão com a assistência logística necessária. As habilidades são avaliadas por meio de uma combinação de entrevistas técnicas e estudos de caso práticos alinhados aos desafios do setor.",
  "resume": "EDUCAÇÃO\nBacharel em Engenharia de Software\nUniversidade de Gerenciamento e Tecnologia | 2016 - 2020about\nSou engenheiro de software com experiência em desenvolvimento de negócios, tenho proficiência em\nGerando leads, expansão de negócios, vendas, lucratividade e criação de estratégia. \nSou adepto com várias metodologias de desenvolvimento de negócios, coleta e analisando dados sobre\nVendas e marketing, minha experiência se estende a chamadas frias, marketing por email, orçamento\nGerenciamento, comunicação do cliente, documentação e gerenciamento de partes interessadas.\nExperiência de trabalho\nExecutivo de marketing digital\nTECNOLOGIA OZI | Jan 2020 - outubro de 2020\nIdentifique tendências e insights com o site do gerenciamento da organização, mídia social\nPlataformas e mantenha -as, mantendo as melhores práticas em mente. \nOtimize o conteúdo para o site e as plataformas de mídia social. \nTrabalhe com vários formatos de conteúdo, como blogs, vídeos, design gráfico, etc.\nForneça relatórios internos e colaborações criativas entre tecnologias e plataformas. Gerente de desenvolvimento de negócios\nSoluções Shayan | Outubro de 2020 - presente \nGerenciou com sucesso milhões de projetos orçamentários e alcançou as metas agendadas do projeto. \nImplementação e gerenciamento do CRM que se concentrou em alavancar a empresa\nativo de dados.\nLeads de geração e gerenciamento práticos usando Salesforce, LinkedIn Sales Navigator,\nAeroleads, etc. \nAlcançaram as metas de vendas, apresentando serviços da empresa a clientes atuais e potenciais em\nRegiões dos EUA, Austrália e Europa.\nDesenvolveu e implementou novos planos de marketing e vendas, como serviços remotos,\nCampanhas de marketing, etc. \nEscrever e projetar e -mails e garantir a entrega de email adequada aos leads.\nTrabalhar em estreita colaboração com desenvolvedores e engenheiros de controle de qualidade para garantir a qualidade e os padrões de\no projeto. \nImensa experiência em vendas, parcerias e desenvolvimento de negócios no Top B2B\nEmpresas de tecnologia.\nRevisou constantemente o feedback do cliente e depois sugeriu maneiras de melhorar o\nníveis de processo e atendimento ao cliente.\nGarantiu que novos clientes se transformassem em uma base de clientes fiel em um nicho especializado\nmercado.\nGerencie os projetos para que o cliente obtenha os melhores e os resultados da qualidade dentro do tempo. CONTATO\nTelefone: +92 3354059293\nE -mail: mzunair60@gmail.com\nBlog: zunair.medium.com\nEndereço: Sociedade de Valencia,\nLahore.\nJava, C#, programação C ++\nWeb e desenvolvimento móvel\nDesenvolvimento funcional cruzado\nDesenvolvimento de Conteúdo da Web\nSdlc\nDocumentationProfessional\nHABILIDADES\nNavigador de vendas\nAeroleads\nSalesforce\nKrayin CRM\nUpwork\nTrello\nJira\nAsana\nNetbeans\nVisual Studio\nUnidade\nAndroid Studioplatforms &\nFerramentas u h a m m a d m u h a m m a d\nZ u n a i r z u n a i rprojects\nEtradn é um aplicativo disponível na App Store e no Google Play. É um mercado online\nApp.\nO aplicativo pertence a um cliente baseado nos EUA e recebeu este projeto da Upwork.\nAs tecnologias usadas são vibração, figma, php, laravel, trello e github.\nTabadol é um aplicativo de mercado on -line com suporte de múltiplos idiomas para compra e\nServiços e bens de venda.\nTrabalhou com equipe, incluindo um líder de equipe, 4 desenvolvedores e 2 engenheiros de controle de qualidade.\nMonitorando os sistemas existentes. Garantir que o sistema forneça um funil eficaz. Desenvolvido\ne implementou técnicas de marketing.\nAs tecnologias usadas são reagir nativas, redux, node.js, react.js, react-i18next, momento.js,\nAxios.\nÉ um aplicativo, assim como o Club House desenvolvido para dispositivos iOS. O aplicativo inclui simples\nNo entanto, a interface do usuário atraente com funcionalidades minimalistas.\nAs tecnologias usadas são rápidas, iOS SDK.\nÉ o jogo de cassino online da loteria.\nServiço amigável em compatibilidade com navegadores da Web, tablets e telefones celulares.\nLaravel, JavaScript, JQuery, JQuery Ui, Moment.js, React.js, Git, etc.\nAplicação funcional cruzada para iOS e Android. Um aplicativo de compras on -line.\nTecnologias usadas são vibração, flagelo sdk, fixação de vibração, arquivo pubspec, recarga a quente, devtools,\nHtml, figma e git.etradn\nTabadol\nFale fácil\nOCG\nNovo TempusProposal & E -mail escrevendo\nForte analítico e \nComunicação\nSolucionador de problemas\nBoas habilidades de análise de negócios\nGerenciamento de tempo\nJogador de equipe\nAprendiz rápido \nHABILIDADES\nProjetos e trabalho de pesquisa\nUi/ ux\nAnimação\nScript\nAndroid Studio\nAndroid SDK\nSQL\nPesquisa sobre novas tendências usando o reconhecimento de texto\nTécnicas e ferramentas usadas\nComunicação com a pessoa de recursos e membros da equipe em primeira pessoa atirando em jogo 3D\nAplicativo de atendimento on -line\nArtigo de pesquisa sobre reconhecimento de texto",
  "details": {
    "name": "Muhammad Zunair",
    "number": "923354059293",
    "skills": [
      "Java",
      "C#",
      "C ++",
      "Web e desenvolvimento móvel",
      "Desenvolvimento funcional cruzado",
      "Desenvolvimento de Conteúdo da Web",
      "Sdlc",
      "Navigador de vendas",
      "Aeroleads",
      "Salesforce",
      "Krayin CRM",
      "Upwork",
      "Trello",
      "Jira",
      "Asana",
      "Netbeans",
      "Visual Studio",
      "Unidade",
      "Android Studio",
      "SQL"
    ],
    "email_id": "mzunair60@gmail.com",
    "location": "Sociedade de Valencia, Lahore",
    "projects": [
      {
        "title": "Etradn",
        "description": "Um aplicativo de mercado on -line disponível na App Store e no Google Play."
      },
      {
        "title": "Tabadol",
        "description": "Um aplicativo de mercado on -line com suporte de múltiplos idiomas para compra e venda de serviços e bens."
      },
      {
        "title": "Fale fácil",
        "description": "Um aplicativo desenvolvido para dispositivos iOS com interface do usuário simples e atraente."
      },
      {
        "title": "OCG",
        "description": "Um jogo de cassino online da loteria."
      },
      {
        "title": "Novo Tempus",
        "description": "Um aplicativo multifuncional para iOS e Android, um aplicativo de compras on-line."
      }
    ],
    "education": [
      {
        "end_date": "06-2020",
        "university": "Universidade de Gerenciamento e Tecnologia",
        "degree_title": "Bacharel em Engenharia de Software"
      }
    ],
    "achievements": [],
    "publications": [],
    "certifications": [],
    "additional_urls": [
      {
        "url": "zunair.medium.com",
        "website_name": "Blog"
      }
    ],
    "executive_summary": "Muhammad Zunair é um engenheiro de software qualificado, com uma forte experiência em desenvolvimento da Web e móveis, proficiente em várias linguagens e ferramentas de programação. Ele demonstrou experiência no gerenciamento de projetos e implementação de estratégias eficazes de desenvolvimento de negócios.",
    "employment_history": [
      {
        "details": "Identifique tendências e insights com o gerenciamento do site da organização, as plataformas de mídia social e mantenha -as, mantendo as melhores práticas em mente. Otimize o conteúdo para o site e as plataformas de mídia social. Trabalhe com vários formatos de conteúdo, como blogs, vídeos, design gráfico etc. Forneça relatórios internos e colaborações criativas entre tecnologias e plataformas.",
        "end_date": "10-2020",
        "location": "Tecnologia Ozi",
        "job_title": "Executivo de marketing digital",
        "start_date": "01-2020",
        "company_name": "Tecnologia Ozi"
      },
      {
        "details": "Gerenciou com sucesso milhões de projetos orçamentários e alcançou as metas agendadas do projeto. Implementação e gerenciamento do CRM focado em alavancar o ativo de dados da empresa. Os leads práticos de geração e gerenciamento usando o Salesforce, o LinkedIn Sales Navigator, a Aeroleads etc. alcançaram as metas de vendas, apresentando serviços da empresa a clientes atuais e potenciais nos EUA, Austrália e Europa. Desenvolvi e implementou novos planos de marketing e vendas, como serviços remotos, campanhas de marketing etc. Escrever e projetar e -mails e garantir a entrega de email adequada aos leads. Trabalhe em estreita colaboração com desenvolvedores e engenheiros de controle de qualidade para garantir a qualidade e os padrões do projeto. Intensidade especializada em vendas, parcerias e desenvolvimento de negócios nas principais empresas de tecnologia B2B. Revisou constantemente o feedback do cliente e depois sugeriu maneiras de melhorar o processo e os níveis de atendimento ao cliente. Garantiu que novos clientes se transformassem em uma base de clientes fiel em um mercado de nicho especializado. Gerencie os projetos para que o cliente obtenha os melhores e os resultados da qualidade dentro do tempo.",
        "end_date": "Presente",
        "location": "Soluções Shayan",
        "job_title": "Gerente de Desenvolvimento de Negócios",
        "start_date": "10-2020",
        "company_name": "Soluções Shayan"
      }
    ]
  }
}