{
  "job_description": "** Título: Gerente de Desenvolvimento de Negócios **  \n\n** Empresa: MarketPros Enterprises **  \n\n** Localização: remoto com potencial viagens para locais de clientes **  \n\n**Sobre nós:**  \nA MarketPros Enterprises é um fornecedor global líder de soluções de negócios inovadoras, com o objetivo de maximizar o crescimento da marca. Trabalhamos com diversas indústrias para aprimorar sua infraestrutura de vendas e fornecer estratégias incomparáveis ​​de envolvimento do cliente.  \n\n** Visão geral da função: **  \nComo gerente de desenvolvimento de negócios da MarketPros Enterprises, você será responsável por liderar iniciativas estratégicas que impulsionam o crescimento dos negócios, aumentam a participação de mercado e fortalecem as relações com os clientes. Você gerenciará equipes multifuncionais para implementar estratégias de vendas, aproveitar as idéias do mercado e impulsionar a expansão da marca.  \n\n** Responsabilidades -chave: **  \n- Desenvolver e implementar estratégias de negócios abrangentes para aumentar o crescimento da receita.  \n- Liderar uma equipe na execução de campanhas de marketing e otimizar os pipelines de vendas.  \n- Utilize ferramentas de análise de dados para produzir informações acionáveis, melhorando o desempenho geral.  \n- Realize pesquisas de mercado para identificar tendências do setor e novas oportunidades de negócios.  \n- Envolva-se com clientes em potencial por meio de apresentações e promova relacionamentos de longo prazo.  \n- Gerenciar sistemas CRM (Salesforce, HubSpot) para otimizar as operações e aprimorar a produtividade.  \n\n** Habilidades preferidas: **  \n- Proficiência em planejamento estratégico e análise de mercado.  \n- Fortes habilidades de liderança com experiência comprovada no desenvolvimento de equipes.  \n- Conhecimento avançado de software CRM e ferramentas de marketing digital.  \n- Excelentes habilidades de comunicação e negociação.  \n\nJunte -se a nós para ultrapassar os limites da inovação de negócios e nos ajudar a alcançar nossos objetivos de expansão.",
  "additional_info": "A MarketPros Enterprises valoriza a diversidade na contratação e incentiva aplicativos de profissionais de negócios experientes com origens variadas. As universidades preferenciais incluem instituições da Ivy League e as principais escolas de negócios. Oferecemos benefícios de realocação para candidatos excepcionais e facilitamos os acordos de trabalho remotos. As competências técnicas e estratégicas são avaliadas através de uma mistura de avaliações psicométricas e entrevistas com estudos de caso.",
  "resume": "Hafsa Naeem \nDesenvolvimento de negócios\nProfissional \nProfissional dinâmico de BD com uma mentalidade de crescimento\n& B2B Expertise nas startups de tecnologia dos EUA \nhafsa.naeem1024@gmail.com \n+92 307 7089974 \nLahore, Paquistão \nLinkedIn.com/in/hafsanaeem92 \nExperiência de trabalho \nDesenvolvimento de negócios \nOdetta.ai \n11/2018 - presente\n, Assim, \n \nLahore, Paquistão \nOdetta é uma plataforma de terceirização on-line com sede nos EUA com a missão de capacitar\nmulheres em Mesa \nTrabalhando com líderes da indústria de tecnologia dos EUA em vários setores, como\nComo software de computador, Ed-Tech, FinTech, Healthcare, E-Commerce &\nVCs \nVendendo soluções de dados como geração de leads, anotação de dados,\nAutomação de marketing, fornecimento de candidatos e muito mais \nFechando acordos com as empresas da Fortune 500 dos EUA e o crescimento de nosso\nBase de clientes de 35 a 150+ em 2020-2021 \nLíder de recrutamento \nOdetta.ai \n03/2019 - 12/2021\n, Assim, \n \nLahore, Paquistão \nOdetta ocupa o #25 na Forbes Melhores Empregadores de Startups dos EUA em 2022,\nsob minha liderança \nUnidades de recrutamento de chumbo; Explorando, lista mais curta e entrevista\ntalento de camada de toda a região de Mesa \nOrientação e treinamento de nossa equipe \nAssistente virtual principal \nOdetta.ai \n05/2019 - 12/2020\n, Assim, \n \nLahore, Paquistão \nPrimeiro funcionário a ser promovido a função de VA \nLidere uma equipe de 2 vas para o nosso CEO \nControlador de qualidade/gerente de projeto \nOdetta.ai \n12/2018 - 12/2020\n, Assim, \n \nLahore, Paquistão \nLidere uma equipe de 15 a 20 pessoas para coleta/enriquecimento de dados\nProjetos para nós, capital de risco \nProjetos de categorização de dados gerenciados para empresas de software \nLidere uma equipe de 50 anotadores para projetos de anotação de dados da IA\nempresas \nRun Ran Campanhas de Vendas e CRM para startups em saúde, aeroespacial,\nFinChs de FinCh e consultoria \nEDUCAÇÃO \nMestrado em Administração de Empresas \nUniversidade Nacional de Computador e Emergente\nCiências \n09/2021 - Presente\n, Assim, \n \nLahore, Paquistão \nMarketing \nAnálise de negócios \nHABILIDADES \nGerenciamento de projetos \nPower bi \nLiderança \nMarketing digital \nCRM \nExtensão fria \nGeração de chumbo \nFornecimento de candidatos \nVendas B2B \nRealizações \nFuncionário da estrela \nSomente funcionário da Odetta como líder de vendas, First VA, VA\nLíder de chumbo e recrutamento por 2 anos \nCertificados \nFundamentos de análise de negócios: competências\n (07/2022 - presente)\n \nEmitido pelo Instituto Internacional de Análise de Negócios ™ \nAnálise de negócios: dados de vendas\n (07/2022 - presente)\n \nEmitido pelo Instituto Internacional de Análise de Negócios ™ \nEstratégias de tomada de decisão\n (07/2022 - presente)\n \nEmitido pela Associação Nacional de Conselhos Estaduais de\nContabilidade \nAnálise de dados para profissionais de negócios\n (07/2022 - presente)\n \nEmitido pelo LinkedIn Learning \nProjeto pessoal \nTecnologia da juventude\n (10/2021 - presente)\n \nCo-fundador e consultor de negócios @ Youth Tech, um crescente\nStartup oferecendo soluções de terceirização para empresas de tecnologia. \nIdiomas \nInglês \nProfiência profissional completa \nurdu \nProficiência nativa ou bilíngue \nInteresses \nAnálise de dados \nEmpreendedorismo \nOrientação de negócios \nFotografia \nSaúde e Fitness \nTecnologia e inovação \nRealizações/tarefas \nRealizações/tarefas \nRealizações/tarefas \nRealizações/tarefas \nCursos",
  "details": {
    "name": "Hafsa Naeem",
    "number": "923077089974",
    "skills": [
      "Gerenciamento de projetos",
      "Power bi",
      "Marketing digital",
      "CRM",
      "Extensão fria",
      "Geração de chumbo",
      "Fornecimento de candidatos",
      "Vendas B2B"
    ],
    "email_id": "hafsa.naeem1024@gmail.com",
    "location": "Lahore, Paquistão",
    "projects": [
      {
        "title": "Tecnologia da juventude",
        "description": "Co-fundador e consultor de negócios @ Youth Tech, uma startup em crescimento que oferece soluções de terceirização para empresas de tecnologia."
      }
    ],
    "education": [
      {
        "end_date": "Presente",
        "university": "Universidade Nacional de Computador e Ciências Emergentes",
        "degree_title": "Mestrado em Administração de Empresas"
      }
    ],
    "achievements": [
      "Star funcionário - O único funcionário da Odetta é um líder de vendas, First VA, VA Líder e Líder de Recrutamento por 2 anos"
    ],
    "publications": [],
    "certifications": [
      {
        "certification_name": "Fundamentos de análise de negócios: competências",
        "issuing_organization": "O Instituto Internacional de Análise de Negócios ™",
        "date_of_issuance": "07-2022"
      },
      {
        "certification_name": "Análise de negócios: dados de vendas",
        "issuing_organization": "O Instituto Internacional de Análise de Negócios ™",
        "date_of_issuance": "07-2022"
      },
      {
        "certification_name": "Estratégias de tomada de decisão",
        "issuing_organization": "Associação Nacional de Conselhos Estaduais de Contabilidade",
        "date_of_issuance": "07-2022"
      },
      {
        "certification_name": "Análise de dados para profissionais de negócios",
        "issuing_organization": "Aprendizagem do LinkedIn",
        "date_of_issuance": "07-2022"
      }
    ],
    "additional_urls": [
      {
        "url": "LinkedIn.com/in/hafsanaeem92",
        "website_name": "LinkedIn"
      }
    ],
    "executive_summary": "Hafsa Naeem é um profissional de desenvolvimento de negócios dinâmico, com ampla experiência em B2B nas startups de tecnologia dos EUA. Ela tem um histórico comprovado para impulsionar o crescimento e gerenciar o relacionamento com os clientes, principalmente no setor de tecnologia. Seus papéis de liderança em Odetta.ai destacam sua capacidade de liderar equipes e acordos significativos próximos com empresas da Fortune 500.",
    "employment_history": [
      {
        "details": "Trabalhando com líderes da indústria de tecnologia dos EUA em vários setores, como software de computador, ED-Tech, Fintech, Healthcare, E-Commerce e VCs. Venda soluções de dados como geração de leads, anotação de dados, automação de marketing, fornecimento de candidatos e muito mais. O fechamento de acordos com as empresas da Fortune 500 e o crescimento de nossa base de clientes de 35 para 150+ em 2020-2021.",
        "end_date": "Presente",
        "location": "Lahore, Paquistão",
        "job_title": "Desenvolvimento de negócios",
        "start_date": "11-2018",
        "company_name": "Odetta.ai"
      },
      {
        "details": "Unidades de recrutamento de chumbo; Explorando, lista restante e entrevistando os melhores talentos de camadas de toda a região de Mesa. Orientação e treinamento de nossa equipe.",
        "end_date": "12-2021",
        "location": "Lahore, Paquistão",
        "job_title": "Líder de recrutamento",
        "start_date": "03-2019",
        "company_name": "Odetta.ai"
      },
      {
        "details": "Primeiro funcionário a ser promovido a função de VA. Lidere uma equipe de 2 VAs para o nosso CEO.",
        "end_date": "12-2020",
        "location": "Lahore, Paquistão",
        "job_title": "Assistente virtual principal",
        "start_date": "05-2019",
        "company_name": "Odetta.ai"
      },
      {
        "details": "Lidere uma equipe de 15 a 20 pessoas para projetos de coleta/enriquecimento de dados para empresas de capital de risco dos EUA. Projetos de categorização de dados gerenciados para empresas de software. Lidere uma equipe de 50 anotadores para projetos de anotação de dados das empresas de IA. Execute campanhas de vendas e CRM para startups em empresas de saúde, aeroespacial, fintech e consultoria.",
        "end_date": "12-2020",
        "location": "Lahore, Paquistão",
        "job_title": "Controlador de qualidade/gerente de projeto",
        "start_date": "12-2018",
        "company_name": "Odetta.ai"
      }
    ]
  }
}