{
  "job_description": "### Gerente de contas -chave na Luxotech Solutions\n\n** Localização: ** Karachi, Paquistão\n\n** Departamento: ** Vendas e marketing\n\n** Relatórios para: ** Diretor de vendas\n\n** Visão geral da função: **\nJunte -se à Luxotech Solutions como gerente de contas importantes, onde você será responsável pelo gerenciamento das principais contas nos segmentos de varejo e hospitalidade em todo o Paquistão. Você impulsionará o crescimento das vendas, gerenciando contas existentes e desenvolvendo estratégias para novas contas. Sua função envolverá coordenar com equipes multifuncionais, analisar tendências do mercado e liderar iniciativas para cumprir as metas de receita.\n\nResponsabilidades ####:\n- Gerencie um portfólio de mais de 15 contas principais, compreendendo usuários finais e parceiros de canal.\n- Dirija a expansão para novos segmentos de mercado, identificando e se envolvendo com possíveis leads.\n- Desenvolva e execute estratégias de gerenciamento de contas para alcançar 110% de obtenção alvo de receita.\n- Utilize ferramentas de análise de dados, como o Power BI, para avaliar as tendências do mercado e gerar insights.\n- Coordenar com equipes internas, incluindo marketing e operações, para garantir o alinhamento estratégico.\n- Liderar negociações contratadas e gerenciar estratégias de preços para otimizar a lucratividade.\n- Relatório sobre o desempenho da conta e as oportunidades de mercado para a gerência sênior regularmente.\n\n#### habilidades essenciais:\n- Fortes habilidades de liderança e gerenciamento de partes interessadas.\n- Proficiência na análise de dados e previsão para informar a tomada de decisão.\n- Experiência em ferramentas como Salesforce, Vistex e SAP ERP para gerenciar funções de vendas.\n- Excelentes habilidades de comunicação para interações com clientes e colaborações internas.\n\n#### qualificações:\n- Mestre de preferência; É necessário um diploma de bacharel em administração de empresas ou campo relacionado.\n- Mais de 5 anos de experiência em gerenciamento de vendas ou desenvolvimento de negócios, com foco no gerenciamento de contas principais.\n- O sucesso demonstrado em contas crescentes e atingindo metas de receita.\n\n#### Benefícios:\n- Salário competitivo com bônus de desempenho.\n- Oportunidades de desenvolvimento profissional e acesso a seminários da indústria.\n- Horário de trabalho flexível.",
  "additional_info": "A Luxotech Solutions valoriza a diversidade e busca candidatos de uma variedade de origens e experiências. As instituições preferidas incluem o Instituto de Administração de Empresas, Karachi e Nuces Fast. A empresa suporta acordos de trabalho híbridos e oferece assistência de realocação para candidatos excepcionais. As habilidades são avaliadas através de uma combinação de testes técnicos, estudos de caso e entrevistas estruturadas com membros do painel de vários departamentos.",
  "resume": "C O N T A C T\n+923021678782p h o n e\nzshehzad28@gmail.come m a i lzohaib shehzad\nGerente de Desenvolvimento de Negócios\nLíder de desenvolvimento de negócios qualificado, oferecendo mais de 3 anos de experiência nas principais operações e\nmelhorando a receita. Trazer experiência em aquisição de clientes e negociação de contratos, juntamente com\nExcelente comunicação interpessoal, construção de relacionamentos e habilidades de liderança de equipe. Resultados\nimpulsionado e proativo com registro demonstrado de realização na reunião e exceder as vendas\ne objetivos de receita.\nExperiência\nRelacionamentos estabelecidos com os principais tomadores de decisão na organização do cliente\npara promover o crescimento e a retenção.\nIdentificou e persegui valiosos oportunidades de negócios para gerar nova empresa\nreceita e melhorar a lucratividade final.\nAcordos negociados e fechados de longo prazo com novos clientes em designado\nterritórios.\nGerou novos negócios com iniciativas de marketing e planos estratégicos.\nGerou novos negócios com iniciativas de marketing e planos estratégicos.\nEntrou em contato com clientes em potencial por telefone, e-mail e consultas pessoais.\nMantida notas meticulosas do cliente e informações de conta atualizadas nos bancos de dados da empresa.\nEstabeleceu os principais indicadores de desempenho para rastrear e analisar o progresso dos negócios e\najustar estratégias de acordo.\nProcesso desenvolvido para analisar o feedback do cliente para incorporar informações sobre o produto\nEstratégias de desenvolvimento.\nServiu como ligação técnica, apoiando engenharia, gerenciamento, compras, vendas\ne marketing, garantia de qualidade e base de suprimentos.\nPlanos de projeto comunicados e progresso para as principais partes interessadas e projetos\ncolaboradores.\nColaborou com usuários empresariais, equipes técnicas, administradores de banco de dados e testes\nequipes durante reuniões de kickoff, design de aplicativos conjuntos e sessões de planejamento para\nvalidar requisitos.\nFiz uma parceria com os membros da equipe do projeto para identificar e abordar rapidamente os problemas.sr. Gerente de Desenvolvimento de Negócios\nGerente de Desenvolvimento de Negócios\nGerenciador de projetos técnicos2022 - atual\n2021 - 2022\n2019 - 2021Cherry Bytes Technologies \nAmrood Labs\nLeads de KP\nA referência será fornecida sob demanda e f e r e n c ee d u c a t i o n\nUniversidade de Sargodhamaster em Tecnologias da Informação2017-2019Research\nDesenvolvimento e planejamento de negócios\nVendas de produtos e serviços\nConstrução de relacionamento e gerenciamento\nNovo desenvolvimento de negócios\nDefinição de objetivos\nGerenciamento de pedidos\nMétricas de desempenho\nControle de qualidade\nGerenciamento de funcionários\nGeração de receita\nInglês\nUrdul a n g u a g ee x p e r t i s e",
  "details": {
    "name": "Zohaib Shehzad",
    "number": "923021678782",
    "skills": [
      "Desenvolvimento de negócios",
      "Vendas de produtos e serviços",
      "Novo desenvolvimento de negócios",
      "Gerenciamento de pedidos",
      "Métricas de desempenho",
      "Controle de qualidade",
      "Gerenciamento de funcionários",
      "Geração de receita"
    ],
    "email_id": "zshehzad28@gmail.com",
    "location": "",
    "projects": [],
    "education": [
      {
        "end_date": "06-2019",
        "university": "Universidade de Sargodha",
        "degree_title": "Mestre em tecnologias de informação"
      }
    ],
    "achievements": [],
    "publications": [],
    "certifications": [],
    "additional_urls": [],
    "executive_summary": "Zohaib Shehzad é um gerente de desenvolvimento de negócios qualificado, com mais de 3 anos de experiência nas principais operações e melhorando a receita. Ele possui experiência em aquisição de clientes e negociação de contratos, demonstrando um forte histórico no cumprimento e excedendo os objetivos de vendas.",
    "employment_history": [
      {
        "details": "Relacionamentos estabelecidos com os principais tomadores de decisão da organização do cliente para promover o crescimento e a retenção. Identificou e buscou oportunidades de negócios valiosas para gerar novas receitas da empresa e melhorar a lucratividade final. Negociou e fechou acordos de longo prazo com novos clientes em territórios designados. Gerou novos negócios com iniciativas de marketing e planos estratégicos. Entrou em contato com clientes em potencial por telefone, e-mail e consultas pessoais. Mantida notas meticulosas do cliente e informações de conta atualizadas nos bancos de dados da empresa. Estabeleceu os principais indicadores de desempenho para rastrear e analisar o progresso dos negócios e ajustar as estratégias de acordo. Processo desenvolvido para analisar o feedback do cliente para incorporar informações sobre as estratégias de desenvolvimento de produtos. Serviu como ligação técnica, apoiando engenharia, gerenciamento, compras, vendas e marketing, garantia de qualidade e base de suprimentos. Planos de projeto comunicados e progresso às principais partes interessadas e colaboradores do projeto. Colaborou com usuários de negócios, equipes técnicas, administradores de banco de dados e equipes de teste durante reuniões de kickoff, design de aplicativos conjunto e sessões de planejamento para validar requisitos. Em parceria com os membros da equipe do projeto para identificar e resolver rapidamente os problemas.",
        "end_date": "Atual",
        "location": "",
        "job_title": "Gerente de projetos técnicos",
        "start_date": "01-2022",
        "company_name": "Tecnologias de cereja bytes"
      },
      {
        "details": "Gerou novos negócios com iniciativas de marketing e planos estratégicos. Entrou em contato com clientes em potencial por telefone, e-mail e consultas pessoais. Mantida notas meticulosas do cliente e informações de conta atualizadas nos bancos de dados da empresa. Estabeleceu os principais indicadores de desempenho para rastrear e analisar o progresso dos negócios e ajustar as estratégias de acordo.",
        "end_date": "12-2022",
        "location": "",
        "job_title": "Gerente de Desenvolvimento de Negócios",
        "start_date": "01-2021",
        "company_name": "Amrood Labs"
      },
      {
        "details": "Identificou e buscou oportunidades de negócios valiosas para gerar novas receitas da empresa e melhorar a lucratividade final. Negociou e fechou acordos de longo prazo com novos clientes em territórios designados.",
        "end_date": "12-2021",
        "location": "",
        "job_title": "Ir. Gerente de Desenvolvimento de Negócios",
        "start_date": "01-2019",
        "company_name": "Leads de KP"
      }
    ]
  }
}