{
  "job_description": "** Título: Gerente de Desenvolvimento de Negócios **  \n\n** Empresa: MarketPros Enterprises **  \n\n** Localização: remoto com potencial viagens para locais de clientes **  \n\n**Sobre nós:**  \nA MarketPros Enterprises é um fornecedor global líder de soluções de negócios inovadoras, com o objetivo de maximizar o crescimento da marca. Trabalhamos com diversas indústrias para aprimorar sua infraestrutura de vendas e fornecer estratégias incomparáveis ​​de envolvimento do cliente.  \n\n** Visão geral da função: **  \nComo gerente de desenvolvimento de negócios da MarketPros Enterprises, você será responsável por liderar iniciativas estratégicas que impulsionam o crescimento dos negócios, aumentam a participação de mercado e fortalecem as relações com os clientes. Você gerenciará equipes multifuncionais para implementar estratégias de vendas, aproveitar as idéias do mercado e impulsionar a expansão da marca.  \n\n** Responsabilidades -chave: **  \n- Desenvolver e implementar estratégias de negócios abrangentes para aumentar o crescimento da receita.  \n- Liderar uma equipe na execução de campanhas de marketing e otimizar os pipelines de vendas.  \n- Utilize ferramentas de análise de dados para produzir informações acionáveis, melhorando o desempenho geral.  \n- Realize pesquisas de mercado para identificar tendências do setor e novas oportunidades de negócios.  \n- Envolva-se com clientes em potencial por meio de apresentações e promova relacionamentos de longo prazo.  \n- Gerenciar sistemas CRM (Salesforce, HubSpot) para otimizar as operações e aprimorar a produtividade.  \n\n** Habilidades preferidas: **  \n- Proficiência em planejamento estratégico e análise de mercado.  \n- Fortes habilidades de liderança com experiência comprovada no desenvolvimento de equipes.  \n- Conhecimento avançado de software CRM e ferramentas de marketing digital.  \n- Excelentes habilidades de comunicação e negociação.  \n\nJunte -se a nós para ultrapassar os limites da inovação de negócios e nos ajudar a alcançar nossos objetivos de expansão.",
  "additional_info": "A MarketPros Enterprises valoriza a diversidade na contratação e incentiva aplicativos de profissionais de negócios experientes com origens variadas. As universidades preferenciais incluem instituições da Ivy League e as principais escolas de negócios. Oferecemos benefícios de realocação para candidatos excepcionais e facilitamos os acordos de trabalho remotos. As competências técnicas e estratégicas são avaliadas através de uma mistura de avaliações psicométricas e entrevistas com estudos de caso.",
  "resume": "Reham Shah  \n \n \n             +923328079859 reham.altaf2@gmail.com @gmail.com  \nValencia Town Lahore, Paquistão Linkedin.com/in/reham -shah -a72b46172  \n \nB2B Sales Development Client Liaison Online Living  \n \nExecutivo de Desenvolvimento de Negócios de julho de 2020 - atual  \n \n❖ Construir e manter relacionamentos bem -sucedidos com clientes em potencial e clientes existentes. \n❖ Colaborar com executivos sobre estratégia de negócios para determinar os objetivos. \n❖ Os leads de clientes com melhor classificação gerados por meio de plataformas freelancers como Upwork, \nFreelancers, Fiverr, LinkedIn.  \n❖ Produtividade maximizada analisando protocolos e identificando áreas para melhoria.  \n❖ Envolvido com os clientes para criar efetivamente relacionamento e relacionamentos duradouros. Resolvido \nDesafios do cliente, oferecendo produtos e serviços relevantes.  \n❖ Forneceu primeiras impressões positivas para receber clientes existentes, novos e em potencial.  \n❖ Ajudou a desenvolver processos de automação de vendas e automação de geração de leads  \n❖ Manutenção de projetos de clientes relacionados ao desenvolvimento de software.  \n❖ Trabalhou com CRMs como Salesforce e Odoo. \n \nExperiências: \n \n Oficial de Desenvolvimento de Negócios da Kodex Technologies (julho de 2020 a setembro de 2020)  \n \n❖ Trabalhou como licitante em várias plataformas de freelancer. \n❖ Trabalhou na geração de leads do LinkedIn. \n❖ Lidou com projetos de clientes relacionados ao desenvolvimento de software. \n \nExecutivo de Desenvolvimento de Negócios na S.T.A.R.S Pvt. (Ltd) (outubro de 2020 a abril de 2021)  \n \n❖ Trabalhou como licitante em várias plataformas de freelancer. \n❖ Trabalhou na geração de leads do LinkedIn. \n❖ Lidou com projetos de clientes relacionados ao desenvolvimento de software.  \n❖ Reunião técnica necessária.  \n❖ Criou escopo de documentos, dtls. \n \nRepresentante de Desenvolvimento de Vendas no TKXEL (maio de 2021 a outubro de 2021)  \n ❖ Enviando e -mail para os leads qualifas do mercado.  \n❖ Convertendo MQLs em chamada de descoberta.  \n❖ Agenda a reunião do Zoom com clientes.  \n❖ Mantenha os dados do cliente no Salesforce CRM.  \n❖ Acompanhamentos de acompanhamentos para leads existentes.  \n \nExecutivo de Desenvolvimento de Negócios no THD Infinity (novembro de 2021 até o presente)  \n \n❖ A licitação em projetos de desenvolvimento de software sobre o upwork platfrom. \n❖ Agenda a chamada de descoberta.  \n❖ Cetação de requisitos técnicos, análise de produtos.  \n❖ Criando documento SOW. \n❖ Criar DTLs e ajudar o desenvolvedor a entender as necessidades do cliente.  \n❖ Acompanhamentos de acompanhamento com clientes existentes e gerando novos leads.    \n \nQualificação acadêmica:  \n \nCiências da Computação - Universidade de Bahria, Lahore - 2016 -2020  \n \nHabilidades suaves e tecnológicas:  \n❖ Boas habilidades de comunicação, verbal e escrita. \n❖ Experiente em lidar com clientes baseados nos EUA. \n❖ Líder de equipe na S.T.A.R.S Corporation.  \n❖ Familiar em variedade de tecnologias e conceitos de desenvolvimento, incluindo C ++, Java, \nHTML/CSS, ágil/scrum, inteligência de negócios. \n❖ Curso da Web e Graphics (NexxusBerry). \n❖ Líder da equipe para o projeto do último ano. \n \nRealizações: \n \n❖ Bahria Got Talent Bulc (cantando). \n❖ 2ª posição garantida no concurso de debates na Universidade de Bahria. \n❖ Funcionário do mês na S.T.A.R.S. \n \nReferências:  \n \nUsman Farooqi, gerente de negócios da Kodex Technologies  \nUsmanfarooqi22@email, +92 3214445372",
  "details": {
    "name": "Reham Shah",
    "number": "923328079859",
    "skills": [
      "C ++",
      "Java",
      "HTML/CSS",
      "Ágil/scrum",
      "Inteligência de negócios",
      "Salesforce",
      "ODOO"
    ],
    "email_id": "reham.altaf2@gmail.com",
    "location": "Valencia Town Lahore, Paquistão",
    "projects": [],
    "education": [
      {
        "end_date": "2020",
        "university": "Universidade da Bahria",
        "degree_title": "Ciências do computador"
      }
    ],
    "achievements": [
      "2ª posição garantida no concurso de debates na Universidade de Bahria",
      "Funcionário do mês na S.T.A.R.S"
    ],
    "publications": [],
    "certifications": [],
    "additional_urls": [
      {
        "url": "LinkedIn.com/in/reham-shah-a72b46172",
        "website_name": "LinkedIn"
      }
    ],
    "executive_summary": "Reham Shah é um executivo de desenvolvimento de negócios qualificado, com forte experiência em desenvolvimento de software e relações com clientes. Ela demonstrou experiência em várias linguagens e ferramentas de programação, contribuindo para o gerenciamento bem -sucedido de projetos e os esforços de geração de leads em várias plataformas freelancers.",
    "employment_history": [
      {
        "details": "Construir e manter relacionamentos bem -sucedidos com clientes em potencial e clientes existentes. Colaborar com executivos sobre estratégia de negócios para determinar os objetivos. Os leads de clientes com melhor classificação gerados por meio de plataformas freelancers como Upwork, Freelancers, Fiverr, LinkedIn. Produtividade maximizada analisando protocolos e identificando áreas para melhoria. Envolvido com os clientes para criar efetivamente relacionamento e relacionamentos duradouros. Resolveu os desafios do cliente, oferecendo produtos e serviços relevantes. Forneceu as primeiras impressões positivas para receber clientes existentes, novos e em potencial. Ajudou a desenvolver processos de automação de vendas e automação de geração de leads. Lidou com projetos de clientes relacionados ao desenvolvimento de software. Trabalhou com CRMs como Salesforce e Odoo.",
        "end_date": "Atual",
        "location": "Lahore, Paquistão",
        "job_title": "Executivo de Desenvolvimento de Negócios",
        "start_date": "07-2020",
        "company_name": "Thd infinito"
      },
      {
        "details": "Trabalhou como licitante em várias plataformas freelancers. Trabalhou na geração de leads do LinkedIn. Lidou com projetos de clientes relacionados ao desenvolvimento de software.",
        "end_date": "09-2020",
        "location": "Lahore, Paquistão",
        "job_title": "Oficial de Desenvolvimento de Negócios",
        "start_date": "07-2020",
        "company_name": "Kodex Technologies"
      },
      {
        "details": "Trabalhou como licitante em várias plataformas freelancers. Trabalhou na geração de leads do LinkedIn. Lidou com projetos de clientes relacionados ao desenvolvimento de software. Coleta de requisitos técnicos. Criou escopo de documentos, DTLS.",
        "end_date": "04-2021",
        "location": "Lahore, Paquistão",
        "job_title": "Executivo de Desenvolvimento de Negócios",
        "start_date": "10-2020",
        "company_name": "S.T.A.R.S Pvt. (Ltd)"
      },
      {
        "details": "Enviando email para leads qualificados do mercado. Convertendo MQLs em chamadas de descoberta. Agendar reuniões de zoom com clientes. Mantenha os dados do cliente sobre o Salesforce CRM. Acompanhamentos de leads existentes.",
        "end_date": "10-2021",
        "location": "Lahore, Paquistão",
        "job_title": "Representante de desenvolvimento de vendas",
        "start_date": "05-2021",
        "company_name": "Tkxel"
      }
    ]
  }
}