{
  "job_description": "Gerente de Desenvolvimento de Negócios\n\n** Empresa fictícia ** está buscando um gerente de desenvolvimento de negócios dinâmico e estratégico para ingressar em nossa equipe crescente. Nesta função, você desenvolverá e executará estratégias de vendas, gerenciará as principais contas e liderará iniciativas de desenvolvimento de negócios para impulsionar o crescimento organizacional.\n\nResponsabilidades ####:\n- Desenvolva e implemente estratégias para o desenvolvimento de negócios para atingir objetivos corporativos.\n- Supervisionar todo o ciclo de vendas, da geração de leads a acordos de fechamento.\n- Gerenciar e orientar uma equipe de executivos de desenvolvimento de negócios, aprimorando seu potencial para otimizar o sucesso da empresa.\n- Aprimore a presença da empresa por meio de engajamento ativo em plataformas on -line como o LinkedIn e os sites de rede profissional.\n-Envolva-se em negociações de alto risco e coordenam com as principais partes interessadas da conta para garantir a satisfação do cliente e as parcerias de longo prazo.\n\n#### Requisitos:\n- Utilize habilidades analíticas para identificar novas oportunidades e tendências de mercado.\n- Use o Microsoft Office Suite de maneira eficaz para planejar, relatar e apresentar estratégias de vendas.\n\nJunte -se a nós para desempenhar um papel fundamental na expansão de nossos negócios localmente e internacionalmente, trabalhando ao lado de uma equipe dinâmica em um ambiente inovador. Se você gosta de tomar iniciativas e liderar iniciativas de negócios impactantes, queremos ouvir você!",
  "additional_info": "Os candidatos preferidos terão se formado nas principais escolas de negócios, como núcleos rápidos ou Lums. A empresa apóia a realocação de funcionários no Paquistão com a assistência logística necessária. As habilidades são avaliadas por meio de uma combinação de entrevistas técnicas e estudos de caso práticos alinhados aos desafios do setor.",
  "resume": "Zubair Ahmed \nExecutivo de Desenvolvimento de Negócios \nUm prospectivo analista de marketing e negócios, um destinatário de ciências da gestão da Universidade de Engenharia e Tecnologia de Ned,\nquem se esforça para posar e responder com uma atitude comercial orientada a resultados no desenvolvimento de garantias de marketing criativo para diversos\nprojetos. Estabelece padrões claros e aplica protocolos para resultados consistentes e de alta qualidade, utilizando habilidades interpessoais, dados\nHabilidades analíticas, excelente gerenciamento de tempo e habilidades de solução de problemas. \nza05760@gmail.com \n03310211624 \nR-280, folha 51, Bloco B, Villas Saima Arabian, Karachi. \nExperiência de trabalho \nExecutivo de Desenvolvimento de Negócios \nPayMob \n2021 - presente\n, Assim, \n \nCarachi \nDefinidas e integradas funções, responsabilidades e processos para\nEquipe de negócios e organização de gerenciamento de dados. \nCriou planilhas usando o Microsoft Excel para diariamente, semanalmente e\nRelatórios mensais. \nDesenvolveu e executou iniciativas estratégicas para implementar a chave\nmudanças e melhorias no desenvolvimento de negócios e vendas\nprogramas. \nUsou o pensamento crítico para dividir problemas, avaliar soluções\ne tomar decisões. \nAnalista de pesquisa de mercado \nEquipamento de engenharia de precisão FZE \n2019 - 2021\n, Assim, \n \nCarachi \nTrabalhou em estreita colaboração com as equipes de desenvolvimento de produtos para criar e\nManter materiais de marketing para apresentações de vendas e cliente\nreuniões na indústria. \nAnalisou os planos de marketing de pré-temporada para gerar melhores vendas e\nComunique -se com os clientes através da chamada/e -mail. \nDesenvolveu estratégias de marketing e problemas resolvidos para dirigir\nVendas, por meio de CRM e informações de banco de dados gerenciadas do mercado. \nUtilizou diferentes ferramentas para analisar tendências de marketing e financeiras como\nAS, SQL, Excel e Power BI e medidas sugeridas para reduzir custos\ne melhorar os processos de negócios. \nEstágio \nUnilever Paquistão \n2019\n, Assim, \n \nCarachi \nAnalisar e examinar os requisitos da empresa para contínua\nprojetos e contratos. \nAtualize e gerencie o banco de dados interno para a seleção do futuro fornecedor\nE seus termos, essas informações são úteis para os próximos projetos. \nRelacionamentos de fornecedores desenvolvidos e reforçados. \nEDUCAÇÃO \nBS - Ciência da Gestão \nUniversidade de Engenharia e Tecnologia de Ned \n2022\n, Assim, \n \nCarachi \nHABILIDADES \nResolução de problemas e análise de negócios \nDesenvolvimento de produtos e estrategista \nCRM \nComunicação comercial e relatórios \nSQL \nMarketing digital \nAnalista de pesquisa de mercado \nEntusiasta da ciência de dados \nHabilidade de liderança \nProjeto e gerenciamento de marca \nHubSpot \nSalesforce \nBoa redociação \nPython \nVisualização de dados \nQuadro \nPower bi \nProjetos pessoais \nCPEC \n- \nProjeto do ano final \nAnalisando o desenvolvimento da infraestrutura logística do Paquistão\ndepois do CPEC e como ele renovará ou reabilitará o\nInfraestrutura do Paquistão, desenvolvendo o especial\nZonas econômicas. Analisamos os diferentes dados industriais em\ncada província do Paquistão e o impacto de SEZs que vão\nremodelar a economia da indústria no Paquistão \nSegurança Midas Paquistão \n- \nProjeto do curso \nProjeto em Midas Safety Pakistan (unidade Karachi) onde eu\nidentificar o processo envolvido na fabricação de seus\nProdutos, isto é, luvas e mangas de segurança. Eu basicamente analisei\nDrivers da cadeia de suprimentos de Midas e examinaram o uso \nde\ntecnologia da Informação. \nIdiomas \nInglês \nProfiência profissional completa \nRealizações/tarefas \nRealizações/tarefas \nRealizações/tarefas",
  "details": {
    "name": "Zubair Ahmed",
    "number": "03310211624",
    "skills": [
      "SQL",
      "Excel",
      "Python",
      "Power bi",
      "Quadro",
      "HubSpot",
      "Salesforce"
    ],
    "email_id": "za05760@gmail.com",
    "location": "Carachi",
    "projects": [
      {
        "title": "CPEC - Projeto do ano final",
        "description": "Analisando o desenvolvimento da infraestrutura logística do Paquistão após o CPEC."
      },
      {
        "title": "Midas Safety Pakistan - Projeto de curso",
        "description": "Analisou os motoristas da cadeia de suprimentos de Midas e examinaram o uso da tecnologia da informação."
      }
    ],
    "education": [
      {
        "end_date": "06-2022",
        "university": "Universidade de Engenharia e Tecnologia de Ned",
        "degree_title": "BS - Ciência da Gestão"
      }
    ],
    "achievements": [],
    "publications": [],
    "certifications": [],
    "additional_urls": [
      {
        "url": "LinkedIn.com/in/zubairahmed",
        "website_name": "LinkedIn"
      }
    ],
    "executive_summary": "Zubair Ahmed é um executivo dedicado de desenvolvimento de negócios, com uma forte experiência em marketing e análise de negócios. Ele possui habilidades técnicas no SQL, Excel, Python e várias ferramentas de visualização de dados, demonstrando um compromisso de impulsionar as melhorias nos negócios e as iniciativas estratégicas.",
    "employment_history": [
      {
        "details": "Funções, responsabilidades e processos definidos e integrados para a equipe de equipes e gerenciamento de dados. Criou planilhas usando o Microsoft Excel para relatórios diários, semanais e mensais. Desenvolveu e executou iniciativas estratégicas para implementar as principais mudanças e melhorias nos programas de desenvolvimento e vendas de negócios.",
        "end_date": "Presente",
        "location": "Carachi",
        "job_title": "Executivo de Desenvolvimento de Negócios",
        "start_date": "01-2021",
        "company_name": "PayMob"
      },
      {
        "details": "Trabalhou em estreita colaboração com as equipes de desenvolvimento de produtos para criar e manter materiais de marketing para apresentações de vendas e reuniões de clientes. Analisou os planos de marketing de pré-temporada para gerar melhores vendas e se comunicar com os clientes através da chamada/e-mail. Desenvolveu estratégias de marketing e problemas resolvidos para impulsionar as vendas, por meio do CRM e das informações gerenciadas do banco de dados do mercado.",
        "end_date": "12-2021",
        "location": "Carachi",
        "job_title": "Analista de pesquisa de mercado",
        "start_date": "01-2019",
        "company_name": "Equipamento de engenharia de precisão FZE"
      },
      {
        "details": "Analisando e examinando os requisitos da empresa para projetos e contratos em andamento. Banco de dados interno atualizado e gerenciado para a seleção do fornecedor futuro e seus termos, essas informações são úteis para os próximos projetos. Relacionamentos de fornecedores desenvolvidos e reforçados.",
        "end_date": "12-2019",
        "location": "Carachi",
        "job_title": "Estágio",
        "start_date": "01-2019",
        "company_name": "Unilever Paquistão"
      }
    ]
  }
}