{
  "job_description": "** Título: Gerente de Desenvolvimento de Negócios **  \n\n** Empresa: MarketPros Enterprises **  \n\n** Localização: remoto com potencial viagens para locais de clientes **  \n\n**Sobre nós:**  \nA MarketPros Enterprises é um fornecedor global líder de soluções de negócios inovadoras, com o objetivo de maximizar o crescimento da marca. Trabalhamos com diversas indústrias para aprimorar sua infraestrutura de vendas e fornecer estratégias incomparáveis ​​de envolvimento do cliente.  \n\n** Visão geral da função: **  \nComo gerente de desenvolvimento de negócios da MarketPros Enterprises, você será responsável por liderar iniciativas estratégicas que impulsionam o crescimento dos negócios, aumentam a participação de mercado e fortalecem as relações com os clientes. Você gerenciará equipes multifuncionais para implementar estratégias de vendas, aproveitar as idéias do mercado e impulsionar a expansão da marca.  \n\n** Responsabilidades -chave: **  \n- Desenvolver e implementar estratégias de negócios abrangentes para aumentar o crescimento da receita.  \n- Liderar uma equipe na execução de campanhas de marketing e otimizar os pipelines de vendas.  \n- Utilize ferramentas de análise de dados para produzir informações acionáveis, melhorando o desempenho geral.  \n- Realize pesquisas de mercado para identificar tendências do setor e novas oportunidades de negócios.  \n- Envolva-se com clientes em potencial por meio de apresentações e promova relacionamentos de longo prazo.  \n- Gerenciar sistemas CRM (Salesforce, HubSpot) para otimizar as operações e aprimorar a produtividade.  \n\n** Habilidades preferidas: **  \n- Proficiência em planejamento estratégico e análise de mercado.  \n- Fortes habilidades de liderança com experiência comprovada no desenvolvimento de equipes.  \n- Conhecimento avançado de software CRM e ferramentas de marketing digital.  \n- Excelentes habilidades de comunicação e negociação.  \n\nJunte -se a nós para ultrapassar os limites da inovação de negócios e nos ajudar a alcançar nossos objetivos de expansão.",
  "additional_info": "A MarketPros Enterprises valoriza a diversidade na contratação e incentiva aplicativos de profissionais de negócios experientes com origens variadas. As universidades preferenciais incluem instituições da Ivy League e as principais escolas de negócios. Oferecemos benefícios de realocação para candidatos excepcionais e facilitamos os acordos de trabalho remotos. As competências técnicas e estratégicas são avaliadas através de uma mistura de avaliações psicométricas e entrevistas com estudos de caso.",
  "resume": "Faique Ali Raza House # 392, K Block, Model Town, Lahore, Pakistan 03143631941 linkedin.com/in/FaiqueAliRaza faiquealiraza@gmail.com Profile • An individual who is focused, honest, team-oriented, deliberate, determined, and most importantly, who makes use of his grey matter. • Vários anos de experiência em desenvolvimento de negócios, geração de vendas e campos de marketing. • Freelancer com melhor classificação no Upwork. • Experiência prática em geração de leads, marketing por email, tele-vendas, navegador de vendas, Salesforce, documentação e CRM. • 1 ano de experiência em marketing de comunicação e tele-sales. • Mais de 9 anos de experiência no campo da música e gerenciamento de eventos. Experiência de trabalho educacional • Matric | Ciência | Autoridade de Aviação Civil LAHORE LAHORE • Intermediário | Pre Eng. | Government College Gulberg Lahore • Bacharel em Ciência da Computação | Os prêmios de habilidades da Universidade de Lahore, realizações e certificações raspam dados | Extração de dados | Leads | E -mails upwork | Fiverr | Freelancer | Guru | Toptal Musician | Produção | Live | Gravações de estúdio • Curso de cinema e documentário | Hunerkada College of Visual & Performing Arts | Lahore | 2020  \n Design de produção para filme e tela | Escola de televisão e rádio australiana de cinema e rádio | 2020 \n Programa Nacional de Alfabetização Financeira para Juventude | Instituto Nacional de Bancos e Finanças (NIBAF) -Paquistão | 2020 \n Certificação em pensamento crítico - tomada de decisão mestre e resolução de problemas. \n Ganhou muitas batalhas musicais no Paquistão. \n Tendo muitas certificações em diferentes atividades e cursos.  • Marketing de conteúdo e publicidade | Universidade de Punjab | E-rozgaar | Lahore | 2020 \nSrs | GDD | Wbd | Marcos | Linhas de tempo • Gerente de Desenvolvimento de Negócios | CrewLogicx Tech | Studios de origami | Abril de 2022 - cont. • Desenvolvimento de negócios e gerente de projetos digitais | Firtle Tech | Meio período | Junho de 2019 - cont. • Executivo de Desenvolvimento de Negócios | Tech de argônio | Lahore | Maio de 2021 - abril de 2022. • Executivo de Desenvolvimento de Negócios | Kodex Technologies | Dezembro de 2020 - maio de 2021. • Executivo de Desenvolvimento de Negócios | Growhawk | Agosto - dezembro de 2020. • Executivo de Desenvolvimento de Negócios | Bizzclan | Lahore | Maio - agosto de 2020. • Agente de telemarketing | Solução nixxe | 2019. Desenvolvedor de Negócios | Especialista no LinkedIn | Leads/Gerador de vendas | Freelancer de upwork com melhor classificação",
  "details": {
    "name": "Faique Ali Raza",
    "number": "03143631941",
    "skills": [
      "Raspagem de dados",
      "Extração de dados",
      "Pistas",
      "E -mails",
      "Salesforce",
      "Documentação",
      "CRM"
    ],
    "email_id": "faiquealiraza@gmail.com",
    "location": "Lahore, Paquistão",
    "projects": [],
    "education": [
      {
        "end_date": "06-2020",
        "university": "Autoridade de aviação civil LAHORE",
        "degree_title": "Matric | Ciência"
      },
      {
        "end_date": "06-2020",
        "university": "Faculdade de governo Gulberg Lahore",
        "degree_title": "Intermediário | Pre Eng."
      },
      {
        "end_date": "06-2020",
        "university": "A Universidade de Lahore",
        "degree_title": "Bacharel em Ciência da Computação"
      }
    ],
    "achievements": [
      "Freelancer de primeira classificação no Upwork",
      "Ganhou muitas batalhas musicais no Paquistão"
    ],
    "publications": [],
    "certifications": [
      {
        "certification_name": "Curso de cinema e documentário",
        "issuing_organization": "Hunerkada College of Visual & Performing Arts",
        "date_of_issuance": "06-2020"
      },
      {
        "certification_name": "Design de produção para cinema e tela",
        "issuing_organization": "Escola de televisão e rádio australiana",
        "date_of_issuance": "06-2020"
      },
      {
        "certification_name": "Programa Nacional de Alfabetização Financeira para Juventude",
        "issuing_organization": "Instituto Nacional de Bancos e Finanças (NIBAF) -Paquistão",
        "date_of_issuance": "06-2020"
      },
      {
        "certification_name": "Marketing de conteúdo e publicidade",
        "issuing_organization": "Universidade de Punjab | E-rozgaar",
        "date_of_issuance": "06-2020"
      }
    ],
    "additional_urls": [
      {
        "url": "LinkedIn.com/in/faiquealiraza",
        "website_name": "LinkedIn"
      }
    ],
    "executive_summary": "Faique Ali Raza é um profissional dedicado, com vasta experiência em desenvolvimento de negócios, geração de vendas e marketing. Ele tem uma forte formação técnica em sistemas de raspagem de dados, geração de leads e CRM, complementados por uma base educacional sólida na ciência da computação. Faique é reconhecido como um freelancer de melhor classificação no Upwork e alcançou um sucesso notável em batalhas musicais em todo o Paquistão.",
    "employment_history": [
      {
        "details": "Gerente de Desenvolvimento de Negócios Responsável por impulsionar as vendas e gerenciar o relacionamento com os clientes.",
        "end_date": "Presente",
        "location": "Lahore",
        "job_title": "Gerente de Desenvolvimento de Negócios",
        "start_date": "04-2022",
        "company_name": "CrewLogicx Tech"
      },
      {
        "details": "Função de meio período com foco no desenvolvimento de negócios e gerenciamento de projetos digitais.",
        "end_date": "Presente",
        "location": "Lahore",
        "job_title": "Desenvolvimento de negócios e gerente de projetos digitais",
        "start_date": "06-2019",
        "company_name": "Firtle Tech"
      },
      {
        "details": "Envolvido em atividades de desenvolvimento de negócios para aprimorar as vendas e a aquisição de clientes.",
        "end_date": "04-2022",
        "location": "Lahore",
        "job_title": "Executivo de Desenvolvimento de Negócios",
        "start_date": "05-2021",
        "company_name": "Tecnologia de Argon"
      },
      {
        "details": "Responsável pela geração de leads e gerenciamento de comunicações do cliente.",
        "end_date": "05-2021",
        "location": "Lahore",
        "job_title": "Executivo de Desenvolvimento de Negócios",
        "start_date": "12-2020",
        "company_name": "Kodex Technologies"
      },
      {
        "details": "Focado na geração de leads e no alcance do cliente.",
        "end_date": "12-2020",
        "location": "Lahore",
        "job_title": "Executivo de Desenvolvimento de Negócios",
        "start_date": "08-2020",
        "company_name": "Growhawk"
      },
      {
        "details": "Conduziu atividades de telemarketing e envolvimento do cliente.",
        "end_date": "12-2019",
        "location": "Lahore",
        "job_title": "Agente de telemarketing",
        "start_date": "01-2019",
        "company_name": "Solução nixxe"
      }
    ]
  }
}