{
  "job_description": "** Título: Gerente de Desenvolvimento de Negócios **  \n\n** Empresa: MarketPros Enterprises **  \n\n** Localização: remoto com potencial viagens para locais de clientes **  \n\n**Sobre nós:**  \nA MarketPros Enterprises é um fornecedor global líder de soluções de negócios inovadoras, com o objetivo de maximizar o crescimento da marca. Trabalhamos com diversas indústrias para aprimorar sua infraestrutura de vendas e fornecer estratégias incomparáveis ​​de envolvimento do cliente.  \n\n** Visão geral da função: **  \nComo gerente de desenvolvimento de negócios da MarketPros Enterprises, você será responsável por liderar iniciativas estratégicas que impulsionam o crescimento dos negócios, aumentam a participação de mercado e fortalecem as relações com os clientes. Você gerenciará equipes multifuncionais para implementar estratégias de vendas, aproveitar as idéias do mercado e impulsionar a expansão da marca.  \n\n** Responsabilidades -chave: **  \n- Desenvolver e implementar estratégias de negócios abrangentes para aumentar o crescimento da receita.  \n- Liderar uma equipe na execução de campanhas de marketing e otimizar os pipelines de vendas.  \n- Utilize ferramentas de análise de dados para produzir informações acionáveis, melhorando o desempenho geral.  \n- Realize pesquisas de mercado para identificar tendências do setor e novas oportunidades de negócios.  \n- Envolva-se com clientes em potencial por meio de apresentações e promova relacionamentos de longo prazo.  \n- Gerenciar sistemas CRM (Salesforce, HubSpot) para otimizar as operações e aprimorar a produtividade.  \n\n** Habilidades preferidas: **  \n- Proficiência em planejamento estratégico e análise de mercado.  \n- Fortes habilidades de liderança com experiência comprovada no desenvolvimento de equipes.  \n- Conhecimento avançado de software CRM e ferramentas de marketing digital.  \n- Excelentes habilidades de comunicação e negociação.  \n\nJunte -se a nós para ultrapassar os limites da inovação de negócios e nos ajudar a alcançar nossos objetivos de expansão.",
  "additional_info": "A MarketPros Enterprises valoriza a diversidade na contratação e incentiva aplicativos de profissionais de negócios experientes com origens variadas. As universidades preferenciais incluem instituições da Ivy League e as principais escolas de negócios. Oferecemos benefícios de realocação para candidatos excepcionais e facilitamos os acordos de trabalho remotos. As competências técnicas e estratégicas são avaliadas através de uma mistura de avaliações psicométricas e entrevistas com estudos de caso.",
  "resume": "Arslan Iqbal\nExecutivo de Desenvolvimento de Negócios \nPerfil pessoal\nLahore, \nPaquistão\n+9233336662181\narsllan.181@hotmail.com\nLinks\nhttps://www.linkedin.com/in/ar-\nslan-iqbal1/\nHabilidades\nVendas e desenvolvimento organizacional \nAtendimento ao Cliente\nPesquisa e análise de mercado \nEmail marketing e aquisição de clientes\nPensamento crítico e resolução de problemas\nPrêmios e certificação\n• Prêmio de melhor geração de leads  \n Gala de Marketing 2022, UCP \nEscola de Negócios.\n• Os fundamentos do digital \nMarketing - Google Digital \nGaragem.\n• Conferência do ICIBM sobre CON-\nquestões temporárias em bus-\nGerenciamento de Ness - Organização \nMembro do Comitê. Resumo Profissional\nExecutivo experiente de desenvolvimento de negócios conhecido por impulsionar as vendas, aprimorando \norganizações e mercados em expansão. Um comunicador estratégico hábil na construção \nRelacionamentos do cliente e implementação de estratégias de crescimento inovadoras. Equipe comprometida \nJogador com fortes habilidades analíticas, excedendo consistentemente os alvos.\nHistórico de emprego\nExecutivo de Desenvolvimento de Negócios, Raheem Solutions Unip. Ltd., \nLahore, Paquistão\n0 9/2 0 2 2 - p re s e n t\n• Desenvolvido e mantido relacionamentos com o cliente, garantindo um cliente excepcional \nsatisfação e lealdade.\n• Colaborar com as equipes de vendas e marketing para alinhar estratégias e en-\nOportunidades de geração de receita de Hance.\n• Ajudei minha equipe de vendas a atingir seus objetivos, utilizando várias ferramentas, como \nComo Apollo, Lusha, entre em contato e o LinkedIn Sales Navigator.\n• Através de upwork e freelancer, eu gero e qualifique liderões com sucesso, \ncontribuindo para um pipeline consistente de clientes em potencial.\nRepresentante de Desenvolvimento de Vendas - Gerente de Estado, \nSeebiz Pvt. Ltd., Lahore, Paquistão.\n0 8/2 0 2 2 - 0 9/2 0 2 2\n• Lidar conosco com clientes por meio de chamadas, mensagens e e -mails. Aumenta o meu \nHabilidades de comunicação e gerenciamento de pessoas\n• Gerenciou um território, supervisionando as atividades de geração de leads e conversão e \nacordos fechados com sucesso.\n• participou de sessões de treinamento de produtos e utilizou o conhecimento do produto para \ncomunicar efetivamente proposições de valor a clientes em potencial.\nEducação\nMestre em Administração de Empresas (MBA) em Marketing, \nUniversidade de Punjab Central, Lahore, Paquistão\n0 3/2 0 1 9 - 0 7/2 0 2 2\n• Programa de MBA concluído com foco em estratégias de marketing, consumidor \ncomportamento e pesquisa de mercado.\n• Especializado em gerenciamento e vendas de marcas, alavancando a experiência para dirigir \ncrescimento nos negócios.\n• Graduado com proficiência em aplicar conceitos de marketing modernos a \ncenários do mundo real.\nBacharel em Comércio, Universidade do Punjab, Lahore, Paquistão.\n0 8/2 0 1 6 - 1 2/2 0 1 8\n• Adquiriu Fundação Forte em Business Essentials: Finanças, Contabilidade, Eco-\nNomics e gerenciamento.\n• Envolvido em projetos colaborativos, aprimorando o trabalho em equipe e as habilidades de comunicação.\n• Desenvolveu uma compreensão abrangente das operações comerciais.\nReferências\nDisponível mediante solicitação. de",
  "details": {
    "name": "Arslan Iqbal",
    "number": "9233336662181",
    "skills": [
      "Vendas e desenvolvimento organizacional",
      "Atendimento ao Cliente",
      "Pesquisa e análise de mercado",
      "Email marketing e aquisição de clientes"
    ],
    "email_id": "arsllan.181@hotmail.com",
    "location": "Lahore, Paquistão",
    "projects": [],
    "education": [
      {
        "end_date": "07-2022",
        "university": "Universidade de Punjab Central",
        "degree_title": "Mestre em Administração de Empresas (MBA) em Marketing"
      },
      {
        "end_date": "12-2018",
        "university": "Universidade do Punjab",
        "degree_title": "Bacharel em Comércio"
      }
    ],
    "achievements": [
      "Melhor Prêmio de Geração de Leads, Marketing Gala 2022, UCP Business School."
    ],
    "publications": [],
    "certifications": [
      {
        "certification_name": "Os fundamentos do marketing digital",
        "issuing_organization": "Garagem digital do Google",
        "date_of_issuance": "01-2022"
      }
    ],
    "additional_urls": [
      {
        "url": "linkedin.com/in/ar-slan-iqbal1/",
        "website_name": "LinkedIn"
      }
    ],
    "executive_summary": "O Arslan Iqbal é um executivo de desenvolvimento de negócios experiente conhecido por impulsionar as vendas e aumentar o crescimento organizacional. Ele tem uma forte formação em gerenciamento de relacionamento com clientes e pesquisa de mercado, demonstrando um compromisso de alcançar uma satisfação e lealdade excepcionais do cliente.",
    "employment_history": [
      {
        "details": "Desenvolveu e manteve o relacionamento com os clientes, garantindo satisfação e lealdade excepcionais do cliente. Colaborou com as equipes de vendas e marketing para alinhar estratégias e aprimorar as oportunidades de geração de receita. Ajudou a equipe de vendas a alcançar suas metas, utilizando várias ferramentas, como Apollo, Lusha, entrar em contato e LinkedIn Sales Navigator. Leads com sucesso gerados e qualificados por meio de upwork e freelancer, contribuindo para um pipeline consistente de clientes em potencial.",
        "end_date": "Presente",
        "location": "Lahore, Paquistão",
        "job_title": "Executivo de Desenvolvimento de Negócios",
        "start_date": "09-2022",
        "company_name": "Raheem Solutions Unip. Ltd."
      },
      {
        "details": "Lidar com clientes dos EUA através de chamadas, mensagens e e -mails, aprimorando as habilidades de comunicação e gerenciamento de pessoas. Gerenciou um território, supervisionando as atividades de geração e conversão de leads e fechou com sucesso acordos. Participou de sessões de treinamento de produtos e utilizou o conhecimento do produto para comunicar efetivamente proposições de valor a clientes em potencial.",
        "end_date": "09-2022",
        "location": "Lahore, Paquistão",
        "job_title": "Representante de Desenvolvimento de Vendas - Gerente de Estado",
        "start_date": "08-2022",
        "company_name": "Seebiz Pvt. Ltd."
      }
    ]
  }
}